Workbook
Name valuevx: 42.314159
Name LocationList: '_Locations'!$A$1:$A$37

Sheet Work Hours Summary
A1: 📊 WORK HOURS SUMMARY
A2: Pay Period: 1-15/16 Jan 2026 | Total Employees: 29
A4: # | B4: Employee Name | C4: Emp # | D4: Total Hrs | E4: Days Wkd | F4: Daily >12 | G4: Wkly >60 | H4: 7+ Days | I4: OT >40 | J4: Wkly <40 | K4: Daily <8 | L4: Days <5 | M4: Period <80 | N4: STATUS
A5: 1 | B5: Abel, Natalie | C5: 4469 | D5: ='Abel, Natalie'!I49 | E5: ='Abel, Natalie'!Q50 | F5: =SUMPRODUCT((('Abel, Natalie'!I14+'Abel, Natalie'!I15)>12)*1)+SUMPRODUCT((('Abel, Natalie'!I16+'Abel, Natalie'!I17)>12)*1)+SUMPRODUCT((('Abel, Natalie'!I18+'Abel, Natalie'!I19)>12)*1)+SUMPRODUCT((('Abel, Natalie'!I20+'Abel, Natalie'!I21)>12)*1)+SUMPRODUCT((('Abel, Natalie'!I22+'Abel, Natalie'!I23)>12)*1)+SUMPRODUCT((('Abel, Natalie'!I24+'Abel, Natalie'!I25)>12)*1)+SUMPRODUCT((('Abel, Natalie'!I26+'Abel, Natalie'!I27)>12)*1)+SUMPRODUCT((('Abel, Natalie'!I30+'Abel, Natalie'!I31)>12)*1)+SUMPRODUCT((('Abel, Natalie'!I32+'Abel, Natalie'!I33)>12)*1)+SUMPRODUCT((('Abel, Natalie'!I34+'Abel, Natalie'!I35)>12)*1)+SUMPRODUCT((('Abel, Natalie'!I36+'Abel, Natalie'!I37)>12)*1)+SUMPRODUCT((('Abel, Natalie'!I38+'Abel, Natalie'!I39)>12)*1)+SUMPRODUCT((('Abel, Natalie'!I40+'Abel, Natalie'!I41)>12)*1)+SUMPRODUCT((('Abel, Natalie'!I42+'Abel, Natalie'!I43)>12)*1)+SUMPRODUCT((('Abel, Natalie'!I45+'Abel, Natalie'!I46)>12)*1)+SUMPRODUCT((('Abel, Natalie'!I47+'Abel, Natalie'!I48)>12)*1) | G5: =IF(MAX(SUM('Abel, Natalie'!I14:I27),SUM('Abel, Natalie'!I30:I43))>60,"Yes","") | H5: =IF(OR(AND(('Abel, Natalie'!I14+'Abel, Natalie'!I15)>0,('Abel, Natalie'!I16+'Abel, Natalie'!I17)>0,('Abel, Natalie'!I18+'Abel, Natalie'!I19)>0,('Abel, Natalie'!I20+'Abel, Natalie'!I21)>0,('Abel, Natalie'!I22+'Abel, Natalie'!I23)>0,('Abel, Natalie'!I24+'Abel, Natalie'!I25)>0,('Abel, Natalie'!I26+'Abel, Natalie'!I27)>0),AND(('Abel, Natalie'!I30+'Abel, Natalie'!I31)>0,('Abel, Natalie'!I32+'Abel, Natalie'!I33)>0,('Abel, Natalie'!I34+'Abel, Natalie'!I35)>0,('Abel, Natalie'!I36+'Abel, Natalie'!I37)>0,('Abel, Natalie'!I38+'Abel, Natalie'!I39)>0,('Abel, Natalie'!I40+'Abel, Natalie'!I41)>0,('Abel, Natalie'!I42+'Abel, Natalie'!I43)>0)),"Yes","") | I5: =IF('Abel, Natalie'!N49>40,"Yes","") | J5: =IF(OR(AND(SUM('Abel, Natalie'!I14:I27)>0,SUM('Abel, Natalie'!I14:I27)<40),AND(SUM('Abel, Natalie'!I30:I43)>0,SUM('Abel, Natalie'!I30:I43)<40)),"Yes","") | K5: =SUMPRODUCT(('Abel, Natalie'!I14:I48>0)*('Abel, Natalie'!I14:I48<8)) | L5: =IF('Abel, Natalie'!Q50<5,"Yes","") | M5: =IF(AND('Abel, Natalie'!I49>0,'Abel, Natalie'!I49<80),"Yes","") | N5: =IF(OR(F5>0,G5="Yes",H5="Yes",I5="Yes"),"⚠️ OVERWORK",IF(OR(J5="Yes",K5>0,L5="Yes",M5="Yes"),"🔻 UNDERWORK","✓ OK"))
A6: 2 | B6: April, Candica Alicia | C6: 5255 | D6: ='April, Candica'!I49 | E6: ='April, Candica'!Q50 | F6: =SUMPRODUCT((('April, Candica'!I14+'April, Candica'!I15)>12)*1)+SUMPRODUCT((('April, Candica'!I16+'April, Candica'!I17)>12)*1)+SUMPRODUCT((('April, Candica'!I18+'April, Candica'!I19)>12)*1)+SUMPRODUCT((('April, Candica'!I20+'April, Candica'!I21)>12)*1)+SUMPRODUCT((('April, Candica'!I22+'April, Candica'!I23)>12)*1)+SUMPRODUCT((('April, Candica'!I24+'April, Candica'!I25)>12)*1)+SUMPRODUCT((('April, Candica'!I26+'April, Candica'!I27)>12)*1)+SUMPRODUCT((('April, Candica'!I30+'April, Candica'!I31)>12)*1)+SUMPRODUCT((('April, Candica'!I32+'April, Candica'!I33)>12)*1)+SUMPRODUCT((('April, Candica'!I34+'April, Candica'!I35)>12)*1)+SUMPRODUCT((('April, Candica'!I36+'April, Candica'!I37)>12)*1)+SUMPRODUCT((('April, Candica'!I38+'April, Candica'!I39)>12)*1)+SUMPRODUCT((('April, Candica'!I40+'April, Candica'!I41)>12)*1)+SUMPRODUCT((('April, Candica'!I42+'April, Candica'!I43)>12)*1)+SUMPRODUCT((('April, Candica'!I45+'April, Candica'!I46)>12)*1)+SUMPRODUCT((('April, Candica'!I47+'April, Candica'!I48)>12)*1) | G6: =IF(MAX(SUM('April, Candica'!I14:I27),SUM('April, Candica'!I30:I43))>60,"Yes","") | H6: =IF(OR(AND(('April, Candica'!I14+'April, Candica'!I15)>0,('April, Candica'!I16+'April, Candica'!I17)>0,('April, Candica'!I18+'April, Candica'!I19)>0,('April, Candica'!I20+'April, Candica'!I21)>0,('April, Candica'!I22+'April, Candica'!I23)>0,('April, Candica'!I24+'April, Candica'!I25)>0,('April, Candica'!I26+'April, Candica'!I27)>0),AND(('April, Candica'!I30+'April, Candica'!I31)>0,('April, Candica'!I32+'April, Candica'!I33)>0,('April, Candica'!I34+'April, Candica'!I35)>0,('April, Candica'!I36+'April, Candica'!I37)>0,('April, Candica'!I38+'April, Candica'!I39)>0,('April, Candica'!I40+'April, Candica'!I41)>0,('April, Candica'!I42+'April, Candica'!I43)>0)),"Yes","") | I6: =IF('April, Candica'!N49>40,"Yes","") | J6: =IF(OR(AND(SUM('April, Candica'!I14:I27)>0,SUM('April, Candica'!I14:I27)<40),AND(SUM('April, Candica'!I30:I43)>0,SUM('April, Candica'!I30:I43)<40)),"Yes","") | K6: =SUMPRODUCT(('April, Candica'!I14:I48>0)*('April, Candica'!I14:I48<8)) | L6: =IF('April, Candica'!Q50<5,"Yes","") | M6: =IF(AND('April, Candica'!I49>0,'April, Candica'!I49<80),"Yes","") | N6: =IF(OR(F6>0,G6="Yes",H6="Yes",I6="Yes"),"⚠️ OVERWORK",IF(OR(J6="Yes",K6>0,L6="Yes",M6="Yes"),"🔻 UNDERWORK","✓ OK"))
A7: 3 | B7: Ash, Carol Veronica | C7: 1105 | D7: ='Ash, Carol'!I49 | E7: ='Ash, Carol'!Q50 | F7: =SUMPRODUCT((('Ash, Carol'!I14+'Ash, Carol'!I15)>12)*1)+SUMPRODUCT((('Ash, Carol'!I16+'Ash, Carol'!I17)>12)*1)+SUMPRODUCT((('Ash, Carol'!I18+'Ash, Carol'!I19)>12)*1)+SUMPRODUCT((('Ash, Carol'!I20+'Ash, Carol'!I21)>12)*1)+SUMPRODUCT((('Ash, Carol'!I22+'Ash, Carol'!I23)>12)*1)+SUMPRODUCT((('Ash, Carol'!I24+'Ash, Carol'!I25)>12)*1)+SUMPRODUCT((('Ash, Carol'!I26+'Ash, Carol'!I27)>12)*1)+SUMPRODUCT((('Ash, Carol'!I30+'Ash, Carol'!I31)>12)*1)+SUMPRODUCT((('Ash, Carol'!I32+'Ash, Carol'!I33)>12)*1)+SUMPRODUCT((('Ash, Carol'!I34+'Ash, Carol'!I35)>12)*1)+SUMPRODUCT((('Ash, Carol'!I36+'Ash, Carol'!I37)>12)*1)+SUMPRODUCT((('Ash, Carol'!I38+'Ash, Carol'!I39)>12)*1)+SUMPRODUCT((('Ash, Carol'!I40+'Ash, Carol'!I41)>12)*1)+SUMPRODUCT((('Ash, Carol'!I42+'Ash, Carol'!I43)>12)*1)+SUMPRODUCT((('Ash, Carol'!I45+'Ash, Carol'!I46)>12)*1)+SUMPRODUCT((('Ash, Carol'!I47+'Ash, Carol'!I48)>12)*1) | G7: =IF(MAX(SUM('Ash, Carol'!I14:I27),SUM('Ash, Carol'!I30:I43))>60,"Yes","") | H7: =IF(OR(AND(('Ash, Carol'!I14+'Ash, Carol'!I15)>0,('Ash, Carol'!I16+'Ash, Carol'!I17)>0,('Ash, Carol'!I18+'Ash, Carol'!I19)>0,('Ash, Carol'!I20+'Ash, Carol'!I21)>0,('Ash, Carol'!I22+'Ash, Carol'!I23)>0,('Ash, Carol'!I24+'Ash, Carol'!I25)>0,('Ash, Carol'!I26+'Ash, Carol'!I27)>0),AND(('Ash, Carol'!I30+'Ash, Carol'!I31)>0,('Ash, Carol'!I32+'Ash, Carol'!I33)>0,('Ash, Carol'!I34+'Ash, Carol'!I35)>0,('Ash, Carol'!I36+'Ash, Carol'!I37)>0,('Ash, Carol'!I38+'Ash, Carol'!I39)>0,('Ash, Carol'!I40+'Ash, Carol'!I41)>0,('Ash, Carol'!I42+'Ash, Carol'!I43)>0)),"Yes","") | I7: =IF('Ash, Carol'!N49>40,"Yes","") | J7: =IF(OR(AND(SUM('Ash, Carol'!I14:I27)>0,SUM('Ash, Carol'!I14:I27)<40),AND(SUM('Ash, Carol'!I30:I43)>0,SUM('Ash, Carol'!I30:I43)<40)),"Yes","") | K7: =SUMPRODUCT(('Ash, Carol'!I14:I48>0)*('Ash, Carol'!I14:I48<8)) | L7: =IF('Ash, Carol'!Q50<5,"Yes","") | M7: =IF(AND('Ash, Carol'!I49>0,'Ash, Carol'!I49<80),"Yes","") | N7: =IF(OR(F7>0,G7="Yes",H7="Yes",I7="Yes"),"⚠️ OVERWORK",IF(OR(J7="Yes",K7>0,L7="Yes",M7="Yes"),"🔻 UNDERWORK","✓ OK"))
A8: 4 | B8: Beharry, Akeela Ashanti | C8: 5520 | D8: ='Beharry, Akeela'!I49 | E8: ='Beharry, Akeela'!Q50 | F8: =SUMPRODUCT((('Beharry, Akeela'!I14+'Beharry, Akeela'!I15)>12)*1)+SUMPRODUCT((('Beharry, Akeela'!I16+'Beharry, Akeela'!I17)>12)*1)+SUMPRODUCT((('Beharry, Akeela'!I18+'Beharry, Akeela'!I19)>12)*1)+SUMPRODUCT((('Beharry, Akeela'!I20+'Beharry, Akeela'!I21)>12)*1)+SUMPRODUCT((('Beharry, Akeela'!I22+'Beharry, Akeela'!I23)>12)*1)+SUMPRODUCT((('Beharry, Akeela'!I24+'Beharry, Akeela'!I25)>12)*1)+SUMPRODUCT((('Beharry, Akeela'!I26+'Beharry, Akeela'!I27)>12)*1)+SUMPRODUCT((('Beharry, Akeela'!I30+'Beharry, Akeela'!I31)>12)*1)+SUMPRODUCT((('Beharry, Akeela'!I32+'Beharry, Akeela'!I33)>12)*1)+SUMPRODUCT((('Beharry, Akeela'!I34+'Beharry, Akeela'!I35)>12)*1)+SUMPRODUCT((('Beharry, Akeela'!I36+'Beharry, Akeela'!I37)>12)*1)+SUMPRODUCT((('Beharry, Akeela'!I38+'Beharry, Akeela'!I39)>12)*1)+SUMPRODUCT((('Beharry, Akeela'!I40+'Beharry, Akeela'!I41)>12)*1)+SUMPRODUCT((('Beharry, Akeela'!I42+'Beharry, Akeela'!I43)>12)*1)+SUMPRODUCT((('Beharry, Akeela'!I45+'Beharry, Akeela'!I46)>12)*1)+SUMPRODUCT((('Beharry, Akeela'!I47+'Beharry, Akeela'!I48)>12)*1) | G8: =IF(MAX(SUM('Beharry, Akeela'!I14:I27),SUM('Beharry, Akeela'!I30:I43))>60,"Yes","") | H8: =IF(OR(AND(('Beharry, Akeela'!I14+'Beharry, Akeela'!I15)>0,('Beharry, Akeela'!I16+'Beharry, Akeela'!I17)>0,('Beharry, Akeela'!I18+'Beharry, Akeela'!I19)>0,('Beharry, Akeela'!I20+'Beharry, Akeela'!I21)>0,('Beharry, Akeela'!I22+'Beharry, Akeela'!I23)>0,('Beharry, Akeela'!I24+'Beharry, Akeela'!I25)>0,('Beharry, Akeela'!I26+'Beharry, Akeela'!I27)>0),AND(('Beharry, Akeela'!I30+'Beharry, Akeela'!I31)>0,('Beharry, Akeela'!I32+'Beharry, Akeela'!I33)>0,('Beharry, Akeela'!I34+'Beharry, Akeela'!I35)>0,('Beharry, Akeela'!I36+'Beharry, Akeela'!I37)>0,('Beharry, Akeela'!I38+'Beharry, Akeela'!I39)>0,('Beharry, Akeela'!I40+'Beharry, Akeela'!I41)>0,('Beharry, Akeela'!I42+'Beharry, Akeela'!I43)>0)),"Yes","") | I8: =IF('Beharry, Akeela'!N49>40,"Yes","") | J8: =IF(OR(AND(SUM('Beharry, Akeela'!I14:I27)>0,SUM('Beharry, Akeela'!I14:I27)<40),AND(SUM('Beharry, Akeela'!I30:I43)>0,SUM('Beharry, Akeela'!I30:I43)<40)),"Yes","") | K8: =SUMPRODUCT(('Beharry, Akeela'!I14:I48>0)*('Beharry, Akeela'!I14:I48<8)) | L8: =IF('Beharry, Akeela'!Q50<5,"Yes","") | M8: =IF(AND('Beharry, Akeela'!I49>0,'Beharry, Akeela'!I49<80),"Yes","") | N8: =IF(OR(F8>0,G8="Yes",H8="Yes",I8="Yes"),"⚠️ OVERWORK",IF(OR(J8="Yes",K8>0,L8="Yes",M8="Yes"),"🔻 UNDERWORK","✓ OK"))
A9: 5 | B9: Blake, Bevon Natifa | C9: 5113 | D9: ='Blake, Bevon'!I49 | E9: ='Blake, Bevon'!Q50 | F9: =SUMPRODUCT((('Blake, Bevon'!I14+'Blake, Bevon'!I15)>12)*1)+SUMPRODUCT((('Blake, Bevon'!I16+'Blake, Bevon'!I17)>12)*1)+SUMPRODUCT((('Blake, Bevon'!I18+'Blake, Bevon'!I19)>12)*1)+SUMPRODUCT((('Blake, Bevon'!I20+'Blake, Bevon'!I21)>12)*1)+SUMPRODUCT((('Blake, Bevon'!I22+'Blake, Bevon'!I23)>12)*1)+SUMPRODUCT((('Blake, Bevon'!I24+'Blake, Bevon'!I25)>12)*1)+SUMPRODUCT((('Blake, Bevon'!I26+'Blake, Bevon'!I27)>12)*1)+SUMPRODUCT((('Blake, Bevon'!I30+'Blake, Bevon'!I31)>12)*1)+SUMPRODUCT((('Blake, Bevon'!I32+'Blake, Bevon'!I33)>12)*1)+SUMPRODUCT((('Blake, Bevon'!I34+'Blake, Bevon'!I35)>12)*1)+SUMPRODUCT((('Blake, Bevon'!I36+'Blake, Bevon'!I37)>12)*1)+SUMPRODUCT((('Blake, Bevon'!I38+'Blake, Bevon'!I39)>12)*1)+SUMPRODUCT((('Blake, Bevon'!I40+'Blake, Bevon'!I41)>12)*1)+SUMPRODUCT((('Blake, Bevon'!I42+'Blake, Bevon'!I43)>12)*1)+SUMPRODUCT((('Blake, Bevon'!I45+'Blake, Bevon'!I46)>12)*1)+SUMPRODUCT((('Blake, Bevon'!I47+'Blake, Bevon'!I48)>12)*1) | G9: =IF(MAX(SUM('Blake, Bevon'!I14:I27),SUM('Blake, Bevon'!I30:I43))>60,"Yes","") | H9: =IF(OR(AND(('Blake, Bevon'!I14+'Blake, Bevon'!I15)>0,('Blake, Bevon'!I16+'Blake, Bevon'!I17)>0,('Blake, Bevon'!I18+'Blake, Bevon'!I19)>0,('Blake, Bevon'!I20+'Blake, Bevon'!I21)>0,('Blake, Bevon'!I22+'Blake, Bevon'!I23)>0,('Blake, Bevon'!I24+'Blake, Bevon'!I25)>0,('Blake, Bevon'!I26+'Blake, Bevon'!I27)>0),AND(('Blake, Bevon'!I30+'Blake, Bevon'!I31)>0,('Blake, Bevon'!I32+'Blake, Bevon'!I33)>0,('Blake, Bevon'!I34+'Blake, Bevon'!I35)>0,('Blake, Bevon'!I36+'Blake, Bevon'!I37)>0,('Blake, Bevon'!I38+'Blake, Bevon'!I39)>0,('Blake, Bevon'!I40+'Blake, Bevon'!I41)>0,('Blake, Bevon'!I42+'Blake, Bevon'!I43)>0)),"Yes","") | I9: =IF('Blake, Bevon'!N49>40,"Yes","") | J9: =IF(OR(AND(SUM('Blake, Bevon'!I14:I27)>0,SUM('Blake, Bevon'!I14:I27)<40),AND(SUM('Blake, Bevon'!I30:I43)>0,SUM('Blake, Bevon'!I30:I43)<40)),"Yes","") | K9: =SUMPRODUCT(('Blake, Bevon'!I14:I48>0)*('Blake, Bevon'!I14:I48<8)) | L9: =IF('Blake, Bevon'!Q50<5,"Yes","") | M9: =IF(AND('Blake, Bevon'!I49>0,'Blake, Bevon'!I49<80),"Yes","") | N9: =IF(OR(F9>0,G9="Yes",H9="Yes",I9="Yes"),"⚠️ OVERWORK",IF(OR(J9="Yes",K9>0,L9="Yes",M9="Yes"),"🔻 UNDERWORK","✓ OK"))
A10: 6 | B10: Charles, Maisha Renitta | C10: 4031 | D10: ='Charles, Maisha'!I49 | E10: ='Charles, Maisha'!Q50 | F10: =SUMPRODUCT((('Charles, Maisha'!I14+'Charles, Maisha'!I15)>12)*1)+SUMPRODUCT((('Charles, Maisha'!I16+'Charles, Maisha'!I17)>12)*1)+SUMPRODUCT((('Charles, Maisha'!I18+'Charles, Maisha'!I19)>12)*1)+SUMPRODUCT((('Charles, Maisha'!I20+'Charles, Maisha'!I21)>12)*1)+SUMPRODUCT((('Charles, Maisha'!I22+'Charles, Maisha'!I23)>12)*1)+SUMPRODUCT((('Charles, Maisha'!I24+'Charles, Maisha'!I25)>12)*1)+SUMPRODUCT((('Charles, Maisha'!I26+'Charles, Maisha'!I27)>12)*1)+SUMPRODUCT((('Charles, Maisha'!I30+'Charles, Maisha'!I31)>12)*1)+SUMPRODUCT((('Charles, Maisha'!I32+'Charles, Maisha'!I33)>12)*1)+SUMPRODUCT((('Charles, Maisha'!I34+'Charles, Maisha'!I35)>12)*1)+SUMPRODUCT((('Charles, Maisha'!I36+'Charles, Maisha'!I37)>12)*1)+SUMPRODUCT((('Charles, Maisha'!I38+'Charles, Maisha'!I39)>12)*1)+SUMPRODUCT((('Charles, Maisha'!I40+'Charles, Maisha'!I41)>12)*1)+SUMPRODUCT((('Charles, Maisha'!I42+'Charles, Maisha'!I43)>12)*1)+SUMPRODUCT((('Charles, Maisha'!I45+'Charles, Maisha'!I46)>12)*1)+SUMPRODUCT((('Charles, Maisha'!I47+'Charles, Maisha'!I48)>12)*1) | G10: =IF(MAX(SUM('Charles, Maisha'!I14:I27),SUM('Charles, Maisha'!I30:I43))>60,"Yes","") | H10: =IF(OR(AND(('Charles, Maisha'!I14+'Charles, Maisha'!I15)>0,('Charles, Maisha'!I16+'Charles, Maisha'!I17)>0,('Charles, Maisha'!I18+'Charles, Maisha'!I19)>0,('Charles, Maisha'!I20+'Charles, Maisha'!I21)>0,('Charles, Maisha'!I22+'Charles, Maisha'!I23)>0,('Charles, Maisha'!I24+'Charles, Maisha'!I25)>0,('Charles, Maisha'!I26+'Charles, Maisha'!I27)>0),AND(('Charles, Maisha'!I30+'Charles, Maisha'!I31)>0,('Charles, Maisha'!I32+'Charles, Maisha'!I33)>0,('Charles, Maisha'!I34+'Charles, Maisha'!I35)>0,('Charles, Maisha'!I36+'Charles, Maisha'!I37)>0,('Charles, Maisha'!I38+'Charles, Maisha'!I39)>0,('Charles, Maisha'!I40+'Charles, Maisha'!I41)>0,('Charles, Maisha'!I42+'Charles, Maisha'!I43)>0)),"Yes","") | I10: =IF('Charles, Maisha'!N49>40,"Yes","") | J10: =IF(OR(AND(SUM('Charles, Maisha'!I14:I27)>0,SUM('Charles, Maisha'!I14:I27)<40),AND(SUM('Charles, Maisha'!I30:I43)>0,SUM('Charles, Maisha'!I30:I43)<40)),"Yes","") | K10: =SUMPRODUCT(('Charles, Maisha'!I14:I48>0)*('Charles, Maisha'!I14:I48<8)) | L10: =IF('Charles, Maisha'!Q50<5,"Yes","") | M10: =IF(AND('Charles, Maisha'!I49>0,'Charles, Maisha'!I49<80),"Yes","") | N10: =IF(OR(F10>0,G10="Yes",H10="Yes",I10="Yes"),"⚠️ OVERWORK",IF(OR(J10="Yes",K10>0,L10="Yes",M10="Yes"),"🔻 UNDERWORK","✓ OK"))
A11: 7 | B11: Cromwell, Dexter Oliver | C11: 2425 | D11: ='Cromwell, Dexter'!I49 | E11: ='Cromwell, Dexter'!Q50 | F11: =SUMPRODUCT((('Cromwell, Dexter'!I14+'Cromwell, Dexter'!I15)>12)*1)+SUMPRODUCT((('Cromwell, Dexter'!I16+'Cromwell, Dexter'!I17)>12)*1)+SUMPRODUCT((('Cromwell, Dexter'!I18+'Cromwell, Dexter'!I19)>12)*1)+SUMPRODUCT((('Cromwell, Dexter'!I20+'Cromwell, Dexter'!I21)>12)*1)+SUMPRODUCT((('Cromwell, Dexter'!I22+'Cromwell, Dexter'!I23)>12)*1)+SUMPRODUCT((('Cromwell, Dexter'!I24+'Cromwell, Dexter'!I25)>12)*1)+SUMPRODUCT((('Cromwell, Dexter'!I26+'Cromwell, Dexter'!I27)>12)*1)+SUMPRODUCT((('Cromwell, Dexter'!I30+'Cromwell, Dexter'!I31)>12)*1)+SUMPRODUCT((('Cromwell, Dexter'!I32+'Cromwell, Dexter'!I33)>12)*1)+SUMPRODUCT((('Cromwell, Dexter'!I34+'Cromwell, Dexter'!I35)>12)*1)+SUMPRODUCT((('Cromwell, Dexter'!I36+'Cromwell, Dexter'!I37)>12)*1)+SUMPRODUCT((('Cromwell, Dexter'!I38+'Cromwell, Dexter'!I39)>12)*1)+SUMPRODUCT((('Cromwell, Dexter'!I40+'Cromwell, Dexter'!I41)>12)*1)+SUMPRODUCT((('Cromwell, Dexter'!I42+'Cromwell, Dexter'!I43)>12)*1)+SUMPRODUCT((('Cromwell, Dexter'!I45+'Cromwell, Dexter'!I46)>12)*1)+SUMPRODUCT((('Cromwell, Dexter'!I47+'Cromwell, Dexter'!I48)>12)*1) | G11: =IF(MAX(SUM('Cromwell, Dexter'!I14:I27),SUM('Cromwell, Dexter'!I30:I43))>60,"Yes","") | H11: =IF(OR(AND(('Cromwell, Dexter'!I14+'Cromwell, Dexter'!I15)>0,('Cromwell, Dexter'!I16+'Cromwell, Dexter'!I17)>0,('Cromwell, Dexter'!I18+'Cromwell, Dexter'!I19)>0,('Cromwell, Dexter'!I20+'Cromwell, Dexter'!I21)>0,('Cromwell, Dexter'!I22+'Cromwell, Dexter'!I23)>0,('Cromwell, Dexter'!I24+'Cromwell, Dexter'!I25)>0,('Cromwell, Dexter'!I26+'Cromwell, Dexter'!I27)>0),AND(('Cromwell, Dexter'!I30+'Cromwell, Dexter'!I31)>0,('Cromwell, Dexter'!I32+'Cromwell, Dexter'!I33)>0,('Cromwell, Dexter'!I34+'Cromwell, Dexter'!I35)>0,('Cromwell, Dexter'!I36+'Cromwell, Dexter'!I37)>0,('Cromwell, Dexter'!I38+'Cromwell, Dexter'!I39)>0,('Cromwell, Dexter'!I40+'Cromwell, Dexter'!I41)>0,('Cromwell, Dexter'!I42+'Cromwell, Dexter'!I43)>0)),"Yes","") | I11: =IF('Cromwell, Dexter'!N49>40,"Yes","") | J11: =IF(OR(AND(SUM('Cromwell, Dexter'!I14:I27)>0,SUM('Cromwell, Dexter'!I14:I27)<40),AND(SUM('Cromwell, Dexter'!I30:I43)>0,SUM('Cromwell, Dexter'!I30:I43)<40)),"Yes","") | K11: =SUMPRODUCT(('Cromwell, Dexter'!I14:I48>0)*('Cromwell, Dexter'!I14:I48<8)) | L11: =IF('Cromwell, Dexter'!Q50<5,"Yes","") | M11: =IF(AND('Cromwell, Dexter'!I49>0,'Cromwell, Dexter'!I49<80),"Yes","") | N11: =IF(OR(F11>0,G11="Yes",H11="Yes",I11="Yes"),"⚠️ OVERWORK",IF(OR(J11="Yes",K11>0,L11="Yes",M11="Yes"),"🔻 UNDERWORK","✓ OK"))
A12: 8 | B12: Eastman, Dennis Rickford | C12: 5367 | D12: ='Eastman, Dennis'!I49 | E12: ='Eastman, Dennis'!Q50 | F12: =SUMPRODUCT((('Eastman, Dennis'!I14+'Eastman, Dennis'!I15)>12)*1)+SUMPRODUCT((('Eastman, Dennis'!I16+'Eastman, Dennis'!I17)>12)*1)+SUMPRODUCT((('Eastman, Dennis'!I18+'Eastman, Dennis'!I19)>12)*1)+SUMPRODUCT((('Eastman, Dennis'!I20+'Eastman, Dennis'!I21)>12)*1)+SUMPRODUCT((('Eastman, Dennis'!I22+'Eastman, Dennis'!I23)>12)*1)+SUMPRODUCT((('Eastman, Dennis'!I24+'Eastman, Dennis'!I25)>12)*1)+SUMPRODUCT((('Eastman, Dennis'!I26+'Eastman, Dennis'!I27)>12)*1)+SUMPRODUCT((('Eastman, Dennis'!I30+'Eastman, Dennis'!I31)>12)*1)+SUMPRODUCT((('Eastman, Dennis'!I32+'Eastman, Dennis'!I33)>12)*1)+SUMPRODUCT((('Eastman, Dennis'!I34+'Eastman, Dennis'!I35)>12)*1)+SUMPRODUCT((('Eastman, Dennis'!I36+'Eastman, Dennis'!I37)>12)*1)+SUMPRODUCT((('Eastman, Dennis'!I38+'Eastman, Dennis'!I39)>12)*1)+SUMPRODUCT((('Eastman, Dennis'!I40+'Eastman, Dennis'!I41)>12)*1)+SUMPRODUCT((('Eastman, Dennis'!I42+'Eastman, Dennis'!I43)>12)*1)+SUMPRODUCT((('Eastman, Dennis'!I45+'Eastman, Dennis'!I46)>12)*1)+SUMPRODUCT((('Eastman, Dennis'!I47+'Eastman, Dennis'!I48)>12)*1) | G12: =IF(MAX(SUM('Eastman, Dennis'!I14:I27),SUM('Eastman, Dennis'!I30:I43))>60,"Yes","") | H12: =IF(OR(AND(('Eastman, Dennis'!I14+'Eastman, Dennis'!I15)>0,('Eastman, Dennis'!I16+'Eastman, Dennis'!I17)>0,('Eastman, Dennis'!I18+'Eastman, Dennis'!I19)>0,('Eastman, Dennis'!I20+'Eastman, Dennis'!I21)>0,('Eastman, Dennis'!I22+'Eastman, Dennis'!I23)>0,('Eastman, Dennis'!I24+'Eastman, Dennis'!I25)>0,('Eastman, Dennis'!I26+'Eastman, Dennis'!I27)>0),AND(('Eastman, Dennis'!I30+'Eastman, Dennis'!I31)>0,('Eastman, Dennis'!I32+'Eastman, Dennis'!I33)>0,('Eastman, Dennis'!I34+'Eastman, Dennis'!I35)>0,('Eastman, Dennis'!I36+'Eastman, Dennis'!I37)>0,('Eastman, Dennis'!I38+'Eastman, Dennis'!I39)>0,('Eastman, Dennis'!I40+'Eastman, Dennis'!I41)>0,('Eastman, Dennis'!I42+'Eastman, Dennis'!I43)>0)),"Yes","") | I12: =IF('Eastman, Dennis'!N49>40,"Yes","") | J12: =IF(OR(AND(SUM('Eastman, Dennis'!I14:I27)>0,SUM('Eastman, Dennis'!I14:I27)<40),AND(SUM('Eastman, Dennis'!I30:I43)>0,SUM('Eastman, Dennis'!I30:I43)<40)),"Yes","") | K12: =SUMPRODUCT(('Eastman, Dennis'!I14:I48>0)*('Eastman, Dennis'!I14:I48<8)) | L12: =IF('Eastman, Dennis'!Q50<5,"Yes","") | M12: =IF(AND('Eastman, Dennis'!I49>0,'Eastman, Dennis'!I49<80),"Yes","") | N12: =IF(OR(F12>0,G12="Yes",H12="Yes",I12="Yes"),"⚠️ OVERWORK",IF(OR(J12="Yes",K12>0,L12="Yes",M12="Yes"),"🔻 UNDERWORK","✓ OK"))
A13: 9 | B13: Eastman, Dorritte Anita | C13: 5062 | D13: ='Eastman, Dorritte'!I49 | E13: ='Eastman, Dorritte'!Q50 | F13: =SUMPRODUCT((('Eastman, Dorritte'!I14+'Eastman, Dorritte'!I15)>12)*1)+SUMPRODUCT((('Eastman, Dorritte'!I16+'Eastman, Dorritte'!I17)>12)*1)+SUMPRODUCT((('Eastman, Dorritte'!I18+'Eastman, Dorritte'!I19)>12)*1)+SUMPRODUCT((('Eastman, Dorritte'!I20+'Eastman, Dorritte'!I21)>12)*1)+SUMPRODUCT((('Eastman, Dorritte'!I22+'Eastman, Dorritte'!I23)>12)*1)+SUMPRODUCT((('Eastman, Dorritte'!I24+'Eastman, Dorritte'!I25)>12)*1)+SUMPRODUCT((('Eastman, Dorritte'!I26+'Eastman, Dorritte'!I27)>12)*1)+SUMPRODUCT((('Eastman, Dorritte'!I30+'Eastman, Dorritte'!I31)>12)*1)+SUMPRODUCT((('Eastman, Dorritte'!I32+'Eastman, Dorritte'!I33)>12)*1)+SUMPRODUCT((('Eastman, Dorritte'!I34+'Eastman, Dorritte'!I35)>12)*1)+SUMPRODUCT((('Eastman, Dorritte'!I36+'Eastman, Dorritte'!I37)>12)*1)+SUMPRODUCT((('Eastman, Dorritte'!I38+'Eastman, Dorritte'!I39)>12)*1)+SUMPRODUCT((('Eastman, Dorritte'!I40+'Eastman, Dorritte'!I41)>12)*1)+SUMPRODUCT((('Eastman, Dorritte'!I42+'Eastman, Dorritte'!I43)>12)*1)+SUMPRODUCT((('Eastman, Dorritte'!I45+'Eastman, Dorritte'!I46)>12)*1)+SUMPRODUCT((('Eastman, Dorritte'!I47+'Eastman, Dorritte'!I48)>12)*1) | G13: =IF(MAX(SUM('Eastman, Dorritte'!I14:I27),SUM('Eastman, Dorritte'!I30:I43))>60,"Yes","") | H13: =IF(OR(AND(('Eastman, Dorritte'!I14+'Eastman, Dorritte'!I15)>0,('Eastman, Dorritte'!I16+'Eastman, Dorritte'!I17)>0,('Eastman, Dorritte'!I18+'Eastman, Dorritte'!I19)>0,('Eastman, Dorritte'!I20+'Eastman, Dorritte'!I21)>0,('Eastman, Dorritte'!I22+'Eastman, Dorritte'!I23)>0,('Eastman, Dorritte'!I24+'Eastman, Dorritte'!I25)>0,('Eastman, Dorritte'!I26+'Eastman, Dorritte'!I27)>0),AND(('Eastman, Dorritte'!I30+'Eastman, Dorritte'!I31)>0,('Eastman, Dorritte'!I32+'Eastman, Dorritte'!I33)>0,('Eastman, Dorritte'!I34+'Eastman, Dorritte'!I35)>0,('Eastman, Dorritte'!I36+'Eastman, Dorritte'!I37)>0,('Eastman, Dorritte'!I38+'Eastman, Dorritte'!I39)>0,('Eastman, Dorritte'!I40+'Eastman, Dorritte'!I41)>0,('Eastman, Dorritte'!I42+'Eastman, Dorritte'!I43)>0)),"Yes","") | I13: =IF('Eastman, Dorritte'!N49>40,"Yes","") | J13: =IF(OR(AND(SUM('Eastman, Dorritte'!I14:I27)>0,SUM('Eastman, Dorritte'!I14:I27)<40),AND(SUM('Eastman, Dorritte'!I30:I43)>0,SUM('Eastman, Dorritte'!I30:I43)<40)),"Yes","") | K13: =SUMPRODUCT(('Eastman, Dorritte'!I14:I48>0)*('Eastman, Dorritte'!I14:I48<8)) | L13: =IF('Eastman, Dorritte'!Q50<5,"Yes","") | M13: =IF(AND('Eastman, Dorritte'!I49>0,'Eastman, Dorritte'!I49<80),"Yes","") | N13: =IF(OR(F13>0,G13="Yes",H13="Yes",I13="Yes"),"⚠️ OVERWORK",IF(OR(J13="Yes",K13>0,L13="Yes",M13="Yes"),"🔻 UNDERWORK","✓ OK"))
A14: 10 | B14: Grant, Earl | C14: 4087 | D14: ='Grant, Earl'!I49 | E14: ='Grant, Earl'!Q50 | F14: =SUMPRODUCT((('Grant, Earl'!I14+'Grant, Earl'!I15)>12)*1)+SUMPRODUCT((('Grant, Earl'!I16+'Grant, Earl'!I17)>12)*1)+SUMPRODUCT((('Grant, Earl'!I18+'Grant, Earl'!I19)>12)*1)+SUMPRODUCT((('Grant, Earl'!I20+'Grant, Earl'!I21)>12)*1)+SUMPRODUCT((('Grant, Earl'!I22+'Grant, Earl'!I23)>12)*1)+SUMPRODUCT((('Grant, Earl'!I24+'Grant, Earl'!I25)>12)*1)+SUMPRODUCT((('Grant, Earl'!I26+'Grant, Earl'!I27)>12)*1)+SUMPRODUCT((('Grant, Earl'!I30+'Grant, Earl'!I31)>12)*1)+SUMPRODUCT((('Grant, Earl'!I32+'Grant, Earl'!I33)>12)*1)+SUMPRODUCT((('Grant, Earl'!I34+'Grant, Earl'!I35)>12)*1)+SUMPRODUCT((('Grant, Earl'!I36+'Grant, Earl'!I37)>12)*1)+SUMPRODUCT((('Grant, Earl'!I38+'Grant, Earl'!I39)>12)*1)+SUMPRODUCT((('Grant, Earl'!I40+'Grant, Earl'!I41)>12)*1)+SUMPRODUCT((('Grant, Earl'!I42+'Grant, Earl'!I43)>12)*1)+SUMPRODUCT((('Grant, Earl'!I45+'Grant, Earl'!I46)>12)*1)+SUMPRODUCT((('Grant, Earl'!I47+'Grant, Earl'!I48)>12)*1) | G14: =IF(MAX(SUM('Grant, Earl'!I14:I27),SUM('Grant, Earl'!I30:I43))>60,"Yes","") | H14: =IF(OR(AND(('Grant, Earl'!I14+'Grant, Earl'!I15)>0,('Grant, Earl'!I16+'Grant, Earl'!I17)>0,('Grant, Earl'!I18+'Grant, Earl'!I19)>0,('Grant, Earl'!I20+'Grant, Earl'!I21)>0,('Grant, Earl'!I22+'Grant, Earl'!I23)>0,('Grant, Earl'!I24+'Grant, Earl'!I25)>0,('Grant, Earl'!I26+'Grant, Earl'!I27)>0),AND(('Grant, Earl'!I30+'Grant, Earl'!I31)>0,('Grant, Earl'!I32+'Grant, Earl'!I33)>0,('Grant, Earl'!I34+'Grant, Earl'!I35)>0,('Grant, Earl'!I36+'Grant, Earl'!I37)>0,('Grant, Earl'!I38+'Grant, Earl'!I39)>0,('Grant, Earl'!I40+'Grant, Earl'!I41)>0,('Grant, Earl'!I42+'Grant, Earl'!I43)>0)),"Yes","") | I14: =IF('Grant, Earl'!N49>40,"Yes","") | J14: =IF(OR(AND(SUM('Grant, Earl'!I14:I27)>0,SUM('Grant, Earl'!I14:I27)<40),AND(SUM('Grant, Earl'!I30:I43)>0,SUM('Grant, Earl'!I30:I43)<40)),"Yes","") | K14: =SUMPRODUCT(('Grant, Earl'!I14:I48>0)*('Grant, Earl'!I14:I48<8)) | L14: =IF('Grant, Earl'!Q50<5,"Yes","") | M14: =IF(AND('Grant, Earl'!I49>0,'Grant, Earl'!I49<80),"Yes","") | N14: =IF(OR(F14>0,G14="Yes",H14="Yes",I14="Yes"),"⚠️ OVERWORK",IF(OR(J14="Yes",K14>0,L14="Yes",M14="Yes"),"🔻 UNDERWORK","✓ OK"))
A15: 11 | B15: Harry, Dennis Eleazar | C15: 2697 | D15: ='Harry, Dennis'!I49 | E15: ='Harry, Dennis'!Q50 | F15: =SUMPRODUCT((('Harry, Dennis'!I14+'Harry, Dennis'!I15)>12)*1)+SUMPRODUCT((('Harry, Dennis'!I16+'Harry, Dennis'!I17)>12)*1)+SUMPRODUCT((('Harry, Dennis'!I18+'Harry, Dennis'!I19)>12)*1)+SUMPRODUCT((('Harry, Dennis'!I20+'Harry, Dennis'!I21)>12)*1)+SUMPRODUCT((('Harry, Dennis'!I22+'Harry, Dennis'!I23)>12)*1)+SUMPRODUCT((('Harry, Dennis'!I24+'Harry, Dennis'!I25)>12)*1)+SUMPRODUCT((('Harry, Dennis'!I26+'Harry, Dennis'!I27)>12)*1)+SUMPRODUCT((('Harry, Dennis'!I30+'Harry, Dennis'!I31)>12)*1)+SUMPRODUCT((('Harry, Dennis'!I32+'Harry, Dennis'!I33)>12)*1)+SUMPRODUCT((('Harry, Dennis'!I34+'Harry, Dennis'!I35)>12)*1)+SUMPRODUCT((('Harry, Dennis'!I36+'Harry, Dennis'!I37)>12)*1)+SUMPRODUCT((('Harry, Dennis'!I38+'Harry, Dennis'!I39)>12)*1)+SUMPRODUCT((('Harry, Dennis'!I40+'Harry, Dennis'!I41)>12)*1)+SUMPRODUCT((('Harry, Dennis'!I42+'Harry, Dennis'!I43)>12)*1)+SUMPRODUCT((('Harry, Dennis'!I45+'Harry, Dennis'!I46)>12)*1)+SUMPRODUCT((('Harry, Dennis'!I47+'Harry, Dennis'!I48)>12)*1) | G15: =IF(MAX(SUM('Harry, Dennis'!I14:I27),SUM('Harry, Dennis'!I30:I43))>60,"Yes","") | H15: =IF(OR(AND(('Harry, Dennis'!I14+'Harry, Dennis'!I15)>0,('Harry, Dennis'!I16+'Harry, Dennis'!I17)>0,('Harry, Dennis'!I18+'Harry, Dennis'!I19)>0,('Harry, Dennis'!I20+'Harry, Dennis'!I21)>0,('Harry, Dennis'!I22+'Harry, Dennis'!I23)>0,('Harry, Dennis'!I24+'Harry, Dennis'!I25)>0,('Harry, Dennis'!I26+'Harry, Dennis'!I27)>0),AND(('Harry, Dennis'!I30+'Harry, Dennis'!I31)>0,('Harry, Dennis'!I32+'Harry, Dennis'!I33)>0,('Harry, Dennis'!I34+'Harry, Dennis'!I35)>0,('Harry, Dennis'!I36+'Harry, Dennis'!I37)>0,('Harry, Dennis'!I38+'Harry, Dennis'!I39)>0,('Harry, Dennis'!I40+'Harry, Dennis'!I41)>0,('Harry, Dennis'!I42+'Harry, Dennis'!I43)>0)),"Yes","") | I15: =IF('Harry, Dennis'!N49>40,"Yes","") | J15: =IF(OR(AND(SUM('Harry, Dennis'!I14:I27)>0,SUM('Harry, Dennis'!I14:I27)<40),AND(SUM('Harry, Dennis'!I30:I43)>0,SUM('Harry, Dennis'!I30:I43)<40)),"Yes","") | K15: =SUMPRODUCT(('Harry, Dennis'!I14:I48>0)*('Harry, Dennis'!I14:I48<8)) | L15: =IF('Harry, Dennis'!Q50<5,"Yes","") | M15: =IF(AND('Harry, Dennis'!I49>0,'Harry, Dennis'!I49<80),"Yes","") | N15: =IF(OR(F15>0,G15="Yes",H15="Yes",I15="Yes"),"⚠️ OVERWORK",IF(OR(J15="Yes",K15>0,L15="Yes",M15="Yes"),"🔻 UNDERWORK","✓ OK"))
A16: 12 | B16: Hector, Aaliyah Anastacia | C16: 5509 | D16: ='Hector, Aaliyah'!I49 | E16: ='Hector, Aaliyah'!Q50 | F16: =SUMPRODUCT((('Hector, Aaliyah'!I14+'Hector, Aaliyah'!I15)>12)*1)+SUMPRODUCT((('Hector, Aaliyah'!I16+'Hector, Aaliyah'!I17)>12)*1)+SUMPRODUCT((('Hector, Aaliyah'!I18+'Hector, Aaliyah'!I19)>12)*1)+SUMPRODUCT((('Hector, Aaliyah'!I20+'Hector, Aaliyah'!I21)>12)*1)+SUMPRODUCT((('Hector, Aaliyah'!I22+'Hector, Aaliyah'!I23)>12)*1)+SUMPRODUCT((('Hector, Aaliyah'!I24+'Hector, Aaliyah'!I25)>12)*1)+SUMPRODUCT((('Hector, Aaliyah'!I26+'Hector, Aaliyah'!I27)>12)*1)+SUMPRODUCT((('Hector, Aaliyah'!I30+'Hector, Aaliyah'!I31)>12)*1)+SUMPRODUCT((('Hector, Aaliyah'!I32+'Hector, Aaliyah'!I33)>12)*1)+SUMPRODUCT((('Hector, Aaliyah'!I34+'Hector, Aaliyah'!I35)>12)*1)+SUMPRODUCT((('Hector, Aaliyah'!I36+'Hector, Aaliyah'!I37)>12)*1)+SUMPRODUCT((('Hector, Aaliyah'!I38+'Hector, Aaliyah'!I39)>12)*1)+SUMPRODUCT((('Hector, Aaliyah'!I40+'Hector, Aaliyah'!I41)>12)*1)+SUMPRODUCT((('Hector, Aaliyah'!I42+'Hector, Aaliyah'!I43)>12)*1)+SUMPRODUCT((('Hector, Aaliyah'!I45+'Hector, Aaliyah'!I46)>12)*1)+SUMPRODUCT((('Hector, Aaliyah'!I47+'Hector, Aaliyah'!I48)>12)*1) | G16: =IF(MAX(SUM('Hector, Aaliyah'!I14:I27),SUM('Hector, Aaliyah'!I30:I43))>60,"Yes","") | H16: =IF(OR(AND(('Hector, Aaliyah'!I14+'Hector, Aaliyah'!I15)>0,('Hector, Aaliyah'!I16+'Hector, Aaliyah'!I17)>0,('Hector, Aaliyah'!I18+'Hector, Aaliyah'!I19)>0,('Hector, Aaliyah'!I20+'Hector, Aaliyah'!I21)>0,('Hector, Aaliyah'!I22+'Hector, Aaliyah'!I23)>0,('Hector, Aaliyah'!I24+'Hector, Aaliyah'!I25)>0,('Hector, Aaliyah'!I26+'Hector, Aaliyah'!I27)>0),AND(('Hector, Aaliyah'!I30+'Hector, Aaliyah'!I31)>0,('Hector, Aaliyah'!I32+'Hector, Aaliyah'!I33)>0,('Hector, Aaliyah'!I34+'Hector, Aaliyah'!I35)>0,('Hector, Aaliyah'!I36+'Hector, Aaliyah'!I37)>0,('Hector, Aaliyah'!I38+'Hector, Aaliyah'!I39)>0,('Hector, Aaliyah'!I40+'Hector, Aaliyah'!I41)>0,('Hector, Aaliyah'!I42+'Hector, Aaliyah'!I43)>0)),"Yes","") | I16: =IF('Hector, Aaliyah'!N49>40,"Yes","") | J16: =IF(OR(AND(SUM('Hector, Aaliyah'!I14:I27)>0,SUM('Hector, Aaliyah'!I14:I27)<40),AND(SUM('Hector, Aaliyah'!I30:I43)>0,SUM('Hector, Aaliyah'!I30:I43)<40)),"Yes","") | K16: =SUMPRODUCT(('Hector, Aaliyah'!I14:I48>0)*('Hector, Aaliyah'!I14:I48<8)) | L16: =IF('Hector, Aaliyah'!Q50<5,"Yes","") | M16: =IF(AND('Hector, Aaliyah'!I49>0,'Hector, Aaliyah'!I49<80),"Yes","") | N16: =IF(OR(F16>0,G16="Yes",H16="Yes",I16="Yes"),"⚠️ OVERWORK",IF(OR(J16="Yes",K16>0,L16="Yes",M16="Yes"),"🔻 UNDERWORK","✓ OK"))
A17: 13 | B17: Hector, Onicka Felicity | C17: 5508 | D17: ='Hector, Onicka'!I49 | E17: ='Hector, Onicka'!Q50 | F17: =SUMPRODUCT((('Hector, Onicka'!I14+'Hector, Onicka'!I15)>12)*1)+SUMPRODUCT((('Hector, Onicka'!I16+'Hector, Onicka'!I17)>12)*1)+SUMPRODUCT((('Hector, Onicka'!I18+'Hector, Onicka'!I19)>12)*1)+SUMPRODUCT((('Hector, Onicka'!I20+'Hector, Onicka'!I21)>12)*1)+SUMPRODUCT((('Hector, Onicka'!I22+'Hector, Onicka'!I23)>12)*1)+SUMPRODUCT((('Hector, Onicka'!I24+'Hector, Onicka'!I25)>12)*1)+SUMPRODUCT((('Hector, Onicka'!I26+'Hector, Onicka'!I27)>12)*1)+SUMPRODUCT((('Hector, Onicka'!I30+'Hector, Onicka'!I31)>12)*1)+SUMPRODUCT((('Hector, Onicka'!I32+'Hector, Onicka'!I33)>12)*1)+SUMPRODUCT((('Hector, Onicka'!I34+'Hector, Onicka'!I35)>12)*1)+SUMPRODUCT((('Hector, Onicka'!I36+'Hector, Onicka'!I37)>12)*1)+SUMPRODUCT((('Hector, Onicka'!I38+'Hector, Onicka'!I39)>12)*1)+SUMPRODUCT((('Hector, Onicka'!I40+'Hector, Onicka'!I41)>12)*1)+SUMPRODUCT((('Hector, Onicka'!I42+'Hector, Onicka'!I43)>12)*1)+SUMPRODUCT((('Hector, Onicka'!I45+'Hector, Onicka'!I46)>12)*1)+SUMPRODUCT((('Hector, Onicka'!I47+'Hector, Onicka'!I48)>12)*1) | G17: =IF(MAX(SUM('Hector, Onicka'!I14:I27),SUM('Hector, Onicka'!I30:I43))>60,"Yes","") | H17: =IF(OR(AND(('Hector, Onicka'!I14+'Hector, Onicka'!I15)>0,('Hector, Onicka'!I16+'Hector, Onicka'!I17)>0,('Hector, Onicka'!I18+'Hector, Onicka'!I19)>0,('Hector, Onicka'!I20+'Hector, Onicka'!I21)>0,('Hector, Onicka'!I22+'Hector, Onicka'!I23)>0,('Hector, Onicka'!I24+'Hector, Onicka'!I25)>0,('Hector, Onicka'!I26+'Hector, Onicka'!I27)>0),AND(('Hector, Onicka'!I30+'Hector, Onicka'!I31)>0,('Hector, Onicka'!I32+'Hector, Onicka'!I33)>0,('Hector, Onicka'!I34+'Hector, Onicka'!I35)>0,('Hector, Onicka'!I36+'Hector, Onicka'!I37)>0,('Hector, Onicka'!I38+'Hector, Onicka'!I39)>0,('Hector, Onicka'!I40+'Hector, Onicka'!I41)>0,('Hector, Onicka'!I42+'Hector, Onicka'!I43)>0)),"Yes","") | I17: =IF('Hector, Onicka'!N49>40,"Yes","") | J17: =IF(OR(AND(SUM('Hector, Onicka'!I14:I27)>0,SUM('Hector, Onicka'!I14:I27)<40),AND(SUM('Hector, Onicka'!I30:I43)>0,SUM('Hector, Onicka'!I30:I43)<40)),"Yes","") | K17: =SUMPRODUCT(('Hector, Onicka'!I14:I48>0)*('Hector, Onicka'!I14:I48<8)) | L17: =IF('Hector, Onicka'!Q50<5,"Yes","") | M17: =IF(AND('Hector, Onicka'!I49>0,'Hector, Onicka'!I49<80),"Yes","") | N17: =IF(OR(F17>0,G17="Yes",H17="Yes",I17="Yes"),"⚠️ OVERWORK",IF(OR(J17="Yes",K17>0,L17="Yes",M17="Yes"),"🔻 UNDERWORK","✓ OK"))
A18: 14 | B18: Inniss, Euci Patrice | C18: 4959 | D18: ='Inniss, Euci'!I49 | E18: ='Inniss, Euci'!Q50 | F18: =SUMPRODUCT((('Inniss, Euci'!I14+'Inniss, Euci'!I15)>12)*1)+SUMPRODUCT((('Inniss, Euci'!I16+'Inniss, Euci'!I17)>12)*1)+SUMPRODUCT((('Inniss, Euci'!I18+'Inniss, Euci'!I19)>12)*1)+SUMPRODUCT((('Inniss, Euci'!I20+'Inniss, Euci'!I21)>12)*1)+SUMPRODUCT((('Inniss, Euci'!I22+'Inniss, Euci'!I23)>12)*1)+SUMPRODUCT((('Inniss, Euci'!I24+'Inniss, Euci'!I25)>12)*1)+SUMPRODUCT((('Inniss, Euci'!I26+'Inniss, Euci'!I27)>12)*1)+SUMPRODUCT((('Inniss, Euci'!I30+'Inniss, Euci'!I31)>12)*1)+SUMPRODUCT((('Inniss, Euci'!I32+'Inniss, Euci'!I33)>12)*1)+SUMPRODUCT((('Inniss, Euci'!I34+'Inniss, Euci'!I35)>12)*1)+SUMPRODUCT((('Inniss, Euci'!I36+'Inniss, Euci'!I37)>12)*1)+SUMPRODUCT((('Inniss, Euci'!I38+'Inniss, Euci'!I39)>12)*1)+SUMPRODUCT((('Inniss, Euci'!I40+'Inniss, Euci'!I41)>12)*1)+SUMPRODUCT((('Inniss, Euci'!I42+'Inniss, Euci'!I43)>12)*1)+SUMPRODUCT((('Inniss, Euci'!I45+'Inniss, Euci'!I46)>12)*1)+SUMPRODUCT((('Inniss, Euci'!I47+'Inniss, Euci'!I48)>12)*1) | G18: =IF(MAX(SUM('Inniss, Euci'!I14:I27),SUM('Inniss, Euci'!I30:I43))>60,"Yes","") | H18: =IF(OR(AND(('Inniss, Euci'!I14+'Inniss, Euci'!I15)>0,('Inniss, Euci'!I16+'Inniss, Euci'!I17)>0,('Inniss, Euci'!I18+'Inniss, Euci'!I19)>0,('Inniss, Euci'!I20+'Inniss, Euci'!I21)>0,('Inniss, Euci'!I22+'Inniss, Euci'!I23)>0,('Inniss, Euci'!I24+'Inniss, Euci'!I25)>0,('Inniss, Euci'!I26+'Inniss, Euci'!I27)>0),AND(('Inniss, Euci'!I30+'Inniss, Euci'!I31)>0,('Inniss, Euci'!I32+'Inniss, Euci'!I33)>0,('Inniss, Euci'!I34+'Inniss, Euci'!I35)>0,('Inniss, Euci'!I36+'Inniss, Euci'!I37)>0,('Inniss, Euci'!I38+'Inniss, Euci'!I39)>0,('Inniss, Euci'!I40+'Inniss, Euci'!I41)>0,('Inniss, Euci'!I42+'Inniss, Euci'!I43)>0)),"Yes","") | I18: =IF('Inniss, Euci'!N49>40,"Yes","") | J18: =IF(OR(AND(SUM('Inniss, Euci'!I14:I27)>0,SUM('Inniss, Euci'!I14:I27)<40),AND(SUM('Inniss, Euci'!I30:I43)>0,SUM('Inniss, Euci'!I30:I43)<40)),"Yes","") | K18: =SUMPRODUCT(('Inniss, Euci'!I14:I48>0)*('Inniss, Euci'!I14:I48<8)) | L18: =IF('Inniss, Euci'!Q50<5,"Yes","") | M18: =IF(AND('Inniss, Euci'!I49>0,'Inniss, Euci'!I49<80),"Yes","") | N18: =IF(OR(F18>0,G18="Yes",H18="Yes",I18="Yes"),"⚠️ OVERWORK",IF(OR(J18="Yes",K18>0,L18="Yes",M18="Yes"),"🔻 UNDERWORK","✓ OK"))
A19: 15 | B19: Khan, Ahmad | C19: 3219 | D19: ='Khan, Ahmad'!I49 | E19: ='Khan, Ahmad'!Q50 | F19: =SUMPRODUCT((('Khan, Ahmad'!I14+'Khan, Ahmad'!I15)>12)*1)+SUMPRODUCT((('Khan, Ahmad'!I16+'Khan, Ahmad'!I17)>12)*1)+SUMPRODUCT((('Khan, Ahmad'!I18+'Khan, Ahmad'!I19)>12)*1)+SUMPRODUCT((('Khan, Ahmad'!I20+'Khan, Ahmad'!I21)>12)*1)+SUMPRODUCT((('Khan, Ahmad'!I22+'Khan, Ahmad'!I23)>12)*1)+SUMPRODUCT((('Khan, Ahmad'!I24+'Khan, Ahmad'!I25)>12)*1)+SUMPRODUCT((('Khan, Ahmad'!I26+'Khan, Ahmad'!I27)>12)*1)+SUMPRODUCT((('Khan, Ahmad'!I30+'Khan, Ahmad'!I31)>12)*1)+SUMPRODUCT((('Khan, Ahmad'!I32+'Khan, Ahmad'!I33)>12)*1)+SUMPRODUCT((('Khan, Ahmad'!I34+'Khan, Ahmad'!I35)>12)*1)+SUMPRODUCT((('Khan, Ahmad'!I36+'Khan, Ahmad'!I37)>12)*1)+SUMPRODUCT((('Khan, Ahmad'!I38+'Khan, Ahmad'!I39)>12)*1)+SUMPRODUCT((('Khan, Ahmad'!I40+'Khan, Ahmad'!I41)>12)*1)+SUMPRODUCT((('Khan, Ahmad'!I42+'Khan, Ahmad'!I43)>12)*1)+SUMPRODUCT((('Khan, Ahmad'!I45+'Khan, Ahmad'!I46)>12)*1)+SUMPRODUCT((('Khan, Ahmad'!I47+'Khan, Ahmad'!I48)>12)*1) | G19: =IF(MAX(SUM('Khan, Ahmad'!I14:I27),SUM('Khan, Ahmad'!I30:I43))>60,"Yes","") | H19: =IF(OR(AND(('Khan, Ahmad'!I14+'Khan, Ahmad'!I15)>0,('Khan, Ahmad'!I16+'Khan, Ahmad'!I17)>0,('Khan, Ahmad'!I18+'Khan, Ahmad'!I19)>0,('Khan, Ahmad'!I20+'Khan, Ahmad'!I21)>0,('Khan, Ahmad'!I22+'Khan, Ahmad'!I23)>0,('Khan, Ahmad'!I24+'Khan, Ahmad'!I25)>0,('Khan, Ahmad'!I26+'Khan, Ahmad'!I27)>0),AND(('Khan, Ahmad'!I30+'Khan, Ahmad'!I31)>0,('Khan, Ahmad'!I32+'Khan, Ahmad'!I33)>0,('Khan, Ahmad'!I34+'Khan, Ahmad'!I35)>0,('Khan, Ahmad'!I36+'Khan, Ahmad'!I37)>0,('Khan, Ahmad'!I38+'Khan, Ahmad'!I39)>0,('Khan, Ahmad'!I40+'Khan, Ahmad'!I41)>0,('Khan, Ahmad'!I42+'Khan, Ahmad'!I43)>0)),"Yes","") | I19: =IF('Khan, Ahmad'!N49>40,"Yes","") | J19: =IF(OR(AND(SUM('Khan, Ahmad'!I14:I27)>0,SUM('Khan, Ahmad'!I14:I27)<40),AND(SUM('Khan, Ahmad'!I30:I43)>0,SUM('Khan, Ahmad'!I30:I43)<40)),"Yes","") | K19: =SUMPRODUCT(('Khan, Ahmad'!I14:I48>0)*('Khan, Ahmad'!I14:I48<8)) | L19: =IF('Khan, Ahmad'!Q50<5,"Yes","") | M19: =IF(AND('Khan, Ahmad'!I49>0,'Khan, Ahmad'!I49<80),"Yes","") | N19: =IF(OR(F19>0,G19="Yes",H19="Yes",I19="Yes"),"⚠️ OVERWORK",IF(OR(J19="Yes",K19>0,L19="Yes",M19="Yes"),"🔻 UNDERWORK","✓ OK"))
A20: 16 | B20: Lawrence, Stephen Rawle | C20: 5134 | D20: ='Lawrence, Stephen'!I49 | E20: ='Lawrence, Stephen'!Q50 | F20: =SUMPRODUCT((('Lawrence, Stephen'!I14+'Lawrence, Stephen'!I15)>12)*1)+SUMPRODUCT((('Lawrence, Stephen'!I16+'Lawrence, Stephen'!I17)>12)*1)+SUMPRODUCT((('Lawrence, Stephen'!I18+'Lawrence, Stephen'!I19)>12)*1)+SUMPRODUCT((('Lawrence, Stephen'!I20+'Lawrence, Stephen'!I21)>12)*1)+SUMPRODUCT((('Lawrence, Stephen'!I22+'Lawrence, Stephen'!I23)>12)*1)+SUMPRODUCT((('Lawrence, Stephen'!I24+'Lawrence, Stephen'!I25)>12)*1)+SUMPRODUCT((('Lawrence, Stephen'!I26+'Lawrence, Stephen'!I27)>12)*1)+SUMPRODUCT((('Lawrence, Stephen'!I30+'Lawrence, Stephen'!I31)>12)*1)+SUMPRODUCT((('Lawrence, Stephen'!I32+'Lawrence, Stephen'!I33)>12)*1)+SUMPRODUCT((('Lawrence, Stephen'!I34+'Lawrence, Stephen'!I35)>12)*1)+SUMPRODUCT((('Lawrence, Stephen'!I36+'Lawrence, Stephen'!I37)>12)*1)+SUMPRODUCT((('Lawrence, Stephen'!I38+'Lawrence, Stephen'!I39)>12)*1)+SUMPRODUCT((('Lawrence, Stephen'!I40+'Lawrence, Stephen'!I41)>12)*1)+SUMPRODUCT((('Lawrence, Stephen'!I42+'Lawrence, Stephen'!I43)>12)*1)+SUMPRODUCT((('Lawrence, Stephen'!I45+'Lawrence, Stephen'!I46)>12)*1)+SUMPRODUCT((('Lawrence, Stephen'!I47+'Lawrence, Stephen'!I48)>12)*1) | G20: =IF(MAX(SUM('Lawrence, Stephen'!I14:I27),SUM('Lawrence, Stephen'!I30:I43))>60,"Yes","") | H20: =IF(OR(AND(('Lawrence, Stephen'!I14+'Lawrence, Stephen'!I15)>0,('Lawrence, Stephen'!I16+'Lawrence, Stephen'!I17)>0,('Lawrence, Stephen'!I18+'Lawrence, Stephen'!I19)>0,('Lawrence, Stephen'!I20+'Lawrence, Stephen'!I21)>0,('Lawrence, Stephen'!I22+'Lawrence, Stephen'!I23)>0,('Lawrence, Stephen'!I24+'Lawrence, Stephen'!I25)>0,('Lawrence, Stephen'!I26+'Lawrence, Stephen'!I27)>0),AND(('Lawrence, Stephen'!I30+'Lawrence, Stephen'!I31)>0,('Lawrence, Stephen'!I32+'Lawrence, Stephen'!I33)>0,('Lawrence, Stephen'!I34+'Lawrence, Stephen'!I35)>0,('Lawrence, Stephen'!I36+'Lawrence, Stephen'!I37)>0,('Lawrence, Stephen'!I38+'Lawrence, Stephen'!I39)>0,('Lawrence, Stephen'!I40+'Lawrence, Stephen'!I41)>0,('Lawrence, Stephen'!I42+'Lawrence, Stephen'!I43)>0)),"Yes","") | I20: =IF('Lawrence, Stephen'!N49>40,"Yes","") | J20: =IF(OR(AND(SUM('Lawrence, Stephen'!I14:I27)>0,SUM('Lawrence, Stephen'!I14:I27)<40),AND(SUM('Lawrence, Stephen'!I30:I43)>0,SUM('Lawrence, Stephen'!I30:I43)<40)),"Yes","") | K20: =SUMPRODUCT(('Lawrence, Stephen'!I14:I48>0)*('Lawrence, Stephen'!I14:I48<8)) | L20: =IF('Lawrence, Stephen'!Q50<5,"Yes","") | M20: =IF(AND('Lawrence, Stephen'!I49>0,'Lawrence, Stephen'!I49<80),"Yes","") | N20: =IF(OR(F20>0,G20="Yes",H20="Yes",I20="Yes"),"⚠️ OVERWORK",IF(OR(J20="Yes",K20>0,L20="Yes",M20="Yes"),"🔻 UNDERWORK","✓ OK"))
A21: 17 | B21: Lawson, Delicia Alicia | C21: 4465 | D21: ='Lawson, Delicia'!I49 | E21: ='Lawson, Delicia'!Q50 | F21: =SUMPRODUCT((('Lawson, Delicia'!I14+'Lawson, Delicia'!I15)>12)*1)+SUMPRODUCT((('Lawson, Delicia'!I16+'Lawson, Delicia'!I17)>12)*1)+SUMPRODUCT((('Lawson, Delicia'!I18+'Lawson, Delicia'!I19)>12)*1)+SUMPRODUCT((('Lawson, Delicia'!I20+'Lawson, Delicia'!I21)>12)*1)+SUMPRODUCT((('Lawson, Delicia'!I22+'Lawson, Delicia'!I23)>12)*1)+SUMPRODUCT((('Lawson, Delicia'!I24+'Lawson, Delicia'!I25)>12)*1)+SUMPRODUCT((('Lawson, Delicia'!I26+'Lawson, Delicia'!I27)>12)*1)+SUMPRODUCT((('Lawson, Delicia'!I30+'Lawson, Delicia'!I31)>12)*1)+SUMPRODUCT((('Lawson, Delicia'!I32+'Lawson, Delicia'!I33)>12)*1)+SUMPRODUCT((('Lawson, Delicia'!I34+'Lawson, Delicia'!I35)>12)*1)+SUMPRODUCT((('Lawson, Delicia'!I36+'Lawson, Delicia'!I37)>12)*1)+SUMPRODUCT((('Lawson, Delicia'!I38+'Lawson, Delicia'!I39)>12)*1)+SUMPRODUCT((('Lawson, Delicia'!I40+'Lawson, Delicia'!I41)>12)*1)+SUMPRODUCT((('Lawson, Delicia'!I42+'Lawson, Delicia'!I43)>12)*1)+SUMPRODUCT((('Lawson, Delicia'!I45+'Lawson, Delicia'!I46)>12)*1)+SUMPRODUCT((('Lawson, Delicia'!I47+'Lawson, Delicia'!I48)>12)*1) | G21: =IF(MAX(SUM('Lawson, Delicia'!I14:I27),SUM('Lawson, Delicia'!I30:I43))>60,"Yes","") | H21: =IF(OR(AND(('Lawson, Delicia'!I14+'Lawson, Delicia'!I15)>0,('Lawson, Delicia'!I16+'Lawson, Delicia'!I17)>0,('Lawson, Delicia'!I18+'Lawson, Delicia'!I19)>0,('Lawson, Delicia'!I20+'Lawson, Delicia'!I21)>0,('Lawson, Delicia'!I22+'Lawson, Delicia'!I23)>0,('Lawson, Delicia'!I24+'Lawson, Delicia'!I25)>0,('Lawson, Delicia'!I26+'Lawson, Delicia'!I27)>0),AND(('Lawson, Delicia'!I30+'Lawson, Delicia'!I31)>0,('Lawson, Delicia'!I32+'Lawson, Delicia'!I33)>0,('Lawson, Delicia'!I34+'Lawson, Delicia'!I35)>0,('Lawson, Delicia'!I36+'Lawson, Delicia'!I37)>0,('Lawson, Delicia'!I38+'Lawson, Delicia'!I39)>0,('Lawson, Delicia'!I40+'Lawson, Delicia'!I41)>0,('Lawson, Delicia'!I42+'Lawson, Delicia'!I43)>0)),"Yes","") | I21: =IF('Lawson, Delicia'!N49>40,"Yes","") | J21: =IF(OR(AND(SUM('Lawson, Delicia'!I14:I27)>0,SUM('Lawson, Delicia'!I14:I27)<40),AND(SUM('Lawson, Delicia'!I30:I43)>0,SUM('Lawson, Delicia'!I30:I43)<40)),"Yes","") | K21: =SUMPRODUCT(('Lawson, Delicia'!I14:I48>0)*('Lawson, Delicia'!I14:I48<8)) | L21: =IF('Lawson, Delicia'!Q50<5,"Yes","") | M21: =IF(AND('Lawson, Delicia'!I49>0,'Lawson, Delicia'!I49<80),"Yes","") | N21: =IF(OR(F21>0,G21="Yes",H21="Yes",I21="Yes"),"⚠️ OVERWORK",IF(OR(J21="Yes",K21>0,L21="Yes",M21="Yes"),"🔻 UNDERWORK","✓ OK"))
A22: 18 | B22: Lewis, Tahandica Fennela | C22: 3767 | D22: ='Lewis, Tahandica'!I49 | E22: ='Lewis, Tahandica'!Q50 | F22: =SUMPRODUCT((('Lewis, Tahandica'!I14+'Lewis, Tahandica'!I15)>12)*1)+SUMPRODUCT((('Lewis, Tahandica'!I16+'Lewis, Tahandica'!I17)>12)*1)+SUMPRODUCT((('Lewis, Tahandica'!I18+'Lewis, Tahandica'!I19)>12)*1)+SUMPRODUCT((('Lewis, Tahandica'!I20+'Lewis, Tahandica'!I21)>12)*1)+SUMPRODUCT((('Lewis, Tahandica'!I22+'Lewis, Tahandica'!I23)>12)*1)+SUMPRODUCT((('Lewis, Tahandica'!I24+'Lewis, Tahandica'!I25)>12)*1)+SUMPRODUCT((('Lewis, Tahandica'!I26+'Lewis, Tahandica'!I27)>12)*1)+SUMPRODUCT((('Lewis, Tahandica'!I30+'Lewis, Tahandica'!I31)>12)*1)+SUMPRODUCT((('Lewis, Tahandica'!I32+'Lewis, Tahandica'!I33)>12)*1)+SUMPRODUCT((('Lewis, Tahandica'!I34+'Lewis, Tahandica'!I35)>12)*1)+SUMPRODUCT((('Lewis, Tahandica'!I36+'Lewis, Tahandica'!I37)>12)*1)+SUMPRODUCT((('Lewis, Tahandica'!I38+'Lewis, Tahandica'!I39)>12)*1)+SUMPRODUCT((('Lewis, Tahandica'!I40+'Lewis, Tahandica'!I41)>12)*1)+SUMPRODUCT((('Lewis, Tahandica'!I42+'Lewis, Tahandica'!I43)>12)*1)+SUMPRODUCT((('Lewis, Tahandica'!I45+'Lewis, Tahandica'!I46)>12)*1)+SUMPRODUCT((('Lewis, Tahandica'!I47+'Lewis, Tahandica'!I48)>12)*1) | G22: =IF(MAX(SUM('Lewis, Tahandica'!I14:I27),SUM('Lewis, Tahandica'!I30:I43))>60,"Yes","") | H22: =IF(OR(AND(('Lewis, Tahandica'!I14+'Lewis, Tahandica'!I15)>0,('Lewis, Tahandica'!I16+'Lewis, Tahandica'!I17)>0,('Lewis, Tahandica'!I18+'Lewis, Tahandica'!I19)>0,('Lewis, Tahandica'!I20+'Lewis, Tahandica'!I21)>0,('Lewis, Tahandica'!I22+'Lewis, Tahandica'!I23)>0,('Lewis, Tahandica'!I24+'Lewis, Tahandica'!I25)>0,('Lewis, Tahandica'!I26+'Lewis, Tahandica'!I27)>0),AND(('Lewis, Tahandica'!I30+'Lewis, Tahandica'!I31)>0,('Lewis, Tahandica'!I32+'Lewis, Tahandica'!I33)>0,('Lewis, Tahandica'!I34+'Lewis, Tahandica'!I35)>0,('Lewis, Tahandica'!I36+'Lewis, Tahandica'!I37)>0,('Lewis, Tahandica'!I38+'Lewis, Tahandica'!I39)>0,('Lewis, Tahandica'!I40+'Lewis, Tahandica'!I41)>0,('Lewis, Tahandica'!I42+'Lewis, Tahandica'!I43)>0)),"Yes","") | I22: =IF('Lewis, Tahandica'!N49>40,"Yes","") | J22: =IF(OR(AND(SUM('Lewis, Tahandica'!I14:I27)>0,SUM('Lewis, Tahandica'!I14:I27)<40),AND(SUM('Lewis, Tahandica'!I30:I43)>0,SUM('Lewis, Tahandica'!I30:I43)<40)),"Yes","") | K22: =SUMPRODUCT(('Lewis, Tahandica'!I14:I48>0)*('Lewis, Tahandica'!I14:I48<8)) | L22: =IF('Lewis, Tahandica'!Q50<5,"Yes","") | M22: =IF(AND('Lewis, Tahandica'!I49>0,'Lewis, Tahandica'!I49<80),"Yes","") | N22: =IF(OR(F22>0,G22="Yes",H22="Yes",I22="Yes"),"⚠️ OVERWORK",IF(OR(J22="Yes",K22>0,L22="Yes",M22="Yes"),"🔻 UNDERWORK","✓ OK"))
A23: 19 | B23: Nelson, Keshia Andrea | C23: 2744 | D23: ='Nelson, Keshia'!I49 | E23: ='Nelson, Keshia'!Q50 | F23: =SUMPRODUCT((('Nelson, Keshia'!I14+'Nelson, Keshia'!I15)>12)*1)+SUMPRODUCT((('Nelson, Keshia'!I16+'Nelson, Keshia'!I17)>12)*1)+SUMPRODUCT((('Nelson, Keshia'!I18+'Nelson, Keshia'!I19)>12)*1)+SUMPRODUCT((('Nelson, Keshia'!I20+'Nelson, Keshia'!I21)>12)*1)+SUMPRODUCT((('Nelson, Keshia'!I22+'Nelson, Keshia'!I23)>12)*1)+SUMPRODUCT((('Nelson, Keshia'!I24+'Nelson, Keshia'!I25)>12)*1)+SUMPRODUCT((('Nelson, Keshia'!I26+'Nelson, Keshia'!I27)>12)*1)+SUMPRODUCT((('Nelson, Keshia'!I30+'Nelson, Keshia'!I31)>12)*1)+SUMPRODUCT((('Nelson, Keshia'!I32+'Nelson, Keshia'!I33)>12)*1)+SUMPRODUCT((('Nelson, Keshia'!I34+'Nelson, Keshia'!I35)>12)*1)+SUMPRODUCT((('Nelson, Keshia'!I36+'Nelson, Keshia'!I37)>12)*1)+SUMPRODUCT((('Nelson, Keshia'!I38+'Nelson, Keshia'!I39)>12)*1)+SUMPRODUCT((('Nelson, Keshia'!I40+'Nelson, Keshia'!I41)>12)*1)+SUMPRODUCT((('Nelson, Keshia'!I42+'Nelson, Keshia'!I43)>12)*1)+SUMPRODUCT((('Nelson, Keshia'!I45+'Nelson, Keshia'!I46)>12)*1)+SUMPRODUCT((('Nelson, Keshia'!I47+'Nelson, Keshia'!I48)>12)*1) | G23: =IF(MAX(SUM('Nelson, Keshia'!I14:I27),SUM('Nelson, Keshia'!I30:I43))>60,"Yes","") | H23: =IF(OR(AND(('Nelson, Keshia'!I14+'Nelson, Keshia'!I15)>0,('Nelson, Keshia'!I16+'Nelson, Keshia'!I17)>0,('Nelson, Keshia'!I18+'Nelson, Keshia'!I19)>0,('Nelson, Keshia'!I20+'Nelson, Keshia'!I21)>0,('Nelson, Keshia'!I22+'Nelson, Keshia'!I23)>0,('Nelson, Keshia'!I24+'Nelson, Keshia'!I25)>0,('Nelson, Keshia'!I26+'Nelson, Keshia'!I27)>0),AND(('Nelson, Keshia'!I30+'Nelson, Keshia'!I31)>0,('Nelson, Keshia'!I32+'Nelson, Keshia'!I33)>0,('Nelson, Keshia'!I34+'Nelson, Keshia'!I35)>0,('Nelson, Keshia'!I36+'Nelson, Keshia'!I37)>0,('Nelson, Keshia'!I38+'Nelson, Keshia'!I39)>0,('Nelson, Keshia'!I40+'Nelson, Keshia'!I41)>0,('Nelson, Keshia'!I42+'Nelson, Keshia'!I43)>0)),"Yes","") | I23: =IF('Nelson, Keshia'!N49>40,"Yes","") | J23: =IF(OR(AND(SUM('Nelson, Keshia'!I14:I27)>0,SUM('Nelson, Keshia'!I14:I27)<40),AND(SUM('Nelson, Keshia'!I30:I43)>0,SUM('Nelson, Keshia'!I30:I43)<40)),"Yes","") | K23: =SUMPRODUCT(('Nelson, Keshia'!I14:I48>0)*('Nelson, Keshia'!I14:I48<8)) | L23: =IF('Nelson, Keshia'!Q50<5,"Yes","") | M23: =IF(AND('Nelson, Keshia'!I49>0,'Nelson, Keshia'!I49<80),"Yes","") | N23: =IF(OR(F23>0,G23="Yes",H23="Yes",I23="Yes"),"⚠️ OVERWORK",IF(OR(J23="Yes",K23>0,L23="Yes",M23="Yes"),"🔻 UNDERWORK","✓ OK"))
A24: 20 | B24: Parris, Ceyon Nickosie | C24: 4885 | D24: ='Parris, Ceyon'!I49 | E24: ='Parris, Ceyon'!Q50 | F24: =SUMPRODUCT((('Parris, Ceyon'!I14+'Parris, Ceyon'!I15)>12)*1)+SUMPRODUCT((('Parris, Ceyon'!I16+'Parris, Ceyon'!I17)>12)*1)+SUMPRODUCT((('Parris, Ceyon'!I18+'Parris, Ceyon'!I19)>12)*1)+SUMPRODUCT((('Parris, Ceyon'!I20+'Parris, Ceyon'!I21)>12)*1)+SUMPRODUCT((('Parris, Ceyon'!I22+'Parris, Ceyon'!I23)>12)*1)+SUMPRODUCT((('Parris, Ceyon'!I24+'Parris, Ceyon'!I25)>12)*1)+SUMPRODUCT((('Parris, Ceyon'!I26+'Parris, Ceyon'!I27)>12)*1)+SUMPRODUCT((('Parris, Ceyon'!I30+'Parris, Ceyon'!I31)>12)*1)+SUMPRODUCT((('Parris, Ceyon'!I32+'Parris, Ceyon'!I33)>12)*1)+SUMPRODUCT((('Parris, Ceyon'!I34+'Parris, Ceyon'!I35)>12)*1)+SUMPRODUCT((('Parris, Ceyon'!I36+'Parris, Ceyon'!I37)>12)*1)+SUMPRODUCT((('Parris, Ceyon'!I38+'Parris, Ceyon'!I39)>12)*1)+SUMPRODUCT((('Parris, Ceyon'!I40+'Parris, Ceyon'!I41)>12)*1)+SUMPRODUCT((('Parris, Ceyon'!I42+'Parris, Ceyon'!I43)>12)*1)+SUMPRODUCT((('Parris, Ceyon'!I45+'Parris, Ceyon'!I46)>12)*1)+SUMPRODUCT((('Parris, Ceyon'!I47+'Parris, Ceyon'!I48)>12)*1) | G24: =IF(MAX(SUM('Parris, Ceyon'!I14:I27),SUM('Parris, Ceyon'!I30:I43))>60,"Yes","") | H24: =IF(OR(AND(('Parris, Ceyon'!I14+'Parris, Ceyon'!I15)>0,('Parris, Ceyon'!I16+'Parris, Ceyon'!I17)>0,('Parris, Ceyon'!I18+'Parris, Ceyon'!I19)>0,('Parris, Ceyon'!I20+'Parris, Ceyon'!I21)>0,('Parris, Ceyon'!I22+'Parris, Ceyon'!I23)>0,('Parris, Ceyon'!I24+'Parris, Ceyon'!I25)>0,('Parris, Ceyon'!I26+'Parris, Ceyon'!I27)>0),AND(('Parris, Ceyon'!I30+'Parris, Ceyon'!I31)>0,('Parris, Ceyon'!I32+'Parris, Ceyon'!I33)>0,('Parris, Ceyon'!I34+'Parris, Ceyon'!I35)>0,('Parris, Ceyon'!I36+'Parris, Ceyon'!I37)>0,('Parris, Ceyon'!I38+'Parris, Ceyon'!I39)>0,('Parris, Ceyon'!I40+'Parris, Ceyon'!I41)>0,('Parris, Ceyon'!I42+'Parris, Ceyon'!I43)>0)),"Yes","") | I24: =IF('Parris, Ceyon'!N49>40,"Yes","") | J24: =IF(OR(AND(SUM('Parris, Ceyon'!I14:I27)>0,SUM('Parris, Ceyon'!I14:I27)<40),AND(SUM('Parris, Ceyon'!I30:I43)>0,SUM('Parris, Ceyon'!I30:I43)<40)),"Yes","") | K24: =SUMPRODUCT(('Parris, Ceyon'!I14:I48>0)*('Parris, Ceyon'!I14:I48<8)) | L24: =IF('Parris, Ceyon'!Q50<5,"Yes","") | M24: =IF(AND('Parris, Ceyon'!I49>0,'Parris, Ceyon'!I49<80),"Yes","") | N24: =IF(OR(F24>0,G24="Yes",H24="Yes",I24="Yes"),"⚠️ OVERWORK",IF(OR(J24="Yes",K24>0,L24="Yes",M24="Yes"),"🔻 UNDERWORK","✓ OK"))
A25: 21 | B25: Phoenix, Ryan | C25: 2826 | D25: ='Phoenix, Ryan'!I49 | E25: ='Phoenix, Ryan'!Q50 | F25: =SUMPRODUCT((('Phoenix, Ryan'!I14+'Phoenix, Ryan'!I15)>12)*1)+SUMPRODUCT((('Phoenix, Ryan'!I16+'Phoenix, Ryan'!I17)>12)*1)+SUMPRODUCT((('Phoenix, Ryan'!I18+'Phoenix, Ryan'!I19)>12)*1)+SUMPRODUCT((('Phoenix, Ryan'!I20+'Phoenix, Ryan'!I21)>12)*1)+SUMPRODUCT((('Phoenix, Ryan'!I22+'Phoenix, Ryan'!I23)>12)*1)+SUMPRODUCT((('Phoenix, Ryan'!I24+'Phoenix, Ryan'!I25)>12)*1)+SUMPRODUCT((('Phoenix, Ryan'!I26+'Phoenix, Ryan'!I27)>12)*1)+SUMPRODUCT((('Phoenix, Ryan'!I30+'Phoenix, Ryan'!I31)>12)*1)+SUMPRODUCT((('Phoenix, Ryan'!I32+'Phoenix, Ryan'!I33)>12)*1)+SUMPRODUCT((('Phoenix, Ryan'!I34+'Phoenix, Ryan'!I35)>12)*1)+SUMPRODUCT((('Phoenix, Ryan'!I36+'Phoenix, Ryan'!I37)>12)*1)+SUMPRODUCT((('Phoenix, Ryan'!I38+'Phoenix, Ryan'!I39)>12)*1)+SUMPRODUCT((('Phoenix, Ryan'!I40+'Phoenix, Ryan'!I41)>12)*1)+SUMPRODUCT((('Phoenix, Ryan'!I42+'Phoenix, Ryan'!I43)>12)*1)+SUMPRODUCT((('Phoenix, Ryan'!I45+'Phoenix, Ryan'!I46)>12)*1)+SUMPRODUCT((('Phoenix, Ryan'!I47+'Phoenix, Ryan'!I48)>12)*1) | G25: =IF(MAX(SUM('Phoenix, Ryan'!I14:I27),SUM('Phoenix, Ryan'!I30:I43))>60,"Yes","") | H25: =IF(OR(AND(('Phoenix, Ryan'!I14+'Phoenix, Ryan'!I15)>0,('Phoenix, Ryan'!I16+'Phoenix, Ryan'!I17)>0,('Phoenix, Ryan'!I18+'Phoenix, Ryan'!I19)>0,('Phoenix, Ryan'!I20+'Phoenix, Ryan'!I21)>0,('Phoenix, Ryan'!I22+'Phoenix, Ryan'!I23)>0,('Phoenix, Ryan'!I24+'Phoenix, Ryan'!I25)>0,('Phoenix, Ryan'!I26+'Phoenix, Ryan'!I27)>0),AND(('Phoenix, Ryan'!I30+'Phoenix, Ryan'!I31)>0,('Phoenix, Ryan'!I32+'Phoenix, Ryan'!I33)>0,('Phoenix, Ryan'!I34+'Phoenix, Ryan'!I35)>0,('Phoenix, Ryan'!I36+'Phoenix, Ryan'!I37)>0,('Phoenix, Ryan'!I38+'Phoenix, Ryan'!I39)>0,('Phoenix, Ryan'!I40+'Phoenix, Ryan'!I41)>0,('Phoenix, Ryan'!I42+'Phoenix, Ryan'!I43)>0)),"Yes","") | I25: =IF('Phoenix, Ryan'!N49>40,"Yes","") | J25: =IF(OR(AND(SUM('Phoenix, Ryan'!I14:I27)>0,SUM('Phoenix, Ryan'!I14:I27)<40),AND(SUM('Phoenix, Ryan'!I30:I43)>0,SUM('Phoenix, Ryan'!I30:I43)<40)),"Yes","") | K25: =SUMPRODUCT(('Phoenix, Ryan'!I14:I48>0)*('Phoenix, Ryan'!I14:I48<8)) | L25: =IF('Phoenix, Ryan'!Q50<5,"Yes","") | M25: =IF(AND('Phoenix, Ryan'!I49>0,'Phoenix, Ryan'!I49<80),"Yes","") | N25: =IF(OR(F25>0,G25="Yes",H25="Yes",I25="Yes"),"⚠️ OVERWORK",IF(OR(J25="Yes",K25>0,L25="Yes",M25="Yes"),"🔻 UNDERWORK","✓ OK"))
A26: 22 | B26: Pollard, Lotoya Letitia | C26: 4850 | D26: ='Pollard, Lotoya'!I49 | E26: ='Pollard, Lotoya'!Q50 | F26: =SUMPRODUCT((('Pollard, Lotoya'!I14+'Pollard, Lotoya'!I15)>12)*1)+SUMPRODUCT((('Pollard, Lotoya'!I16+'Pollard, Lotoya'!I17)>12)*1)+SUMPRODUCT((('Pollard, Lotoya'!I18+'Pollard, Lotoya'!I19)>12)*1)+SUMPRODUCT((('Pollard, Lotoya'!I20+'Pollard, Lotoya'!I21)>12)*1)+SUMPRODUCT((('Pollard, Lotoya'!I22+'Pollard, Lotoya'!I23)>12)*1)+SUMPRODUCT((('Pollard, Lotoya'!I24+'Pollard, Lotoya'!I25)>12)*1)+SUMPRODUCT((('Pollard, Lotoya'!I26+'Pollard, Lotoya'!I27)>12)*1)+SUMPRODUCT((('Pollard, Lotoya'!I30+'Pollard, Lotoya'!I31)>12)*1)+SUMPRODUCT((('Pollard, Lotoya'!I32+'Pollard, Lotoya'!I33)>12)*1)+SUMPRODUCT((('Pollard, Lotoya'!I34+'Pollard, Lotoya'!I35)>12)*1)+SUMPRODUCT((('Pollard, Lotoya'!I36+'Pollard, Lotoya'!I37)>12)*1)+SUMPRODUCT((('Pollard, Lotoya'!I38+'Pollard, Lotoya'!I39)>12)*1)+SUMPRODUCT((('Pollard, Lotoya'!I40+'Pollard, Lotoya'!I41)>12)*1)+SUMPRODUCT((('Pollard, Lotoya'!I42+'Pollard, Lotoya'!I43)>12)*1)+SUMPRODUCT((('Pollard, Lotoya'!I45+'Pollard, Lotoya'!I46)>12)*1)+SUMPRODUCT((('Pollard, Lotoya'!I47+'Pollard, Lotoya'!I48)>12)*1) | G26: =IF(MAX(SUM('Pollard, Lotoya'!I14:I27),SUM('Pollard, Lotoya'!I30:I43))>60,"Yes","") | H26: =IF(OR(AND(('Pollard, Lotoya'!I14+'Pollard, Lotoya'!I15)>0,('Pollard, Lotoya'!I16+'Pollard, Lotoya'!I17)>0,('Pollard, Lotoya'!I18+'Pollard, Lotoya'!I19)>0,('Pollard, Lotoya'!I20+'Pollard, Lotoya'!I21)>0,('Pollard, Lotoya'!I22+'Pollard, Lotoya'!I23)>0,('Pollard, Lotoya'!I24+'Pollard, Lotoya'!I25)>0,('Pollard, Lotoya'!I26+'Pollard, Lotoya'!I27)>0),AND(('Pollard, Lotoya'!I30+'Pollard, Lotoya'!I31)>0,('Pollard, Lotoya'!I32+'Pollard, Lotoya'!I33)>0,('Pollard, Lotoya'!I34+'Pollard, Lotoya'!I35)>0,('Pollard, Lotoya'!I36+'Pollard, Lotoya'!I37)>0,('Pollard, Lotoya'!I38+'Pollard, Lotoya'!I39)>0,('Pollard, Lotoya'!I40+'Pollard, Lotoya'!I41)>0,('Pollard, Lotoya'!I42+'Pollard, Lotoya'!I43)>0)),"Yes","") | I26: =IF('Pollard, Lotoya'!N49>40,"Yes","") | J26: =IF(OR(AND(SUM('Pollard, Lotoya'!I14:I27)>0,SUM('Pollard, Lotoya'!I14:I27)<40),AND(SUM('Pollard, Lotoya'!I30:I43)>0,SUM('Pollard, Lotoya'!I30:I43)<40)),"Yes","") | K26: =SUMPRODUCT(('Pollard, Lotoya'!I14:I48>0)*('Pollard, Lotoya'!I14:I48<8)) | L26: =IF('Pollard, Lotoya'!Q50<5,"Yes","") | M26: =IF(AND('Pollard, Lotoya'!I49>0,'Pollard, Lotoya'!I49<80),"Yes","") | N26: =IF(OR(F26>0,G26="Yes",H26="Yes",I26="Yes"),"⚠️ OVERWORK",IF(OR(J26="Yes",K26>0,L26="Yes",M26="Yes"),"🔻 UNDERWORK","✓ OK"))
A27: 23 | B27: Reynolds, Kevin Timothy | C27: 4658 | D27: ='Reynolds, Kevin'!I49 | E27: ='Reynolds, Kevin'!Q50 | F27: =SUMPRODUCT((('Reynolds, Kevin'!I14+'Reynolds, Kevin'!I15)>12)*1)+SUMPRODUCT((('Reynolds, Kevin'!I16+'Reynolds, Kevin'!I17)>12)*1)+SUMPRODUCT((('Reynolds, Kevin'!I18+'Reynolds, Kevin'!I19)>12)*1)+SUMPRODUCT((('Reynolds, Kevin'!I20+'Reynolds, Kevin'!I21)>12)*1)+SUMPRODUCT((('Reynolds, Kevin'!I22+'Reynolds, Kevin'!I23)>12)*1)+SUMPRODUCT((('Reynolds, Kevin'!I24+'Reynolds, Kevin'!I25)>12)*1)+SUMPRODUCT((('Reynolds, Kevin'!I26+'Reynolds, Kevin'!I27)>12)*1)+SUMPRODUCT((('Reynolds, Kevin'!I30+'Reynolds, Kevin'!I31)>12)*1)+SUMPRODUCT((('Reynolds, Kevin'!I32+'Reynolds, Kevin'!I33)>12)*1)+SUMPRODUCT((('Reynolds, Kevin'!I34+'Reynolds, Kevin'!I35)>12)*1)+SUMPRODUCT((('Reynolds, Kevin'!I36+'Reynolds, Kevin'!I37)>12)*1)+SUMPRODUCT((('Reynolds, Kevin'!I38+'Reynolds, Kevin'!I39)>12)*1)+SUMPRODUCT((('Reynolds, Kevin'!I40+'Reynolds, Kevin'!I41)>12)*1)+SUMPRODUCT((('Reynolds, Kevin'!I42+'Reynolds, Kevin'!I43)>12)*1)+SUMPRODUCT((('Reynolds, Kevin'!I45+'Reynolds, Kevin'!I46)>12)*1)+SUMPRODUCT((('Reynolds, Kevin'!I47+'Reynolds, Kevin'!I48)>12)*1) | G27: =IF(MAX(SUM('Reynolds, Kevin'!I14:I27),SUM('Reynolds, Kevin'!I30:I43))>60,"Yes","") | H27: =IF(OR(AND(('Reynolds, Kevin'!I14+'Reynolds, Kevin'!I15)>0,('Reynolds, Kevin'!I16+'Reynolds, Kevin'!I17)>0,('Reynolds, Kevin'!I18+'Reynolds, Kevin'!I19)>0,('Reynolds, Kevin'!I20+'Reynolds, Kevin'!I21)>0,('Reynolds, Kevin'!I22+'Reynolds, Kevin'!I23)>0,('Reynolds, Kevin'!I24+'Reynolds, Kevin'!I25)>0,('Reynolds, Kevin'!I26+'Reynolds, Kevin'!I27)>0),AND(('Reynolds, Kevin'!I30+'Reynolds, Kevin'!I31)>0,('Reynolds, Kevin'!I32+'Reynolds, Kevin'!I33)>0,('Reynolds, Kevin'!I34+'Reynolds, Kevin'!I35)>0,('Reynolds, Kevin'!I36+'Reynolds, Kevin'!I37)>0,('Reynolds, Kevin'!I38+'Reynolds, Kevin'!I39)>0,('Reynolds, Kevin'!I40+'Reynolds, Kevin'!I41)>0,('Reynolds, Kevin'!I42+'Reynolds, Kevin'!I43)>0)),"Yes","") | I27: =IF('Reynolds, Kevin'!N49>40,"Yes","") | J27: =IF(OR(AND(SUM('Reynolds, Kevin'!I14:I27)>0,SUM('Reynolds, Kevin'!I14:I27)<40),AND(SUM('Reynolds, Kevin'!I30:I43)>0,SUM('Reynolds, Kevin'!I30:I43)<40)),"Yes","") | K27: =SUMPRODUCT(('Reynolds, Kevin'!I14:I48>0)*('Reynolds, Kevin'!I14:I48<8)) | L27: =IF('Reynolds, Kevin'!Q50<5,"Yes","") | M27: =IF(AND('Reynolds, Kevin'!I49>0,'Reynolds, Kevin'!I49<80),"Yes","") | N27: =IF(OR(F27>0,G27="Yes",H27="Yes",I27="Yes"),"⚠️ OVERWORK",IF(OR(J27="Yes",K27>0,L27="Yes",M27="Yes"),"🔻 UNDERWORK","✓ OK"))
A28: 24 | B28: Roberts, Odetta Kenesia Shannele | C28: 5466 | D28: ='Roberts, Odetta'!I49 | E28: ='Roberts, Odetta'!Q50 | F28: =SUMPRODUCT((('Roberts, Odetta'!I14+'Roberts, Odetta'!I15)>12)*1)+SUMPRODUCT((('Roberts, Odetta'!I16+'Roberts, Odetta'!I17)>12)*1)+SUMPRODUCT((('Roberts, Odetta'!I18+'Roberts, Odetta'!I19)>12)*1)+SUMPRODUCT((('Roberts, Odetta'!I20+'Roberts, Odetta'!I21)>12)*1)+SUMPRODUCT((('Roberts, Odetta'!I22+'Roberts, Odetta'!I23)>12)*1)+SUMPRODUCT((('Roberts, Odetta'!I24+'Roberts, Odetta'!I25)>12)*1)+SUMPRODUCT((('Roberts, Odetta'!I26+'Roberts, Odetta'!I27)>12)*1)+SUMPRODUCT((('Roberts, Odetta'!I30+'Roberts, Odetta'!I31)>12)*1)+SUMPRODUCT((('Roberts, Odetta'!I32+'Roberts, Odetta'!I33)>12)*1)+SUMPRODUCT((('Roberts, Odetta'!I34+'Roberts, Odetta'!I35)>12)*1)+SUMPRODUCT((('Roberts, Odetta'!I36+'Roberts, Odetta'!I37)>12)*1)+SUMPRODUCT((('Roberts, Odetta'!I38+'Roberts, Odetta'!I39)>12)*1)+SUMPRODUCT((('Roberts, Odetta'!I40+'Roberts, Odetta'!I41)>12)*1)+SUMPRODUCT((('Roberts, Odetta'!I42+'Roberts, Odetta'!I43)>12)*1)+SUMPRODUCT((('Roberts, Odetta'!I45+'Roberts, Odetta'!I46)>12)*1)+SUMPRODUCT((('Roberts, Odetta'!I47+'Roberts, Odetta'!I48)>12)*1) | G28: =IF(MAX(SUM('Roberts, Odetta'!I14:I27),SUM('Roberts, Odetta'!I30:I43))>60,"Yes","") | H28: =IF(OR(AND(('Roberts, Odetta'!I14+'Roberts, Odetta'!I15)>0,('Roberts, Odetta'!I16+'Roberts, Odetta'!I17)>0,('Roberts, Odetta'!I18+'Roberts, Odetta'!I19)>0,('Roberts, Odetta'!I20+'Roberts, Odetta'!I21)>0,('Roberts, Odetta'!I22+'Roberts, Odetta'!I23)>0,('Roberts, Odetta'!I24+'Roberts, Odetta'!I25)>0,('Roberts, Odetta'!I26+'Roberts, Odetta'!I27)>0),AND(('Roberts, Odetta'!I30+'Roberts, Odetta'!I31)>0,('Roberts, Odetta'!I32+'Roberts, Odetta'!I33)>0,('Roberts, Odetta'!I34+'Roberts, Odetta'!I35)>0,('Roberts, Odetta'!I36+'Roberts, Odetta'!I37)>0,('Roberts, Odetta'!I38+'Roberts, Odetta'!I39)>0,('Roberts, Odetta'!I40+'Roberts, Odetta'!I41)>0,('Roberts, Odetta'!I42+'Roberts, Odetta'!I43)>0)),"Yes","") | I28: =IF('Roberts, Odetta'!N49>40,"Yes","") | J28: =IF(OR(AND(SUM('Roberts, Odetta'!I14:I27)>0,SUM('Roberts, Odetta'!I14:I27)<40),AND(SUM('Roberts, Odetta'!I30:I43)>0,SUM('Roberts, Odetta'!I30:I43)<40)),"Yes","") | K28: =SUMPRODUCT(('Roberts, Odetta'!I14:I48>0)*('Roberts, Odetta'!I14:I48<8)) | L28: =IF('Roberts, Odetta'!Q50<5,"Yes","") | M28: =IF(AND('Roberts, Odetta'!I49>0,'Roberts, Odetta'!I49<80),"Yes","") | N28: =IF(OR(F28>0,G28="Yes",H28="Yes",I28="Yes"),"⚠️ OVERWORK",IF(OR(J28="Yes",K28>0,L28="Yes",M28="Yes"),"🔻 UNDERWORK","✓ OK"))
A29: 25 | B29: Robinson, Candacy Olivia | C29: 4784 | D29: ='Robinson, Candacy'!I49 | E29: ='Robinson, Candacy'!Q50 | F29: =SUMPRODUCT((('Robinson, Candacy'!I14+'Robinson, Candacy'!I15)>12)*1)+SUMPRODUCT((('Robinson, Candacy'!I16+'Robinson, Candacy'!I17)>12)*1)+SUMPRODUCT((('Robinson, Candacy'!I18+'Robinson, Candacy'!I19)>12)*1)+SUMPRODUCT((('Robinson, Candacy'!I20+'Robinson, Candacy'!I21)>12)*1)+SUMPRODUCT((('Robinson, Candacy'!I22+'Robinson, Candacy'!I23)>12)*1)+SUMPRODUCT((('Robinson, Candacy'!I24+'Robinson, Candacy'!I25)>12)*1)+SUMPRODUCT((('Robinson, Candacy'!I26+'Robinson, Candacy'!I27)>12)*1)+SUMPRODUCT((('Robinson, Candacy'!I30+'Robinson, Candacy'!I31)>12)*1)+SUMPRODUCT((('Robinson, Candacy'!I32+'Robinson, Candacy'!I33)>12)*1)+SUMPRODUCT((('Robinson, Candacy'!I34+'Robinson, Candacy'!I35)>12)*1)+SUMPRODUCT((('Robinson, Candacy'!I36+'Robinson, Candacy'!I37)>12)*1)+SUMPRODUCT((('Robinson, Candacy'!I38+'Robinson, Candacy'!I39)>12)*1)+SUMPRODUCT((('Robinson, Candacy'!I40+'Robinson, Candacy'!I41)>12)*1)+SUMPRODUCT((('Robinson, Candacy'!I42+'Robinson, Candacy'!I43)>12)*1)+SUMPRODUCT((('Robinson, Candacy'!I45+'Robinson, Candacy'!I46)>12)*1)+SUMPRODUCT((('Robinson, Candacy'!I47+'Robinson, Candacy'!I48)>12)*1) | G29: =IF(MAX(SUM('Robinson, Candacy'!I14:I27),SUM('Robinson, Candacy'!I30:I43))>60,"Yes","") | H29: =IF(OR(AND(('Robinson, Candacy'!I14+'Robinson, Candacy'!I15)>0,('Robinson, Candacy'!I16+'Robinson, Candacy'!I17)>0,('Robinson, Candacy'!I18+'Robinson, Candacy'!I19)>0,('Robinson, Candacy'!I20+'Robinson, Candacy'!I21)>0,('Robinson, Candacy'!I22+'Robinson, Candacy'!I23)>0,('Robinson, Candacy'!I24+'Robinson, Candacy'!I25)>0,('Robinson, Candacy'!I26+'Robinson, Candacy'!I27)>0),AND(('Robinson, Candacy'!I30+'Robinson, Candacy'!I31)>0,('Robinson, Candacy'!I32+'Robinson, Candacy'!I33)>0,('Robinson, Candacy'!I34+'Robinson, Candacy'!I35)>0,('Robinson, Candacy'!I36+'Robinson, Candacy'!I37)>0,('Robinson, Candacy'!I38+'Robinson, Candacy'!I39)>0,('Robinson, Candacy'!I40+'Robinson, Candacy'!I41)>0,('Robinson, Candacy'!I42+'Robinson, Candacy'!I43)>0)),"Yes","") | I29: =IF('Robinson, Candacy'!N49>40,"Yes","") | J29: =IF(OR(AND(SUM('Robinson, Candacy'!I14:I27)>0,SUM('Robinson, Candacy'!I14:I27)<40),AND(SUM('Robinson, Candacy'!I30:I43)>0,SUM('Robinson, Candacy'!I30:I43)<40)),"Yes","") | K29: =SUMPRODUCT(('Robinson, Candacy'!I14:I48>0)*('Robinson, Candacy'!I14:I48<8)) | L29: =IF('Robinson, Candacy'!Q50<5,"Yes","") | M29: =IF(AND('Robinson, Candacy'!I49>0,'Robinson, Candacy'!I49<80),"Yes","") | N29: =IF(OR(F29>0,G29="Yes",H29="Yes",I29="Yes"),"⚠️ OVERWORK",IF(OR(J29="Yes",K29>0,L29="Yes",M29="Yes"),"🔻 UNDERWORK","✓ OK"))
A30: 26 | B30: Smith, Tiffany Natalya | C30: 5408 | D30: ='Smith, Tiffany'!I49 | E30: ='Smith, Tiffany'!Q50 | F30: =SUMPRODUCT((('Smith, Tiffany'!I14+'Smith, Tiffany'!I15)>12)*1)+SUMPRODUCT((('Smith, Tiffany'!I16+'Smith, Tiffany'!I17)>12)*1)+SUMPRODUCT((('Smith, Tiffany'!I18+'Smith, Tiffany'!I19)>12)*1)+SUMPRODUCT((('Smith, Tiffany'!I20+'Smith, Tiffany'!I21)>12)*1)+SUMPRODUCT((('Smith, Tiffany'!I22+'Smith, Tiffany'!I23)>12)*1)+SUMPRODUCT((('Smith, Tiffany'!I24+'Smith, Tiffany'!I25)>12)*1)+SUMPRODUCT((('Smith, Tiffany'!I26+'Smith, Tiffany'!I27)>12)*1)+SUMPRODUCT((('Smith, Tiffany'!I30+'Smith, Tiffany'!I31)>12)*1)+SUMPRODUCT((('Smith, Tiffany'!I32+'Smith, Tiffany'!I33)>12)*1)+SUMPRODUCT((('Smith, Tiffany'!I34+'Smith, Tiffany'!I35)>12)*1)+SUMPRODUCT((('Smith, Tiffany'!I36+'Smith, Tiffany'!I37)>12)*1)+SUMPRODUCT((('Smith, Tiffany'!I38+'Smith, Tiffany'!I39)>12)*1)+SUMPRODUCT((('Smith, Tiffany'!I40+'Smith, Tiffany'!I41)>12)*1)+SUMPRODUCT((('Smith, Tiffany'!I42+'Smith, Tiffany'!I43)>12)*1)+SUMPRODUCT((('Smith, Tiffany'!I45+'Smith, Tiffany'!I46)>12)*1)+SUMPRODUCT((('Smith, Tiffany'!I47+'Smith, Tiffany'!I48)>12)*1) | G30: =IF(MAX(SUM('Smith, Tiffany'!I14:I27),SUM('Smith, Tiffany'!I30:I43))>60,"Yes","") | H30: =IF(OR(AND(('Smith, Tiffany'!I14+'Smith, Tiffany'!I15)>0,('Smith, Tiffany'!I16+'Smith, Tiffany'!I17)>0,('Smith, Tiffany'!I18+'Smith, Tiffany'!I19)>0,('Smith, Tiffany'!I20+'Smith, Tiffany'!I21)>0,('Smith, Tiffany'!I22+'Smith, Tiffany'!I23)>0,('Smith, Tiffany'!I24+'Smith, Tiffany'!I25)>0,('Smith, Tiffany'!I26+'Smith, Tiffany'!I27)>0),AND(('Smith, Tiffany'!I30+'Smith, Tiffany'!I31)>0,('Smith, Tiffany'!I32+'Smith, Tiffany'!I33)>0,('Smith, Tiffany'!I34+'Smith, Tiffany'!I35)>0,('Smith, Tiffany'!I36+'Smith, Tiffany'!I37)>0,('Smith, Tiffany'!I38+'Smith, Tiffany'!I39)>0,('Smith, Tiffany'!I40+'Smith, Tiffany'!I41)>0,('Smith, Tiffany'!I42+'Smith, Tiffany'!I43)>0)),"Yes","") | I30: =IF('Smith, Tiffany'!N49>40,"Yes","") | J30: =IF(OR(AND(SUM('Smith, Tiffany'!I14:I27)>0,SUM('Smith, Tiffany'!I14:I27)<40),AND(SUM('Smith, Tiffany'!I30:I43)>0,SUM('Smith, Tiffany'!I30:I43)<40)),"Yes","") | K30: =SUMPRODUCT(('Smith, Tiffany'!I14:I48>0)*('Smith, Tiffany'!I14:I48<8)) | L30: =IF('Smith, Tiffany'!Q50<5,"Yes","") | M30: =IF(AND('Smith, Tiffany'!I49>0,'Smith, Tiffany'!I49<80),"Yes","") | N30: =IF(OR(F30>0,G30="Yes",H30="Yes",I30="Yes"),"⚠️ OVERWORK",IF(OR(J30="Yes",K30>0,L30="Yes",M30="Yes"),"🔻 UNDERWORK","✓ OK"))
A31: 27 | B31: Spencer, Renita Denita | C31: 5510 | D31: ='Spencer, Renita'!I49 | E31: ='Spencer, Renita'!Q50 | F31: =SUMPRODUCT((('Spencer, Renita'!I14+'Spencer, Renita'!I15)>12)*1)+SUMPRODUCT((('Spencer, Renita'!I16+'Spencer, Renita'!I17)>12)*1)+SUMPRODUCT((('Spencer, Renita'!I18+'Spencer, Renita'!I19)>12)*1)+SUMPRODUCT((('Spencer, Renita'!I20+'Spencer, Renita'!I21)>12)*1)+SUMPRODUCT((('Spencer, Renita'!I22+'Spencer, Renita'!I23)>12)*1)+SUMPRODUCT((('Spencer, Renita'!I24+'Spencer, Renita'!I25)>12)*1)+SUMPRODUCT((('Spencer, Renita'!I26+'Spencer, Renita'!I27)>12)*1)+SUMPRODUCT((('Spencer, Renita'!I30+'Spencer, Renita'!I31)>12)*1)+SUMPRODUCT((('Spencer, Renita'!I32+'Spencer, Renita'!I33)>12)*1)+SUMPRODUCT((('Spencer, Renita'!I34+'Spencer, Renita'!I35)>12)*1)+SUMPRODUCT((('Spencer, Renita'!I36+'Spencer, Renita'!I37)>12)*1)+SUMPRODUCT((('Spencer, Renita'!I38+'Spencer, Renita'!I39)>12)*1)+SUMPRODUCT((('Spencer, Renita'!I40+'Spencer, Renita'!I41)>12)*1)+SUMPRODUCT((('Spencer, Renita'!I42+'Spencer, Renita'!I43)>12)*1)+SUMPRODUCT((('Spencer, Renita'!I45+'Spencer, Renita'!I46)>12)*1)+SUMPRODUCT((('Spencer, Renita'!I47+'Spencer, Renita'!I48)>12)*1) | G31: =IF(MAX(SUM('Spencer, Renita'!I14:I27),SUM('Spencer, Renita'!I30:I43))>60,"Yes","") | H31: =IF(OR(AND(('Spencer, Renita'!I14+'Spencer, Renita'!I15)>0,('Spencer, Renita'!I16+'Spencer, Renita'!I17)>0,('Spencer, Renita'!I18+'Spencer, Renita'!I19)>0,('Spencer, Renita'!I20+'Spencer, Renita'!I21)>0,('Spencer, Renita'!I22+'Spencer, Renita'!I23)>0,('Spencer, Renita'!I24+'Spencer, Renita'!I25)>0,('Spencer, Renita'!I26+'Spencer, Renita'!I27)>0),AND(('Spencer, Renita'!I30+'Spencer, Renita'!I31)>0,('Spencer, Renita'!I32+'Spencer, Renita'!I33)>0,('Spencer, Renita'!I34+'Spencer, Renita'!I35)>0,('Spencer, Renita'!I36+'Spencer, Renita'!I37)>0,('Spencer, Renita'!I38+'Spencer, Renita'!I39)>0,('Spencer, Renita'!I40+'Spencer, Renita'!I41)>0,('Spencer, Renita'!I42+'Spencer, Renita'!I43)>0)),"Yes","") | I31: =IF('Spencer, Renita'!N49>40,"Yes","") | J31: =IF(OR(AND(SUM('Spencer, Renita'!I14:I27)>0,SUM('Spencer, Renita'!I14:I27)<40),AND(SUM('Spencer, Renita'!I30:I43)>0,SUM('Spencer, Renita'!I30:I43)<40)),"Yes","") | K31: =SUMPRODUCT(('Spencer, Renita'!I14:I48>0)*('Spencer, Renita'!I14:I48<8)) | L31: =IF('Spencer, Renita'!Q50<5,"Yes","") | M31: =IF(AND('Spencer, Renita'!I49>0,'Spencer, Renita'!I49<80),"Yes","") | N31: =IF(OR(F31>0,G31="Yes",H31="Yes",I31="Yes"),"⚠️ OVERWORK",IF(OR(J31="Yes",K31>0,L31="Yes",M31="Yes"),"🔻 UNDERWORK","✓ OK"))
A32: 28 | B32: Venture, Ollivina | C32: 1319 | D32: ='Venture, Ollivina'!I49 | E32: ='Venture, Ollivina'!Q50 | F32: =SUMPRODUCT((('Venture, Ollivina'!I14+'Venture, Ollivina'!I15)>12)*1)+SUMPRODUCT((('Venture, Ollivina'!I16+'Venture, Ollivina'!I17)>12)*1)+SUMPRODUCT((('Venture, Ollivina'!I18+'Venture, Ollivina'!I19)>12)*1)+SUMPRODUCT((('Venture, Ollivina'!I20+'Venture, Ollivina'!I21)>12)*1)+SUMPRODUCT((('Venture, Ollivina'!I22+'Venture, Ollivina'!I23)>12)*1)+SUMPRODUCT((('Venture, Ollivina'!I24+'Venture, Ollivina'!I25)>12)*1)+SUMPRODUCT((('Venture, Ollivina'!I26+'Venture, Ollivina'!I27)>12)*1)+SUMPRODUCT((('Venture, Ollivina'!I30+'Venture, Ollivina'!I31)>12)*1)+SUMPRODUCT((('Venture, Ollivina'!I32+'Venture, Ollivina'!I33)>12)*1)+SUMPRODUCT((('Venture, Ollivina'!I34+'Venture, Ollivina'!I35)>12)*1)+SUMPRODUCT((('Venture, Ollivina'!I36+'Venture, Ollivina'!I37)>12)*1)+SUMPRODUCT((('Venture, Ollivina'!I38+'Venture, Ollivina'!I39)>12)*1)+SUMPRODUCT((('Venture, Ollivina'!I40+'Venture, Ollivina'!I41)>12)*1)+SUMPRODUCT((('Venture, Ollivina'!I42+'Venture, Ollivina'!I43)>12)*1)+SUMPRODUCT((('Venture, Ollivina'!I45+'Venture, Ollivina'!I46)>12)*1)+SUMPRODUCT((('Venture, Ollivina'!I47+'Venture, Ollivina'!I48)>12)*1) | G32: =IF(MAX(SUM('Venture, Ollivina'!I14:I27),SUM('Venture, Ollivina'!I30:I43))>60,"Yes","") | H32: =IF(OR(AND(('Venture, Ollivina'!I14+'Venture, Ollivina'!I15)>0,('Venture, Ollivina'!I16+'Venture, Ollivina'!I17)>0,('Venture, Ollivina'!I18+'Venture, Ollivina'!I19)>0,('Venture, Ollivina'!I20+'Venture, Ollivina'!I21)>0,('Venture, Ollivina'!I22+'Venture, Ollivina'!I23)>0,('Venture, Ollivina'!I24+'Venture, Ollivina'!I25)>0,('Venture, Ollivina'!I26+'Venture, Ollivina'!I27)>0),AND(('Venture, Ollivina'!I30+'Venture, Ollivina'!I31)>0,('Venture, Ollivina'!I32+'Venture, Ollivina'!I33)>0,('Venture, Ollivina'!I34+'Venture, Ollivina'!I35)>0,('Venture, Ollivina'!I36+'Venture, Ollivina'!I37)>0,('Venture, Ollivina'!I38+'Venture, Ollivina'!I39)>0,('Venture, Ollivina'!I40+'Venture, Ollivina'!I41)>0,('Venture, Ollivina'!I42+'Venture, Ollivina'!I43)>0)),"Yes","") | I32: =IF('Venture, Ollivina'!N49>40,"Yes","") | J32: =IF(OR(AND(SUM('Venture, Ollivina'!I14:I27)>0,SUM('Venture, Ollivina'!I14:I27)<40),AND(SUM('Venture, Ollivina'!I30:I43)>0,SUM('Venture, Ollivina'!I30:I43)<40)),"Yes","") | K32: =SUMPRODUCT(('Venture, Ollivina'!I14:I48>0)*('Venture, Ollivina'!I14:I48<8)) | L32: =IF('Venture, Ollivina'!Q50<5,"Yes","") | M32: =IF(AND('Venture, Ollivina'!I49>0,'Venture, Ollivina'!I49<80),"Yes","") | N32: =IF(OR(F32>0,G32="Yes",H32="Yes",I32="Yes"),"⚠️ OVERWORK",IF(OR(J32="Yes",K32>0,L32="Yes",M32="Yes"),"🔻 UNDERWORK","✓ OK"))
A33: 29 | B33: Vincent, Fucien | C33: 5478 | D33: ='Vincent, Fucien'!I49 | E33: ='Vincent, Fucien'!Q50 | F33: =SUMPRODUCT((('Vincent, Fucien'!I14+'Vincent, Fucien'!I15)>12)*1)+SUMPRODUCT((('Vincent, Fucien'!I16+'Vincent, Fucien'!I17)>12)*1)+SUMPRODUCT((('Vincent, Fucien'!I18+'Vincent, Fucien'!I19)>12)*1)+SUMPRODUCT((('Vincent, Fucien'!I20+'Vincent, Fucien'!I21)>12)*1)+SUMPRODUCT((('Vincent, Fucien'!I22+'Vincent, Fucien'!I23)>12)*1)+SUMPRODUCT((('Vincent, Fucien'!I24+'Vincent, Fucien'!I25)>12)*1)+SUMPRODUCT((('Vincent, Fucien'!I26+'Vincent, Fucien'!I27)>12)*1)+SUMPRODUCT((('Vincent, Fucien'!I30+'Vincent, Fucien'!I31)>12)*1)+SUMPRODUCT((('Vincent, Fucien'!I32+'Vincent, Fucien'!I33)>12)*1)+SUMPRODUCT((('Vincent, Fucien'!I34+'Vincent, Fucien'!I35)>12)*1)+SUMPRODUCT((('Vincent, Fucien'!I36+'Vincent, Fucien'!I37)>12)*1)+SUMPRODUCT((('Vincent, Fucien'!I38+'Vincent, Fucien'!I39)>12)*1)+SUMPRODUCT((('Vincent, Fucien'!I40+'Vincent, Fucien'!I41)>12)*1)+SUMPRODUCT((('Vincent, Fucien'!I42+'Vincent, Fucien'!I43)>12)*1)+SUMPRODUCT((('Vincent, Fucien'!I45+'Vincent, Fucien'!I46)>12)*1)+SUMPRODUCT((('Vincent, Fucien'!I47+'Vincent, Fucien'!I48)>12)*1) | G33: =IF(MAX(SUM('Vincent, Fucien'!I14:I27),SUM('Vincent, Fucien'!I30:I43))>60,"Yes","") | H33: =IF(OR(AND(('Vincent, Fucien'!I14+'Vincent, Fucien'!I15)>0,('Vincent, Fucien'!I16+'Vincent, Fucien'!I17)>0,('Vincent, Fucien'!I18+'Vincent, Fucien'!I19)>0,('Vincent, Fucien'!I20+'Vincent, Fucien'!I21)>0,('Vincent, Fucien'!I22+'Vincent, Fucien'!I23)>0,('Vincent, Fucien'!I24+'Vincent, Fucien'!I25)>0,('Vincent, Fucien'!I26+'Vincent, Fucien'!I27)>0),AND(('Vincent, Fucien'!I30+'Vincent, Fucien'!I31)>0,('Vincent, Fucien'!I32+'Vincent, Fucien'!I33)>0,('Vincent, Fucien'!I34+'Vincent, Fucien'!I35)>0,('Vincent, Fucien'!I36+'Vincent, Fucien'!I37)>0,('Vincent, Fucien'!I38+'Vincent, Fucien'!I39)>0,('Vincent, Fucien'!I40+'Vincent, Fucien'!I41)>0,('Vincent, Fucien'!I42+'Vincent, Fucien'!I43)>0)),"Yes","") | I33: =IF('Vincent, Fucien'!N49>40,"Yes","") | J33: =IF(OR(AND(SUM('Vincent, Fucien'!I14:I27)>0,SUM('Vincent, Fucien'!I14:I27)<40),AND(SUM('Vincent, Fucien'!I30:I43)>0,SUM('Vincent, Fucien'!I30:I43)<40)),"Yes","") | K33: =SUMPRODUCT(('Vincent, Fucien'!I14:I48>0)*('Vincent, Fucien'!I14:I48<8)) | L33: =IF('Vincent, Fucien'!Q50<5,"Yes","") | M33: =IF(AND('Vincent, Fucien'!I49>0,'Vincent, Fucien'!I49<80),"Yes","") | N33: =IF(OR(F33>0,G33="Yes",H33="Yes",I33="Yes"),"⚠️ OVERWORK",IF(OR(J33="Yes",K33>0,L33="Yes",M33="Yes"),"🔻 UNDERWORK","✓ OK"))
A35: SUMMARY
A36: ⚠️ Overwork Flags: | C36: =COUNTIF(N5:N34,"⚠️ OVERWORK")
A37: 🔻 Underwork Flags: | C37: =COUNTIF(N5:N34,"🔻 UNDERWORK")
A38: ✓ OK: | C38: =COUNTIF(N5:N34,"✓ OK")
A40: THRESHOLDS:
A41: Overwork: Daily >12hrs | Weekly >60hrs | 7+ consecutive days | OT >40hrs/period
A42: Underwork: Weekly <40hrs | Daily <8hrs (when worked) | <5 days/week | Period <80hrs total

Sheet upload
A1: PAYROLL_ID | B1: EMPLOYEENAME | C1: INCOME_CODE | D1: HOURS | E1: DOLLARS
A2: ='Payroll Summary'!B4 | B2: ='Payroll Summary'!A4 | C2: ANNLEAVE | D2: ='Payroll Summary'!J4
A3: =A2 | B3: =B2 | C3: NR | D3: ='Payroll Summary'!D4
A4: =A3 | B4: =B3 | C4: OT1 | D4: ='Payroll Summary'!F4
A5: =A4 | B5: =B4 | C5: 80125 | D5: ='Payroll Summary'!G4
A6: =A5 | B6: =B5 | C6: INCENTIVE | D6: ='Payroll Summary'!L4
A7: =A6 | B7: =B6 | C7: MA | D7: ='Payroll Summary'!I4
A8: =A7 | B8: =B7 | C8: OT | D8: ='Payroll Summary'!E4
A9: =A8 | B9: =B8 | C9: RA | D9: ='Payroll Summary'!H4
A10: ='Payroll Summary'!B5 | B10: ='Payroll Summary'!A5 | C10: ANNLEAVE | D10: ='Payroll Summary'!J5
A11: =A10 | B11: =B10 | C11: NR | D11: ='Payroll Summary'!D5
A12: =A11 | B12: =B11 | C12: OT1 | D12: ='Payroll Summary'!F5
A13: =A12 | B13: =B12 | C13: 80125 | D13: ='Payroll Summary'!G5
A14: =A13 | B14: =B13 | C14: INCENTIVE | D14: ='Payroll Summary'!L5
A15: =A14 | B15: =B14 | C15: MA | D15: ='Payroll Summary'!I5
A16: =A15 | B16: =B15 | C16: OT | D16: ='Payroll Summary'!E5
A17: =A16 | B17: =B16 | C17: RA | D17: ='Payroll Summary'!H5
A18: ='Payroll Summary'!B6 | B18: ='Payroll Summary'!A6 | C18: ANNLEAVE | D18: ='Payroll Summary'!J6
A19: =A18 | B19: =B18 | C19: NR | D19: ='Payroll Summary'!D6
A20: =A19 | B20: =B19 | C20: OT1 | D20: ='Payroll Summary'!F6
A21: =A20 | B21: =B20 | C21: 80125 | D21: ='Payroll Summary'!G6
A22: =A21 | B22: =B21 | C22: INCENTIVE | D22: ='Payroll Summary'!L6
A23: =A22 | B23: =B22 | C23: MA | D23: ='Payroll Summary'!I6
A24: =A23 | B24: =B23 | C24: OT | D24: ='Payroll Summary'!E6
A25: =A24 | B25: =B24 | C25: RA | D25: ='Payroll Summary'!H6
A26: ='Payroll Summary'!B7 | B26: ='Payroll Summary'!A7 | C26: ANNLEAVE | D26: ='Payroll Summary'!J7
A27: =A26 | B27: =B26 | C27: NR | D27: ='Payroll Summary'!D7
A28: =A27 | B28: =B27 | C28: OT1 | D28: ='Payroll Summary'!F7
A29: =A28 | B29: =B28 | C29: 80125 | D29: ='Payroll Summary'!G7
A30: =A29 | B30: =B29 | C30: INCENTIVE | D30: ='Payroll Summary'!L7
A31: =A30 | B31: =B30 | C31: MA | D31: ='Payroll Summary'!I7
A32: =A31 | B32: =B31 | C32: OT | D32: ='Payroll Summary'!E7
A33: =A32 | B33: =B32 | C33: RA | D33: ='Payroll Summary'!H7
A34: ='Payroll Summary'!B8 | B34: ='Payroll Summary'!A8 | C34: ANNLEAVE | D34: ='Payroll Summary'!J8
A35: =A34 | B35: =B34 | C35: NR | D35: ='Payroll Summary'!D8
A36: =A35 | B36: =B35 | C36: OT1 | D36: ='Payroll Summary'!F8
A37: =A36 | B37: =B36 | C37: 80125 | D37: ='Payroll Summary'!G8
A38: =A37 | B38: =B37 | C38: INCENTIVE | D38: ='Payroll Summary'!L8
A39: =A38 | B39: =B38 | C39: MA | D39: ='Payroll Summary'!I8
A40: =A39 | B40: =B39 | C40: OT | D40: ='Payroll Summary'!E8
A41: =A40 | B41: =B40 | C41: RA | D41: ='Payroll Summary'!H8
A42: ='Payroll Summary'!B9 | B42: ='Payroll Summary'!A9 | C42: ANNLEAVE | D42: ='Payroll Summary'!J9
A43: =A42 | B43: =B42 | C43: NR | D43: ='Payroll Summary'!D9
A44: =A43 | B44: =B43 | C44: OT1 | D44: ='Payroll Summary'!F9
A45: =A44 | B45: =B44 | C45: 80125 | D45: ='Payroll Summary'!G9
A46: =A45 | B46: =B45 | C46: INCENTIVE | D46: ='Payroll Summary'!L9
A47: =A46 | B47: =B46 | C47: MA | D47: ='Payroll Summary'!I9
A48: =A47 | B48: =B47 | C48: OT | D48: ='Payroll Summary'!E9
A49: =A48 | B49: =B48 | C49: RA | D49: ='Payroll Summary'!H9
A50: ='Payroll Summary'!B10 | B50: ='Payroll Summary'!A10 | C50: ANNLEAVE | D50: ='Payroll Summary'!J10
A51: =A50 | B51: =B50 | C51: NR | D51: ='Payroll Summary'!D10
A52: =A51 | B52: =B51 | C52: OT1 | D52: ='Payroll Summary'!F10
A53: =A52 | B53: =B52 | C53: 80125 | D53: ='Payroll Summary'!G10
A54: =A53 | B54: =B53 | C54: INCENTIVE | D54: ='Payroll Summary'!L10
A55: =A54 | B55: =B54 | C55: MA | D55: ='Payroll Summary'!I10
A56: =A55 | B56: =B55 | C56: OT | D56: ='Payroll Summary'!E10
A57: =A56 | B57: =B56 | C57: RA | D57: ='Payroll Summary'!H10
A58: ='Payroll Summary'!B11 | B58: ='Payroll Summary'!A11 | C58: ANNLEAVE | D58: ='Payroll Summary'!J11
A59: =A58 | B59: =B58 | C59: NR | D59: ='Payroll Summary'!D11
A60: =A59 | B60: =B59 | C60: OT1 | D60: ='Payroll Summary'!F11
A61: =A60 | B61: =B60 | C61: 80125 | D61: ='Payroll Summary'!G11
A62: =A61 | B62: =B61 | C62: INCENTIVE | D62: ='Payroll Summary'!L11
A63: =A62 | B63: =B62 | C63: MA | D63: ='Payroll Summary'!I11
A64: =A63 | B64: =B63 | C64: OT | D64: ='Payroll Summary'!E11
A65: =A64 | B65: =B64 | C65: RA | D65: ='Payroll Summary'!H11
A66: ='Payroll Summary'!B12 | B66: ='Payroll Summary'!A12 | C66: ANNLEAVE | D66: ='Payroll Summary'!J12
A67: =A66 | B67: =B66 | C67: NR | D67: ='Payroll Summary'!D12
A68: =A67 | B68: =B67 | C68: OT1 | D68: ='Payroll Summary'!F12
A69: =A68 | B69: =B68 | C69: 80125 | D69: ='Payroll Summary'!G12
A70: =A69 | B70: =B69 | C70: INCENTIVE | D70: ='Payroll Summary'!L12
A71: =A70 | B71: =B70 | C71: MA | D71: ='Payroll Summary'!I12
A72: =A71 | B72: =B71 | C72: OT | D72: ='Payroll Summary'!E12
A73: =A72 | B73: =B72 | C73: RA | D73: ='Payroll Summary'!H12
A74: ='Payroll Summary'!B13 | B74: ='Payroll Summary'!A13 | C74: ANNLEAVE | D74: ='Payroll Summary'!J13
A75: =A74 | B75: =B74 | C75: NR | D75: ='Payroll Summary'!D13
A76: =A75 | B76: =B75 | C76: OT1 | D76: ='Payroll Summary'!F13
A77: =A76 | B77: =B76 | C77: 80125 | D77: ='Payroll Summary'!G13
A78: =A77 | B78: =B77 | C78: INCENTIVE | D78: ='Payroll Summary'!L13
A79: =A78 | B79: =B78 | C79: MA | D79: ='Payroll Summary'!I13
A80: =A79 | B80: =B79 | C80: OT | D80: ='Payroll Summary'!E13
A81: =A80 | B81: =B80 | C81: RA | D81: ='Payroll Summary'!H13
A82: ='Payroll Summary'!B14 | B82: ='Payroll Summary'!A14 | C82: ANNLEAVE | D82: ='Payroll Summary'!J14
A83: =A82 | B83: =B82 | C83: NR | D83: ='Payroll Summary'!D14
A84: =A83 | B84: =B83 | C84: OT1 | D84: ='Payroll Summary'!F14
A85: =A84 | B85: =B84 | C85: 80125 | D85: ='Payroll Summary'!G14
A86: =A85 | B86: =B85 | C86: INCENTIVE | D86: ='Payroll Summary'!L14
A87: =A86 | B87: =B86 | C87: MA | D87: ='Payroll Summary'!I14
A88: =A87 | B88: =B87 | C88: OT | D88: ='Payroll Summary'!E14
A89: =A88 | B89: =B88 | C89: RA | D89: ='Payroll Summary'!H14
A90: ='Payroll Summary'!B15 | B90: ='Payroll Summary'!A15 | C90: ANNLEAVE | D90: ='Payroll Summary'!J15
A91: =A90 | B91: =B90 | C91: NR | D91: ='Payroll Summary'!D15
A92: =A91 | B92: =B91 | C92: OT1 | D92: ='Payroll Summary'!F15
A93: =A92 | B93: =B92 | C93: 80125 | D93: ='Payroll Summary'!G15
A94: =A93 | B94: =B93 | C94: INCENTIVE | D94: ='Payroll Summary'!L15
A95: =A94 | B95: =B94 | C95: MA | D95: ='Payroll Summary'!I15
A96: =A95 | B96: =B95 | C96: OT | D96: ='Payroll Summary'!E15
A97: =A96 | B97: =B96 | C97: RA | D97: ='Payroll Summary'!H15
A98: ='Payroll Summary'!B16 | B98: ='Payroll Summary'!A16 | C98: ANNLEAVE | D98: ='Payroll Summary'!J16
A99: =A98 | B99: =B98 | C99: NR | D99: ='Payroll Summary'!D16
A100: =A99 | B100: =B99 | C100: OT1 | D100: ='Payroll Summary'!F16
...

Sheet Payroll Summary
A1: Master Payroll Summary
A3: Name | B3: Number | C3: Agency | D3: Basic Hrs | E3: Overtime Hrs | F3: Hol Hrs | G3: Responsibilities | H3: Risk | I3: Meals | J3: Annual Leave Hrs | K3: Days Worked | L3: Incentive
A4: ='Nelson, Keshia'!M5 | B4: ='Nelson, Keshia'!M4 | C4: ='Nelson, Keshia'!O7 | D4: ='Nelson, Keshia'!M49 | E4: ='Nelson, Keshia'!N49 | F4: ='Nelson, Keshia'!O49 | G4: ='Nelson, Keshia'!P49 | H4: ='Nelson, Keshia'!Q49 | I4: ='Nelson, Keshia'!R49 | J4: ='Nelson, Keshia'!S49 | K4: ='Nelson, Keshia'!Q50
A5: ='Abel, Natalie'!M5 | B5: ='Abel, Natalie'!M4 | C5: ='Abel, Natalie'!O7 | D5: ='Abel, Natalie'!M49 | E5: ='Abel, Natalie'!N49 | F5: ='Abel, Natalie'!O49 | G5: ='Abel, Natalie'!P49 | H5: ='Abel, Natalie'!Q49 | I5: ='Abel, Natalie'!R49 | J5: ='Abel, Natalie'!S49 | K5: ='Abel, Natalie'!Q50
A6: ='April, Candica'!M5 | B6: ='April, Candica'!M4 | C6: ='April, Candica'!O7 | D6: ='April, Candica'!M49 | E6: ='April, Candica'!N49 | F6: ='April, Candica'!O49 | G6: ='April, Candica'!P49 | H6: ='April, Candica'!Q49 | I6: ='April, Candica'!R49 | J6: ='April, Candica'!S49 | K6: ='April, Candica'!Q50
A7: ='Beharry, Akeela'!M5 | B7: ='Beharry, Akeela'!M4 | C7: ='Beharry, Akeela'!O7 | D7: ='Beharry, Akeela'!M49 | E7: ='Beharry, Akeela'!N49 | F7: ='Beharry, Akeela'!O49 | G7: ='Beharry, Akeela'!P49 | H7: ='Beharry, Akeela'!Q49 | I7: ='Beharry, Akeela'!R49 | J7: ='Beharry, Akeela'!S49 | K7: ='Beharry, Akeela'!Q50
A8: ='Charles, Maisha'!M5 | B8: ='Charles, Maisha'!M4 | C8: ='Charles, Maisha'!O7 | D8: ='Charles, Maisha'!M49 | E8: ='Charles, Maisha'!N49 | F8: ='Charles, Maisha'!O49 | G8: ='Charles, Maisha'!P49 | H8: ='Charles, Maisha'!Q49 | I8: ='Charles, Maisha'!R49 | J8: ='Charles, Maisha'!S49 | K8: ='Charles, Maisha'!Q50
A9: ='Eastman, Dennis'!M5 | B9: ='Eastman, Dennis'!M4 | C9: ='Eastman, Dennis'!O7 | D9: ='Eastman, Dennis'!M49 | E9: ='Eastman, Dennis'!N49 | F9: ='Eastman, Dennis'!O49 | G9: ='Eastman, Dennis'!P49 | H9: ='Eastman, Dennis'!Q49 | I9: ='Eastman, Dennis'!R49 | J9: ='Eastman, Dennis'!S49 | K9: ='Eastman, Dennis'!Q50
A10: ='Eastman, Dorritte'!M5 | B10: ='Eastman, Dorritte'!M4 | C10: ='Eastman, Dorritte'!O7 | D10: ='Eastman, Dorritte'!M49 | E10: ='Eastman, Dorritte'!N49 | F10: ='Eastman, Dorritte'!O49 | G10: ='Eastman, Dorritte'!P49 | H10: ='Eastman, Dorritte'!Q49 | I10: ='Eastman, Dorritte'!R49 | J10: ='Eastman, Dorritte'!S49 | K10: ='Eastman, Dorritte'!Q50
A11: ='Hector, Aaliyah'!M5 | B11: ='Hector, Aaliyah'!M4 | C11: ='Hector, Aaliyah'!O7 | D11: ='Hector, Aaliyah'!M49 | E11: ='Hector, Aaliyah'!N49 | F11: ='Hector, Aaliyah'!O49 | G11: ='Hector, Aaliyah'!P49 | H11: ='Hector, Aaliyah'!Q49 | I11: ='Hector, Aaliyah'!R49 | J11: ='Hector, Aaliyah'!S49 | K11: ='Hector, Aaliyah'!Q50
A12: ='Hector, Onicka'!M5 | B12: ='Hector, Onicka'!M4 | C12: ='Hector, Onicka'!O7 | D12: ='Hector, Onicka'!M49 | E12: ='Hector, Onicka'!N49 | F12: ='Hector, Onicka'!O49 | G12: ='Hector, Onicka'!P49 | H12: ='Hector, Onicka'!Q49 | I12: ='Hector, Onicka'!R49 | J12: ='Hector, Onicka'!S49 | K12: ='Hector, Onicka'!Q50
A13: ='Lawrence, Stephen'!M5 | B13: ='Lawrence, Stephen'!M4 | C13: ='Lawrence, Stephen'!O7 | D13: ='Lawrence, Stephen'!M49 | E13: ='Lawrence, Stephen'!N49 | F13: ='Lawrence, Stephen'!O49 | G13: ='Lawrence, Stephen'!P49 | H13: ='Lawrence, Stephen'!Q49 | I13: ='Lawrence, Stephen'!R49 | J13: ='Lawrence, Stephen'!S49 | K13: ='Lawrence, Stephen'!Q50
A14: ='Lawson, Delicia'!M5 | B14: ='Lawson, Delicia'!M4 | C14: ='Lawson, Delicia'!O7 | D14: ='Lawson, Delicia'!M49 | E14: ='Lawson, Delicia'!N49 | F14: ='Lawson, Delicia'!O49 | G14: ='Lawson, Delicia'!P49 | H14: ='Lawson, Delicia'!Q49 | I14: ='Lawson, Delicia'!R49 | J14: ='Lawson, Delicia'!S49 | K14: ='Lawson, Delicia'!Q50
A15: ='Lewis, Tahandica'!M5 | B15: ='Lewis, Tahandica'!M4 | C15: ='Lewis, Tahandica'!O7 | D15: ='Lewis, Tahandica'!M49 | E15: ='Lewis, Tahandica'!N49 | F15: ='Lewis, Tahandica'!O49 | G15: ='Lewis, Tahandica'!P49 | H15: ='Lewis, Tahandica'!Q49 | I15: ='Lewis, Tahandica'!R49 | J15: ='Lewis, Tahandica'!S49 | K15: ='Lewis, Tahandica'!Q50
A16: ='Parris, Ceyon'!M5 | B16: ='Parris, Ceyon'!M4 | C16: ='Parris, Ceyon'!O7 | D16: ='Parris, Ceyon'!M49 | E16: ='Parris, Ceyon'!N49 | F16: ='Parris, Ceyon'!O49 | G16: ='Parris, Ceyon'!P49 | H16: ='Parris, Ceyon'!Q49 | I16: ='Parris, Ceyon'!R49 | J16: ='Parris, Ceyon'!S49 | K16: ='Parris, Ceyon'!Q50
A17: ='Phoenix, Ryan'!M5 | B17: ='Phoenix, Ryan'!M4 | C17: ='Phoenix, Ryan'!O7 | D17: ='Phoenix, Ryan'!M49 | E17: ='Phoenix, Ryan'!N49 | F17: ='Phoenix, Ryan'!O49 | G17: ='Phoenix, Ryan'!P49 | H17: ='Phoenix, Ryan'!Q49 | I17: ='Phoenix, Ryan'!R49 | J17: ='Phoenix, Ryan'!S49 | K17: ='Phoenix, Ryan'!Q50
A18: ='Pollard, Lotoya'!M5 | B18: ='Pollard, Lotoya'!M4 | C18: ='Pollard, Lotoya'!O7 | D18: ='Pollard, Lotoya'!M49 | E18: ='Pollard, Lotoya'!N49 | F18: ='Pollard, Lotoya'!O49 | G18: ='Pollard, Lotoya'!P49 | H18: ='Pollard, Lotoya'!Q49 | I18: ='Pollard, Lotoya'!R49 | J18: ='Pollard, Lotoya'!S49 | K18: ='Pollard, Lotoya'!Q50
A19: ='Reynolds, Kevin'!M5 | B19: ='Reynolds, Kevin'!M4 | C19: ='Reynolds, Kevin'!O7 | D19: ='Reynolds, Kevin'!M49 | E19: ='Reynolds, Kevin'!N49 | F19: ='Reynolds, Kevin'!O49 | G19: ='Reynolds, Kevin'!P49 | H19: ='Reynolds, Kevin'!Q49 | I19: ='Reynolds, Kevin'!R49 | J19: ='Reynolds, Kevin'!S49 | K19: ='Reynolds, Kevin'!Q50
A20: ='Roberts, Odetta'!M5 | B20: ='Roberts, Odetta'!M4 | C20: ='Roberts, Odetta'!O7 | D20: ='Roberts, Odetta'!M49 | E20: ='Roberts, Odetta'!N49 | F20: ='Roberts, Odetta'!O49 | G20: ='Roberts, Odetta'!P49 | H20: ='Roberts, Odetta'!Q49 | I20: ='Roberts, Odetta'!R49 | J20: ='Roberts, Odetta'!S49 | K20: ='Roberts, Odetta'!Q50
A21: ='Robinson, Candacy'!M5 | B21: ='Robinson, Candacy'!M4 | C21: ='Robinson, Candacy'!O7 | D21: ='Robinson, Candacy'!M49 | E21: ='Robinson, Candacy'!N49 | F21: ='Robinson, Candacy'!O49 | G21: ='Robinson, Candacy'!P49 | H21: ='Robinson, Candacy'!Q49 | I21: ='Robinson, Candacy'!R49 | J21: ='Robinson, Candacy'!S49 | K21: ='Robinson, Candacy'!Q50
A22: ='Spencer, Renita'!M5 | B22: ='Spencer, Renita'!M4 | C22: ='Spencer, Renita'!O7 | D22: ='Spencer, Renita'!M49 | E22: ='Spencer, Renita'!N49 | F22: ='Spencer, Renita'!O49 | G22: ='Spencer, Renita'!P49 | H22: ='Spencer, Renita'!Q49 | I22: ='Spencer, Renita'!R49 | J22: ='Spencer, Renita'!S49 | K22: ='Spencer, Renita'!Q50
A23: ='Blake, Bevon'!M5 | B23: ='Blake, Bevon'!M4 | C23: ='Blake, Bevon'!O7 | D23: ='Blake, Bevon'!M49 | E23: ='Blake, Bevon'!N49 | F23: ='Blake, Bevon'!O49 | G23: ='Blake, Bevon'!P49 | H23: ='Blake, Bevon'!Q49 | I23: ='Blake, Bevon'!R49 | J23: ='Blake, Bevon'!S49 | K23: ='Blake, Bevon'!Q50
A24: ='Smith, Tiffany'!M5 | B24: ='Smith, Tiffany'!M4 | C24: ='Smith, Tiffany'!O7 | D24: ='Smith, Tiffany'!M49 | E24: ='Smith, Tiffany'!N49 | F24: ='Smith, Tiffany'!O49 | G24: ='Smith, Tiffany'!P49 | H24: ='Smith, Tiffany'!Q49 | I24: ='Smith, Tiffany'!R49 | J24: ='Smith, Tiffany'!S49 | K24: ='Smith, Tiffany'!Q50
A25: ='Ash, Carol'!M5 | B25: ='Ash, Carol'!M4 | C25: ='Ash, Carol'!O7 | D25: ='Ash, Carol'!M49 | E25: ='Ash, Carol'!N49 | F25: ='Ash, Carol'!O49 | G25: ='Ash, Carol'!P49 | H25: ='Ash, Carol'!Q49 | I25: ='Ash, Carol'!R49 | J25: ='Ash, Carol'!S49 | K25: ='Ash, Carol'!Q50
A26: ='Cromwell, Dexter'!M5 | B26: ='Cromwell, Dexter'!M4 | C26: ='Cromwell, Dexter'!O7 | D26: ='Cromwell, Dexter'!M49 | E26: ='Cromwell, Dexter'!N49 | F26: ='Cromwell, Dexter'!O49 | G26: ='Cromwell, Dexter'!P49 | H26: ='Cromwell, Dexter'!Q49 | I26: ='Cromwell, Dexter'!R49 | J26: ='Cromwell, Dexter'!S49 | K26: ='Cromwell, Dexter'!Q50
A27: ='Grant, Earl'!M5 | B27: ='Grant, Earl'!M4 | C27: ='Grant, Earl'!O7 | D27: ='Grant, Earl'!M49 | E27: ='Grant, Earl'!N49 | F27: ='Grant, Earl'!O49 | G27: ='Grant, Earl'!P49 | H27: ='Grant, Earl'!Q49 | I27: ='Grant, Earl'!R49 | J27: ='Grant, Earl'!S49 | K27: ='Grant, Earl'!Q50
A28: ='Harry, Dennis'!M5 | B28: ='Harry, Dennis'!M4 | C28: ='Harry, Dennis'!O7 | D28: ='Harry, Dennis'!M49 | E28: ='Harry, Dennis'!N49 | F28: ='Harry, Dennis'!O49 | G28: ='Harry, Dennis'!P49 | H28: ='Harry, Dennis'!Q49 | I28: ='Harry, Dennis'!R49 | J28: ='Harry, Dennis'!S49 | K28: ='Harry, Dennis'!Q50
A29: ='Inniss, Euci'!M5 | B29: ='Inniss, Euci'!M4 | C29: ='Inniss, Euci'!O7 | D29: ='Inniss, Euci'!M49 | E29: ='Inniss, Euci'!N49 | F29: ='Inniss, Euci'!O49 | G29: ='Inniss, Euci'!P49 | H29: ='Inniss, Euci'!Q49 | I29: ='Inniss, Euci'!R49 | J29: ='Inniss, Euci'!S49 | K29: ='Inniss, Euci'!Q50
A30: ='Khan, Ahmad'!M5 | B30: ='Khan, Ahmad'!M4 | C30: ='Khan, Ahmad'!O7 | D30: ='Khan, Ahmad'!M49 | E30: ='Khan, Ahmad'!N49 | F30: ='Khan, Ahmad'!O49 | G30: ='Khan, Ahmad'!P49 | H30: ='Khan, Ahmad'!Q49 | I30: ='Khan, Ahmad'!R49 | J30: ='Khan, Ahmad'!S49 | K30: ='Khan, Ahmad'!Q50
A31: ='Vincent, Fucien'!M5 | B31: ='Vincent, Fucien'!M4 | C31: ='Vincent, Fucien'!O7 | D31: ='Vincent, Fucien'!M49 | E31: ='Vincent, Fucien'!N49 | F31: ='Vincent, Fucien'!O49 | G31: ='Vincent, Fucien'!P49 | H31: ='Vincent, Fucien'!Q49 | I31: ='Vincent, Fucien'!R49 | J31: ='Vincent, Fucien'!S49 | K31: ='Vincent, Fucien'!Q50
A105: TOTAL | D105: =SUM(D4:D104) | E105: =SUM(E4:E104) | F105: =SUM(F4:F104) | G105: =SUM(G4:G104) | H105: =SUM(H4:H104) | I105: =SUM(I4:I104) | J105: =SUM(J4:J104) | L105: =SUM(L4:L104)
A107: PAYROLL APPROVAL
A108: Pay Period Start: | F108: Pay Period End:
A109: Prepared By: | F109: Prepared Date:
A110: Checked By: | F110: Checked Date:
A111: Approved By: | F111: Approved Date:
A112: Payment Method / Bank: | F112: Total Net Pay:
A113: Notes:
A115: Signatures (if required):
A116: I confirm the above payroll has been reviewed and approved for processing.

Sheet TEMPLATE
V2: 2025 | Z2: Month: | AA2: 3
V3: =DATE(V2,AA2,1)
C4: Federal Manangement Systems | K4: Employee Number: | V4: Su | W4: M | X4: Tu | Y4: W | Z4: Th | AA4: F | AB4: Sa | AD4: Overtime Options
K5: Employee Name: | M5: Claudette Yearwood | V5: =IF(MONTH($V$3)<>MONTH($V$3-WEEKDAY($V$3,1)+(ROW(V5)-ROW($V$5))*7+(COLUMN(V5)-COLUMN($V$5)+1)),"",$V$3-WEEKDAY($V$3,1)+(ROW(V5)-ROW($V$5))*7+(COLUMN(V5)-COLUMN($V$5)+1)) | W5: =IF(MONTH($V$3)<>MONTH($V$3-WEEKDAY($V$3,1)+(ROW(W5)-ROW($V$5))*7+(COLUMN(W5)-COLUMN($V$5)+1)),"",$V$3-WEEKDAY($V$3,1)+(ROW(W5)-ROW($V$5))*7+(COLUMN(W5)-COLUMN($V$5)+1)) | X5: =IF(MONTH($V$3)<>MONTH($V$3-WEEKDAY($V$3,1)+(ROW(X5)-ROW($V$5))*7+(COLUMN(X5)-COLUMN($V$5)+1)),"",$V$3-WEEKDAY($V$3,1)+(ROW(X5)-ROW($V$5))*7+(COLUMN(X5)-COLUMN($V$5)+1)) | Y5: =IF(MONTH($V$3)<>MONTH($V$3-WEEKDAY($V$3,1)+(ROW(Y5)-ROW($V$5))*7+(COLUMN(Y5)-COLUMN($V$5)+1)),"",$V$3-WEEKDAY($V$3,1)+(ROW(Y5)-ROW($V$5))*7+(COLUMN(Y5)-COLUMN($V$5)+1)) | Z5: =IF(MONTH($V$3)<>MONTH($V$3-WEEKDAY($V$3,1)+(ROW(Z5)-ROW($V$5))*7+(COLUMN(Z5)-COLUMN($V$5)+1)),"",$V$3-WEEKDAY($V$3,1)+(ROW(Z5)-ROW($V$5))*7+(COLUMN(Z5)-COLUMN($V$5)+1)) | AA5: =IF(MONTH($V$3)<>MONTH($V$3-WEEKDAY($V$3,1)+(ROW(AA5)-ROW($V$5))*7+(COLUMN(AA5)-COLUMN($V$5)+1)),"",$V$3-WEEKDAY($V$3,1)+(ROW(AA5)-ROW($V$5))*7+(COLUMN(AA5)-COLUMN($V$5)+1)) | AB5: =IF(MONTH($V$3)<>MONTH($V$3-WEEKDAY($V$3,1)+(ROW(AB5)-ROW($V$5))*7+(COLUMN(AB5)-COLUMN($V$5)+1)),"",$V$3-WEEKDAY($V$3,1)+(ROW(AB5)-ROW($V$5))*7+(COLUMN(AB5)-COLUMN($V$5)+1)) | AE5: TRUE
C6: 120 Peter Rose St | M6: Armed or unarmed | O6: Unarmed | V6: =IF(MONTH($V$3)<>MONTH($V$3-WEEKDAY($V$3,1)+(ROW(V6)-ROW($V$5))*7+(COLUMN(V6)-COLUMN($V$5)+1)),"",$V$3-WEEKDAY($V$3,1)+(ROW(V6)-ROW($V$5))*7+(COLUMN(V6)-COLUMN($V$5)+1)) | W6: =IF(MONTH($V$3)<>MONTH($V$3-WEEKDAY($V$3,1)+(ROW(W6)-ROW($V$5))*7+(COLUMN(W6)-COLUMN($V$5)+1)),"",$V$3-WEEKDAY($V$3,1)+(ROW(W6)-ROW($V$5))*7+(COLUMN(W6)-COLUMN($V$5)+1)) | X6: =IF(MONTH($V$3)<>MONTH($V$3-WEEKDAY($V$3,1)+(ROW(X6)-ROW($V$5))*7+(COLUMN(X6)-COLUMN($V$5)+1)),"",$V$3-WEEKDAY($V$3,1)+(ROW(X6)-ROW($V$5))*7+(COLUMN(X6)-COLUMN($V$5)+1)) | Y6: =IF(MONTH($V$3)<>MONTH($V$3-WEEKDAY($V$3,1)+(ROW(Y6)-ROW($V$5))*7+(COLUMN(Y6)-COLUMN($V$5)+1)),"",$V$3-WEEKDAY($V$3,1)+(ROW(Y6)-ROW($V$5))*7+(COLUMN(Y6)-COLUMN($V$5)+1)) | Z6: =IF(MONTH($V$3)<>MONTH($V$3-WEEKDAY($V$3,1)+(ROW(Z6)-ROW($V$5))*7+(COLUMN(Z6)-COLUMN($V$5)+1)),"",$V$3-WEEKDAY($V$3,1)+(ROW(Z6)-ROW($V$5))*7+(COLUMN(Z6)-COLUMN($V$5)+1)) | AA6: =IF(MONTH($V$3)<>MONTH($V$3-WEEKDAY($V$3,1)+(ROW(AA6)-ROW($V$5))*7+(COLUMN(AA6)-COLUMN($V$5)+1)),"",$V$3-WEEKDAY($V$3,1)+(ROW(AA6)-ROW($V$5))*7+(COLUMN(AA6)-COLUMN($V$5)+1)) | AB6: =IF(MONTH($V$3)<>MONTH($V$3-WEEKDAY($V$3,1)+(ROW(AB6)-ROW($V$5))*7+(COLUMN(AB6)-COLUMN($V$5)+1)),"",$V$3-WEEKDAY($V$3,1)+(ROW(AB6)-ROW($V$5))*7+(COLUMN(AB6)-COLUMN($V$5)+1)) | AD6: After: | AE6: 8 | AF6: Hrs
C7: Queenstown | M7: Agency | O7: Caricom | V7: =IF(MONTH($V$3)<>MONTH($V$3-WEEKDAY($V$3,1)+(ROW(V7)-ROW($V$5))*7+(COLUMN(V7)-COLUMN($V$5)+1)),"",$V$3-WEEKDAY($V$3,1)+(ROW(V7)-ROW($V$5))*7+(COLUMN(V7)-COLUMN($V$5)+1)) | W7: =IF(MONTH($V$3)<>MONTH($V$3-WEEKDAY($V$3,1)+(ROW(W7)-ROW($V$5))*7+(COLUMN(W7)-COLUMN($V$5)+1)),"",$V$3-WEEKDAY($V$3,1)+(ROW(W7)-ROW($V$5))*7+(COLUMN(W7)-COLUMN($V$5)+1)) | X7: =IF(MONTH($V$3)<>MONTH($V$3-WEEKDAY($V$3,1)+(ROW(X7)-ROW($V$5))*7+(COLUMN(X7)-COLUMN($V$5)+1)),"",$V$3-WEEKDAY($V$3,1)+(ROW(X7)-ROW($V$5))*7+(COLUMN(X7)-COLUMN($V$5)+1)) | Y7: =IF(MONTH($V$3)<>MONTH($V$3-WEEKDAY($V$3,1)+(ROW(Y7)-ROW($V$5))*7+(COLUMN(Y7)-COLUMN($V$5)+1)),"",$V$3-WEEKDAY($V$3,1)+(ROW(Y7)-ROW($V$5))*7+(COLUMN(Y7)-COLUMN($V$5)+1)) | Z7: =IF(MONTH($V$3)<>MONTH($V$3-WEEKDAY($V$3,1)+(ROW(Z7)-ROW($V$5))*7+(COLUMN(Z7)-COLUMN($V$5)+1)),"",$V$3-WEEKDAY($V$3,1)+(ROW(Z7)-ROW($V$5))*7+(COLUMN(Z7)-COLUMN($V$5)+1)) | AA7: =IF(MONTH($V$3)<>MONTH($V$3-WEEKDAY($V$3,1)+(ROW(AA7)-ROW($V$5))*7+(COLUMN(AA7)-COLUMN($V$5)+1)),"",$V$3-WEEKDAY($V$3,1)+(ROW(AA7)-ROW($V$5))*7+(COLUMN(AA7)-COLUMN($V$5)+1)) | AB7: =IF(MONTH($V$3)<>MONTH($V$3-WEEKDAY($V$3,1)+(ROW(AB7)-ROW($V$5))*7+(COLUMN(AB7)-COLUMN($V$5)+1)),"",$V$3-WEEKDAY($V$3,1)+(ROW(AB7)-ROW($V$5))*7+(COLUMN(AB7)-COLUMN($V$5)+1))
C8: Georgetown, Guyana | V8: =IF(MONTH($V$3)<>MONTH($V$3-WEEKDAY($V$3,1)+(ROW(V8)-ROW($V$5))*7+(COLUMN(V8)-COLUMN($V$5)+1)),"",$V$3-WEEKDAY($V$3,1)+(ROW(V8)-ROW($V$5))*7+(COLUMN(V8)-COLUMN($V$5)+1)) | W8: =IF(MONTH($V$3)<>MONTH($V$3-WEEKDAY($V$3,1)+(ROW(W8)-ROW($V$5))*7+(COLUMN(W8)-COLUMN($V$5)+1)),"",$V$3-WEEKDAY($V$3,1)+(ROW(W8)-ROW($V$5))*7+(COLUMN(W8)-COLUMN($V$5)+1)) | X8: =IF(MONTH($V$3)<>MONTH($V$3-WEEKDAY($V$3,1)+(ROW(X8)-ROW($V$5))*7+(COLUMN(X8)-COLUMN($V$5)+1)),"",$V$3-WEEKDAY($V$3,1)+(ROW(X8)-ROW($V$5))*7+(COLUMN(X8)-COLUMN($V$5)+1)) | Y8: =IF(MONTH($V$3)<>MONTH($V$3-WEEKDAY($V$3,1)+(ROW(Y8)-ROW($V$5))*7+(COLUMN(Y8)-COLUMN($V$5)+1)),"",$V$3-WEEKDAY($V$3,1)+(ROW(Y8)-ROW($V$5))*7+(COLUMN(Y8)-COLUMN($V$5)+1)) | Z8: =IF(MONTH($V$3)<>MONTH($V$3-WEEKDAY($V$3,1)+(ROW(Z8)-ROW($V$5))*7+(COLUMN(Z8)-COLUMN($V$5)+1)),"",$V$3-WEEKDAY($V$3,1)+(ROW(Z8)-ROW($V$5))*7+(COLUMN(Z8)-COLUMN($V$5)+1)) | AA8: =IF(MONTH($V$3)<>MONTH($V$3-WEEKDAY($V$3,1)+(ROW(AA8)-ROW($V$5))*7+(COLUMN(AA8)-COLUMN($V$5)+1)),"",$V$3-WEEKDAY($V$3,1)+(ROW(AA8)-ROW($V$5))*7+(COLUMN(AA8)-COLUMN($V$5)+1)) | AB8: =IF(MONTH($V$3)<>MONTH($V$3-WEEKDAY($V$3,1)+(ROW(AB8)-ROW($V$5))*7+(COLUMN(AB8)-COLUMN($V$5)+1)),"",$V$3-WEEKDAY($V$3,1)+(ROW(AB8)-ROW($V$5))*7+(COLUMN(AB8)-COLUMN($V$5)+1)) | AE8: TRUE
C10: 592-223-7560 | K10: Week Starting: | M10: 45977 | T10: [42] | V10: =IF(MONTH($V$3)<>MONTH($V$3-WEEKDAY($V$3,1)+(ROW(V10)-ROW($V$5))*7+(COLUMN(V10)-COLUMN($V$5)+1)),"",$V$3-WEEKDAY($V$3,1)+(ROW(V10)-ROW($V$5))*7+(COLUMN(V10)-COLUMN($V$5)+1)) | W10: =IF(MONTH($V$3)<>MONTH($V$3-WEEKDAY($V$3,1)+(ROW(W10)-ROW($V$5))*7+(COLUMN(W10)-COLUMN($V$5)+1)),"",$V$3-WEEKDAY($V$3,1)+(ROW(W10)-ROW($V$5))*7+(COLUMN(W10)-COLUMN($V$5)+1)) | X10: =IF(MONTH($V$3)<>MONTH($V$3-WEEKDAY($V$3,1)+(ROW(X10)-ROW($V$5))*7+(COLUMN(X10)-COLUMN($V$5)+1)),"",$V$3-WEEKDAY($V$3,1)+(ROW(X10)-ROW($V$5))*7+(COLUMN(X10)-COLUMN($V$5)+1)) | Y10: =IF(MONTH($V$3)<>MONTH($V$3-WEEKDAY($V$3,1)+(ROW(Y10)-ROW($V$5))*7+(COLUMN(Y10)-COLUMN($V$5)+1)),"",$V$3-WEEKDAY($V$3,1)+(ROW(Y10)-ROW($V$5))*7+(COLUMN(Y10)-COLUMN($V$5)+1)) | Z10: =IF(MONTH($V$3)<>MONTH($V$3-WEEKDAY($V$3,1)+(ROW(Z10)-ROW($V$5))*7+(COLUMN(Z10)-COLUMN($V$5)+1)),"",$V$3-WEEKDAY($V$3,1)+(ROW(Z10)-ROW($V$5))*7+(COLUMN(Z10)-COLUMN($V$5)+1)) | AA10: =IF(MONTH($V$3)<>MONTH($V$3-WEEKDAY($V$3,1)+(ROW(AA10)-ROW($V$5))*7+(COLUMN(AA10)-COLUMN($V$5)+1)),"",$V$3-WEEKDAY($V$3,1)+(ROW(AA10)-ROW($V$5))*7+(COLUMN(AA10)-COLUMN($V$5)+1)) | AB10: =IF(MONTH($V$3)<>MONTH($V$3-WEEKDAY($V$3,1)+(ROW(AB10)-ROW($V$5))*7+(COLUMN(AB10)-COLUMN($V$5)+1)),"",$V$3-WEEKDAY($V$3,1)+(ROW(AB10)-ROW($V$5))*7+(COLUMN(AB10)-COLUMN($V$5)+1)) | AD10: After: | AE10: 40 | AF10: Hrs
V11: =IF(MONTH($V$3)<>MONTH($V$3-WEEKDAY($V$3,1)+(ROW(V11)-ROW($V$5))*7+(COLUMN(V11)-COLUMN($V$5)+1)),"",$V$3-WEEKDAY($V$3,1)+(ROW(V11)-ROW($V$5))*7+(COLUMN(V11)-COLUMN($V$5)+1)) | W11: =IF(MONTH($V$3)<>MONTH($V$3-WEEKDAY($V$3,1)+(ROW(W11)-ROW($V$5))*7+(COLUMN(W11)-COLUMN($V$5)+1)),"",$V$3-WEEKDAY($V$3,1)+(ROW(W11)-ROW($V$5))*7+(COLUMN(W11)-COLUMN($V$5)+1)) | X11: =IF(MONTH($V$3)<>MONTH($V$3-WEEKDAY($V$3,1)+(ROW(X11)-ROW($V$5))*7+(COLUMN(X11)-COLUMN($V$5)+1)),"",$V$3-WEEKDAY($V$3,1)+(ROW(X11)-ROW($V$5))*7+(COLUMN(X11)-COLUMN($V$5)+1)) | Y11: =IF(MONTH($V$3)<>MONTH($V$3-WEEKDAY($V$3,1)+(ROW(Y11)-ROW($V$5))*7+(COLUMN(Y11)-COLUMN($V$5)+1)),"",$V$3-WEEKDAY($V$3,1)+(ROW(Y11)-ROW($V$5))*7+(COLUMN(Y11)-COLUMN($V$5)+1)) | Z11: =IF(MONTH($V$3)<>MONTH($V$3-WEEKDAY($V$3,1)+(ROW(Z11)-ROW($V$5))*7+(COLUMN(Z11)-COLUMN($V$5)+1)),"",$V$3-WEEKDAY($V$3,1)+(ROW(Z11)-ROW($V$5))*7+(COLUMN(Z11)-COLUMN($V$5)+1)) | AA11: =IF(MONTH($V$3)<>MONTH($V$3-WEEKDAY($V$3,1)+(ROW(AA11)-ROW($V$5))*7+(COLUMN(AA11)-COLUMN($V$5)+1)),"",$V$3-WEEKDAY($V$3,1)+(ROW(AA11)-ROW($V$5))*7+(COLUMN(AA11)-COLUMN($V$5)+1)) | AB11: =IF(MONTH($V$3)<>MONTH($V$3-WEEKDAY($V$3,1)+(ROW(AB11)-ROW($V$5))*7+(COLUMN(AB11)-COLUMN($V$5)+1)),"",$V$3-WEEKDAY($V$3,1)+(ROW(AB11)-ROW($V$5))*7+(COLUMN(AB11)-COLUMN($V$5)+1))
A12: Day Off | B12: Holiday Double | C12: Day of Week | D12: Time In | E12: Time Out | G12: Time In | H12: Time Out | I12: Total Hrs | J12: Location | K12: Supervisor | L12: Supervisor Approval | M12: Regular Hrs | N12: Overtime Hrs | O12: Hol Hrs | P12: Responsibilities | Q12: Risk | R12: Meals | S12: Vac Hrs | T12: Reason for Overtime
A14: Annual Leave | C14: =M10 | D14: 0.29166667 | E14: =IF(D14="", "", IF(D14=TIME(0,0,0), 0, IF(AND(D14>=TIME(0,0,1), D14<=TIME(2,0,0)), TIME(7,0,0), IF(AND(D14>=TIME(5,0,0), D14<=TIME(8,0,0)), TIME(12,0,0), IF(AND(D14>TIME(8,0,0), D14<=TIME(13,59,0)), TIME(15,0,0), IF(AND(D14>=TIME(14,0,0), D14<=TIME(17,59,0)), TIME(21,0,0), IF(AND(D14>=TIME(18,0,0), D14<=TIME(21,59,0)), TIME(0,0,0), IF(AND(D14>=TIME(22,0,0), D14<=TIME(23,59,59)), TIME(7,0,0), "")))))))) | G14: =E14 | I14: =ROUND(IF(OR(D14="",E14="",E14=0),0,IF(H14="",MOD(E14-D14,1)*24,MOD(H14-D14,1)*24)),2) | J14: Nept P1 | K14: John Daniels | L14: FALSE | M14: =IF(OR($A14="Holiday",$A15="Holiday"),IF(OR($C14="",$D14=""),0, IF(OR($A14="Holiday",$A15="Holiday"),0, IF(AND(NOT(OR($A14="Annual Leave",$A15="Annual Leave")),$A14="Off day"),0, IF($I14+$I15>=8,IF($I14>=8,8,$I14),$I14) )))+IF(MOD(ROW(),2)=0,8,0),IF(OR($C14="",$D14=""),0, IF(OR($A14="Holiday",$A15="Holiday"),0, IF(AND(NOT(OR($A14="Annual Leave",$A15="Annual Leave")),$A14="Off day"),0, IF($I14+$I15>=8,IF($I14>=8,8,$I14),$I14) )))) | N14: =IF(OR($C14="",$D14=""),0, IF(OR($A14="Holiday",$A15="Holiday"), IF(ISNUMBER(MATCH(TRIM($B14),{"Phagwah","Good Friday","Easter Monday","Labour Day","Christmas","Eid ul Azha","Romans-2","Globe-12","Neptune P1"},0)),0,$I14), IF(AND(NOT(OR($A14="Annual Leave",$A15="Annual Leave")),$A14="Off day"),$I14, MAX(0,$I14-$M14) ))) | O14: =IF(AND(OR($A14="Holiday",$A15="Holiday"), ISNUMBER(MATCH(TRIM($B14),{"Phagwah","Good Friday","Easter Monday","Labour Day","Christmas","Eid ul Azha","Romans-2","Globe-12","Neptune P1"},0))), $I14,0) | R14: =IF(OR($O$7="Canteen",$O$7="Head Office"),0,IF(OR($I14>0,$I15>0), IF( OR( AND($D14>=TIME(5,0,0),$D14<=TIME(7,0,0)), AND($D14>=TIME(14,0,0),$D14<=TIME(15,0,0)), AND($D14>=TIME(18,0,0),$D14<=TIME(19,0,0)), AND($D15>=TIME(5,0,0),$D15<=TIME(7,0,0)), AND($D15>=TIME(14,0,0),$D15<=TIME(15,0,0)), AND($D15>=TIME(18,0,0),$D15<=TIME(19,0,0)) ), IF($I14>0,1,0), 0 ), 0)) | S14: =IF(OR($A14="Annual Leave",$A15="Annual Leave"),IF($A14="Annual Leave",8,0),0)
A15: On Day | C15: =C14 | E15: =IF(D15=0, 0, IF(AND(D15>=TIME(0,0,1), D15<=TIME(2,0,0)), TIME(7,0,0), IF(AND(D15>=TIME(5,0,0), D15<=TIME(8,0,0)), TIME(12,0,0), IF(AND(D15>TIME(8,0,0), D15<=TIME(13,59,0)), TIME(15,0,0), IF(AND(D15>=TIME(14,0,0), D15<=TIME(17,59,0)), TIME(21,0,0), IF(AND(D15>=TIME(18,0,0), D15<=TIME(21,59,0)), TIME(0,0,0), IF(AND(D15>=TIME(22,0,0), D15<=TIME(23,59,59)), TIME(7,0,0), ""))))))) | G15: =E15 | I15: =ROUND(IF(OR(D15="",E15="",E15=0),0,IF(H15="",MOD(E15-D15,1)*24,MOD(H15-D15,1)*24)),2) | L15: FALSE | M15: =IF(OR($A15="Holiday",$A14="Holiday"),IF(OR($C15="",$D15=""),0, IF(OR($A14="Holiday",$A15="Holiday"),0, IF(AND(NOT(OR($A14="Annual Leave",$A15="Annual Leave")),$A15="Off day"),0, IF($I14+$I15>=8,IF($I14>=8,0,8-$I14),$I15) )))+IF(MOD(ROW(),2)=0,8,0),IF(OR($C15="",$D15=""),0, IF(OR($A14="Holiday",$A15="Holiday"),0, IF(AND(NOT(OR($A14="Annual Leave",$A15="Annual Leave")),$A15="Off day"),0, IF($I14+$I15>=8,IF($I14>=8,0,8-$I14),$I15) )))) | N15: =IF(OR($C15="",$D15=""),0, IF(OR($A14="Holiday",$A15="Holiday"), IF(ISNUMBER(MATCH(TRIM($B15),{"Phagwah","Good Friday","Easter Monday","Labour Day","Christmas","Eid ul Azha","Romans-2","Globe-12","Neptune P1"},0)),0,$I15), IF(AND(NOT(OR($A14="Annual Leave",$A15="Annual Leave")),$A15="Off day"),$I15, MAX(0,$I15-$M15) ))) | O15: =IF(AND(OR($A14="Holiday",$A15="Holiday"), ISNUMBER(MATCH(TRIM($B15),{"Phagwah","Good Friday","Easter Monday","Labour Day","Christmas","Eid ul Azha","Romans-2","Globe-12","Neptune P1"},0))), $I15,0) | R15: =IF(OR($O$7="Canteen",$O$7="Head Office"),0,IF(OR($I14>0,$I15>0), IF( OR( AND($D14>=TIME(5,0,0),$D14<=TIME(7,0,0)), AND($D14>=TIME(14,0,0),$D14<=TIME(15,0,0)), AND($D14>=TIME(18,0,0),$D14<=TIME(19,0,0)), AND($D15>=TIME(5,0,0),$D15<=TIME(7,0,0)), AND($D15>=TIME(14,0,0),$D15<=TIME(15,0,0)), AND($D15>=TIME(18,0,0),$D15<=TIME(19,0,0)) ), IF(AND($I14=0,$I15>0),1,0), 0 ), 0)) | S15: =IF(OR($A14="Annual Leave",$A15="Annual Leave"),IF(AND($A14<>"Annual Leave",$A15="Annual Leave"),8,0),0)
A16: On Day | C16: =C14+1 | E16: =IF(D16=0, 0, IF(AND(D16>=TIME(0,0,1), D16<=TIME(2,0,0)), TIME(7,0,0), IF(AND(D16>=TIME(5,0,0), D16<=TIME(8,0,0)), TIME(12,0,0), IF(AND(D16>TIME(8,0,0), D16<=TIME(13,59,0)), TIME(15,0,0), IF(AND(D16>=TIME(14,0,0), D16<=TIME(17,59,0)), TIME(21,0,0), IF(AND(D16>=TIME(18,0,0), D16<=TIME(21,59,0)), TIME(0,0,0), IF(AND(D16>=TIME(22,0,0), D16<=TIME(23,59,59)), TIME(7,0,0), ""))))))) | G16: =E16 | I16: =ROUND(IF(OR(D16="",E16="",E16=0),0,IF(H16="",MOD(E16-D16,1)*24,MOD(H16-D16,1)*24)),2) | L16: FALSE | M16: =IF(OR($A16="Holiday",$A17="Holiday"),IF(OR($C16="",$D16=""),0, IF(OR($A16="Holiday",$A17="Holiday"),0, IF(AND(NOT(OR($A16="Annual Leave",$A17="Annual Leave")),$A16="Off day"),0, IF($I16+$I17>=8,IF($I16>=8,8,$I16),$I16) )))+IF(MOD(ROW(),2)=0,8,0),IF(OR($C16="",$D16=""),0, IF(OR($A16="Holiday",$A17="Holiday"),0, IF(AND(NOT(OR($A16="Annual Leave",$A17="Annual Leave")),$A16="Off day"),0, IF($I16+$I17>=8,IF($I16>=8,8,$I16),$I16) )))) | N16: =IF(OR($C16="",$D16=""),0, IF(OR($A16="Holiday",$A17="Holiday"), IF(ISNUMBER(MATCH(TRIM($B16),{"Phagwah","Good Friday","Easter Monday","Labour Day","Christmas","Eid ul Azha","Romans-2","Globe-12","Neptune P1"},0)),0,$I16), IF(AND(NOT(OR($A16="Annual Leave",$A17="Annual Leave")),$A16="Off day"),$I16, MAX(0,$I16-$M16) ))) | O16: =IF(AND(OR($A16="Holiday",$A17="Holiday"), ISNUMBER(MATCH(TRIM($B16),{"Phagwah","Good Friday","Easter Monday","Labour Day","Christmas","Eid ul Azha","Romans-2","Globe-12","Neptune P1"},0))), $I16,0) | R16: =IF(OR($O$7="Canteen",$O$7="Head Office"),0,IF(OR($I16>0,$I17>0), IF( OR( AND($D16>=TIME(5,0,0),$D16<=TIME(7,0,0)), AND($D16>=TIME(14,0,0),$D16<=TIME(15,0,0)), AND($D16>=TIME(18,0,0),$D16<=TIME(19,0,0)), AND($D17>=TIME(5,0,0),$D17<=TIME(7,0,0)), AND($D17>=TIME(14,0,0),$D17<=TIME(15,0,0)), AND($D17>=TIME(18,0,0),$D17<=TIME(19,0,0)) ), IF($I16>0,1,0), 0 ), 0)) | S16: =IF(OR($A16="Annual Leave",$A17="Annual Leave"),IF($A16="Annual Leave",8,0),0)
A17: On Day | C17: =C16 | D17: 0.79166667 | E17: =IF(D17=0, 0, IF(AND(D17>=TIME(0,0,1), D17<=TIME(2,0,0)), TIME(7,0,0), IF(AND(D17>=TIME(5,0,0), D17<=TIME(8,0,0)), TIME(12,0,0), IF(AND(D17>TIME(8,0,0), D17<=TIME(13,59,0)), TIME(15,0,0), IF(AND(D17>=TIME(14,0,0), D17<=TIME(17,59,0)), TIME(21,0,0), IF(AND(D17>=TIME(18,0,0), D17<=TIME(21,59,0)), TIME(0,0,0), IF(AND(D17>=TIME(22,0,0), D17<=TIME(23,59,59)), TIME(7,0,0), ""))))))) | G17: =E17 | I17: =ROUND(IF(OR(D17="",E17="",E17=0),0,IF(H17="",MOD(E17-D17,1)*24,MOD(H17-D17,1)*24)),2) | M17: =IF(OR($A17="Holiday",$A16="Holiday"),IF(OR($C17="",$D17=""),0, IF(OR($A16="Holiday",$A17="Holiday"),0, IF(AND(NOT(OR($A16="Annual Leave",$A17="Annual Leave")),$A17="Off day"),0, IF($I16+$I17>=8,IF($I16>=8,0,8-$I16),$I17) )))+IF(MOD(ROW(),2)=0,8,0),IF(OR($C17="",$D17=""),0, IF(OR($A16="Holiday",$A17="Holiday"),0, IF(AND(NOT(OR($A16="Annual Leave",$A17="Annual Leave")),$A17="Off day"),0, IF($I16+$I17>=8,IF($I16>=8,0,8-$I16),$I17) )))) | N17: =IF(OR($C17="",$D17=""),0, IF(OR($A16="Holiday",$A17="Holiday"), IF(ISNUMBER(MATCH(TRIM($B17),{"Phagwah","Good Friday","Easter Monday","Labour Day","Christmas","Eid ul Azha","Romans-2","Globe-12","Neptune P1"},0)),0,$I17), IF(AND(NOT(OR($A16="Annual Leave",$A17="Annual Leave")),$A17="Off day"),$I17, MAX(0,$I17-$M17) ))) | O17: =IF(AND(OR($A16="Holiday",$A17="Holiday"), ISNUMBER(MATCH(TRIM($B17),{"Phagwah","Good Friday","Easter Monday","Labour Day","Christmas","Eid ul Azha","Romans-2","Globe-12","Neptune P1"},0))), $I17,0) | R17: =IF(OR($O$7="Canteen",$O$7="Head Office"),0,IF(OR($I16>0,$I17>0), IF( OR( AND($D16>=TIME(5,0,0),$D16<=TIME(7,0,0)), AND($D16>=TIME(14,0,0),$D16<=TIME(15,0,0)), AND($D16>=TIME(18,0,0),$D16<=TIME(19,0,0)), AND($D17>=TIME(5,0,0),$D17<=TIME(7,0,0)), AND($D17>=TIME(14,0,0),$D17<=TIME(15,0,0)), AND($D17>=TIME(18,0,0),$D17<=TIME(19,0,0)) ), IF(AND($I16=0,$I17>0),1,0), 0 ), 0)) | S17: =IF(OR($A16="Annual Leave",$A17="Annual Leave"),IF(AND($A16<>"Annual Leave",$A17="Annual Leave"),8,0),0)
A18: On Day | C18: =C16+1 | E18: =IF(D18=0, 0, IF(AND(D18>=TIME(0,0,1), D18<=TIME(2,0,0)), TIME(7,0,0), IF(AND(D18>=TIME(5,0,0), D18<=TIME(8,0,0)), TIME(12,0,0), IF(AND(D18>TIME(8,0,0), D18<=TIME(13,59,0)), TIME(15,0,0), IF(AND(D18>=TIME(14,0,0), D18<=TIME(17,59,0)), TIME(21,0,0), IF(AND(D18>=TIME(18,0,0), D18<=TIME(21,59,0)), TIME(0,0,0), IF(AND(D18>=TIME(22,0,0), D18<=TIME(23,59,59)), TIME(7,0,0), ""))))))) | G18: =E18 | I18: =ROUND(IF(OR(D18="",E18="",E18=0),0,IF(H18="",MOD(E18-D18,1)*24,MOD(H18-D18,1)*24)),2) | L18: FALSE | M18: =IF(OR($A18="Holiday",$A19="Holiday"),IF(OR($C18="",$D18=""),0, IF(OR($A18="Holiday",$A19="Holiday"),0, IF(AND(NOT(OR($A18="Annual Leave",$A19="Annual Leave")),$A18="Off day"),0, IF($I18+$I19>=8,IF($I18>=8,8,$I18),$I18) )))+IF(MOD(ROW(),2)=0,8,0),IF(OR($C18="",$D18=""),0, IF(OR($A18="Holiday",$A19="Holiday"),0, IF(AND(NOT(OR($A18="Annual Leave",$A19="Annual Leave")),$A18="Off day"),0, IF($I18+$I19>=8,IF($I18>=8,8,$I18),$I18) )))) | N18: =IF(OR($C18="",$D18=""),0, IF(OR($A18="Holiday",$A19="Holiday"), IF(ISNUMBER(MATCH(TRIM($B18),{"Phagwah","Good Friday","Easter Monday","Labour Day","Christmas","Eid ul Azha","Romans-2","Globe-12","Neptune P1"},0)),0,$I18), IF(AND(NOT(OR($A18="Annual Leave",$A19="Annual Leave")),$A18="Off day"),$I18, MAX(0,$I18-$M18) ))) | O18: =IF(AND(OR($A18="Holiday",$A19="Holiday"), ISNUMBER(MATCH(TRIM($B18),{"Phagwah","Good Friday","Easter Monday","Labour Day","Christmas","Eid ul Azha","Romans-2","Globe-12","Neptune P1"},0))), $I18,0) | R18: =IF(OR($O$7="Canteen",$O$7="Head Office"),0,IF(OR($I18>0,$I19>0), IF( OR( AND($D18>=TIME(5,0,0),$D18<=TIME(7,0,0)), AND($D18>=TIME(14,0,0),$D18<=TIME(15,0,0)), AND($D18>=TIME(18,0,0),$D18<=TIME(19,0,0)), AND($D19>=TIME(5,0,0),$D19<=TIME(7,0,0)), AND($D19>=TIME(14,0,0),$D19<=TIME(15,0,0)), AND($D19>=TIME(18,0,0),$D19<=TIME(19,0,0)) ), IF($I18>0,1,0), 0 ), 0)) | S18: =IF(OR($A18="Annual Leave",$A19="Annual Leave"),IF($A18="Annual Leave",8,0),0)
A19: On Day | C19: =C18 | D19: 0.79166667 | E19: =IF(D19=0, 0, IF(AND(D19>=TIME(0,0,1), D19<=TIME(2,0,0)), TIME(7,0,0), IF(AND(D19>=TIME(5,0,0), D19<=TIME(8,0,0)), TIME(12,0,0), IF(AND(D19>TIME(8,0,0), D19<=TIME(13,59,0)), TIME(15,0,0), IF(AND(D19>=TIME(14,0,0), D19<=TIME(17,59,0)), TIME(21,0,0), IF(AND(D19>=TIME(18,0,0), D19<=TIME(21,59,0)), TIME(0,0,0), IF(AND(D19>=TIME(22,0,0), D19<=TIME(23,59,59)), TIME(7,0,0), ""))))))) | G19: =E19 | I19: =ROUND(IF(OR(D19="",E19="",E19=0),0,IF(H19="",MOD(E19-D19,1)*24,MOD(H19-D19,1)*24)),2) | L19: FALSE | M19: =IF(OR($A19="Holiday",$A18="Holiday"),IF(OR($C19="",$D19=""),0, IF(OR($A18="Holiday",$A19="Holiday"),0, IF(AND(NOT(OR($A18="Annual Leave",$A19="Annual Leave")),$A19="Off day"),0, IF($I18+$I19>=8,IF($I18>=8,0,8-$I18),$I19) )))+IF(MOD(ROW(),2)=0,8,0),IF(OR($C19="",$D19=""),0, IF(OR($A18="Holiday",$A19="Holiday"),0, IF(AND(NOT(OR($A18="Annual Leave",$A19="Annual Leave")),$A19="Off day"),0, IF($I18+$I19>=8,IF($I18>=8,0,8-$I18),$I19) )))) | N19: =IF(OR($C19="",$D19=""),0, IF(OR($A18="Holiday",$A19="Holiday"), IF(ISNUMBER(MATCH(TRIM($B19),{"Phagwah","Good Friday","Easter Monday","Labour Day","Christmas","Eid ul Azha","Romans-2","Globe-12","Neptune P1"},0)),0,$I19), IF(AND(NOT(OR($A18="Annual Leave",$A19="Annual Leave")),$A19="Off day"),$I19, MAX(0,$I19-$M19) ))) | O19: =IF(AND(OR($A18="Holiday",$A19="Holiday"), ISNUMBER(MATCH(TRIM($B19),{"Phagwah","Good Friday","Easter Monday","Labour Day","Christmas","Eid ul Azha","Romans-2","Globe-12","Neptune P1"},0))), $I19,0) | R19: =IF(OR($O$7="Canteen",$O$7="Head Office"),0,IF(OR($I18>0,$I19>0), IF( OR( AND($D18>=TIME(5,0,0),$D18<=TIME(7,0,0)), AND($D18>=TIME(14,0,0),$D18<=TIME(15,0,0)), AND($D18>=TIME(18,0,0),$D18<=TIME(19,0,0)), AND($D19>=TIME(5,0,0),$D19<=TIME(7,0,0)), AND($D19>=TIME(14,0,0),$D19<=TIME(15,0,0)), AND($D19>=TIME(18,0,0),$D19<=TIME(19,0,0)) ), IF(AND($I18=0,$I19>0),1,0), 0 ), 0)) | S19: =IF(OR($A18="Annual Leave",$A19="Annual Leave"),IF(AND($A18<>"Annual Leave",$A19="Annual Leave"),8,0),0)
A20: On Day | C20: =C18+1 | E20: =IF(D20=0, 0, IF(AND(D20>=TIME(0,0,1), D20<=TIME(2,0,0)), TIME(7,0,0), IF(AND(D20>=TIME(5,0,0), D20<=TIME(8,0,0)), TIME(12,0,0), IF(AND(D20>TIME(8,0,0), D20<=TIME(13,59,0)), TIME(15,0,0), IF(AND(D20>=TIME(14,0,0), D20<=TIME(17,59,0)), TIME(21,0,0), IF(AND(D20>=TIME(18,0,0), D20<=TIME(21,59,0)), TIME(0,0,0), IF(AND(D20>=TIME(22,0,0), D20<=TIME(23,59,59)), TIME(7,0,0), ""))))))) | G20: =E20 | I20: =ROUND(IF(OR(D20="",E20="",E20=0),0,IF(H20="",MOD(E20-D20,1)*24,MOD(H20-D20,1)*24)),2) | L20: FALSE | M20: =IF(OR($A20="Holiday",$A21="Holiday"),IF(OR($C20="",$D20=""),0, IF(OR($A20="Holiday",$A21="Holiday"),0, IF(AND(NOT(OR($A20="Annual Leave",$A21="Annual Leave")),$A20="Off day"),0, IF($I20+$I21>=8,IF($I20>=8,8,$I20),$I20) )))+IF(MOD(ROW(),2)=0,8,0),IF(OR($C20="",$D20=""),0, IF(OR($A20="Holiday",$A21="Holiday"),0, IF(AND(NOT(OR($A20="Annual Leave",$A21="Annual Leave")),$A20="Off day"),0, IF($I20+$I21>=8,IF($I20>=8,8,$I20),$I20) )))) | N20: =IF(OR($C20="",$D20=""),0, IF(OR($A20="Holiday",$A21="Holiday"), IF(ISNUMBER(MATCH(TRIM($B20),{"Phagwah","Good Friday","Easter Monday","Labour Day","Christmas","Eid ul Azha","Romans-2","Globe-12","Neptune P1"},0)),0,$I20), IF(AND(NOT(OR($A20="Annual Leave",$A21="Annual Leave")),$A20="Off day"),$I20, MAX(0,$I20-$M20) ))) | O20: =IF(AND(OR($A20="Holiday",$A21="Holiday"), ISNUMBER(MATCH(TRIM($B20),{"Phagwah","Good Friday","Easter Monday","Labour Day","Christmas","Eid ul Azha","Romans-2","Globe-12","Neptune P1"},0))), $I20,0) | R20: =IF(OR($O$7="Canteen",$O$7="Head Office"),0,IF(OR($I20>0,$I21>0), IF( OR( AND($D20>=TIME(5,0,0),$D20<=TIME(7,0,0)), AND($D20>=TIME(14,0,0),$D20<=TIME(15,0,0)), AND($D20>=TIME(18,0,0),$D20<=TIME(19,0,0)), AND($D21>=TIME(5,0,0),$D21<=TIME(7,0,0)), AND($D21>=TIME(14,0,0),$D21<=TIME(15,0,0)), AND($D21>=TIME(18,0,0),$D21<=TIME(19,0,0)) ), IF($I20>0,1,0), 0 ), 0)) | S20: =IF(OR($A20="Annual Leave",$A21="Annual Leave"),IF($A20="Annual Leave",8,0),0)
A21: On Day | C21: =C20 | D21: 0.79166667 | E21: =IF(D21=0, 0, IF(AND(D21>=TIME(0,0,1), D21<=TIME(2,0,0)), TIME(7,0,0), IF(AND(D21>=TIME(5,0,0), D21<=TIME(8,0,0)), TIME(12,0,0), IF(AND(D21>TIME(8,0,0), D21<=TIME(13,59,0)), TIME(15,0,0), IF(AND(D21>=TIME(14,0,0), D21<=TIME(17,59,0)), TIME(21,0,0), IF(AND(D21>=TIME(18,0,0), D21<=TIME(21,59,0)), TIME(0,0,0), IF(AND(D21>=TIME(22,0,0), D21<=TIME(23,59,59)), TIME(7,0,0), ""))))))) | G21: =E21 | I21: =ROUND(IF(OR(D21="",E21="",E21=0),0,IF(H21="",MOD(E21-D21,1)*24,MOD(H21-D21,1)*24)),2) | L21: FALSE | M21: =IF(OR($A21="Holiday",$A20="Holiday"),IF(OR($C21="",$D21=""),0, IF(OR($A20="Holiday",$A21="Holiday"),0, IF(AND(NOT(OR($A20="Annual Leave",$A21="Annual Leave")),$A21="Off day"),0, IF($I20+$I21>=8,IF($I20>=8,0,8-$I20),$I21) )))+IF(MOD(ROW(),2)=0,8,0),IF(OR($C21="",$D21=""),0, IF(OR($A20="Holiday",$A21="Holiday"),0, IF(AND(NOT(OR($A20="Annual Leave",$A21="Annual Leave")),$A21="Off day"),0, IF($I20+$I21>=8,IF($I20>=8,0,8-$I20),$I21) )))) | N21: =IF(OR($C21="",$D21=""),0, IF(OR($A20="Holiday",$A21="Holiday"), IF(ISNUMBER(MATCH(TRIM($B21),{"Phagwah","Good Friday","Easter Monday","Labour Day","Christmas","Eid ul Azha","Romans-2","Globe-12","Neptune P1"},0)),0,$I21), IF(AND(NOT(OR($A20="Annual Leave",$A21="Annual Leave")),$A21="Off day"),$I21, MAX(0,$I21-$M21) ))) | O21: =IF(AND(OR($A20="Holiday",$A21="Holiday"), ISNUMBER(MATCH(TRIM($B21),{"Phagwah","Good Friday","Easter Monday","Labour Day","Christmas","Eid ul Azha","Romans-2","Globe-12","Neptune P1"},0))), $I21,0) | R21: =IF(OR($O$7="Canteen",$O$7="Head Office"),0,IF(OR($I20>0,$I21>0), IF( OR( AND($D20>=TIME(5,0,0),$D20<=TIME(7,0,0)), AND($D20>=TIME(14,0,0),$D20<=TIME(15,0,0)), AND($D20>=TIME(18,0,0),$D20<=TIME(19,0,0)), AND($D21>=TIME(5,0,0),$D21<=TIME(7,0,0)), AND($D21>=TIME(14,0,0),$D21<=TIME(15,0,0)), AND($D21>=TIME(18,0,0),$D21<=TIME(19,0,0)) ), IF(AND($I20=0,$I21>0),1,0), 0 ), 0)) | S21: =IF(OR($A20="Annual Leave",$A21="Annual Leave"),IF(AND($A20<>"Annual Leave",$A21="Annual Leave"),8,0),0)
A22: On Day | C22: =C20+1 | D22: 0.29166667 | E22: =IF(D22=0, 0, IF(AND(D22>=TIME(0,0,1), D22<=TIME(2,0,0)), TIME(7,0,0), IF(AND(D22>=TIME(5,0,0), D22<=TIME(8,0,0)), TIME(12,0,0), IF(AND(D22>TIME(8,0,0), D22<=TIME(13,59,0)), TIME(15,0,0), IF(AND(D22>=TIME(14,0,0), D22<=TIME(17,59,0)), TIME(21,0,0), IF(AND(D22>=TIME(18,0,0), D22<=TIME(21,59,0)), TIME(0,0,0), IF(AND(D22>=TIME(22,0,0), D22<=TIME(23,59,59)), TIME(7,0,0), ""))))))) | G22: =E22 | I22: =ROUND(IF(OR(D22="",E22="",E22=0),0,IF(H22="",MOD(E22-D22,1)*24,MOD(H22-D22,1)*24)),2) | L22: FALSE | M22: =IF(OR($A22="Holiday",$A23="Holiday"),IF(OR($C22="",$D22=""),0, IF(OR($A22="Holiday",$A23="Holiday"),0, IF(AND(NOT(OR($A22="Annual Leave",$A23="Annual Leave")),$A22="Off day"),0, IF($I22+$I23>=8,IF($I22>=8,8,$I22),$I22) )))+IF(MOD(ROW(),2)=0,8,0),IF(OR($C22="",$D22=""),0, IF(OR($A22="Holiday",$A23="Holiday"),0, IF(AND(NOT(OR($A22="Annual Leave",$A23="Annual Leave")),$A22="Off day"),0, IF($I22+$I23>=8,IF($I22>=8,8,$I22),$I22) )))) | N22: =IF(OR($C22="",$D22=""),0, IF(OR($A22="Holiday",$A23="Holiday"), IF(ISNUMBER(MATCH(TRIM($B22),{"Phagwah","Good Friday","Easter Monday","Labour Day","Christmas","Eid ul Azha","Romans-2","Globe-12","Neptune P1"},0)),0,$I22), IF(AND(NOT(OR($A22="Annual Leave",$A23="Annual Leave")),$A22="Off day"),$I22, MAX(0,$I22-$M22) ))) | O22: =IF(AND(OR($A22="Holiday",$A23="Holiday"), ISNUMBER(MATCH(TRIM($B22),{"Phagwah","Good Friday","Easter Monday","Labour Day","Christmas","Eid ul Azha","Romans-2","Globe-12","Neptune P1"},0))), $I22,0) | R22: =IF(OR($O$7="Canteen",$O$7="Head Office"),0,IF(OR($I22>0,$I23>0), IF( OR( AND($D22>=TIME(5,0,0),$D22<=TIME(7,0,0)), AND($D22>=TIME(14,0,0),$D22<=TIME(15,0,0)), AND($D22>=TIME(18,0,0),$D22<=TIME(19,0,0)), AND($D23>=TIME(5,0,0),$D23<=TIME(7,0,0)), AND($D23>=TIME(14,0,0),$D23<=TIME(15,0,0)), AND($D23>=TIME(18,0,0),$D23<=TIME(19,0,0)) ), IF($I22>0,1,0), 0 ), 0)) | S22: =IF(OR($A22="Annual Leave",$A23="Annual Leave"),IF($A22="Annual Leave",8,0),0)
A23: On Day | C23: =C22 | D23: 0.625 | E23: =IF(D23=0, 0, IF(AND(D23>=TIME(0,0,1), D23<=TIME(2,0,0)), TIME(7,0,0), IF(AND(D23>=TIME(5,0,0), D23<=TIME(8,0,0)), TIME(12,0,0), IF(AND(D23>TIME(8,0,0), D23<=TIME(13,59,0)), TIME(15,0,0), IF(AND(D23>=TIME(14,0,0), D23<=TIME(17,59,0)), TIME(21,0,0), IF(AND(D23>=TIME(18,0,0), D23<=TIME(21,59,0)), TIME(0,0,0), IF(AND(D23>=TIME(22,0,0), D23<=TIME(23,59,59)), TIME(7,0,0), ""))))))) | G23: =E23 | I23: =ROUND(IF(OR(D23="",E23="",E23=0),0,IF(H23="",MOD(E23-D23,1)*24,MOD(H23-D23,1)*24)),2) | L23: FALSE | M23: =IF(OR($A23="Holiday",$A22="Holiday"),IF(OR($C23="",$D23=""),0, IF(OR($A22="Holiday",$A23="Holiday"),0, IF(AND(NOT(OR($A22="Annual Leave",$A23="Annual Leave")),$A23="Off day"),0, IF($I22+$I23>=8,IF($I22>=8,0,8-$I22),$I23) )))+IF(MOD(ROW(),2)=0,8,0),IF(OR($C23="",$D23=""),0, IF(OR($A22="Holiday",$A23="Holiday"),0, IF(AND(NOT(OR($A22="Annual Leave",$A23="Annual Leave")),$A23="Off day"),0, IF($I22+$I23>=8,IF($I22>=8,0,8-$I22),$I23) )))) | N23: =IF(OR($C23="",$D23=""),0, IF(OR($A22="Holiday",$A23="Holiday"), IF(ISNUMBER(MATCH(TRIM($B23),{"Phagwah","Good Friday","Easter Monday","Labour Day","Christmas","Eid ul Azha","Romans-2","Globe-12","Neptune P1"},0)),0,$I23), IF(AND(NOT(OR($A22="Annual Leave",$A23="Annual Leave")),$A23="Off day"),$I23, MAX(0,$I23-$M23) ))) | O23: =IF(AND(OR($A22="Holiday",$A23="Holiday"), ISNUMBER(MATCH(TRIM($B23),{"Phagwah","Good Friday","Easter Monday","Labour Day","Christmas","Eid ul Azha","Romans-2","Globe-12","Neptune P1"},0))), $I23,0) | R23: =IF(OR($O$7="Canteen",$O$7="Head Office"),0,IF(OR($I22>0,$I23>0), IF( OR( AND($D22>=TIME(5,0,0),$D22<=TIME(7,0,0)), AND($D22>=TIME(14,0,0),$D22<=TIME(15,0,0)), AND($D22>=TIME(18,0,0),$D22<=TIME(19,0,0)), AND($D23>=TIME(5,0,0),$D23<=TIME(7,0,0)), AND($D23>=TIME(14,0,0),$D23<=TIME(15,0,0)), AND($D23>=TIME(18,0,0),$D23<=TIME(19,0,0)) ), IF(AND($I22=0,$I23>0),1,0), 0 ), 0)) | S23: =IF(OR($A22="Annual Leave",$A23="Annual Leave"),IF(AND($A22<>"Annual Leave",$A23="Annual Leave"),8,0),0)
A24: On Day | C24: =C22+1 | D24: 0.29166667 | E24: =IF(D24=0, 0, IF(AND(D24>=TIME(0,0,1), D24<=TIME(2,0,0)), TIME(7,0,0), IF(AND(D24>=TIME(5,0,0), D24<=TIME(8,0,0)), TIME(12,0,0), IF(AND(D24>TIME(8,0,0), D24<=TIME(13,59,0)), TIME(15,0,0), IF(AND(D24>=TIME(14,0,0), D24<=TIME(17,59,0)), TIME(21,0,0), IF(AND(D24>=TIME(18,0,0), D24<=TIME(21,59,0)), TIME(0,0,0), IF(AND(D24>=TIME(22,0,0), D24<=TIME(23,59,59)), TIME(7,0,0), ""))))))) | G24: =E24 | I24: =ROUND(IF(OR(D24="",E24="",E24=0),0,IF(H24="",MOD(E24-D24,1)*24,MOD(H24-D24,1)*24)),2) | L24: FALSE | M24: =IF(OR($A24="Holiday",$A25="Holiday"),IF(OR($C24="",$D24=""),0, IF(OR($A24="Holiday",$A25="Holiday"),0, IF(AND(NOT(OR($A24="Annual Leave",$A25="Annual Leave")),$A24="Off day"),0, IF($I24+$I25>=8,IF($I24>=8,8,$I24),$I24) )))+IF(MOD(ROW(),2)=0,8,0),IF(OR($C24="",$D24=""),0, IF(OR($A24="Holiday",$A25="Holiday"),0, IF(AND(NOT(OR($A24="Annual Leave",$A25="Annual Leave")),$A24="Off day"),0, IF($I24+$I25>=8,IF($I24>=8,8,$I24),$I24) )))) | N24: =IF(OR($C24="",$D24=""),0, IF(OR($A24="Holiday",$A25="Holiday"), IF(ISNUMBER(MATCH(TRIM($B24),{"Phagwah","Good Friday","Easter Monday","Labour Day","Christmas","Eid ul Azha","Romans-2","Globe-12","Neptune P1"},0)),0,$I24), IF(AND(NOT(OR($A24="Annual Leave",$A25="Annual Leave")),$A24="Off day"),$I24, MAX(0,$I24-$M24) ))) | O24: =IF(AND(OR($A24="Holiday",$A25="Holiday"), ISNUMBER(MATCH(TRIM($B24),{"Phagwah","Good Friday","Easter Monday","Labour Day","Christmas","Eid ul Azha","Romans-2","Globe-12","Neptune P1"},0))), $I24,0) | R24: =IF(OR($O$7="Canteen",$O$7="Head Office"),0,IF(OR($I24>0,$I25>0), IF( OR( AND($D24>=TIME(5,0,0),$D24<=TIME(7,0,0)), AND($D24>=TIME(14,0,0),$D24<=TIME(15,0,0)), AND($D24>=TIME(18,0,0),$D24<=TIME(19,0,0)), AND($D25>=TIME(5,0,0),$D25<=TIME(7,0,0)), AND($D25>=TIME(14,0,0),$D25<=TIME(15,0,0)), AND($D25>=TIME(18,0,0),$D25<=TIME(19,0,0)) ), IF($I24>0,1,0), 0 ), 0)) | S24: =IF(OR($A24="Annual Leave",$A25="Annual Leave"),IF($A24="Annual Leave",8,0),0)
A25: On Day | C25: =C24 | D25: 0.625 | E25: =IF(D25=0, 0, IF(AND(D25>=TIME(0,0,1), D25<=TIME(2,0,0)), TIME(7,0,0), IF(AND(D25>=TIME(5,0,0), D25<=TIME(8,0,0)), TIME(12,0,0), IF(AND(D25>TIME(8,0,0), D25<=TIME(13,59,0)), TIME(15,0,0), IF(AND(D25>=TIME(14,0,0), D25<=TIME(17,59,0)), TIME(21,0,0), IF(AND(D25>=TIME(18,0,0), D25<=TIME(21,59,0)), TIME(0,0,0), IF(AND(D25>=TIME(22,0,0), D25<=TIME(23,59,59)), TIME(7,0,0), ""))))))) | G25: =E25 | I25: =ROUND(IF(OR(D25="",E25="",E25=0),0,IF(H25="",MOD(E25-D25,1)*24,MOD(H25-D25,1)*24)),2) | L25: FALSE | M25: =IF(OR($A25="Holiday",$A24="Holiday"),IF(OR($C25="",$D25=""),0, IF(OR($A24="Holiday",$A25="Holiday"),0, IF(AND(NOT(OR($A24="Annual Leave",$A25="Annual Leave")),$A25="Off day"),0, IF($I24+$I25>=8,IF($I24>=8,0,8-$I24),$I25) )))+IF(MOD(ROW(),2)=0,8,0),IF(OR($C25="",$D25=""),0, IF(OR($A24="Holiday",$A25="Holiday"),0, IF(AND(NOT(OR($A24="Annual Leave",$A25="Annual Leave")),$A25="Off day"),0, IF($I24+$I25>=8,IF($I24>=8,0,8-$I24),$I25) )))) | N25: =IF(OR($C25="",$D25=""),0, IF(OR($A24="Holiday",$A25="Holiday"), IF(ISNUMBER(MATCH(TRIM($B25),{"Phagwah","Good Friday","Easter Monday","Labour Day","Christmas","Eid ul Azha","Romans-2","Globe-12","Neptune P1"},0)),0,$I25), IF(AND(NOT(OR($A24="Annual Leave",$A25="Annual Leave")),$A25="Off day"),$I25, MAX(0,$I25-$M25) ))) | O25: =IF(AND(OR($A24="Holiday",$A25="Holiday"), ISNUMBER(MATCH(TRIM($B25),{"Phagwah","Good Friday","Easter Monday","Labour Day","Christmas","Eid ul Azha","Romans-2","Globe-12","Neptune P1"},0))), $I25,0) | R25: =IF(OR($O$7="Canteen",$O$7="Head Office"),0,IF(OR($I24>0,$I25>0), IF( OR( AND($D24>=TIME(5,0,0),$D24<=TIME(7,0,0)), AND($D24>=TIME(14,0,0),$D24<=TIME(15,0,0)), AND($D24>=TIME(18,0,0),$D24<=TIME(19,0,0)), AND($D25>=TIME(5,0,0),$D25<=TIME(7,0,0)), AND($D25>=TIME(14,0,0),$D25<=TIME(15,0,0)), AND($D25>=TIME(18,0,0),$D25<=TIME(19,0,0)) ), IF(AND($I24=0,$I25>0),1,0), 0 ), 0)) | S25: =IF(OR($A24="Annual Leave",$A25="Annual Leave"),IF(AND($A24<>"Annual Leave",$A25="Annual Leave"),8,0),0)
A26: On Day | C26: =C24+1 | D26: 0.29166667 | E26: =IF(D26=0, 0, IF(AND(D26>=TIME(0,0,1), D26<=TIME(2,0,0)), TIME(7,0,0), IF(AND(D26>=TIME(5,0,0), D26<=TIME(8,0,0)), TIME(12,0,0), IF(AND(D26>TIME(8,0,0), D26<=TIME(13,59,0)), TIME(15,0,0), IF(AND(D26>=TIME(14,0,0), D26<=TIME(17,59,0)), TIME(21,0,0), IF(AND(D26>=TIME(18,0,0), D26<=TIME(21,59,0)), TIME(0,0,0), IF(AND(D26>=TIME(22,0,0), D26<=TIME(23,59,59)), TIME(7,0,0), ""))))))) | G26: =E26 | I26: =ROUND(IF(OR(D26="",E26="",E26=0),0,IF(H26="",MOD(E26-D26,1)*24,MOD(H26-D26,1)*24)),2) | L26: FALSE | M26: =IF(OR($A26="Holiday",$A27="Holiday"),IF(OR($C26="",$D26=""),0, IF(OR($A26="Holiday",$A27="Holiday"),0, IF(AND(NOT(OR($A26="Annual Leave",$A27="Annual Leave")),$A26="Off day"),0, IF($I26+$I27>=8,IF($I26>=8,8,$I26),$I26) )))+IF(MOD(ROW(),2)=0,8,0),IF(OR($C26="",$D26=""),0, IF(OR($A26="Holiday",$A27="Holiday"),0, IF(AND(NOT(OR($A26="Annual Leave",$A27="Annual Leave")),$A26="Off day"),0, IF($I26+$I27>=8,IF($I26>=8,8,$I26),$I26) )))) | N26: =IF(OR($C26="",$D26=""),0, IF(OR($A26="Holiday",$A27="Holiday"), IF(ISNUMBER(MATCH(TRIM($B26),{"Phagwah","Good Friday","Easter Monday","Labour Day","Christmas","Eid ul Azha","Romans-2","Globe-12","Neptune P1"},0)),0,$I26), IF(AND(NOT(OR($A26="Annual Leave",$A27="Annual Leave")),$A26="Off day"),$I26, MAX(0,$I26-$M26) ))) | O26: =IF(AND(OR($A26="Holiday",$A27="Holiday"), ISNUMBER(MATCH(TRIM($B26),{"Phagwah","Good Friday","Easter Monday","Labour Day","Christmas","Eid ul Azha","Romans-2","Globe-12","Neptune P1"},0))), $I26,0) | R26: =IF(OR($O$7="Canteen",$O$7="Head Office"),0,IF(OR($I26>0,$I27>0), IF( OR( AND($D26>=TIME(5,0,0),$D26<=TIME(7,0,0)), AND($D26>=TIME(14,0,0),$D26<=TIME(15,0,0)), AND($D26>=TIME(18,0,0),$D26<=TIME(19,0,0)), AND($D27>=TIME(5,0,0),$D27<=TIME(7,0,0)), AND($D27>=TIME(14,0,0),$D27<=TIME(15,0,0)), AND($D27>=TIME(18,0,0),$D27<=TIME(19,0,0)) ), IF($I26>0,1,0), 0 ), 0)) | S26: =IF(OR($A26="Annual Leave",$A27="Annual Leave"),IF($A26="Annual Leave",8,0),0)
A27: On Day | C27: =C26 | E27: =IF(D27=0, 0, IF(AND(D27>=TIME(0,0,1), D27<=TIME(2,0,0)), TIME(7,0,0), IF(AND(D27>=TIME(5,0,0), D27<=TIME(8,0,0)), TIME(12,0,0), IF(AND(D27>TIME(8,0,0), D27<=TIME(13,59,0)), TIME(15,0,0), IF(AND(D27>=TIME(14,0,0), D27<=TIME(17,59,0)), TIME(21,0,0), IF(AND(D27>=TIME(18,0,0), D27<=TIME(21,59,0)), TIME(0,0,0), IF(AND(D27>=TIME(22,0,0), D27<=TIME(23,59,59)), TIME(7,0,0), ""))))))) | G27: =E27 | I27: =ROUND(IF(OR(D27="",E27="",E27=0),0,IF(H27="",MOD(E27-D27,1)*24,MOD(H27-D27,1)*24)),2) | L27: FALSE | M27: =IF(OR($A27="Holiday",$A26="Holiday"),IF(OR($C27="",$D27=""),0, IF(OR($A26="Holiday",$A27="Holiday"),0, IF(AND(NOT(OR($A26="Annual Leave",$A27="Annual Leave")),$A27="Off day"),0, IF($I26+$I27>=8,IF($I26>=8,0,8-$I26),$I27) )))+IF(MOD(ROW(),2)=0,8,0),IF(OR($C27="",$D27=""),0, IF(OR($A26="Holiday",$A27="Holiday"),0, IF(AND(NOT(OR($A26="Annual Leave",$A27="Annual Leave")),$A27="Off day"),0, IF($I26+$I27>=8,IF($I26>=8,0,8-$I26),$I27) )))) | N27: =IF(OR($C27="",$D27=""),0, IF(OR($A26="Holiday",$A27="Holiday"), IF(ISNUMBER(MATCH(TRIM($B27),{"Phagwah","Good Friday","Easter Monday","Labour Day","Christmas","Eid ul Azha","Romans-2","Globe-12","Neptune P1"},0)),0,$I27), IF(AND(NOT(OR($A26="Annual Leave",$A27="Annual Leave")),$A27="Off day"),$I27, MAX(0,$I27-$M27) ))) | O27: =IF(AND(OR($A26="Holiday",$A27="Holiday"), ISNUMBER(MATCH(TRIM($B27),{"Phagwah","Good Friday","Easter Monday","Labour Day","Christmas","Eid ul Azha","Romans-2","Globe-12","Neptune P1"},0))), $I27,0) | R27: =IF(OR($O$7="Canteen",$O$7="Head Office"),0,IF(OR($I26>0,$I27>0), IF( OR( AND($D26>=TIME(5,0,0),$D26<=TIME(7,0,0)), AND($D26>=TIME(14,0,0),$D26<=TIME(15,0,0)), AND($D26>=TIME(18,0,0),$D26<=TIME(19,0,0)), AND($D27>=TIME(5,0,0),$D27<=TIME(7,0,0)), AND($D27>=TIME(14,0,0),$D27<=TIME(15,0,0)), AND($D27>=TIME(18,0,0),$D27<=TIME(19,0,0)) ), IF(AND($I26=0,$I27>0),1,0), 0 ), 0)) | S27: =IF(OR($A26="Annual Leave",$A27="Annual Leave"),IF(AND($A26<>"Annual Leave",$A27="Annual Leave"),8,0),0)
M28: =IF(OR($A28="Holiday",$A29="Holiday"),IF(OR($C28="",$D28=""),0, IF(OR($A28="Holiday",$A29="Holiday"),0, IF(AND(NOT(OR($A28="Annual Leave",$A29="Annual Leave")),$A28="Off day"),0, IF($I28+$I29>=8,IF($I28>=8,8,$I28),$I28) )))+IF(MOD(ROW(),2)=0,8,0),IF(OR($C28="",$D28=""),0, IF(OR($A28="Holiday",$A29="Holiday"),0, IF(AND(NOT(OR($A28="Annual Leave",$A29="Annual Leave")),$A28="Off day"),0, IF($I28+$I29>=8,IF($I28>=8,8,$I28),$I28) )))) | N28: =IF(OR($C28="",$D28=""),0, IF(OR($A28="Holiday",$A29="Holiday"), IF(ISNUMBER(MATCH(TRIM($B28),{"Phagwah","Good Friday","Easter Monday","Labour Day","Christmas","Eid ul Azha","Romans-2","Globe-12","Neptune P1"},0)),0,$I28), IF(AND(NOT(OR($A28="Annual Leave",$A29="Annual Leave")),$A28="Off day"),$I28, MAX(0,$I28-$M28) ))) | O28: =IF(AND(OR($A28="Holiday",$A29="Holiday"), ISNUMBER(MATCH(TRIM($B28),{"Phagwah","Good Friday","Easter Monday","Labour Day","Christmas","Eid ul Azha","Romans-2","Globe-12","Neptune P1"},0))), $I28,0) | S28: =IF(OR($A28="Annual Leave",$A29="Annual Leave"),IF($A28="Annual Leave",8,0),0) | T28: =SUM(T14:T27)
E29: =IF(D29=0, 0, IF(AND(D29>=TIME(0,0,1), D29<=TIME(2,0,0)), TIME(7,0,0), IF(AND(D29>=TIME(5,0,0), D29<=TIME(8,0,0)), TIME(12,0,0), IF(AND(D29>TIME(8,0,0), D29<=TIME(13,59,0)), TIME(15,0,0), IF(AND(D29>=TIME(14,0,0), D29<=TIME(17,59,0)), TIME(21,0,0), IF(AND(D29>=TIME(18,0,0), D29<=TIME(21,59,0)), TIME(0,0,0), IF(AND(D29>=TIME(22,0,0), D29<=TIME(23,59,59)), TIME(7,0,0), ""))))))) | M29: =IF(OR($A29="Holiday",$A28="Holiday"),IF(OR($C29="",$D29=""),0, IF(OR($A28="Holiday",$A29="Holiday"),0, IF(AND(NOT(OR($A28="Annual Leave",$A29="Annual Leave")),$A29="Off day"),0, IF($I28+$I29>=8,IF($I28>=8,0,8-$I28),$I29) )))+IF(MOD(ROW(),2)=0,8,0),IF(OR($C29="",$D29=""),0, IF(OR($A28="Holiday",$A29="Holiday"),0, IF(AND(NOT(OR($A28="Annual Leave",$A29="Annual Leave")),$A29="Off day"),0, IF($I28+$I29>=8,IF($I28>=8,0,8-$I28),$I29) )))) | N29: =IF(OR($C29="",$D29=""),0, IF(OR($A28="Holiday",$A29="Holiday"), IF(ISNUMBER(MATCH(TRIM($B29),{"Phagwah","Good Friday","Easter Monday","Labour Day","Christmas","Eid ul Azha","Romans-2","Globe-12","Neptune P1"},0)),0,$I29), IF(AND(NOT(OR($A28="Annual Leave",$A29="Annual Leave")),$A29="Off day"),$I29, MAX(0,$I29-$M29) ))) | O29: =IF(AND(OR($A28="Holiday",$A29="Holiday"), ISNUMBER(MATCH(TRIM($B29),{"Phagwah","Good Friday","Easter Monday","Labour Day","Christmas","Eid ul Azha","Romans-2","Globe-12","Neptune P1"},0))), $I29,0) | R29: =IF(OR($O$7="Canteen",$O$7="Head Office"),0,IF( AND( SUMIFS(I:I, C:C, C29) >= 8, COUNTIFS(C$14:C29, C29)=1, OR( TEXT(D29,"hh:mm:ss")="07:00:00", TEXT(D29,"hh:mm:ss")="15:00:00", TEXT(D29,"hh:mm:ss")="23:00:00", TEXT(D30,"hh:mm:ss")="07:00:00", TEXT(D30,"hh:mm:ss")="15:00:00", TEXT(D30,"hh:mm:ss")="23:00:00" ) ), 1, 0 )) | S29: =IF(OR($A28="Annual Leave",$A29="Annual Leave"),IF(AND($A28<>"Annual Leave",$A29="Annual Leave"),8,0),0)
A30: On Day | C30: =C27+1 | D30: 0.29166667 | E30: =IF(D30=0, 0, IF(AND(D30>=TIME(0,0,1), D30<=TIME(2,0,0)), TIME(7,0,0), IF(AND(D30>=TIME(5,0,0), D30<=TIME(8,0,0)), TIME(12,0,0), IF(AND(D30>TIME(8,0,0), D30<=TIME(13,59,0)), TIME(15,0,0), IF(AND(D30>=TIME(14,0,0), D30<=TIME(17,59,0)), TIME(21,0,0), IF(AND(D30>=TIME(18,0,0), D30<=TIME(21,59,0)), TIME(0,0,0), IF(AND(D30>=TIME(22,0,0), D30<=TIME(23,59,59)), TIME(7,0,0), ""))))))) | G30: =E30 | I30: =ROUND(IF(OR(D30="",E30="",E30=0),0,IF(H30="",MOD(E30-D30,1)*24,MOD(H30-D30,1)*24)),2) | L30: FALSE | M30: =IF(OR($A30="Holiday",$A31="Holiday"),IF(OR($C30="",$D30=""),0, IF(OR($A30="Holiday",$A31="Holiday"),0, IF(AND(NOT(OR($A30="Annual Leave",$A31="Annual Leave")),$A30="Off day"),0, IF($I30+$I31>=8,IF($I30>=8,8,$I30),$I30) )))+IF(MOD(ROW(),2)=0,8,0),IF(OR($C30="",$D30=""),0, IF(OR($A30="Holiday",$A31="Holiday"),0, IF(AND(NOT(OR($A30="Annual Leave",$A31="Annual Leave")),$A30="Off day"),0, IF($I30+$I31>=8,IF($I30>=8,8,$I30),$I30) )))) | N30: =IF(OR($C30="",$D30=""),0, IF(OR($A30="Holiday",$A31="Holiday"), IF(ISNUMBER(MATCH(TRIM($B30),{"Phagwah","Good Friday","Easter Monday","Labour Day","Christmas","Eid ul Azha","Romans-2","Globe-12","Neptune P1"},0)),0,$I30), IF(AND(NOT(OR($A30="Annual Leave",$A31="Annual Leave")),$A30="Off day"),$I30, MAX(0,$I30-$M30) ))) | O30: =IF(AND(OR($A30="Holiday",$A31="Holiday"), ISNUMBER(MATCH(TRIM($B30),{"Phagwah","Good Friday","Easter Monday","Labour Day","Christmas","Eid ul Azha","Romans-2","Globe-12","Neptune P1"},0))), $I30,0) | R30: =IF(OR($O$7="Canteen",$O$7="Head Office"),0,IF( AND( SUMIFS(I:I, C:C, C30) >= 8, COUNTIFS(C$14:C30, C30)=1, OR( TEXT(D30,"hh:mm:ss")="07:00:00", TEXT(D30,"hh:mm:ss")="15:00:00", TEXT(D30,"hh:mm:ss")="23:00:00", TEXT(D31,"hh:mm:ss")="07:00:00", TEXT(D31,"hh:mm:ss")="15:00:00", TEXT(D31,"hh:mm:ss")="23:00:00" ) ), 1, 0 )) | S30: =IF(OR($A30="Annual Leave",$A31="Annual Leave"),IF($A30="Annual Leave",8,0),0)
A31: On Day | C31: =C30 | D31: Dps | E31: =IF(D31=0, 0, IF(AND(D31>=TIME(0,0,1), D31<=TIME(2,0,0)), TIME(7,0,0), IF(AND(D31>=TIME(5,0,0), D31<=TIME(8,0,0)), TIME(12,0,0), IF(AND(D31>TIME(8,0,0), D31<=TIME(13,59,0)), TIME(15,0,0), IF(AND(D31>=TIME(14,0,0), D31<=TIME(17,59,0)), TIME(21,0,0), IF(AND(D31>=TIME(18,0,0), D31<=TIME(21,59,0)), TIME(0,0,0), IF(AND(D31>=TIME(22,0,0), D31<=TIME(23,59,59)), TIME(7,0,0), ""))))))) | G31: =E31 | I31: =ROUND(IF(OR(D31="",E31="",E31=0),0,IF(H31="",MOD(E31-D31,1)*24,MOD(H31-D31,1)*24)),2) | L31: FALSE | M31: =IF(OR($A31="Holiday",$A30="Holiday"),IF(OR($C31="",$D31=""),0, IF(OR($A30="Holiday",$A31="Holiday"),0, IF(AND(NOT(OR($A30="Annual Leave",$A31="Annual Leave")),$A31="Off day"),0, IF($I30+$I31>=8,IF($I30>=8,0,8-$I30),$I31) )))+IF(MOD(ROW(),2)=0,8,0),IF(OR($C31="",$D31=""),0, IF(OR($A30="Holiday",$A31="Holiday"),0, IF(AND(NOT(OR($A30="Annual Leave",$A31="Annual Leave")),$A31="Off day"),0, IF($I30+$I31>=8,IF($I30>=8,0,8-$I30),$I31) )))) | N31: =IF(OR($C31="",$D31=""),0, IF(OR($A30="Holiday",$A31="Holiday"), IF(ISNUMBER(MATCH(TRIM($B31),{"Phagwah","Good Friday","Easter Monday","Labour Day","Christmas","Eid ul Azha","Romans-2","Globe-12","Neptune P1"},0)),0,$I31), IF(AND(NOT(OR($A30="Annual Leave",$A31="Annual Leave")),$A31="Off day"),$I31, MAX(0,$I31-$M31) ))) | O31: =IF(AND(OR($A30="Holiday",$A31="Holiday"), ISNUMBER(MATCH(TRIM($B31),{"Phagwah","Good Friday","Easter Monday","Labour Day","Christmas","Eid ul Azha","Romans-2","Globe-12","Neptune P1"},0))), $I31,0) | R31: =IF(OR($O$7="Canteen",$O$7="Head Office"),0,IF( AND( SUMIFS(I:I, C:C, C31) >= 8, COUNTIFS(C$14:C31, C31)=1, OR( TEXT(D31,"hh:mm:ss")="07:00:00", TEXT(D31,"hh:mm:ss")="15:00:00", TEXT(D31,"hh:mm:ss")="23:00:00", TEXT(D32,"hh:mm:ss")="07:00:00", TEXT(D32,"hh:mm:ss")="15:00:00", TEXT(D32,"hh:mm:ss")="23:00:00" ) ), 1, 0 )) | S31: =IF(OR($A30="Annual Leave",$A31="Annual Leave"),IF(AND($A30<>"Annual Leave",$A31="Annual Leave"),8,0),0)
A32: On Day | C32: =C30+1 | D32: 0.29166667 | E32: =IF(D32=0, 0, IF(AND(D32>=TIME(0,0,1), D32<=TIME(2,0,0)), TIME(7,0,0), IF(AND(D32>=TIME(5,0,0), D32<=TIME(8,0,0)), TIME(12,0,0), IF(AND(D32>TIME(8,0,0), D32<=TIME(13,59,0)), TIME(15,0,0), IF(AND(D32>=TIME(14,0,0), D32<=TIME(17,59,0)), TIME(21,0,0), IF(AND(D32>=TIME(18,0,0), D32<=TIME(21,59,0)), TIME(0,0,0), IF(AND(D32>=TIME(22,0,0), D32<=TIME(23,59,59)), TIME(7,0,0), ""))))))) | G32: =E32 | I32: =ROUND(IF(OR(D32="",E32="",E32=0),0,IF(H32="",MOD(E32-D32,1)*24,MOD(H32-D32,1)*24)),2) | L32: FALSE | M32: =IF(OR($A32="Holiday",$A33="Holiday"),IF(OR($C32="",$D32=""),0, IF(OR($A32="Holiday",$A33="Holiday"),0, IF(AND(NOT(OR($A32="Annual Leave",$A33="Annual Leave")),$A32="Off day"),0, IF($I32+$I33>=8,IF($I32>=8,8,$I32),$I32) )))+IF(MOD(ROW(),2)=0,8,0),IF(OR($C32="",$D32=""),0, IF(OR($A32="Holiday",$A33="Holiday"),0, IF(AND(NOT(OR($A32="Annual Leave",$A33="Annual Leave")),$A32="Off day"),0, IF($I32+$I33>=8,IF($I32>=8,8,$I32),$I32) )))) | N32: =IF(OR($C32="",$D32=""),0, IF(OR($A32="Holiday",$A33="Holiday"), IF(ISNUMBER(MATCH(TRIM($B32),{"Phagwah","Good Friday","Easter Monday","Labour Day","Christmas","Eid ul Azha","Romans-2","Globe-12","Neptune P1"},0)),0,$I32), IF(AND(NOT(OR($A32="Annual Leave",$A33="Annual Leave")),$A32="Off day"),$I32, MAX(0,$I32-$M32) ))) | O32: =IF(AND(OR($A32="Holiday",$A33="Holiday"), ISNUMBER(MATCH(TRIM($B32),{"Phagwah","Good Friday","Easter Monday","Labour Day","Christmas","Eid ul Azha","Romans-2","Globe-12","Neptune P1"},0))), $I32,0) | R32: =IF(OR($O$7="Canteen",$O$7="Head Office"),0,IF( AND( SUMIFS(I:I, C:C, C32) >= 8, COUNTIFS(C$14:C32, C32)=1, OR( TEXT(D32,"hh:mm:ss")="07:00:00", TEXT(D32,"hh:mm:ss")="15:00:00", TEXT(D32,"hh:mm:ss")="23:00:00", TEXT(D33,"hh:mm:ss")="07:00:00", TEXT(D33,"hh:mm:ss")="15:00:00", TEXT(D33,"hh:mm:ss")="23:00:00" ) ), 1, 0 )) | S32: =IF(OR($A32="Annual Leave",$A33="Annual Leave"),IF($A32="Annual Leave",8,0),0)
A33: On Day | C33: =C32 | D33: 0.625 | E33: =IF(D33=0, 0, IF(AND(D33>=TIME(0,0,1), D33<=TIME(2,0,0)), TIME(7,0,0), IF(AND(D33>=TIME(5,0,0), D33<=TIME(8,0,0)), TIME(12,0,0), IF(AND(D33>TIME(8,0,0), D33<=TIME(13,59,0)), TIME(15,0,0), IF(AND(D33>=TIME(14,0,0), D33<=TIME(17,59,0)), TIME(21,0,0), IF(AND(D33>=TIME(18,0,0), D33<=TIME(21,59,0)), TIME(0,0,0), IF(AND(D33>=TIME(22,0,0), D33<=TIME(23,59,59)), TIME(7,0,0), ""))))))) | G33: =E33 | I33: =ROUND(IF(OR(D33="",E33="",E33=0),0,IF(H33="",MOD(E33-D33,1)*24,MOD(H33-D33,1)*24)),2) | L33: FALSE | M33: =IF(OR($A33="Holiday",$A32="Holiday"),IF(OR($C33="",$D33=""),0, IF(OR($A32="Holiday",$A33="Holiday"),0, IF(AND(NOT(OR($A32="Annual Leave",$A33="Annual Leave")),$A33="Off day"),0, IF($I32+$I33>=8,IF($I32>=8,0,8-$I32),$I33) )))+IF(MOD(ROW(),2)=0,8,0),IF(OR($C33="",$D33=""),0, IF(OR($A32="Holiday",$A33="Holiday"),0, IF(AND(NOT(OR($A32="Annual Leave",$A33="Annual Leave")),$A33="Off day"),0, IF($I32+$I33>=8,IF($I32>=8,0,8-$I32),$I33) )))) | N33: =IF(OR($C33="",$D33=""),0, IF(OR($A32="Holiday",$A33="Holiday"), IF(ISNUMBER(MATCH(TRIM($B33),{"Phagwah","Good Friday","Easter Monday","Labour Day","Christmas","Eid ul Azha","Romans-2","Globe-12","Neptune P1"},0)),0,$I33), IF(AND(NOT(OR($A32="Annual Leave",$A33="Annual Leave")),$A33="Off day"),$I33, MAX(0,$I33-$M33) ))) | O33: =IF(AND(OR($A32="Holiday",$A33="Holiday"), ISNUMBER(MATCH(TRIM($B33),{"Phagwah","Good Friday","Easter Monday","Labour Day","Christmas","Eid ul Azha","Romans-2","Globe-12","Neptune P1"},0))), $I33,0) | R33: =IF(OR($O$7="Canteen",$O$7="Head Office"),0,IF( AND( SUMIFS(I:I, C:C, C33) >= 8, COUNTIFS(C$14:C33, C33)=1, OR( TEXT(D33,"hh:mm:ss")="07:00:00", TEXT(D33,"hh:mm:ss")="15:00:00", TEXT(D33,"hh:mm:ss")="23:00:00", TEXT(D34,"hh:mm:ss")="07:00:00", TEXT(D34,"hh:mm:ss")="15:00:00", TEXT(D34,"hh:mm:ss")="23:00:00" ) ), 1, 0 )) | S33: =IF(OR($A32="Annual Leave",$A33="Annual Leave"),IF(AND($A32<>"Annual Leave",$A33="Annual Leave"),8,0),0)
A34: On Day | C34: =C32+1 | D34: 0.29166667 | E34: =IF(D34=0, 0, IF(AND(D34>=TIME(0,0,1), D34<=TIME(2,0,0)), TIME(7,0,0), IF(AND(D34>=TIME(5,0,0), D34<=TIME(8,0,0)), TIME(12,0,0), IF(AND(D34>TIME(8,0,0), D34<=TIME(13,59,0)), TIME(15,0,0), IF(AND(D34>=TIME(14,0,0), D34<=TIME(17,59,0)), TIME(21,0,0), IF(AND(D34>=TIME(18,0,0), D34<=TIME(21,59,0)), TIME(0,0,0), IF(AND(D34>=TIME(22,0,0), D34<=TIME(23,59,59)), TIME(7,0,0), ""))))))) | G34: =E34 | I34: =ROUND(IF(OR(D34="",E34="",E34=0),0,IF(H34="",MOD(E34-D34,1)*24,MOD(H34-D34,1)*24)),2) | L34: FALSE | M34: =IF(OR($A34="Holiday",$A35="Holiday"),IF(OR($C34="",$D34=""),0, IF(OR($A34="Holiday",$A35="Holiday"),0, IF(AND(NOT(OR($A34="Annual Leave",$A35="Annual Leave")),$A34="Off day"),0, IF($I34+$I35>=8,IF($I34>=8,8,$I34),$I34) )))+IF(MOD(ROW(),2)=0,8,0),IF(OR($C34="",$D34=""),0, IF(OR($A34="Holiday",$A35="Holiday"),0, IF(AND(NOT(OR($A34="Annual Leave",$A35="Annual Leave")),$A34="Off day"),0, IF($I34+$I35>=8,IF($I34>=8,8,$I34),$I34) )))) | N34: =IF(OR($C34="",$D34=""),0, IF(OR($A34="Holiday",$A35="Holiday"), IF(ISNUMBER(MATCH(TRIM($B34),{"Phagwah","Good Friday","Easter Monday","Labour Day","Christmas","Eid ul Azha","Romans-2","Globe-12","Neptune P1"},0)),0,$I34), IF(AND(NOT(OR($A34="Annual Leave",$A35="Annual Leave")),$A34="Off day"),$I34, MAX(0,$I34-$M34) ))) | O34: =IF(AND(OR($A34="Holiday",$A35="Holiday"), ISNUMBER(MATCH(TRIM($B34),{"Phagwah","Good Friday","Easter Monday","Labour Day","Christmas","Eid ul Azha","Romans-2","Globe-12","Neptune P1"},0))), $I34,0) | R34: =IF(OR($O$7="Canteen",$O$7="Head Office"),0,IF( AND( SUMIFS(I:I, C:C, C34) >= 8, COUNTIFS(C$14:C34, C34)=1, OR( TEXT(D34,"hh:mm:ss")="07:00:00", TEXT(D34,"hh:mm:ss")="15:00:00", TEXT(D34,"hh:mm:ss")="23:00:00", TEXT(D35,"hh:mm:ss")="07:00:00", TEXT(D35,"hh:mm:ss")="15:00:00", TEXT(D35,"hh:mm:ss")="23:00:00" ) ), 1, 0 )) | S34: =IF(OR($A34="Annual Leave",$A35="Annual Leave"),IF($A34="Annual Leave",8,0),0)
A35: On Day | C35: =C34 | D35: 0.625 | E35: =IF(D35=0, 0, IF(AND(D35>=TIME(0,0,1), D35<=TIME(2,0,0)), TIME(7,0,0), IF(AND(D35>=TIME(5,0,0), D35<=TIME(8,0,0)), TIME(12,0,0), IF(AND(D35>TIME(8,0,0), D35<=TIME(13,59,0)), TIME(15,0,0), IF(AND(D35>=TIME(14,0,0), D35<=TIME(17,59,0)), TIME(21,0,0), IF(AND(D35>=TIME(18,0,0), D35<=TIME(21,59,0)), TIME(0,0,0), IF(AND(D35>=TIME(22,0,0), D35<=TIME(23,59,59)), TIME(7,0,0), ""))))))) | G35: =E35 | I35: =ROUND(IF(OR(D35="",E35="",E35=0),0,IF(H35="",MOD(E35-D35,1)*24,MOD(H35-D35,1)*24)),2) | L35: FALSE | M35: =IF(OR($A35="Holiday",$A34="Holiday"),IF(OR($C35="",$D35=""),0, IF(OR($A34="Holiday",$A35="Holiday"),0, IF(AND(NOT(OR($A34="Annual Leave",$A35="Annual Leave")),$A35="Off day"),0, IF($I34+$I35>=8,IF($I34>=8,0,8-$I34),$I35) )))+IF(MOD(ROW(),2)=0,8,0),IF(OR($C35="",$D35=""),0, IF(OR($A34="Holiday",$A35="Holiday"),0, IF(AND(NOT(OR($A34="Annual Leave",$A35="Annual Leave")),$A35="Off day"),0, IF($I34+$I35>=8,IF($I34>=8,0,8-$I34),$I35) )))) | N35: =IF(OR($C35="",$D35=""),0, IF(OR($A34="Holiday",$A35="Holiday"), IF(ISNUMBER(MATCH(TRIM($B35),{"Phagwah","Good Friday","Easter Monday","Labour Day","Christmas","Eid ul Azha","Romans-2","Globe-12","Neptune P1"},0)),0,$I35), IF(AND(NOT(OR($A34="Annual Leave",$A35="Annual Leave")),$A35="Off day"),$I35, MAX(0,$I35-$M35) ))) | O35: =IF(AND(OR($A34="Holiday",$A35="Holiday"), ISNUMBER(MATCH(TRIM($B35),{"Phagwah","Good Friday","Easter Monday","Labour Day","Christmas","Eid ul Azha","Romans-2","Globe-12","Neptune P1"},0))), $I35,0) | R35: =IF(OR($O$7="Canteen",$O$7="Head Office"),0,IF( AND( SUMIFS(I:I, C:C, C35) >= 8, COUNTIFS(C$14:C35, C35)=1, OR( TEXT(D35,"hh:mm:ss")="07:00:00", TEXT(D35,"hh:mm:ss")="15:00:00", TEXT(D35,"hh:mm:ss")="23:00:00", TEXT(D36,"hh:mm:ss")="07:00:00", TEXT(D36,"hh:mm:ss")="15:00:00", TEXT(D36,"hh:mm:ss")="23:00:00" ) ), 1, 0 )) | S35: =IF(OR($A34="Annual Leave",$A35="Annual Leave"),IF(AND($A34<>"Annual Leave",$A35="Annual Leave"),8,0),0)
A36: On Day | C36: =C34+1 | D36: 0.29166667 | E36: =IF(D36=0, 0, IF(AND(D36>=TIME(0,0,1), D36<=TIME(2,0,0)), TIME(7,0,0), IF(AND(D36>=TIME(5,0,0), D36<=TIME(8,0,0)), TIME(12,0,0), IF(AND(D36>TIME(8,0,0), D36<=TIME(13,59,0)), TIME(15,0,0), IF(AND(D36>=TIME(14,0,0), D36<=TIME(17,59,0)), TIME(21,0,0), IF(AND(D36>=TIME(18,0,0), D36<=TIME(21,59,0)), TIME(0,0,0), IF(AND(D36>=TIME(22,0,0), D36<=TIME(23,59,59)), TIME(7,0,0), ""))))))) | G36: =E36 | I36: =ROUND(IF(OR(D36="",E36="",E36=0),0,IF(H36="",MOD(E36-D36,1)*24,MOD(H36-D36,1)*24)),2) | L36: FALSE | M36: =IF(OR($A36="Holiday",$A37="Holiday"),IF(OR($C36="",$D36=""),0, IF(OR($A36="Holiday",$A37="Holiday"),0, IF(AND(NOT(OR($A36="Annual Leave",$A37="Annual Leave")),$A36="Off day"),0, IF($I36+$I37>=8,IF($I36>=8,8,$I36),$I36) )))+IF(MOD(ROW(),2)=0,8,0),IF(OR($C36="",$D36=""),0, IF(OR($A36="Holiday",$A37="Holiday"),0, IF(AND(NOT(OR($A36="Annual Leave",$A37="Annual Leave")),$A36="Off day"),0, IF($I36+$I37>=8,IF($I36>=8,8,$I36),$I36) )))) | N36: =IF(OR($C36="",$D36=""),0, IF(OR($A36="Holiday",$A37="Holiday"), IF(ISNUMBER(MATCH(TRIM($B36),{"Phagwah","Good Friday","Easter Monday","Labour Day","Christmas","Eid ul Azha","Romans-2","Globe-12","Neptune P1"},0)),0,$I36), IF(AND(NOT(OR($A36="Annual Leave",$A37="Annual Leave")),$A36="Off day"),$I36, MAX(0,$I36-$M36) ))) | O36: =IF(AND(OR($A36="Holiday",$A37="Holiday"), ISNUMBER(MATCH(TRIM($B36),{"Phagwah","Good Friday","Easter Monday","Labour Day","Christmas","Eid ul Azha","Romans-2","Globe-12","Neptune P1"},0))), $I36,0) | R36: =IF(OR($O$7="Canteen",$O$7="Head Office"),0,IF( AND( SUMIFS(I:I, C:C, C36) >= 8, COUNTIFS(C$14:C36, C36)=1, OR( TEXT(D36,"hh:mm:ss")="07:00:00", TEXT(D36,"hh:mm:ss")="15:00:00", TEXT(D36,"hh:mm:ss")="23:00:00", TEXT(D37,"hh:mm:ss")="07:00:00", TEXT(D37,"hh:mm:ss")="15:00:00", TEXT(D37,"hh:mm:ss")="23:00:00" ) ), 1, 0 )) | S36: =IF(OR($A36="Annual Leave",$A37="Annual Leave"),IF($A36="Annual Leave",8,0),0)
A37: On Day | C37: =C36 | D37: 0.625 | E37: =IF(D37=0, 0, IF(AND(D37>=TIME(0,0,1), D37<=TIME(2,0,0)), TIME(7,0,0), IF(AND(D37>=TIME(5,0,0), D37<=TIME(8,0,0)), TIME(12,0,0), IF(AND(D37>TIME(8,0,0), D37<=TIME(13,59,0)), TIME(15,0,0), IF(AND(D37>=TIME(14,0,0), D37<=TIME(17,59,0)), TIME(21,0,0), IF(AND(D37>=TIME(18,0,0), D37<=TIME(21,59,0)), TIME(0,0,0), IF(AND(D37>=TIME(22,0,0), D37<=TIME(23,59,59)), TIME(7,0,0), ""))))))) | G37: =E37 | I37: =ROUND(IF(OR(D37="",E37="",E37=0),0,IF(H37="",MOD(E37-D37,1)*24,MOD(H37-D37,1)*24)),2) | L37: FALSE | M37: =IF(OR($A37="Holiday",$A36="Holiday"),IF(OR($C37="",$D37=""),0, IF(OR($A36="Holiday",$A37="Holiday"),0, IF(AND(NOT(OR($A36="Annual Leave",$A37="Annual Leave")),$A37="Off day"),0, IF($I36+$I37>=8,IF($I36>=8,0,8-$I36),$I37) )))+IF(MOD(ROW(),2)=0,8,0),IF(OR($C37="",$D37=""),0, IF(OR($A36="Holiday",$A37="Holiday"),0, IF(AND(NOT(OR($A36="Annual Leave",$A37="Annual Leave")),$A37="Off day"),0, IF($I36+$I37>=8,IF($I36>=8,0,8-$I36),$I37) )))) | N37: =IF(OR($C37="",$D37=""),0, IF(OR($A36="Holiday",$A37="Holiday"), IF(ISNUMBER(MATCH(TRIM($B37),{"Phagwah","Good Friday","Easter Monday","Labour Day","Christmas","Eid ul Azha","Romans-2","Globe-12","Neptune P1"},0)),0,$I37), IF(AND(NOT(OR($A36="Annual Leave",$A37="Annual Leave")),$A37="Off day"),$I37, MAX(0,$I37-$M37) ))) | O37: =IF(AND(OR($A36="Holiday",$A37="Holiday"), ISNUMBER(MATCH(TRIM($B37),{"Phagwah","Good Friday","Easter Monday","Labour Day","Christmas","Eid ul Azha","Romans-2","Globe-12","Neptune P1"},0))), $I37,0) | R37: =IF(OR($O$7="Canteen",$O$7="Head Office"),0,IF( AND( SUMIFS(I:I, C:C, C37) >= 8, COUNTIFS(C$14:C37, C37)=1, OR( TEXT(D37,"hh:mm:ss")="07:00:00", TEXT(D37,"hh:mm:ss")="15:00:00", TEXT(D37,"hh:mm:ss")="23:00:00", TEXT(D38,"hh:mm:ss")="07:00:00", TEXT(D38,"hh:mm:ss")="15:00:00", TEXT(D38,"hh:mm:ss")="23:00:00" ) ), 1, 0 )) | S37: =IF(OR($A36="Annual Leave",$A37="Annual Leave"),IF(AND($A36<>"Annual Leave",$A37="Annual Leave"),8,0),0)
A38: On Day | C38: =C36+1 | D38: 0.29166667 | E38: =IF(D38=0, 0, IF(AND(D38>=TIME(0,0,1), D38<=TIME(2,0,0)), TIME(7,0,0), IF(AND(D38>=TIME(5,0,0), D38<=TIME(8,0,0)), TIME(12,0,0), IF(AND(D38>TIME(8,0,0), D38<=TIME(13,59,0)), TIME(15,0,0), IF(AND(D38>=TIME(14,0,0), D38<=TIME(17,59,0)), TIME(21,0,0), IF(AND(D38>=TIME(18,0,0), D38<=TIME(21,59,0)), TIME(0,0,0), IF(AND(D38>=TIME(22,0,0), D38<=TIME(23,59,59)), TIME(7,0,0), ""))))))) | G38: =E38 | I38: =ROUND(IF(OR(D38="",E38="",E38=0),0,IF(H38="",MOD(E38-D38,1)*24,MOD(H38-D38,1)*24)),2) | L38: FALSE | M38: =IF(OR($A38="Holiday",$A39="Holiday"),IF(OR($C38="",$D38=""),0, IF(OR($A38="Holiday",$A39="Holiday"),0, IF(AND(NOT(OR($A38="Annual Leave",$A39="Annual Leave")),$A38="Off day"),0, IF($I38+$I39>=8,IF($I38>=8,8,$I38),$I38) )))+IF(MOD(ROW(),2)=0,8,0),IF(OR($C38="",$D38=""),0, IF(OR($A38="Holiday",$A39="Holiday"),0, IF(AND(NOT(OR($A38="Annual Leave",$A39="Annual Leave")),$A38="Off day"),0, IF($I38+$I39>=8,IF($I38>=8,8,$I38),$I38) )))) | N38: =IF(OR($C38="",$D38=""),0, IF(OR($A38="Holiday",$A39="Holiday"), IF(ISNUMBER(MATCH(TRIM($B38),{"Phagwah","Good Friday","Easter Monday","Labour Day","Christmas","Eid ul Azha","Romans-2","Globe-12","Neptune P1"},0)),0,$I38), IF(AND(NOT(OR($A38="Annual Leave",$A39="Annual Leave")),$A38="Off day"),$I38, MAX(0,$I38-$M38) ))) | O38: =IF(AND(OR($A38="Holiday",$A39="Holiday"), ISNUMBER(MATCH(TRIM($B38),{"Phagwah","Good Friday","Easter Monday","Labour Day","Christmas","Eid ul Azha","Romans-2","Globe-12","Neptune P1"},0))), $I38,0) | R38: =IF(OR($O$7="Canteen",$O$7="Head Office"),0,IF( AND( SUMIFS(I:I, C:C, C38) >= 8, COUNTIFS(C$14:C38, C38)=1, OR( TEXT(D38,"hh:mm:ss")="07:00:00", TEXT(D38,"hh:mm:ss")="15:00:00", TEXT(D38,"hh:mm:ss")="23:00:00", TEXT(D39,"hh:mm:ss")="07:00:00", TEXT(D39,"hh:mm:ss")="15:00:00", TEXT(D39,"hh:mm:ss")="23:00:00" ) ), 1, 0 )) | S38: =IF(OR($A38="Annual Leave",$A39="Annual Leave"),IF($A38="Annual Leave",8,0),0)
A39: On Day | C39: =C38 | D39: 0.625 | E39: =IF(D39=0, 0, IF(AND(D39>=TIME(0,0,1), D39<=TIME(2,0,0)), TIME(7,0,0), IF(AND(D39>=TIME(5,0,0), D39<=TIME(8,0,0)), TIME(12,0,0), IF(AND(D39>TIME(8,0,0), D39<=TIME(13,59,0)), TIME(15,0,0), IF(AND(D39>=TIME(14,0,0), D39<=TIME(17,59,0)), TIME(21,0,0), IF(AND(D39>=TIME(18,0,0), D39<=TIME(21,59,0)), TIME(0,0,0), IF(AND(D39>=TIME(22,0,0), D39<=TIME(23,59,59)), TIME(7,0,0), ""))))))) | G39: =E39 | I39: =ROUND(IF(OR(D39="",E39="",E39=0),0,IF(H39="",MOD(E39-D39,1)*24,MOD(H39-D39,1)*24)),2) | L39: FALSE | M39: =IF(OR($A39="Holiday",$A38="Holiday"),IF(OR($C39="",$D39=""),0, IF(OR($A38="Holiday",$A39="Holiday"),0, IF(AND(NOT(OR($A38="Annual Leave",$A39="Annual Leave")),$A39="Off day"),0, IF($I38+$I39>=8,IF($I38>=8,0,8-$I38),$I39) )))+IF(MOD(ROW(),2)=0,8,0),IF(OR($C39="",$D39=""),0, IF(OR($A38="Holiday",$A39="Holiday"),0, IF(AND(NOT(OR($A38="Annual Leave",$A39="Annual Leave")),$A39="Off day"),0, IF($I38+$I39>=8,IF($I38>=8,0,8-$I38),$I39) )))) | N39: =IF(OR($C39="",$D39=""),0, IF(OR($A38="Holiday",$A39="Holiday"), IF(ISNUMBER(MATCH(TRIM($B39),{"Phagwah","Good Friday","Easter Monday","Labour Day","Christmas","Eid ul Azha","Romans-2","Globe-12","Neptune P1"},0)),0,$I39), IF(AND(NOT(OR($A38="Annual Leave",$A39="Annual Leave")),$A39="Off day"),$I39, MAX(0,$I39-$M39) ))) | O39: =IF(AND(OR($A38="Holiday",$A39="Holiday"), ISNUMBER(MATCH(TRIM($B39),{"Phagwah","Good Friday","Easter Monday","Labour Day","Christmas","Eid ul Azha","Romans-2","Globe-12","Neptune P1"},0))), $I39,0) | R39: =IF(OR($O$7="Canteen",$O$7="Head Office"),0,IF( AND( SUMIFS(I:I, C:C, C39) >= 8, COUNTIFS(C$14:C39, C39)=1, OR( TEXT(D39,"hh:mm:ss")="07:00:00", TEXT(D39,"hh:mm:ss")="15:00:00", TEXT(D39,"hh:mm:ss")="23:00:00", TEXT(D40,"hh:mm:ss")="07:00:00", TEXT(D40,"hh:mm:ss")="15:00:00", TEXT(D40,"hh:mm:ss")="23:00:00" ) ), 1, 0 )) | S39: =IF(OR($A38="Annual Leave",$A39="Annual Leave"),IF(AND($A38<>"Annual Leave",$A39="Annual Leave"),8,0),0)
A40: On Day | C40: =C38+1 | D40: 0.29166667 | E40: =IF(D40=0, 0, IF(AND(D40>=TIME(0,0,1), D40<=TIME(2,0,0)), TIME(7,0,0), IF(AND(D40>=TIME(5,0,0), D40<=TIME(8,0,0)), TIME(12,0,0), IF(AND(D40>TIME(8,0,0), D40<=TIME(13,59,0)), TIME(15,0,0), IF(AND(D40>=TIME(14,0,0), D40<=TIME(17,59,0)), TIME(21,0,0), IF(AND(D40>=TIME(18,0,0), D40<=TIME(21,59,0)), TIME(0,0,0), IF(AND(D40>=TIME(22,0,0), D40<=TIME(23,59,59)), TIME(7,0,0), ""))))))) | G40: =E40 | I40: =ROUND(IF(OR(D40="",E40="",E40=0),0,IF(H40="",MOD(E40-D40,1)*24,MOD(H40-D40,1)*24)),2) | L40: FALSE | M40: =IF(OR($A40="Holiday",$A41="Holiday"),IF(OR($C40="",$D40=""),0, IF(OR($A40="Holiday",$A41="Holiday"),0, IF(AND(NOT(OR($A40="Annual Leave",$A41="Annual Leave")),$A40="Off day"),0, IF($I40+$I41>=8,IF($I40>=8,8,$I40),$I40) )))+IF(MOD(ROW(),2)=0,8,0),IF(OR($C40="",$D40=""),0, IF(OR($A40="Holiday",$A41="Holiday"),0, IF(AND(NOT(OR($A40="Annual Leave",$A41="Annual Leave")),$A40="Off day"),0, IF($I40+$I41>=8,IF($I40>=8,8,$I40),$I40) )))) | N40: =IF(OR($C40="",$D40=""),0, IF(OR($A40="Holiday",$A41="Holiday"), IF(ISNUMBER(MATCH(TRIM($B40),{"Phagwah","Good Friday","Easter Monday","Labour Day","Christmas","Eid ul Azha","Romans-2","Globe-12","Neptune P1"},0)),0,$I40), IF(AND(NOT(OR($A40="Annual Leave",$A41="Annual Leave")),$A40="Off day"),$I40, MAX(0,$I40-$M40) ))) | O40: =IF(AND(OR($A40="Holiday",$A41="Holiday"), ISNUMBER(MATCH(TRIM($B40),{"Phagwah","Good Friday","Easter Monday","Labour Day","Christmas","Eid ul Azha","Romans-2","Globe-12","Neptune P1"},0))), $I40,0) | R40: =IF(OR($O$7="Canteen",$O$7="Head Office"),0,IF( AND( SUMIFS(I:I, C:C, C40) >= 8, COUNTIFS(C$14:C40, C40)=1, OR( TEXT(D40,"hh:mm:ss")="07:00:00", TEXT(D40,"hh:mm:ss")="15:00:00", TEXT(D40,"hh:mm:ss")="23:00:00", TEXT(D41,"hh:mm:ss")="07:00:00", TEXT(D41,"hh:mm:ss")="15:00:00", TEXT(D41,"hh:mm:ss")="23:00:00" ) ), 1, 0 )) | S40: =IF(OR($A40="Annual Leave",$A41="Annual Leave"),IF($A40="Annual Leave",8,0),0)
A41: On Day | C41: =C40 | D41: 0.625 | E41: =IF(D41=0, 0, IF(AND(D41>=TIME(0,0,1), D41<=TIME(2,0,0)), TIME(7,0,0), IF(AND(D41>=TIME(5,0,0), D41<=TIME(8,0,0)), TIME(12,0,0), IF(AND(D41>TIME(8,0,0), D41<=TIME(13,59,0)), TIME(15,0,0), IF(AND(D41>=TIME(14,0,0), D41<=TIME(17,59,0)), TIME(21,0,0), IF(AND(D41>=TIME(18,0,0), D41<=TIME(21,59,0)), TIME(0,0,0), IF(AND(D41>=TIME(22,0,0), D41<=TIME(23,59,59)), TIME(7,0,0), ""))))))) | G41: =E41 | I41: =ROUND(IF(OR(D41="",E41="",E41=0),0,IF(H41="",MOD(E41-D41,1)*24,MOD(H41-D41,1)*24)),2) | L41: FALSE | M41: =IF(OR($A41="Holiday",$A40="Holiday"),IF(OR($C41="",$D41=""),0, IF(OR($A40="Holiday",$A41="Holiday"),0, IF(AND(NOT(OR($A40="Annual Leave",$A41="Annual Leave")),$A41="Off day"),0, IF($I40+$I41>=8,IF($I40>=8,0,8-$I40),$I41) )))+IF(MOD(ROW(),2)=0,8,0),IF(OR($C41="",$D41=""),0, IF(OR($A40="Holiday",$A41="Holiday"),0, IF(AND(NOT(OR($A40="Annual Leave",$A41="Annual Leave")),$A41="Off day"),0, IF($I40+$I41>=8,IF($I40>=8,0,8-$I40),$I41) )))) | N41: =IF(OR($C41="",$D41=""),0, IF(OR($A40="Holiday",$A41="Holiday"), IF(ISNUMBER(MATCH(TRIM($B41),{"Phagwah","Good Friday","Easter Monday","Labour Day","Christmas","Eid ul Azha","Romans-2","Globe-12","Neptune P1"},0)),0,$I41), IF(AND(NOT(OR($A40="Annual Leave",$A41="Annual Leave")),$A41="Off day"),$I41, MAX(0,$I41-$M41) ))) | O41: =IF(AND(OR($A40="Holiday",$A41="Holiday"), ISNUMBER(MATCH(TRIM($B41),{"Phagwah","Good Friday","Easter Monday","Labour Day","Christmas","Eid ul Azha","Romans-2","Globe-12","Neptune P1"},0))), $I41,0) | R41: =IF(OR($O$7="Canteen",$O$7="Head Office"),0,IF( AND( SUMIFS(I:I, C:C, C41) >= 8, COUNTIFS(C$14:C41, C41)=1, OR( TEXT(D41,"hh:mm:ss")="07:00:00", TEXT(D41,"hh:mm:ss")="15:00:00", TEXT(D41,"hh:mm:ss")="23:00:00", TEXT(D42,"hh:mm:ss")="07:00:00", TEXT(D42,"hh:mm:ss")="15:00:00", TEXT(D42,"hh:mm:ss")="23:00:00" ) ), 1, 0 )) | S41: =IF(OR($A40="Annual Leave",$A41="Annual Leave"),IF(AND($A40<>"Annual Leave",$A41="Annual Leave"),8,0),0)
A42: On Day | C42: =C40+1 | E42: =IF(D42=0, 0, IF(AND(D42>=TIME(0,0,1), D42<=TIME(2,0,0)), TIME(7,0,0), IF(AND(D42>=TIME(5,0,0), D42<=TIME(8,0,0)), TIME(12,0,0), IF(AND(D42>TIME(8,0,0), D42<=TIME(13,59,0)), TIME(15,0,0), IF(AND(D42>=TIME(14,0,0), D42<=TIME(17,59,0)), TIME(21,0,0), IF(AND(D42>=TIME(18,0,0), D42<=TIME(21,59,0)), TIME(0,0,0), IF(AND(D42>=TIME(22,0,0), D42<=TIME(23,59,59)), TIME(7,0,0), ""))))))) | G42: =E42 | I42: =ROUND(IF(OR(D42="",E42="",E42=0),0,IF(H42="",MOD(E42-D42,1)*24,MOD(H42-D42,1)*24)),2) | L42: FALSE | M42: =IF(OR($A42="Holiday",$A43="Holiday"),IF(OR($C42="",$D42=""),0, IF(OR($A42="Holiday",$A43="Holiday"),0, IF(AND(NOT(OR($A42="Annual Leave",$A43="Annual Leave")),$A42="Off day"),0, IF($I42+$I43>=8,IF($I42>=8,8,$I42),$I42) )))+IF(MOD(ROW(),2)=0,8,0),IF(OR($C42="",$D42=""),0, IF(OR($A42="Holiday",$A43="Holiday"),0, IF(AND(NOT(OR($A42="Annual Leave",$A43="Annual Leave")),$A42="Off day"),0, IF($I42+$I43>=8,IF($I42>=8,8,$I42),$I42) )))) | N42: =IF(OR($C42="",$D42=""),0, IF(OR($A42="Holiday",$A43="Holiday"), IF(ISNUMBER(MATCH(TRIM($B42),{"Phagwah","Good Friday","Easter Monday","Labour Day","Christmas","Eid ul Azha","Romans-2","Globe-12","Neptune P1"},0)),0,$I42), IF(AND(NOT(OR($A42="Annual Leave",$A43="Annual Leave")),$A42="Off day"),$I42, MAX(0,$I42-$M42) ))) | O42: =IF(AND(OR($A42="Holiday",$A43="Holiday"), ISNUMBER(MATCH(TRIM($B42),{"Phagwah","Good Friday","Easter Monday","Labour Day","Christmas","Eid ul Azha","Romans-2","Globe-12","Neptune P1"},0))), $I42,0) | R42: =IF(OR($O$7="Canteen",$O$7="Head Office"),0,IF( AND( SUMIFS(I:I, C:C, C42) >= 8, COUNTIFS(C$14:C42, C42)=1, OR( TEXT(D42,"hh:mm:ss")="07:00:00", TEXT(D42,"hh:mm:ss")="15:00:00", TEXT(D42,"hh:mm:ss")="23:00:00", TEXT(D43,"hh:mm:ss")="07:00:00", TEXT(D43,"hh:mm:ss")="15:00:00", TEXT(D43,"hh:mm:ss")="23:00:00" ) ), 1, 0 )) | S42: =IF(OR($A42="Annual Leave",$A43="Annual Leave"),IF($A42="Annual Leave",8,0),0)
A43: On Day | C43: =C42 | E43: =IF(D43=0, 0, IF(AND(D43>=TIME(0,0,1), D43<=TIME(2,0,0)), TIME(7,0,0), IF(AND(D43>=TIME(5,0,0), D43<=TIME(8,0,0)), TIME(12,0,0), IF(AND(D43>TIME(8,0,0), D43<=TIME(13,59,0)), TIME(15,0,0), IF(AND(D43>=TIME(14,0,0), D43<=TIME(17,59,0)), TIME(21,0,0), IF(AND(D43>=TIME(18,0,0), D43<=TIME(21,59,0)), TIME(0,0,0), IF(AND(D43>=TIME(22,0,0), D43<=TIME(23,59,59)), TIME(7,0,0), ""))))))) | G43: =E43 | I43: =ROUND(IF(OR(D43="",E43="",E43=0),0,IF(H43="",MOD(E43-D43,1)*24,MOD(H43-D43,1)*24)),2) | L43: FALSE | M43: =IF(OR($A43="Holiday",$A42="Holiday"),IF(OR($C43="",$D43=""),0, IF(OR($A42="Holiday",$A43="Holiday"),0, IF(AND(NOT(OR($A42="Annual Leave",$A43="Annual Leave")),$A43="Off day"),0, IF($I42+$I43>=8,IF($I42>=8,0,8-$I42),$I43) )))+IF(MOD(ROW(),2)=0,8,0),IF(OR($C43="",$D43=""),0, IF(OR($A42="Holiday",$A43="Holiday"),0, IF(AND(NOT(OR($A42="Annual Leave",$A43="Annual Leave")),$A43="Off day"),0, IF($I42+$I43>=8,IF($I42>=8,0,8-$I42),$I43) )))) | N43: =IF(OR($C43="",$D43=""),0, IF(OR($A42="Holiday",$A43="Holiday"), IF(ISNUMBER(MATCH(TRIM($B43),{"Phagwah","Good Friday","Easter Monday","Labour Day","Christmas","Eid ul Azha","Romans-2","Globe-12","Neptune P1"},0)),0,$I43), IF(AND(NOT(OR($A42="Annual Leave",$A43="Annual Leave")),$A43="Off day"),$I43, MAX(0,$I43-$M43) ))) | O43: =IF(AND(OR($A42="Holiday",$A43="Holiday"), ISNUMBER(MATCH(TRIM($B43),{"Phagwah","Good Friday","Easter Monday","Labour Day","Christmas","Eid ul Azha","Romans-2","Globe-12","Neptune P1"},0))), $I43,0) | R43: =IF(OR($O$7="Canteen",$O$7="Head Office"),0,IF( AND( SUMIFS(I:I, C:C, C43) >= 8, COUNTIFS(C$14:C43, C43)=1, OR( TEXT(D43,"hh:mm:ss")="07:00:00", TEXT(D43,"hh:mm:ss")="15:00:00", TEXT(D43,"hh:mm:ss")="23:00:00", TEXT(D49,"hh:mm:ss")="07:00:00", TEXT(D49,"hh:mm:ss")="15:00:00", TEXT(D49,"hh:mm:ss")="23:00:00" ) ), 1, 0 )) | S43: =IF(OR($A42="Annual Leave",$A43="Annual Leave"),IF(AND($A42<>"Annual Leave",$A43="Annual Leave"),8,0),0)
M44: =IF(OR($A44="Holiday",$A45="Holiday"),IF(OR($C44="",$D44=""),0, IF(OR($A44="Holiday",$A45="Holiday"),0, IF(AND(NOT(OR($A44="Annual Leave",$A45="Annual Leave")),$A44="Off day"),0, IF($I44+$I45>=8,IF($I44>=8,8,$I44),$I44) )))+IF(MOD(ROW(),2)=0,8,0),IF(OR($C44="",$D44=""),0, IF(OR($A44="Holiday",$A45="Holiday"),0, IF(AND(NOT(OR($A44="Annual Leave",$A45="Annual Leave")),$A44="Off day"),0, IF($I44+$I45>=8,IF($I44>=8,8,$I44),$I44) )))) | N44: =IF(OR($C44="",$D44=""),0, IF(OR($A44="Holiday",$A45="Holiday"), IF(ISNUMBER(MATCH(TRIM($B44),{"Phagwah","Good Friday","Easter Monday","Labour Day","Christmas","Eid ul Azha","Romans-2","Globe-12","Neptune P1"},0)),0,$I44), IF(AND(NOT(OR($A44="Annual Leave",$A45="Annual Leave")),$A44="Off day"),$I44, MAX(0,$I44-$M44) ))) | O44: =IF(AND(OR($A44="Holiday",$A45="Holiday"), ISNUMBER(MATCH(TRIM($B44),{"Phagwah","Good Friday","Easter Monday","Labour Day","Christmas","Eid ul Azha","Romans-2","Globe-12","Neptune P1"},0))), $I44,0) | S44: =IF(OR($A44="Annual Leave",$A45="Annual Leave"),IF($A44="Annual Leave",8,0),0)
A45: On Day | C45: =C42+1 | E45: =IF(D45=0, 0, IF(AND(D45>=TIME(0,0,1), D45<=TIME(2,0,0)), TIME(7,0,0), IF(AND(D45>=TIME(5,0,0), D45<=TIME(8,0,0)), TIME(12,0,0), IF(AND(D45>TIME(8,0,0), D45<=TIME(13,59,0)), TIME(15,0,0), IF(AND(D45>=TIME(14,0,0), D45<=TIME(17,59,0)), TIME(21,0,0), IF(AND(D45>=TIME(18,0,0), D45<=TIME(21,59,0)), TIME(0,0,0), IF(AND(D45>=TIME(22,0,0), D45<=TIME(23,59,59)), TIME(7,0,0), ""))))))) | G45: =E45 | I45: =ROUND(IF(OR(D45="",E45="",E45=0),0,IF(H45="",MOD(E45-D45,1)*24,MOD(H45-D45,1)*24)),2) | L45: FALSE | M45: =IF(OR($A45="Holiday",$A44="Holiday"),IF(OR($C45="",$D45=""),0, IF(OR($A44="Holiday",$A45="Holiday"),0, IF(AND(NOT(OR($A44="Annual Leave",$A45="Annual Leave")),$A45="Off day"),0, IF($I44+$I45>=8,IF($I44>=8,0,8-$I44),$I45) )))+IF(MOD(ROW(),2)=0,8,0),IF(OR($C45="",$D45=""),0, IF(OR($A44="Holiday",$A45="Holiday"),0, IF(AND(NOT(OR($A44="Annual Leave",$A45="Annual Leave")),$A45="Off day"),0, IF($I44+$I45>=8,IF($I44>=8,0,8-$I44),$I45) )))) | N45: =IF(OR($C45="",$D45=""),0, IF(OR($A44="Holiday",$A45="Holiday"), IF(ISNUMBER(MATCH(TRIM($B45),{"Phagwah","Good Friday","Easter Monday","Labour Day","Christmas","Eid ul Azha","Romans-2","Globe-12","Neptune P1"},0)),0,$I45), IF(AND(NOT(OR($A44="Annual Leave",$A45="Annual Leave")),$A45="Off day"),$I45, MAX(0,$I45-$M45) ))) | O45: =IF(AND(OR($A44="Holiday",$A45="Holiday"), ISNUMBER(MATCH(TRIM($B45),{"Phagwah","Good Friday","Easter Monday","Labour Day","Christmas","Eid ul Azha","Romans-2","Globe-12","Neptune P1"},0))), $I45,0) | R45: =IF(OR($O$7="Canteen",$O$7="Head Office"),0,IF( AND( SUMIFS(I:I, C:C, C45) >= 8, COUNTIFS(C$14:C45, C45)=1, OR( TEXT(D45,"hh:mm:ss")="07:00:00", TEXT(D45,"hh:mm:ss")="15:00:00", TEXT(D45,"hh:mm:ss")="23:00:00", TEXT(D46,"hh:mm:ss")="07:00:00", TEXT(D46,"hh:mm:ss")="15:00:00", TEXT(D46,"hh:mm:ss")="23:00:00" ) ), 1, 0 )) | S45: =IF(OR($A44="Annual Leave",$A45="Annual Leave"),IF(AND($A44<>"Annual Leave",$A45="Annual Leave"),8,0),0)
A46: On Day | C46: =C45 | E46: =IF(D46=0, 0, IF(AND(D46>=TIME(0,0,1), D46<=TIME(2,0,0)), TIME(7,0,0), IF(AND(D46>=TIME(5,0,0), D46<=TIME(8,0,0)), TIME(12,0,0), IF(AND(D46>TIME(8,0,0), D46<=TIME(13,59,0)), TIME(15,0,0), IF(AND(D46>=TIME(14,0,0), D46<=TIME(17,59,0)), TIME(21,0,0), IF(AND(D46>=TIME(18,0,0), D46<=TIME(21,59,0)), TIME(0,0,0), IF(AND(D46>=TIME(22,0,0), D46<=TIME(23,59,59)), TIME(7,0,0), ""))))))) | G46: =E46 | I46: =ROUND(IF(OR(D46="",E46="",E46=0),0,IF(H46="",MOD(E46-D46,1)*24,MOD(H46-D46,1)*24)),2) | L46: FALSE | M46: =IF(OR($A46="Holiday",$A47="Holiday"),IF(OR($C46="",$D46=""),0, IF(OR($A46="Holiday",$A47="Holiday"),0, IF(AND(NOT(OR($A46="Annual Leave",$A47="Annual Leave")),$A46="Off day"),0, IF($I46+$I47>=8,IF($I46>=8,8,$I46),$I46) )))+IF(MOD(ROW(),2)=0,8,0),IF(OR($C46="",$D46=""),0, IF(OR($A46="Holiday",$A47="Holiday"),0, IF(AND(NOT(OR($A46="Annual Leave",$A47="Annual Leave")),$A46="Off day"),0, IF($I46+$I47>=8,IF($I46>=8,8,$I46),$I46) )))) | N46: =IF(OR($C46="",$D46=""),0, IF(OR($A46="Holiday",$A47="Holiday"), IF(ISNUMBER(MATCH(TRIM($B46),{"Phagwah","Good Friday","Easter Monday","Labour Day","Christmas","Eid ul Azha","Romans-2","Globe-12","Neptune P1"},0)),0,$I46), IF(AND(NOT(OR($A46="Annual Leave",$A47="Annual Leave")),$A46="Off day"),$I46, MAX(0,$I46-$M46) ))) | O46: =IF(AND(OR($A46="Holiday",$A47="Holiday"), ISNUMBER(MATCH(TRIM($B46),{"Phagwah","Good Friday","Easter Monday","Labour Day","Christmas","Eid ul Azha","Romans-2","Globe-12","Neptune P1"},0))), $I46,0) | R46: =IF(OR($O$7="Canteen",$O$7="Head Office"),0,IF( AND( SUMIFS(I:I, C:C, C46) >= 8, COUNTIFS(C$14:C46, C46)=1, OR( TEXT(D46,"hh:mm:ss")="07:00:00", TEXT(D46,"hh:mm:ss")="15:00:00", TEXT(D46,"hh:mm:ss")="23:00:00", TEXT(D51,"hh:mm:ss")="07:00:00", TEXT(D51,"hh:mm:ss")="15:00:00", TEXT(D51,"hh:mm:ss")="23:00:00" ) ), 1, 0 )) | S46: =IF(OR($A46="Annual Leave",$A47="Annual Leave"),IF($A46="Annual Leave",8,0),0)
A47: On Day | C47: =C45+1 | E47: =IF(D47=0, 0, IF(AND(D47>=TIME(0,0,1), D47<=TIME(2,0,0)), TIME(7,0,0), IF(AND(D47>=TIME(5,0,0), D47<=TIME(8,0,0)), TIME(12,0,0), IF(AND(D47>TIME(8,0,0), D47<=TIME(13,59,0)), TIME(15,0,0), IF(AND(D47>=TIME(14,0,0), D47<=TIME(17,59,0)), TIME(21,0,0), IF(AND(D47>=TIME(18,0,0), D47<=TIME(21,59,0)), TIME(0,0,0), IF(AND(D47>=TIME(22,0,0), D47<=TIME(23,59,59)), TIME(7,0,0), ""))))))) | G47: =E47 | I47: =ROUND(IF(OR(D47="",E47="",E47=0),0,IF(H47="",MOD(E47-D47,1)*24,MOD(H47-D47,1)*24)),2) | L47: FALSE | M47: =IF(OR($A47="Holiday",$A46="Holiday"),IF(OR($C47="",$D47=""),0, IF(OR($A46="Holiday",$A47="Holiday"),0, IF(AND(NOT(OR($A46="Annual Leave",$A47="Annual Leave")),$A47="Off day"),0, IF($I46+$I47>=8,IF($I46>=8,0,8-$I46),$I47) )))+IF(MOD(ROW(),2)=0,8,0),IF(OR($C47="",$D47=""),0, IF(OR($A46="Holiday",$A47="Holiday"),0, IF(AND(NOT(OR($A46="Annual Leave",$A47="Annual Leave")),$A47="Off day"),0, IF($I46+$I47>=8,IF($I46>=8,0,8-$I46),$I47) )))) | N47: =IF(OR($C47="",$D47=""),0, IF(OR($A46="Holiday",$A47="Holiday"), IF(ISNUMBER(MATCH(TRIM($B47),{"Phagwah","Good Friday","Easter Monday","Labour Day","Christmas","Eid ul Azha","Romans-2","Globe-12","Neptune P1"},0)),0,$I47), IF(AND(NOT(OR($A46="Annual Leave",$A47="Annual Leave")),$A47="Off day"),$I47, MAX(0,$I47-$M47) ))) | O47: =IF(AND(OR($A46="Holiday",$A47="Holiday"), ISNUMBER(MATCH(TRIM($B47),{"Phagwah","Good Friday","Easter Monday","Labour Day","Christmas","Eid ul Azha","Romans-2","Globe-12","Neptune P1"},0))), $I47,0) | R47: =IF(OR($O$7="Canteen",$O$7="Head Office"),0,IF( AND( SUMIFS(I:I, C:C, C47) >= 8, COUNTIFS(C$14:C47, C47)=1, OR( TEXT(D47,"hh:mm:ss")="07:00:00", TEXT(D47,"hh:mm:ss")="15:00:00", TEXT(D47,"hh:mm:ss")="23:00:00", TEXT(D48,"hh:mm:ss")="07:00:00", TEXT(D48,"hh:mm:ss")="15:00:00", TEXT(D48,"hh:mm:ss")="23:00:00" ) ), 1, 0 )) | S47: =IF(OR($A46="Annual Leave",$A47="Annual Leave"),IF(AND($A46<>"Annual Leave",$A47="Annual Leave"),8,0),0)
A48: On Day | C48: =C47 | E48: =IF(D48=0, 0, IF(AND(D48>=TIME(0,0,1), D48<=TIME(2,0,0)), TIME(7,0,0), IF(AND(D48>=TIME(5,0,0), D48<=TIME(8,0,0)), TIME(12,0,0), IF(AND(D48>TIME(8,0,0), D48<=TIME(13,59,0)), TIME(15,0,0), IF(AND(D48>=TIME(14,0,0), D48<=TIME(17,59,0)), TIME(21,0,0), IF(AND(D48>=TIME(18,0,0), D48<=TIME(21,59,0)), TIME(0,0,0), IF(AND(D48>=TIME(22,0,0), D48<=TIME(23,59,59)), TIME(7,0,0), ""))))))) | G48: =E48 | I48: =ROUND(IF(OR(D48="",E48="",E48=0),0,IF(H48="",MOD(E48-D48,1)*24,MOD(H48-D48,1)*24)),2) | L48: FALSE | M48: =IF(OR($A48="Holiday",$A49="Holiday"),IF(OR($C48="",$D48=""),0, IF(OR($A48="Holiday",$A49="Holiday"),0, IF(AND(NOT(OR($A48="Annual Leave",$A49="Annual Leave")),$A48="Off day"),0, IF($I48+$I49>=8,IF($I48>=8,8,$I48),$I48) )))+IF(MOD(ROW(),2)=0,8,0),IF(OR($C48="",$D48=""),0, IF(OR($A48="Holiday",$A49="Holiday"),0, IF(AND(NOT(OR($A48="Annual Leave",$A49="Annual Leave")),$A48="Off day"),0, IF($I48+$I49>=8,IF($I48>=8,8,$I48),$I48) )))) | N48: =IF(OR($C48="",$D48=""),0, IF(OR($A48="Holiday",$A49="Holiday"), IF(ISNUMBER(MATCH(TRIM($B48),{"Phagwah","Good Friday","Easter Monday","Labour Day","Christmas","Eid ul Azha","Romans-2","Globe-12","Neptune P1"},0)),0,$I48), IF(AND(NOT(OR($A48="Annual Leave",$A49="Annual Leave")),$A48="Off day"),$I48, MAX(0,$I48-$M48) ))) | R48: =IF(OR($O$7="Canteen",$O$7="Head Office"),0,IF( AND( SUMIFS(I:I, C:C, C48) >= 8, COUNTIFS(C$14:C48, C48)=1, OR( TEXT(D48,"hh:mm:ss")="07:00:00", TEXT(D48,"hh:mm:ss")="15:00:00", TEXT(D48,"hh:mm:ss")="23:00:00", TEXT(D53,"hh:mm:ss")="07:00:00", TEXT(D53,"hh:mm:ss")="15:00:00", TEXT(D53,"hh:mm:ss")="23:00:00" ) ), 1, 0 ))
H49: Total Hrs: | I49: =SUM(I14:I48) | M49: =SUM(M14:M48) | N49: =SUM(N14:N48) | O49: =SUM(O14:O48) | P49: =SUM(P14:P48) | Q49: =IF($O$6<>"Armed",0,LOOKUP($Q$50,{0,1,2,3,4,5,6,7,8,9,10,11,12,13,14},{0,384,769,1153,1153,1538,1923,2307,2692,3076,3461,3846,4239,4615,5000})) | R49: =SUM(R14:R48) | S49: =SUM(S14:S48) | T49: =SUM(T30:T43)
P50: Days Worked | Q50: =SUM(--(SUM(I14:I15)>0),--(SUM(I16:I17)>0),--(SUM(I18:I19)>0),--(SUM(I20:I21)>0),--(SUM(I22:I23)>0),--(SUM(I24:I25)>0),--(SUM(I26:I27)>0),--(SUM(I30:I31)>0),--(SUM(I32:I33)>0),--(SUM(I34:I35)>0),--(SUM(I36:I37)>0),--(SUM(I38:I39)>0),--(SUM(I40:I41)>0),--(SUM(I42:I43)>0),--(SUM(I45:I46)>0),--(SUM(I47:I48)>0))
C52: Employee Signature | F52: Date
C54: Manager Signature | F54: Date | I54: {42}

Sheet Nelson, Keshia
V2: 2025 | Z2: Month: | AA2: 3
V3: =DATE(V2,AA2,1)
C4: Federal Manangement Systems | K4: Employee Number: | M4: 2744 | V4: Su | W4: M | X4: Tu | Y4: W | Z4: Th | AA4: F | AB4: Sa | AD4: Overtime Options
K5: Employee Name: | M5: Nelson, Keshia Andrea | V5: =IF(MONTH($V$3)<>MONTH($V$3-WEEKDAY($V$3,1)+(ROW(V5)-ROW($V$5))*7+(COLUMN(V5)-COLUMN($V$5)+1)),"",$V$3-WEEKDAY($V$3,1)+(ROW(V5)-ROW($V$5))*7+(COLUMN(V5)-COLUMN($V$5)+1)) | W5: =IF(MONTH($V$3)<>MONTH($V$3-WEEKDAY($V$3,1)+(ROW(W5)-ROW($V$5))*7+(COLUMN(W5)-COLUMN($V$5)+1)),"",$V$3-WEEKDAY($V$3,1)+(ROW(W5)-ROW($V$5))*7+(COLUMN(W5)-COLUMN($V$5)+1)) | X5: =IF(MONTH($V$3)<>MONTH($V$3-WEEKDAY($V$3,1)+(ROW(X5)-ROW($V$5))*7+(COLUMN(X5)-COLUMN($V$5)+1)),"",$V$3-WEEKDAY($V$3,1)+(ROW(X5)-ROW($V$5))*7+(COLUMN(X5)-COLUMN($V$5)+1)) | Y5: =IF(MONTH($V$3)<>MONTH($V$3-WEEKDAY($V$3,1)+(ROW(Y5)-ROW($V$5))*7+(COLUMN(Y5)-COLUMN($V$5)+1)),"",$V$3-WEEKDAY($V$3,1)+(ROW(Y5)-ROW($V$5))*7+(COLUMN(Y5)-COLUMN($V$5)+1)) | Z5: =IF(MONTH($V$3)<>MONTH($V$3-WEEKDAY($V$3,1)+(ROW(Z5)-ROW($V$5))*7+(COLUMN(Z5)-COLUMN($V$5)+1)),"",$V$3-WEEKDAY($V$3,1)+(ROW(Z5)-ROW($V$5))*7+(COLUMN(Z5)-COLUMN($V$5)+1)) | AA5: =IF(MONTH($V$3)<>MONTH($V$3-WEEKDAY($V$3,1)+(ROW(AA5)-ROW($V$5))*7+(COLUMN(AA5)-COLUMN($V$5)+1)),"",$V$3-WEEKDAY($V$3,1)+(ROW(AA5)-ROW($V$5))*7+(COLUMN(AA5)-COLUMN($V$5)+1)) | AB5: =IF(MONTH($V$3)<>MONTH($V$3-WEEKDAY($V$3,1)+(ROW(AB5)-ROW($V$5))*7+(COLUMN(AB5)-COLUMN($V$5)+1)),"",$V$3-WEEKDAY($V$3,1)+(ROW(AB5)-ROW($V$5))*7+(COLUMN(AB5)-COLUMN($V$5)+1)) | AE5: TRUE
C6: 120 Peter Rose St | M6: Armed or unarmed | O6: Unarmed | V6: =IF(MONTH($V$3)<>MONTH($V$3-WEEKDAY($V$3,1)+(ROW(V6)-ROW($V$5))*7+(COLUMN(V6)-COLUMN($V$5)+1)),"",$V$3-WEEKDAY($V$3,1)+(ROW(V6)-ROW($V$5))*7+(COLUMN(V6)-COLUMN($V$5)+1)) | W6: =IF(MONTH($V$3)<>MONTH($V$3-WEEKDAY($V$3,1)+(ROW(W6)-ROW($V$5))*7+(COLUMN(W6)-COLUMN($V$5)+1)),"",$V$3-WEEKDAY($V$3,1)+(ROW(W6)-ROW($V$5))*7+(COLUMN(W6)-COLUMN($V$5)+1)) | X6: =IF(MONTH($V$3)<>MONTH($V$3-WEEKDAY($V$3,1)+(ROW(X6)-ROW($V$5))*7+(COLUMN(X6)-COLUMN($V$5)+1)),"",$V$3-WEEKDAY($V$3,1)+(ROW(X6)-ROW($V$5))*7+(COLUMN(X6)-COLUMN($V$5)+1)) | Y6: =IF(MONTH($V$3)<>MONTH($V$3-WEEKDAY($V$3,1)+(ROW(Y6)-ROW($V$5))*7+(COLUMN(Y6)-COLUMN($V$5)+1)),"",$V$3-WEEKDAY($V$3,1)+(ROW(Y6)-ROW($V$5))*7+(COLUMN(Y6)-COLUMN($V$5)+1)) | Z6: =IF(MONTH($V$3)<>MONTH($V$3-WEEKDAY($V$3,1)+(ROW(Z6)-ROW($V$5))*7+(COLUMN(Z6)-COLUMN($V$5)+1)),"",$V$3-WEEKDAY($V$3,1)+(ROW(Z6)-ROW($V$5))*7+(COLUMN(Z6)-COLUMN($V$5)+1)) | AA6: =IF(MONTH($V$3)<>MONTH($V$3-WEEKDAY($V$3,1)+(ROW(AA6)-ROW($V$5))*7+(COLUMN(AA6)-COLUMN($V$5)+1)),"",$V$3-WEEKDAY($V$3,1)+(ROW(AA6)-ROW($V$5))*7+(COLUMN(AA6)-COLUMN($V$5)+1)) | AB6: =IF(MONTH($V$3)<>MONTH($V$3-WEEKDAY($V$3,1)+(ROW(AB6)-ROW($V$5))*7+(COLUMN(AB6)-COLUMN($V$5)+1)),"",$V$3-WEEKDAY($V$3,1)+(ROW(AB6)-ROW($V$5))*7+(COLUMN(AB6)-COLUMN($V$5)+1)) | AD6: After: | AE6: 8
C7: Queenstown | M7: Agency | O7: Caricom | V7: =IF(MONTH($V$3)<>MONTH($V$3-WEEKDAY($V$3,1)+(ROW(V7)-ROW($V$5))*7+(COLUMN(V7)-COLUMN($V$5)+1)),"",$V$3-WEEKDAY($V$3,1)+(ROW(V7)-ROW($V$5))*7+(COLUMN(V7)-COLUMN($V$5)+1)) | W7: =IF(MONTH($V$3)<>MONTH($V$3-WEEKDAY($V$3,1)+(ROW(W7)-ROW($V$5))*7+(COLUMN(W7)-COLUMN($V$5)+1)),"",$V$3-WEEKDAY($V$3,1)+(ROW(W7)-ROW($V$5))*7+(COLUMN(W7)-COLUMN($V$5)+1)) | X7: =IF(MONTH($V$3)<>MONTH($V$3-WEEKDAY($V$3,1)+(ROW(X7)-ROW($V$5))*7+(COLUMN(X7)-COLUMN($V$5)+1)),"",$V$3-WEEKDAY($V$3,1)+(ROW(X7)-ROW($V$5))*7+(COLUMN(X7)-COLUMN($V$5)+1)) | Y7: =IF(MONTH($V$3)<>MONTH($V$3-WEEKDAY($V$3,1)+(ROW(Y7)-ROW($V$5))*7+(COLUMN(Y7)-COLUMN($V$5)+1)),"",$V$3-WEEKDAY($V$3,1)+(ROW(Y7)-ROW($V$5))*7+(COLUMN(Y7)-COLUMN($V$5)+1)) | Z7: =IF(MONTH($V$3)<>MONTH($V$3-WEEKDAY($V$3,1)+(ROW(Z7)-ROW($V$5))*7+(COLUMN(Z7)-COLUMN($V$5)+1)),"",$V$3-WEEKDAY($V$3,1)+(ROW(Z7)-ROW($V$5))*7+(COLUMN(Z7)-COLUMN($V$5)+1)) | AA7: =IF(MONTH($V$3)<>MONTH($V$3-WEEKDAY($V$3,1)+(ROW(AA7)-ROW($V$5))*7+(COLUMN(AA7)-COLUMN($V$5)+1)),"",$V$3-WEEKDAY($V$3,1)+(ROW(AA7)-ROW($V$5))*7+(COLUMN(AA7)-COLUMN($V$5)+1)) | AB7: =IF(MONTH($V$3)<>MONTH($V$3-WEEKDAY($V$3,1)+(ROW(AB7)-ROW($V$5))*7+(COLUMN(AB7)-COLUMN($V$5)+1)),"",$V$3-WEEKDAY($V$3,1)+(ROW(AB7)-ROW($V$5))*7+(COLUMN(AB7)-COLUMN($V$5)+1))
C8: Georgetown, Guyana | V8: =IF(MONTH($V$3)<>MONTH($V$3-WEEKDAY($V$3,1)+(ROW(V8)-ROW($V$5))*7+(COLUMN(V8)-COLUMN($V$5)+1)),"",$V$3-WEEKDAY($V$3,1)+(ROW(V8)-ROW($V$5))*7+(COLUMN(V8)-COLUMN($V$5)+1)) | W8: =IF(MONTH($V$3)<>MONTH($V$3-WEEKDAY($V$3,1)+(ROW(W8)-ROW($V$5))*7+(COLUMN(W8)-COLUMN($V$5)+1)),"",$V$3-WEEKDAY($V$3,1)+(ROW(W8)-ROW($V$5))*7+(COLUMN(W8)-COLUMN($V$5)+1)) | X8: =IF(MONTH($V$3)<>MONTH($V$3-WEEKDAY($V$3,1)+(ROW(X8)-ROW($V$5))*7+(COLUMN(X8)-COLUMN($V$5)+1)),"",$V$3-WEEKDAY($V$3,1)+(ROW(X8)-ROW($V$5))*7+(COLUMN(X8)-COLUMN($V$5)+1)) | Y8: =IF(MONTH($V$3)<>MONTH($V$3-WEEKDAY($V$3,1)+(ROW(Y8)-ROW($V$5))*7+(COLUMN(Y8)-COLUMN($V$5)+1)),"",$V$3-WEEKDAY($V$3,1)+(ROW(Y8)-ROW($V$5))*7+(COLUMN(Y8)-COLUMN($V$5)+1)) | Z8: =IF(MONTH($V$3)<>MONTH($V$3-WEEKDAY($V$3,1)+(ROW(Z8)-ROW($V$5))*7+(COLUMN(Z8)-COLUMN($V$5)+1)),"",$V$3-WEEKDAY($V$3,1)+(ROW(Z8)-ROW($V$5))*7+(COLUMN(Z8)-COLUMN($V$5)+1)) | AA8: =IF(MONTH($V$3)<>MONTH($V$3-WEEKDAY($V$3,1)+(ROW(AA8)-ROW($V$5))*7+(COLUMN(AA8)-COLUMN($V$5)+1)),"",$V$3-WEEKDAY($V$3,1)+(ROW(AA8)-ROW($V$5))*7+(COLUMN(AA8)-COLUMN($V$5)+1)) | AB8: =IF(MONTH($V$3)<>MONTH($V$3-WEEKDAY($V$3,1)+(ROW(AB8)-ROW($V$5))*7+(COLUMN(AB8)-COLUMN($V$5)+1)),"",$V$3-WEEKDAY($V$3,1)+(ROW(AB8)-ROW($V$5))*7+(COLUMN(AB8)-COLUMN($V$5)+1)) | AE8: TRUE
C10: 592-223-7560 | K10: Week Starting: | M10: 46023 | T10: [42] | V10: =IF(MONTH($V$3)<>MONTH($V$3-WEEKDAY($V$3,1)+(ROW(V10)-ROW($V$5))*7+(COLUMN(V10)-COLUMN($V$5)+1)),"",$V$3-WEEKDAY($V$3,1)+(ROW(V10)-ROW($V$5))*7+(COLUMN(V10)-COLUMN($V$5)+1)) | W10: =IF(MONTH($V$3)<>MONTH($V$3-WEEKDAY($V$3,1)+(ROW(W10)-ROW($V$5))*7+(COLUMN(W10)-COLUMN($V$5)+1)),"",$V$3-WEEKDAY($V$3,1)+(ROW(W10)-ROW($V$5))*7+(COLUMN(W10)-COLUMN($V$5)+1)) | X10: =IF(MONTH($V$3)<>MONTH($V$3-WEEKDAY($V$3,1)+(ROW(X10)-ROW($V$5))*7+(COLUMN(X10)-COLUMN($V$5)+1)),"",$V$3-WEEKDAY($V$3,1)+(ROW(X10)-ROW($V$5))*7+(COLUMN(X10)-COLUMN($V$5)+1)) | Y10: =IF(MONTH($V$3)<>MONTH($V$3-WEEKDAY($V$3,1)+(ROW(Y10)-ROW($V$5))*7+(COLUMN(Y10)-COLUMN($V$5)+1)),"",$V$3-WEEKDAY($V$3,1)+(ROW(Y10)-ROW($V$5))*7+(COLUMN(Y10)-COLUMN($V$5)+1)) | Z10: =IF(MONTH($V$3)<>MONTH($V$3-WEEKDAY($V$3,1)+(ROW(Z10)-ROW($V$5))*7+(COLUMN(Z10)-COLUMN($V$5)+1)),"",$V$3-WEEKDAY($V$3,1)+(ROW(Z10)-ROW($V$5))*7+(COLUMN(Z10)-COLUMN($V$5)+1)) | AA10: =IF(MONTH($V$3)<>MONTH($V$3-WEEKDAY($V$3,1)+(ROW(AA10)-ROW($V$5))*7+(COLUMN(AA10)-COLUMN($V$5)+1)),"",$V$3-WEEKDAY($V$3,1)+(ROW(AA10)-ROW($V$5))*7+(COLUMN(AA10)-COLUMN($V$5)+1)) | AB10: =IF(MONTH($V$3)<>MONTH($V$3-WEEKDAY($V$3,1)+(ROW(AB10)-ROW($V$5))*7+(COLUMN(AB10)-COLUMN($V$5)+1)),"",$V$3-WEEKDAY($V$3,1)+(ROW(AB10)-ROW($V$5))*7+(COLUMN(AB10)-COLUMN($V$5)+1)) | AD10: After: | AE10: 40
K11: Carry Forward Hrs: | L11: 0 | V11: =IF(MONTH($V$3)<>MONTH($V$3-WEEKDAY($V$3,1)+(ROW(V11)-ROW($V$5))*7+(COLUMN(V11)-COLUMN($V$5)+1)),"",$V$3-WEEKDAY($V$3,1)+(ROW(V11)-ROW($V$5))*7+(COLUMN(V11)-COLUMN($V$5)+1)) | W11: =IF(MONTH($V$3)<>MONTH($V$3-WEEKDAY($V$3,1)+(ROW(W11)-ROW($V$5))*7+(COLUMN(W11)-COLUMN($V$5)+1)),"",$V$3-WEEKDAY($V$3,1)+(ROW(W11)-ROW($V$5))*7+(COLUMN(W11)-COLUMN($V$5)+1)) | X11: =IF(MONTH($V$3)<>MONTH($V$3-WEEKDAY($V$3,1)+(ROW(X11)-ROW($V$5))*7+(COLUMN(X11)-COLUMN($V$5)+1)),"",$V$3-WEEKDAY($V$3,1)+(ROW(X11)-ROW($V$5))*7+(COLUMN(X11)-COLUMN($V$5)+1)) | Y11: =IF(MONTH($V$3)<>MONTH($V$3-WEEKDAY($V$3,1)+(ROW(Y11)-ROW($V$5))*7+(COLUMN(Y11)-COLUMN($V$5)+1)),"",$V$3-WEEKDAY($V$3,1)+(ROW(Y11)-ROW($V$5))*7+(COLUMN(Y11)-COLUMN($V$5)+1)) | Z11: =IF(MONTH($V$3)<>MONTH($V$3-WEEKDAY($V$3,1)+(ROW(Z11)-ROW($V$5))*7+(COLUMN(Z11)-COLUMN($V$5)+1)),"",$V$3-WEEKDAY($V$3,1)+(ROW(Z11)-ROW($V$5))*7+(COLUMN(Z11)-COLUMN($V$5)+1)) | AA11: =IF(MONTH($V$3)<>MONTH($V$3-WEEKDAY($V$3,1)+(ROW(AA11)-ROW($V$5))*7+(COLUMN(AA11)-COLUMN($V$5)+1)),"",$V$3-WEEKDAY($V$3,1)+(ROW(AA11)-ROW($V$5))*7+(COLUMN(AA11)-COLUMN($V$5)+1)) | AB11: =IF(MONTH($V$3)<>MONTH($V$3-WEEKDAY($V$3,1)+(ROW(AB11)-ROW($V$5))*7+(COLUMN(AB11)-COLUMN($V$5)+1)),"",$V$3-WEEKDAY($V$3,1)+(ROW(AB11)-ROW($V$5))*7+(COLUMN(AB11)-COLUMN($V$5)+1))
A12: Day Off | B12: Holiday Double | C12: Day of Week | D12: Time In | E12: Time Out | G12: Time In | H12: Time Out | I12: Total Hrs | J12: Location | K12: Supervisor | L12: Supervisor Approval | M12: Regular Hrs | N12: Overtime Hrs | O12: Hol Hrs | P12: Responsibilities | Q12: Risk | R12: Meals | S12: Vac Hrs | T12: Reason for Overtime | U12: Wkly Reg Avail | V12: Orig Reg | W12: Wkly OT Adj | X12: Week Start | Y12: Wk Hrs Before
A14: On Day | C14: =M10 | E14: =IF(D14="", "", IF(D14=TIME(0,0,0), 0, IF(AND(D14>=TIME(0,0,1), D14<=TIME(2,0,0)), TIME(7,0,0), IF(AND(D14>=TIME(5,0,0), D14<=TIME(8,0,0)), TIME(12,0,0), IF(AND(D14>TIME(8,0,0), D14<=TIME(13,59,0)), TIME(15,0,0), IF(AND(D14>=TIME(14,0,0), D14<=TIME(17,59,0)), TIME(21,0,0), IF(AND(D14>=TIME(18,0,0), D14<=TIME(21,59,0)), TIME(0,0,0), IF(AND(D14>=TIME(22,0,0), D14<=TIME(23,59,59)), TIME(7,0,0), "")))))))) | G14: =E14 | I14: =ROUND(IF(OR(D14="",E14="",E14=0),0,IF(H14="",MOD(E14-D14,1)*24,MOD(H14-D14,1)*24)),2) | M14: =MAX(0,V14-W14) | N14: =(IF(OR($C14="",$D14=""),0, IF(OR($A14="Holiday",$A15="Holiday"), IF(ISNUMBER(MATCH(TRIM($B14),{"Phagwah","Good Friday","Easter Monday","Labour Day","Christmas","Eid ul Azha","Romans-2","Globe-12","Neptune P1"},0)),0,$I14), IF(AND(NOT(OR($A14="Annual Leave",$A15="Annual Leave")),$A14="Off day"),$I14, MAX(0,$I14-$V14) ))))+W14 | O14: =IF(AND(OR($A14="Holiday",$A15="Holiday"), ISNUMBER(MATCH(TRIM($B14),{"Phagwah","Good Friday","Easter Monday","Labour Day","Christmas","Eid ul Azha","Romans-2","Globe-12","Neptune P1"},0))), $I14,0) | P14: =IF(OR($O$7="Canteen",$O$7="Head Office"),0,IF($I14<=0,0,IF(OR(OR(TRIM($J14)="Hebrews",TRIM($J14)="Romans",TRIM($J14)="Romans-2",TRIM($J14)="Globe",TRIM($J14)="Globe-12",TRIM($J14)="Neptune P1"),AND($I15>0,OR(TRIM($J15)="Hebrews",TRIM($J15)="Romans",TRIM($J15)="Romans-2",TRIM($J15)="Globe",TRIM($J15)="Globe-12",TRIM($J15)="Neptune P1"))),1,0))) | R14: =IF(OR($O$7="Canteen",$O$7="Head Office"),0,IF(OR($I14>0,$I15>0), IF( OR( AND($D14>=TIME(5,0,0),$D14<=TIME(7,0,0)), AND($D14>=TIME(14,0,0),$D14<=TIME(15,0,0)), AND($D14>=TIME(18,0,0),$D14<=TIME(19,0,0)), AND($D15>=TIME(5,0,0),$D15<=TIME(7,0,0)), AND($D15>=TIME(14,0,0),$D15<=TIME(15,0,0)), AND($D15>=TIME(18,0,0),$D15<=TIME(19,0,0)) ), IF($I14>0,1,0), 0 ), 0)) | S14: =IF(OR($A14="Annual Leave",$A15="Annual Leave"),IF($A14="Annual Leave",8,0),0) | U14: =MAX(0,40-Y14) | V14: =IF(OR($A14="Holiday",$A15="Holiday"),IF(OR($C14="",$D14=""),0, IF(OR($A14="Holiday",$A15="Holiday"),0, IF(AND(NOT(OR($A14="Annual Leave",$A15="Annual Leave")),$A14="Off day"),0, IF($I14+$I15>=8,IF($I14>=8,8,$I14),$I14) )))+IF(MOD(ROW(),2)=0,8,0),IF(OR($C14="",$D14=""),0, IF(OR($A14="Holiday",$A15="Holiday"),0, IF(AND(NOT(OR($A14="Annual Leave",$A15="Annual Leave")),$A14="Off day"),0, IF($I14+$I15>=8,IF($I14>=8,8,$I14),$I14) )))) | W14: =MAX(0,V14-U14) | X14: =IF(C14="","",C14-WEEKDAY(C14,1)+1) | Y14: =IF(X14=X14,$L$11,0)
A15: On Day | C15: =C14 | E15: =IF(D15="", "", IF(D15=TIME(0,0,0), 0, IF(AND(D15>=TIME(0,0,1), D15<=TIME(2,0,0)), TIME(7,0,0), IF(AND(D15>=TIME(5,0,0), D15<=TIME(8,0,0)), TIME(12,0,0), IF(AND(D15>TIME(8,0,0), D15<=TIME(13,59,0)), TIME(15,0,0), IF(AND(D15>=TIME(14,0,0), D15<=TIME(17,59,0)), TIME(21,0,0), IF(AND(D15>=TIME(18,0,0), D15<=TIME(21,59,0)), TIME(0,0,0), IF(AND(D15>=TIME(22,0,0), D15<=TIME(23,59,59)), TIME(7,0,0), "")))))))) | G15: =E15 | I15: =ROUND(IF(OR(D15="",E15="",E15=0),0,IF(H15="",MOD(E15-D15,1)*24,MOD(H15-D15,1)*24)),2) | M15: =MAX(0,V15-W15) | N15: =(IF(OR($C15="",$D15=""),0, IF(OR($A14="Holiday",$A15="Holiday"), IF(ISNUMBER(MATCH(TRIM($B15),{"Phagwah","Good Friday","Easter Monday","Labour Day","Christmas","Eid ul Azha","Romans-2","Globe-12","Neptune P1"},0)),0,$I15), IF(AND(NOT(OR($A14="Annual Leave",$A15="Annual Leave")),$A15="Off day"),$I15, MAX(0,$I15-$V15) ))))+W15 | O15: =IF(AND(OR($A14="Holiday",$A15="Holiday"), ISNUMBER(MATCH(TRIM($B15),{"Phagwah","Good Friday","Easter Monday","Labour Day","Christmas","Eid ul Azha","Romans-2","Globe-12","Neptune P1"},0))), $I15,0) | P15: =IF(OR($O$7="Canteen",$O$7="Head Office"),0,IF($I15<=0,0,IF(AND($I14<=0,OR(TRIM($J15)="Hebrews",TRIM($J15)="Romans",TRIM($J15)="Romans-2",TRIM($J15)="Globe",TRIM($J15)="Globe-12",TRIM($J15)="Neptune P1")),1,0))) | R15: =IF(OR($O$7="Canteen",$O$7="Head Office"),0,IF(OR($I14>0,$I15>0), IF( OR( AND($D14>=TIME(5,0,0),$D14<=TIME(7,0,0)), AND($D14>=TIME(14,0,0),$D14<=TIME(15,0,0)), AND($D14>=TIME(18,0,0),$D14<=TIME(19,0,0)), AND($D15>=TIME(5,0,0),$D15<=TIME(7,0,0)), AND($D15>=TIME(14,0,0),$D15<=TIME(15,0,0)), AND($D15>=TIME(18,0,0),$D15<=TIME(19,0,0)) ), IF(AND($I14=0,$I15>0),1,0), 0 ), 0)) | S15: =IF(OR($A14="Annual Leave",$A15="Annual Leave"),IF(AND($A14<>"Annual Leave",$A15="Annual Leave"),8,0),0) | U15: =MAX(0,40-Y15) | V15: =IF(OR($A15="Holiday",$A14="Holiday"),IF(OR($C15="",$D15=""),0, IF(OR($A14="Holiday",$A15="Holiday"),0, IF(AND(NOT(OR($A14="Annual Leave",$A15="Annual Leave")),$A15="Off day"),0, IF($I14+$I15>=8,IF($I14>=8,0,8-$I14),$I15) )))+IF(MOD(ROW(),2)=0,8,0),IF(OR($C15="",$D15=""),0, IF(OR($A14="Holiday",$A15="Holiday"),0, IF(AND(NOT(OR($A14="Annual Leave",$A15="Annual Leave")),$A15="Off day"),0, IF($I14+$I15>=8,IF($I14>=8,0,8-$I14),$I15) )))) | W15: =MAX(0,V15-U15) | X15: =IF(C15="","",C15-WEEKDAY(C15,1)+1) | Y15: =SUMPRODUCT(($X$14:$X14=X15)*(($V$14:$V14)+($O$14:$O14)))+IF(X15=X14,$L$11,0)
A16: On Day | C16: =C14+1 | E16: =IF(D16="", "", IF(D16=TIME(0,0,0), 0, IF(AND(D16>=TIME(0,0,1), D16<=TIME(2,0,0)), TIME(7,0,0), IF(AND(D16>=TIME(5,0,0), D16<=TIME(8,0,0)), TIME(12,0,0), IF(AND(D16>TIME(8,0,0), D16<=TIME(13,59,0)), TIME(15,0,0), IF(AND(D16>=TIME(14,0,0), D16<=TIME(17,59,0)), TIME(21,0,0), IF(AND(D16>=TIME(18,0,0), D16<=TIME(21,59,0)), TIME(0,0,0), IF(AND(D16>=TIME(22,0,0), D16<=TIME(23,59,59)), TIME(7,0,0), "")))))))) | G16: =E16 | I16: =ROUND(IF(OR(D16="",E16="",E16=0),0,IF(H16="",MOD(E16-D16,1)*24,MOD(H16-D16,1)*24)),2) | M16: =MAX(0,V16-W16) | N16: =(IF(OR($C16="",$D16=""),0, IF(OR($A16="Holiday",$A17="Holiday"), IF(ISNUMBER(MATCH(TRIM($B16),{"Phagwah","Good Friday","Easter Monday","Labour Day","Christmas","Eid ul Azha","Romans-2","Globe-12","Neptune P1"},0)),0,$I16), IF(AND(NOT(OR($A16="Annual Leave",$A17="Annual Leave")),$A16="Off day"),$I16, MAX(0,$I16-$V16) ))))+W16 | O16: =IF(AND(OR($A16="Holiday",$A17="Holiday"), ISNUMBER(MATCH(TRIM($B16),{"Phagwah","Good Friday","Easter Monday","Labour Day","Christmas","Eid ul Azha","Romans-2","Globe-12","Neptune P1"},0))), $I16,0) | P16: =IF(OR($O$7="Canteen",$O$7="Head Office"),0,IF($I16<=0,0,IF(OR(OR(TRIM($J16)="Hebrews",TRIM($J16)="Romans",TRIM($J16)="Romans-2",TRIM($J16)="Globe",TRIM($J16)="Globe-12",TRIM($J16)="Neptune P1"),AND($I17>0,OR(TRIM($J17)="Hebrews",TRIM($J17)="Romans",TRIM($J17)="Romans-2",TRIM($J17)="Globe",TRIM($J17)="Globe-12",TRIM($J17)="Neptune P1"))),1,0))) | R16: =IF(OR($O$7="Canteen",$O$7="Head Office"),0,IF(OR($I16>0,$I17>0), IF( OR( AND($D16>=TIME(5,0,0),$D16<=TIME(7,0,0)), AND($D16>=TIME(14,0,0),$D16<=TIME(15,0,0)), AND($D16>=TIME(18,0,0),$D16<=TIME(19,0,0)), AND($D17>=TIME(5,0,0),$D17<=TIME(7,0,0)), AND($D17>=TIME(14,0,0),$D17<=TIME(15,0,0)), AND($D17>=TIME(18,0,0),$D17<=TIME(19,0,0)) ), IF($I16>0,1,0), 0 ), 0)) | S16: =IF(OR($A16="Annual Leave",$A17="Annual Leave"),IF($A16="Annual Leave",8,0),0) | U16: =MAX(0,40-Y16) | V16: =IF(OR($A16="Holiday",$A17="Holiday"),IF(OR($C16="",$D16=""),0, IF(OR($A16="Holiday",$A17="Holiday"),0, IF(AND(NOT(OR($A16="Annual Leave",$A17="Annual Leave")),$A16="Off day"),0, IF($I16+$I17>=8,IF($I16>=8,8,$I16),$I16) )))+IF(MOD(ROW(),2)=0,8,0),IF(OR($C16="",$D16=""),0, IF(OR($A16="Holiday",$A17="Holiday"),0, IF(AND(NOT(OR($A16="Annual Leave",$A17="Annual Leave")),$A16="Off day"),0, IF($I16+$I17>=8,IF($I16>=8,8,$I16),$I16) )))) | W16: =MAX(0,V16-U16) | X16: =IF(C16="","",C16-WEEKDAY(C16,1)+1) | Y16: =SUMPRODUCT(($X$14:$X15=X16)*(($V$14:$V15)+($O$14:$O15)))+IF(X16=X14,$L$11,0)
A17: On Day | C17: =C16 | E17: =IF(D17="", "", IF(D17=TIME(0,0,0), 0, IF(AND(D17>=TIME(0,0,1), D17<=TIME(2,0,0)), TIME(7,0,0), IF(AND(D17>=TIME(5,0,0), D17<=TIME(8,0,0)), TIME(12,0,0), IF(AND(D17>TIME(8,0,0), D17<=TIME(13,59,0)), TIME(15,0,0), IF(AND(D17>=TIME(14,0,0), D17<=TIME(17,59,0)), TIME(21,0,0), IF(AND(D17>=TIME(18,0,0), D17<=TIME(21,59,0)), TIME(0,0,0), IF(AND(D17>=TIME(22,0,0), D17<=TIME(23,59,59)), TIME(7,0,0), "")))))))) | G17: =E17 | I17: =ROUND(IF(OR(D17="",E17="",E17=0),0,IF(H17="",MOD(E17-D17,1)*24,MOD(H17-D17,1)*24)),2) | M17: =MAX(0,V17-W17) | N17: =(IF(OR($C17="",$D17=""),0, IF(OR($A16="Holiday",$A17="Holiday"), IF(ISNUMBER(MATCH(TRIM($B17),{"Phagwah","Good Friday","Easter Monday","Labour Day","Christmas","Eid ul Azha","Romans-2","Globe-12","Neptune P1"},0)),0,$I17), IF(AND(NOT(OR($A16="Annual Leave",$A17="Annual Leave")),$A17="Off day"),$I17, MAX(0,$I17-$V17) ))))+W17 | O17: =IF(AND(OR($A16="Holiday",$A17="Holiday"), ISNUMBER(MATCH(TRIM($B17),{"Phagwah","Good Friday","Easter Monday","Labour Day","Christmas","Eid ul Azha","Romans-2","Globe-12","Neptune P1"},0))), $I17,0) | P17: =IF(OR($O$7="Canteen",$O$7="Head Office"),0,IF($I17<=0,0,IF(AND($I16<=0,OR(TRIM($J17)="Hebrews",TRIM($J17)="Romans",TRIM($J17)="Romans-2",TRIM($J17)="Globe",TRIM($J17)="Globe-12",TRIM($J17)="Neptune P1")),1,0))) | R17: =IF(OR($O$7="Canteen",$O$7="Head Office"),0,IF(OR($I16>0,$I17>0), IF( OR( AND($D16>=TIME(5,0,0),$D16<=TIME(7,0,0)), AND($D16>=TIME(14,0,0),$D16<=TIME(15,0,0)), AND($D16>=TIME(18,0,0),$D16<=TIME(19,0,0)), AND($D17>=TIME(5,0,0),$D17<=TIME(7,0,0)), AND($D17>=TIME(14,0,0),$D17<=TIME(15,0,0)), AND($D17>=TIME(18,0,0),$D17<=TIME(19,0,0)) ), IF(AND($I16=0,$I17>0),1,0), 0 ), 0)) | S17: =IF(OR($A16="Annual Leave",$A17="Annual Leave"),IF(AND($A16<>"Annual Leave",$A17="Annual Leave"),8,0),0) | U17: =MAX(0,40-Y17) | V17: =IF(OR($A17="Holiday",$A16="Holiday"),IF(OR($C17="",$D17=""),0, IF(OR($A16="Holiday",$A17="Holiday"),0, IF(AND(NOT(OR($A16="Annual Leave",$A17="Annual Leave")),$A17="Off day"),0, IF($I16+$I17>=8,IF($I16>=8,0,8-$I16),$I17) )))+IF(MOD(ROW(),2)=0,8,0),IF(OR($C17="",$D17=""),0, IF(OR($A16="Holiday",$A17="Holiday"),0, IF(AND(NOT(OR($A16="Annual Leave",$A17="Annual Leave")),$A17="Off day"),0, IF($I16+$I17>=8,IF($I16>=8,0,8-$I16),$I17) )))) | W17: =MAX(0,V17-U17) | X17: =IF(C17="","",C17-WEEKDAY(C17,1)+1) | Y17: =SUMPRODUCT(($X$14:$X16=X17)*(($V$14:$V16)+($O$14:$O16)))+IF(X17=X14,$L$11,0)
A18: On Day | C18: =C16+1 | E18: =IF(D18="", "", IF(D18=TIME(0,0,0), 0, IF(AND(D18>=TIME(0,0,1), D18<=TIME(2,0,0)), TIME(7,0,0), IF(AND(D18>=TIME(5,0,0), D18<=TIME(8,0,0)), TIME(12,0,0), IF(AND(D18>TIME(8,0,0), D18<=TIME(13,59,0)), TIME(15,0,0), IF(AND(D18>=TIME(14,0,0), D18<=TIME(17,59,0)), TIME(21,0,0), IF(AND(D18>=TIME(18,0,0), D18<=TIME(21,59,0)), TIME(0,0,0), IF(AND(D18>=TIME(22,0,0), D18<=TIME(23,59,59)), TIME(7,0,0), "")))))))) | G18: =E18 | I18: =ROUND(IF(OR(D18="",E18="",E18=0),0,IF(H18="",MOD(E18-D18,1)*24,MOD(H18-D18,1)*24)),2) | M18: =MAX(0,V18-W18) | N18: =(IF(OR($C18="",$D18=""),0, IF(OR($A18="Holiday",$A19="Holiday"), IF(ISNUMBER(MATCH(TRIM($B18),{"Phagwah","Good Friday","Easter Monday","Labour Day","Christmas","Eid ul Azha","Romans-2","Globe-12","Neptune P1"},0)),0,$I18), IF(AND(NOT(OR($A18="Annual Leave",$A19="Annual Leave")),$A18="Off day"),$I18, MAX(0,$I18-$V18) ))))+W18 | O18: =IF(AND(OR($A18="Holiday",$A19="Holiday"), ISNUMBER(MATCH(TRIM($B18),{"Phagwah","Good Friday","Easter Monday","Labour Day","Christmas","Eid ul Azha","Romans-2","Globe-12","Neptune P1"},0))), $I18,0) | P18: =IF(OR($O$7="Canteen",$O$7="Head Office"),0,IF($I18<=0,0,IF(OR(OR(TRIM($J18)="Hebrews",TRIM($J18)="Romans",TRIM($J18)="Romans-2",TRIM($J18)="Globe",TRIM($J18)="Globe-12",TRIM($J18)="Neptune P1"),AND($I19>0,OR(TRIM($J19)="Hebrews",TRIM($J19)="Romans",TRIM($J19)="Romans-2",TRIM($J19)="Globe",TRIM($J19)="Globe-12",TRIM($J19)="Neptune P1"))),1,0))) | R18: =IF(OR($O$7="Canteen",$O$7="Head Office"),0,IF(OR($I18>0,$I19>0), IF( OR( AND($D18>=TIME(5,0,0),$D18<=TIME(7,0,0)), AND($D18>=TIME(14,0,0),$D18<=TIME(15,0,0)), AND($D18>=TIME(18,0,0),$D18<=TIME(19,0,0)), AND($D19>=TIME(5,0,0),$D19<=TIME(7,0,0)), AND($D19>=TIME(14,0,0),$D19<=TIME(15,0,0)), AND($D19>=TIME(18,0,0),$D19<=TIME(19,0,0)) ), IF($I18>0,1,0), 0 ), 0)) | S18: =IF(OR($A18="Annual Leave",$A19="Annual Leave"),IF($A18="Annual Leave",8,0),0) | U18: =MAX(0,40-Y18) | V18: =IF(OR($A18="Holiday",$A19="Holiday"),IF(OR($C18="",$D18=""),0, IF(OR($A18="Holiday",$A19="Holiday"),0, IF(AND(NOT(OR($A18="Annual Leave",$A19="Annual Leave")),$A18="Off day"),0, IF($I18+$I19>=8,IF($I18>=8,8,$I18),$I18) )))+IF(MOD(ROW(),2)=0,8,0),IF(OR($C18="",$D18=""),0, IF(OR($A18="Holiday",$A19="Holiday"),0, IF(AND(NOT(OR($A18="Annual Leave",$A19="Annual Leave")),$A18="Off day"),0, IF($I18+$I19>=8,IF($I18>=8,8,$I18),$I18) )))) | W18: =MAX(0,V18-U18) | X18: =IF(C18="","",C18-WEEKDAY(C18,1)+1) | Y18: =SUMPRODUCT(($X$14:$X17=X18)*(($V$14:$V17)+($O$14:$O17)))+IF(X18=X14,$L$11,0)
A19: On Day | C19: =C18 | E19: =IF(D19="", "", IF(D19=TIME(0,0,0), 0, IF(AND(D19>=TIME(0,0,1), D19<=TIME(2,0,0)), TIME(7,0,0), IF(AND(D19>=TIME(5,0,0), D19<=TIME(8,0,0)), TIME(12,0,0), IF(AND(D19>TIME(8,0,0), D19<=TIME(13,59,0)), TIME(15,0,0), IF(AND(D19>=TIME(14,0,0), D19<=TIME(17,59,0)), TIME(21,0,0), IF(AND(D19>=TIME(18,0,0), D19<=TIME(21,59,0)), TIME(0,0,0), IF(AND(D19>=TIME(22,0,0), D19<=TIME(23,59,59)), TIME(7,0,0), "")))))))) | G19: =E19 | I19: =ROUND(IF(OR(D19="",E19="",E19=0),0,IF(H19="",MOD(E19-D19,1)*24,MOD(H19-D19,1)*24)),2) | M19: =MAX(0,V19-W19) | N19: =(IF(OR($C19="",$D19=""),0, IF(OR($A18="Holiday",$A19="Holiday"), IF(ISNUMBER(MATCH(TRIM($B19),{"Phagwah","Good Friday","Easter Monday","Labour Day","Christmas","Eid ul Azha","Romans-2","Globe-12","Neptune P1"},0)),0,$I19), IF(AND(NOT(OR($A18="Annual Leave",$A19="Annual Leave")),$A19="Off day"),$I19, MAX(0,$I19-$V19) ))))+W19 | O19: =IF(AND(OR($A18="Holiday",$A19="Holiday"), ISNUMBER(MATCH(TRIM($B19),{"Phagwah","Good Friday","Easter Monday","Labour Day","Christmas","Eid ul Azha","Romans-2","Globe-12","Neptune P1"},0))), $I19,0) | P19: =IF(OR($O$7="Canteen",$O$7="Head Office"),0,IF($I19<=0,0,IF(AND($I18<=0,OR(TRIM($J19)="Hebrews",TRIM($J19)="Romans",TRIM($J19)="Romans-2",TRIM($J19)="Globe",TRIM($J19)="Globe-12",TRIM($J19)="Neptune P1")),1,0))) | R19: =IF(OR($O$7="Canteen",$O$7="Head Office"),0,IF(OR($I18>0,$I19>0), IF( OR( AND($D18>=TIME(5,0,0),$D18<=TIME(7,0,0)), AND($D18>=TIME(14,0,0),$D18<=TIME(15,0,0)), AND($D18>=TIME(18,0,0),$D18<=TIME(19,0,0)), AND($D19>=TIME(5,0,0),$D19<=TIME(7,0,0)), AND($D19>=TIME(14,0,0),$D19<=TIME(15,0,0)), AND($D19>=TIME(18,0,0),$D19<=TIME(19,0,0)) ), IF(AND($I18=0,$I19>0),1,0), 0 ), 0)) | S19: =IF(OR($A18="Annual Leave",$A19="Annual Leave"),IF(AND($A18<>"Annual Leave",$A19="Annual Leave"),8,0),0) | U19: =MAX(0,40-Y19) | V19: =IF(OR($A19="Holiday",$A18="Holiday"),IF(OR($C19="",$D19=""),0, IF(OR($A18="Holiday",$A19="Holiday"),0, IF(AND(NOT(OR($A18="Annual Leave",$A19="Annual Leave")),$A19="Off day"),0, IF($I18+$I19>=8,IF($I18>=8,0,8-$I18),$I19) )))+IF(MOD(ROW(),2)=0,8,0),IF(OR($C19="",$D19=""),0, IF(OR($A18="Holiday",$A19="Holiday"),0, IF(AND(NOT(OR($A18="Annual Leave",$A19="Annual Leave")),$A19="Off day"),0, IF($I18+$I19>=8,IF($I18>=8,0,8-$I18),$I19) )))) | W19: =MAX(0,V19-U19) | X19: =IF(C19="","",C19-WEEKDAY(C19,1)+1) | Y19: =SUMPRODUCT(($X$14:$X18=X19)*(($V$14:$V18)+($O$14:$O18)))+IF(X19=X14,$L$11,0)
A20: On Day | C20: =C18+1 | E20: =IF(D20="", "", IF(D20=TIME(0,0,0), 0, IF(AND(D20>=TIME(0,0,1), D20<=TIME(2,0,0)), TIME(7,0,0), IF(AND(D20>=TIME(5,0,0), D20<=TIME(8,0,0)), TIME(12,0,0), IF(AND(D20>TIME(8,0,0), D20<=TIME(13,59,0)), TIME(15,0,0), IF(AND(D20>=TIME(14,0,0), D20<=TIME(17,59,0)), TIME(21,0,0), IF(AND(D20>=TIME(18,0,0), D20<=TIME(21,59,0)), TIME(0,0,0), IF(AND(D20>=TIME(22,0,0), D20<=TIME(23,59,59)), TIME(7,0,0), "")))))))) | G20: =E20 | I20: =ROUND(IF(OR(D20="",E20="",E20=0),0,IF(H20="",MOD(E20-D20,1)*24,MOD(H20-D20,1)*24)),2) | M20: =MAX(0,V20-W20) | N20: =(IF(OR($C20="",$D20=""),0, IF(OR($A20="Holiday",$A21="Holiday"), IF(ISNUMBER(MATCH(TRIM($B20),{"Phagwah","Good Friday","Easter Monday","Labour Day","Christmas","Eid ul Azha","Romans-2","Globe-12","Neptune P1"},0)),0,$I20), IF(AND(NOT(OR($A20="Annual Leave",$A21="Annual Leave")),$A20="Off day"),$I20, MAX(0,$I20-$V20) ))))+W20 | O20: =IF(AND(OR($A20="Holiday",$A21="Holiday"), ISNUMBER(MATCH(TRIM($B20),{"Phagwah","Good Friday","Easter Monday","Labour Day","Christmas","Eid ul Azha","Romans-2","Globe-12","Neptune P1"},0))), $I20,0) | P20: =IF(OR($O$7="Canteen",$O$7="Head Office"),0,IF($I20<=0,0,IF(OR(OR(TRIM($J20)="Hebrews",TRIM($J20)="Romans",TRIM($J20)="Romans-2",TRIM($J20)="Globe",TRIM($J20)="Globe-12",TRIM($J20)="Neptune P1"),AND($I21>0,OR(TRIM($J21)="Hebrews",TRIM($J21)="Romans",TRIM($J21)="Romans-2",TRIM($J21)="Globe",TRIM($J21)="Globe-12",TRIM($J21)="Neptune P1"))),1,0))) | R20: =IF(OR($O$7="Canteen",$O$7="Head Office"),0,IF(OR($I20>0,$I21>0), IF( OR( AND($D20>=TIME(5,0,0),$D20<=TIME(7,0,0)), AND($D20>=TIME(14,0,0),$D20<=TIME(15,0,0)), AND($D20>=TIME(18,0,0),$D20<=TIME(19,0,0)), AND($D21>=TIME(5,0,0),$D21<=TIME(7,0,0)), AND($D21>=TIME(14,0,0),$D21<=TIME(15,0,0)), AND($D21>=TIME(18,0,0),$D21<=TIME(19,0,0)) ), IF($I20>0,1,0), 0 ), 0)) | S20: =IF(OR($A20="Annual Leave",$A21="Annual Leave"),IF($A20="Annual Leave",8,0),0) | U20: =MAX(0,40-Y20) | V20: =IF(OR($A20="Holiday",$A21="Holiday"),IF(OR($C20="",$D20=""),0, IF(OR($A20="Holiday",$A21="Holiday"),0, IF(AND(NOT(OR($A20="Annual Leave",$A21="Annual Leave")),$A20="Off day"),0, IF($I20+$I21>=8,IF($I20>=8,8,$I20),$I20) )))+IF(MOD(ROW(),2)=0,8,0),IF(OR($C20="",$D20=""),0, IF(OR($A20="Holiday",$A21="Holiday"),0, IF(AND(NOT(OR($A20="Annual Leave",$A21="Annual Leave")),$A20="Off day"),0, IF($I20+$I21>=8,IF($I20>=8,8,$I20),$I20) )))) | W20: =MAX(0,V20-U20) | X20: =IF(C20="","",C20-WEEKDAY(C20,1)+1) | Y20: =SUMPRODUCT(($X$14:$X19=X20)*(($V$14:$V19)+($O$14:$O19)))+IF(X20=X14,$L$11,0)
A21: On Day | C21: =C20 | E21: =IF(D21="", "", IF(D21=TIME(0,0,0), 0, IF(AND(D21>=TIME(0,0,1), D21<=TIME(2,0,0)), TIME(7,0,0), IF(AND(D21>=TIME(5,0,0), D21<=TIME(8,0,0)), TIME(12,0,0), IF(AND(D21>TIME(8,0,0), D21<=TIME(13,59,0)), TIME(15,0,0), IF(AND(D21>=TIME(14,0,0), D21<=TIME(17,59,0)), TIME(21,0,0), IF(AND(D21>=TIME(18,0,0), D21<=TIME(21,59,0)), TIME(0,0,0), IF(AND(D21>=TIME(22,0,0), D21<=TIME(23,59,59)), TIME(7,0,0), "")))))))) | G21: =E21 | I21: =ROUND(IF(OR(D21="",E21="",E21=0),0,IF(H21="",MOD(E21-D21,1)*24,MOD(H21-D21,1)*24)),2) | M21: =MAX(0,V21-W21) | N21: =(IF(OR($C21="",$D21=""),0, IF(OR($A20="Holiday",$A21="Holiday"), IF(ISNUMBER(MATCH(TRIM($B21),{"Phagwah","Good Friday","Easter Monday","Labour Day","Christmas","Eid ul Azha","Romans-2","Globe-12","Neptune P1"},0)),0,$I21), IF(AND(NOT(OR($A20="Annual Leave",$A21="Annual Leave")),$A21="Off day"),$I21, MAX(0,$I21-$V21) ))))+W21 | O21: =IF(AND(OR($A20="Holiday",$A21="Holiday"), ISNUMBER(MATCH(TRIM($B21),{"Phagwah","Good Friday","Easter Monday","Labour Day","Christmas","Eid ul Azha","Romans-2","Globe-12","Neptune P1"},0))), $I21,0) | P21: =IF(OR($O$7="Canteen",$O$7="Head Office"),0,IF($I21<=0,0,IF(AND($I20<=0,OR(TRIM($J21)="Hebrews",TRIM($J21)="Romans",TRIM($J21)="Romans-2",TRIM($J21)="Globe",TRIM($J21)="Globe-12",TRIM($J21)="Neptune P1")),1,0))) | R21: =IF(OR($O$7="Canteen",$O$7="Head Office"),0,IF(OR($I20>0,$I21>0), IF( OR( AND($D20>=TIME(5,0,0),$D20<=TIME(7,0,0)), AND($D20>=TIME(14,0,0),$D20<=TIME(15,0,0)), AND($D20>=TIME(18,0,0),$D20<=TIME(19,0,0)), AND($D21>=TIME(5,0,0),$D21<=TIME(7,0,0)), AND($D21>=TIME(14,0,0),$D21<=TIME(15,0,0)), AND($D21>=TIME(18,0,0),$D21<=TIME(19,0,0)) ), IF(AND($I20=0,$I21>0),1,0), 0 ), 0)) | S21: =IF(OR($A20="Annual Leave",$A21="Annual Leave"),IF(AND($A20<>"Annual Leave",$A21="Annual Leave"),8,0),0) | U21: =MAX(0,40-Y21) | V21: =IF(OR($A21="Holiday",$A20="Holiday"),IF(OR($C21="",$D21=""),0, IF(OR($A20="Holiday",$A21="Holiday"),0, IF(AND(NOT(OR($A20="Annual Leave",$A21="Annual Leave")),$A21="Off day"),0, IF($I20+$I21>=8,IF($I20>=8,0,8-$I20),$I21) )))+IF(MOD(ROW(),2)=0,8,0),IF(OR($C21="",$D21=""),0, IF(OR($A20="Holiday",$A21="Holiday"),0, IF(AND(NOT(OR($A20="Annual Leave",$A21="Annual Leave")),$A21="Off day"),0, IF($I20+$I21>=8,IF($I20>=8,0,8-$I20),$I21) )))) | W21: =MAX(0,V21-U21) | X21: =IF(C21="","",C21-WEEKDAY(C21,1)+1) | Y21: =SUMPRODUCT(($X$14:$X20=X21)*(($V$14:$V20)+($O$14:$O20)))+IF(X21=X14,$L$11,0)
A22: On Day | C22: =C20+1 | E22: =IF(D22="", "", IF(D22=TIME(0,0,0), 0, IF(AND(D22>=TIME(0,0,1), D22<=TIME(2,0,0)), TIME(7,0,0), IF(AND(D22>=TIME(5,0,0), D22<=TIME(8,0,0)), TIME(12,0,0), IF(AND(D22>TIME(8,0,0), D22<=TIME(13,59,0)), TIME(15,0,0), IF(AND(D22>=TIME(14,0,0), D22<=TIME(17,59,0)), TIME(21,0,0), IF(AND(D22>=TIME(18,0,0), D22<=TIME(21,59,0)), TIME(0,0,0), IF(AND(D22>=TIME(22,0,0), D22<=TIME(23,59,59)), TIME(7,0,0), "")))))))) | G22: =E22 | I22: =ROUND(IF(OR(D22="",E22="",E22=0),0,IF(H22="",MOD(E22-D22,1)*24,MOD(H22-D22,1)*24)),2) | M22: =MAX(0,V22-W22) | N22: =(IF(OR($C22="",$D22=""),0, IF(OR($A22="Holiday",$A23="Holiday"), IF(ISNUMBER(MATCH(TRIM($B22),{"Phagwah","Good Friday","Easter Monday","Labour Day","Christmas","Eid ul Azha","Romans-2","Globe-12","Neptune P1"},0)),0,$I22), IF(AND(NOT(OR($A22="Annual Leave",$A23="Annual Leave")),$A22="Off day"),$I22, MAX(0,$I22-$V22) ))))+W22 | O22: =IF(AND(OR($A22="Holiday",$A23="Holiday"), ISNUMBER(MATCH(TRIM($B22),{"Phagwah","Good Friday","Easter Monday","Labour Day","Christmas","Eid ul Azha","Romans-2","Globe-12","Neptune P1"},0))), $I22,0) | P22: =IF(OR($O$7="Canteen",$O$7="Head Office"),0,IF($I22<=0,0,IF(OR(OR(TRIM($J22)="Hebrews",TRIM($J22)="Romans",TRIM($J22)="Romans-2",TRIM($J22)="Globe",TRIM($J22)="Globe-12",TRIM($J22)="Neptune P1"),AND($I23>0,OR(TRIM($J23)="Hebrews",TRIM($J23)="Romans",TRIM($J23)="Romans-2",TRIM($J23)="Globe",TRIM($J23)="Globe-12",TRIM($J23)="Neptune P1"))),1,0))) | R22: =IF(OR($O$7="Canteen",$O$7="Head Office"),0,IF(OR($I22>0,$I23>0), IF( OR( AND($D22>=TIME(5,0,0),$D22<=TIME(7,0,0)), AND($D22>=TIME(14,0,0),$D22<=TIME(15,0,0)), AND($D22>=TIME(18,0,0),$D22<=TIME(19,0,0)), AND($D23>=TIME(5,0,0),$D23<=TIME(7,0,0)), AND($D23>=TIME(14,0,0),$D23<=TIME(15,0,0)), AND($D23>=TIME(18,0,0),$D23<=TIME(19,0,0)) ), IF($I22>0,1,0), 0 ), 0)) | S22: =IF(OR($A22="Annual Leave",$A23="Annual Leave"),IF($A22="Annual Leave",8,0),0) | U22: =MAX(0,40-Y22) | V22: =IF(OR($A22="Holiday",$A23="Holiday"),IF(OR($C22="",$D22=""),0, IF(OR($A22="Holiday",$A23="Holiday"),0, IF(AND(NOT(OR($A22="Annual Leave",$A23="Annual Leave")),$A22="Off day"),0, IF($I22+$I23>=8,IF($I22>=8,8,$I22),$I22) )))+IF(MOD(ROW(),2)=0,8,0),IF(OR($C22="",$D22=""),0, IF(OR($A22="Holiday",$A23="Holiday"),0, IF(AND(NOT(OR($A22="Annual Leave",$A23="Annual Leave")),$A22="Off day"),0, IF($I22+$I23>=8,IF($I22>=8,8,$I22),$I22) )))) | W22: =MAX(0,V22-U22) | X22: =IF(C22="","",C22-WEEKDAY(C22,1)+1) | Y22: =SUMPRODUCT(($X$14:$X21=X22)*(($V$14:$V21)+($O$14:$O21)))+IF(X22=X14,$L$11,0)
A23: On Day | C23: =C22 | E23: =IF(D23="", "", IF(D23=TIME(0,0,0), 0, IF(AND(D23>=TIME(0,0,1), D23<=TIME(2,0,0)), TIME(7,0,0), IF(AND(D23>=TIME(5,0,0), D23<=TIME(8,0,0)), TIME(12,0,0), IF(AND(D23>TIME(8,0,0), D23<=TIME(13,59,0)), TIME(15,0,0), IF(AND(D23>=TIME(14,0,0), D23<=TIME(17,59,0)), TIME(21,0,0), IF(AND(D23>=TIME(18,0,0), D23<=TIME(21,59,0)), TIME(0,0,0), IF(AND(D23>=TIME(22,0,0), D23<=TIME(23,59,59)), TIME(7,0,0), "")))))))) | G23: =E23 | I23: =ROUND(IF(OR(D23="",E23="",E23=0),0,IF(H23="",MOD(E23-D23,1)*24,MOD(H23-D23,1)*24)),2) | M23: =MAX(0,V23-W23) | N23: =(IF(OR($C23="",$D23=""),0, IF(OR($A22="Holiday",$A23="Holiday"), IF(ISNUMBER(MATCH(TRIM($B23),{"Phagwah","Good Friday","Easter Monday","Labour Day","Christmas","Eid ul Azha","Romans-2","Globe-12","Neptune P1"},0)),0,$I23), IF(AND(NOT(OR($A22="Annual Leave",$A23="Annual Leave")),$A23="Off day"),$I23, MAX(0,$I23-$V23) ))))+W23 | O23: =IF(AND(OR($A22="Holiday",$A23="Holiday"), ISNUMBER(MATCH(TRIM($B23),{"Phagwah","Good Friday","Easter Monday","Labour Day","Christmas","Eid ul Azha","Romans-2","Globe-12","Neptune P1"},0))), $I23,0) | P23: =IF(OR($O$7="Canteen",$O$7="Head Office"),0,IF($I23<=0,0,IF(AND($I22<=0,OR(TRIM($J23)="Hebrews",TRIM($J23)="Romans",TRIM($J23)="Romans-2",TRIM($J23)="Globe",TRIM($J23)="Globe-12",TRIM($J23)="Neptune P1")),1,0))) | R23: =IF(OR($O$7="Canteen",$O$7="Head Office"),0,IF(OR($I22>0,$I23>0), IF( OR( AND($D22>=TIME(5,0,0),$D22<=TIME(7,0,0)), AND($D22>=TIME(14,0,0),$D22<=TIME(15,0,0)), AND($D22>=TIME(18,0,0),$D22<=TIME(19,0,0)), AND($D23>=TIME(5,0,0),$D23<=TIME(7,0,0)), AND($D23>=TIME(14,0,0),$D23<=TIME(15,0,0)), AND($D23>=TIME(18,0,0),$D23<=TIME(19,0,0)) ), IF(AND($I22=0,$I23>0),1,0), 0 ), 0)) | S23: =IF(OR($A22="Annual Leave",$A23="Annual Leave"),IF(AND($A22<>"Annual Leave",$A23="Annual Leave"),8,0),0) | U23: =MAX(0,40-Y23) | V23: =IF(OR($A23="Holiday",$A22="Holiday"),IF(OR($C23="",$D23=""),0, IF(OR($A22="Holiday",$A23="Holiday"),0, IF(AND(NOT(OR($A22="Annual Leave",$A23="Annual Leave")),$A23="Off day"),0, IF($I22+$I23>=8,IF($I22>=8,0,8-$I22),$I23) )))+IF(MOD(ROW(),2)=0,8,0),IF(OR($C23="",$D23=""),0, IF(OR($A22="Holiday",$A23="Holiday"),0, IF(AND(NOT(OR($A22="Annual Leave",$A23="Annual Leave")),$A23="Off day"),0, IF($I22+$I23>=8,IF($I22>=8,0,8-$I22),$I23) )))) | W23: =MAX(0,V23-U23) | X23: =IF(C23="","",C23-WEEKDAY(C23,1)+1) | Y23: =SUMPRODUCT(($X$14:$X22=X23)*(($V$14:$V22)+($O$14:$O22)))+IF(X23=X14,$L$11,0)
A24: On Day | C24: =C22+1 | E24: =IF(D24="", "", IF(D24=TIME(0,0,0), 0, IF(AND(D24>=TIME(0,0,1), D24<=TIME(2,0,0)), TIME(7,0,0), IF(AND(D24>=TIME(5,0,0), D24<=TIME(8,0,0)), TIME(12,0,0), IF(AND(D24>TIME(8,0,0), D24<=TIME(13,59,0)), TIME(15,0,0), IF(AND(D24>=TIME(14,0,0), D24<=TIME(17,59,0)), TIME(21,0,0), IF(AND(D24>=TIME(18,0,0), D24<=TIME(21,59,0)), TIME(0,0,0), IF(AND(D24>=TIME(22,0,0), D24<=TIME(23,59,59)), TIME(7,0,0), "")))))))) | G24: =E24 | I24: =ROUND(IF(OR(D24="",E24="",E24=0),0,IF(H24="",MOD(E24-D24,1)*24,MOD(H24-D24,1)*24)),2) | M24: =MAX(0,V24-W24) | N24: =(IF(OR($C24="",$D24=""),0, IF(OR($A24="Holiday",$A25="Holiday"), IF(ISNUMBER(MATCH(TRIM($B24),{"Phagwah","Good Friday","Easter Monday","Labour Day","Christmas","Eid ul Azha","Romans-2","Globe-12","Neptune P1"},0)),0,$I24), IF(AND(NOT(OR($A24="Annual Leave",$A25="Annual Leave")),$A24="Off day"),$I24, MAX(0,$I24-$V24) ))))+W24 | O24: =IF(AND(OR($A24="Holiday",$A25="Holiday"), ISNUMBER(MATCH(TRIM($B24),{"Phagwah","Good Friday","Easter Monday","Labour Day","Christmas","Eid ul Azha","Romans-2","Globe-12","Neptune P1"},0))), $I24,0) | P24: =IF(OR($O$7="Canteen",$O$7="Head Office"),0,IF($I24<=0,0,IF(OR(OR(TRIM($J24)="Hebrews",TRIM($J24)="Romans",TRIM($J24)="Romans-2",TRIM($J24)="Globe",TRIM($J24)="Globe-12",TRIM($J24)="Neptune P1"),AND($I25>0,OR(TRIM($J25)="Hebrews",TRIM($J25)="Romans",TRIM($J25)="Romans-2",TRIM($J25)="Globe",TRIM($J25)="Globe-12",TRIM($J25)="Neptune P1"))),1,0))) | R24: =IF(OR($O$7="Canteen",$O$7="Head Office"),0,IF(OR($I24>0,$I25>0), IF( OR( AND($D24>=TIME(5,0,0),$D24<=TIME(7,0,0)), AND($D24>=TIME(14,0,0),$D24<=TIME(15,0,0)), AND($D24>=TIME(18,0,0),$D24<=TIME(19,0,0)), AND($D25>=TIME(5,0,0),$D25<=TIME(7,0,0)), AND($D25>=TIME(14,0,0),$D25<=TIME(15,0,0)), AND($D25>=TIME(18,0,0),$D25<=TIME(19,0,0)) ), IF($I24>0,1,0), 0 ), 0)) | S24: =IF(OR($A24="Annual Leave",$A25="Annual Leave"),IF($A24="Annual Leave",8,0),0) | U24: =MAX(0,40-Y24) | V24: =IF(OR($A24="Holiday",$A25="Holiday"),IF(OR($C24="",$D24=""),0, IF(OR($A24="Holiday",$A25="Holiday"),0, IF(AND(NOT(OR($A24="Annual Leave",$A25="Annual Leave")),$A24="Off day"),0, IF($I24+$I25>=8,IF($I24>=8,8,$I24),$I24) )))+IF(MOD(ROW(),2)=0,8,0),IF(OR($C24="",$D24=""),0, IF(OR($A24="Holiday",$A25="Holiday"),0, IF(AND(NOT(OR($A24="Annual Leave",$A25="Annual Leave")),$A24="Off day"),0, IF($I24+$I25>=8,IF($I24>=8,8,$I24),$I24) )))) | W24: =MAX(0,V24-U24) | X24: =IF(C24="","",C24-WEEKDAY(C24,1)+1) | Y24: =SUMPRODUCT(($X$14:$X23=X24)*(($V$14:$V23)+($O$14:$O23)))+IF(X24=X14,$L$11,0)
