Workbook
Name valuevx: 42.314159

Sheet Work Hours Summary
A1: 📊 WORK HOURS SUMMARY
A2: Pay Period: 1-15/16 Jan 2026 | Total Employees: 104
A4: # | B4: Employee Name | C4: Emp # | D4: Total Hrs | E4: Days Wkd | F4: Daily >12 | G4: Wkly >60 | H4: 7+ Days | I4: OT >40 | J4: Wkly <40 | K4: Daily <8 | L4: Days <5 | M4: Period <80 | N4: STATUS
A5: 1 | B5: Agard, Desiree Ann | C5: 810 | D5: ='Agard, Desiree Ann'!I49 | E5: ='Agard, Desiree Ann'!Q50 | F5: =SUMPRODUCT((('Agard, Desiree Ann'!I14+'Agard, Desiree Ann'!I15)>12)*1)+SUMPRODUCT((('Agard, Desiree Ann'!I16+'Agard, Desiree Ann'!I17)>12)*1)+SUMPRODUCT((('Agard, Desiree Ann'!I18+'Agard, Desiree Ann'!I19)>12)*1)+SUMPRODUCT((('Agard, Desiree Ann'!I20+'Agard, Desiree Ann'!I21)>12)*1)+SUMPRODUCT((('Agard, Desiree Ann'!I22+'Agard, Desiree Ann'!I23)>12)*1)+SUMPRODUCT((('Agard, Desiree Ann'!I24+'Agard, Desiree Ann'!I25)>12)*1)+SUMPRODUCT((('Agard, Desiree Ann'!I26+'Agard, Desiree Ann'!I27)>12)*1)+SUMPRODUCT((('Agard, Desiree Ann'!I30+'Agard, Desiree Ann'!I31)>12)*1)+SUMPRODUCT((('Agard, Desiree Ann'!I32+'Agard, Desiree Ann'!I33)>12)*1)+SUMPRODUCT((('Agard, Desiree Ann'!I34+'Agard, Desiree Ann'!I35)>12)*1)+SUMPRODUCT((('Agard, Desiree Ann'!I36+'Agard, Desiree Ann'!I37)>12)*1)+SUMPRODUCT((('Agard, Desiree Ann'!I38+'Agard, Desiree Ann'!I39)>12)*1)+SUMPRODUCT((('Agard, Desiree Ann'!I40+'Agard, Desiree Ann'!I41)>12)*1)+SUMPRODUCT((('Agard, Desiree Ann'!I42+'Agard, Desiree Ann'!I43)>12)*1)+SUMPRODUCT((('Agard, Desiree Ann'!I45+'Agard, Desiree Ann'!I46)>12)*1)+SUMPRODUCT((('Agard, Desiree Ann'!I47+'Agard, Desiree Ann'!I48)>12)*1) | G5: =IF(MAX(SUM('Agard, Desiree Ann'!I14:I27),SUM('Agard, Desiree Ann'!I30:I43))>60,"Yes","") | H5: =IF(OR(AND(('Agard, Desiree Ann'!I14+'Agard, Desiree Ann'!I15)>0,('Agard, Desiree Ann'!I16+'Agard, Desiree Ann'!I17)>0,('Agard, Desiree Ann'!I18+'Agard, Desiree Ann'!I19)>0,('Agard, Desiree Ann'!I20+'Agard, Desiree Ann'!I21)>0,('Agard, Desiree Ann'!I22+'Agard, Desiree Ann'!I23)>0,('Agard, Desiree Ann'!I24+'Agard, Desiree Ann'!I25)>0,('Agard, Desiree Ann'!I26+'Agard, Desiree Ann'!I27)>0),AND(('Agard, Desiree Ann'!I30+'Agard, Desiree Ann'!I31)>0,('Agard, Desiree Ann'!I32+'Agard, Desiree Ann'!I33)>0,('Agard, Desiree Ann'!I34+'Agard, Desiree Ann'!I35)>0,('Agard, Desiree Ann'!I36+'Agard, Desiree Ann'!I37)>0,('Agard, Desiree Ann'!I38+'Agard, Desiree Ann'!I39)>0,('Agard, Desiree Ann'!I40+'Agard, Desiree Ann'!I41)>0,('Agard, Desiree Ann'!I42+'Agard, Desiree Ann'!I43)>0)),"Yes","") | I5: =IF('Agard, Desiree Ann'!N49>40,"Yes","") | J5: =IF(OR(AND(SUM('Agard, Desiree Ann'!I14:I27)>0,SUM('Agard, Desiree Ann'!I14:I27)<40),AND(SUM('Agard, Desiree Ann'!I30:I43)>0,SUM('Agard, Desiree Ann'!I30:I43)<40)),"Yes","") | K5: =SUMPRODUCT(('Agard, Desiree Ann'!I14:I48>0)*('Agard, Desiree Ann'!I14:I48<8)) | L5: =IF('Agard, Desiree Ann'!Q50<5,"Yes","") | M5: =IF(AND('Agard, Desiree Ann'!I49>0,'Agard, Desiree Ann'!I49<80),"Yes","") | N5: =IF(OR(F5>0,G5="Yes",H5="Yes",I5="Yes"),"⚠️ OVERWORK",IF(OR(J5="Yes",K5>0,L5="Yes",M5="Yes"),"🔻 UNDERWORK","✓ OK"))
A6: 2 | B6: Alphonso, Tanika Amira | C6: 4699 | D6: ='Alphonso, Tanika Amira'!I49 | E6: ='Alphonso, Tanika Amira'!Q50 | F6: =SUMPRODUCT((('Alphonso, Tanika Amira'!I14+'Alphonso, Tanika Amira'!I15)>12)*1)+SUMPRODUCT((('Alphonso, Tanika Amira'!I16+'Alphonso, Tanika Amira'!I17)>12)*1)+SUMPRODUCT((('Alphonso, Tanika Amira'!I18+'Alphonso, Tanika Amira'!I19)>12)*1)+SUMPRODUCT((('Alphonso, Tanika Amira'!I20+'Alphonso, Tanika Amira'!I21)>12)*1)+SUMPRODUCT((('Alphonso, Tanika Amira'!I22+'Alphonso, Tanika Amira'!I23)>12)*1)+SUMPRODUCT((('Alphonso, Tanika Amira'!I24+'Alphonso, Tanika Amira'!I25)>12)*1)+SUMPRODUCT((('Alphonso, Tanika Amira'!I26+'Alphonso, Tanika Amira'!I27)>12)*1)+SUMPRODUCT((('Alphonso, Tanika Amira'!I30+'Alphonso, Tanika Amira'!I31)>12)*1)+SUMPRODUCT((('Alphonso, Tanika Amira'!I32+'Alphonso, Tanika Amira'!I33)>12)*1)+SUMPRODUCT((('Alphonso, Tanika Amira'!I34+'Alphonso, Tanika Amira'!I35)>12)*1)+SUMPRODUCT((('Alphonso, Tanika Amira'!I36+'Alphonso, Tanika Amira'!I37)>12)*1)+SUMPRODUCT((('Alphonso, Tanika Amira'!I38+'Alphonso, Tanika Amira'!I39)>12)*1)+SUMPRODUCT((('Alphonso, Tanika Amira'!I40+'Alphonso, Tanika Amira'!I41)>12)*1)+SUMPRODUCT((('Alphonso, Tanika Amira'!I42+'Alphonso, Tanika Amira'!I43)>12)*1)+SUMPRODUCT((('Alphonso, Tanika Amira'!I45+'Alphonso, Tanika Amira'!I46)>12)*1)+SUMPRODUCT((('Alphonso, Tanika Amira'!I47+'Alphonso, Tanika Amira'!I48)>12)*1) | G6: =IF(MAX(SUM('Alphonso, Tanika Amira'!I14:I27),SUM('Alphonso, Tanika Amira'!I30:I43))>60,"Yes","") | H6: =IF(OR(AND(('Alphonso, Tanika Amira'!I14+'Alphonso, Tanika Amira'!I15)>0,('Alphonso, Tanika Amira'!I16+'Alphonso, Tanika Amira'!I17)>0,('Alphonso, Tanika Amira'!I18+'Alphonso, Tanika Amira'!I19)>0,('Alphonso, Tanika Amira'!I20+'Alphonso, Tanika Amira'!I21)>0,('Alphonso, Tanika Amira'!I22+'Alphonso, Tanika Amira'!I23)>0,('Alphonso, Tanika Amira'!I24+'Alphonso, Tanika Amira'!I25)>0,('Alphonso, Tanika Amira'!I26+'Alphonso, Tanika Amira'!I27)>0),AND(('Alphonso, Tanika Amira'!I30+'Alphonso, Tanika Amira'!I31)>0,('Alphonso, Tanika Amira'!I32+'Alphonso, Tanika Amira'!I33)>0,('Alphonso, Tanika Amira'!I34+'Alphonso, Tanika Amira'!I35)>0,('Alphonso, Tanika Amira'!I36+'Alphonso, Tanika Amira'!I37)>0,('Alphonso, Tanika Amira'!I38+'Alphonso, Tanika Amira'!I39)>0,('Alphonso, Tanika Amira'!I40+'Alphonso, Tanika Amira'!I41)>0,('Alphonso, Tanika Amira'!I42+'Alphonso, Tanika Amira'!I43)>0)),"Yes","") | I6: =IF('Alphonso, Tanika Amira'!N49>40,"Yes","") | J6: =IF(OR(AND(SUM('Alphonso, Tanika Amira'!I14:I27)>0,SUM('Alphonso, Tanika Amira'!I14:I27)<40),AND(SUM('Alphonso, Tanika Amira'!I30:I43)>0,SUM('Alphonso, Tanika Amira'!I30:I43)<40)),"Yes","") | K6: =SUMPRODUCT(('Alphonso, Tanika Amira'!I14:I48>0)*('Alphonso, Tanika Amira'!I14:I48<8)) | L6: =IF('Alphonso, Tanika Amira'!Q50<5,"Yes","") | M6: =IF(AND('Alphonso, Tanika Amira'!I49>0,'Alphonso, Tanika Amira'!I49<80),"Yes","") | N6: =IF(OR(F6>0,G6="Yes",H6="Yes",I6="Yes"),"⚠️ OVERWORK",IF(OR(J6="Yes",K6>0,L6="Yes",M6="Yes"),"🔻 UNDERWORK","✓ OK"))
A7: 3 | B7: Alstrom, Melanie Yolandia | C7: 1922 | D7: ='Alstrom, Melanie Yolandia'!I49 | E7: ='Alstrom, Melanie Yolandia'!Q50 | F7: =SUMPRODUCT((('Alstrom, Melanie Yolandia'!I14+'Alstrom, Melanie Yolandia'!I15)>12)*1)+SUMPRODUCT((('Alstrom, Melanie Yolandia'!I16+'Alstrom, Melanie Yolandia'!I17)>12)*1)+SUMPRODUCT((('Alstrom, Melanie Yolandia'!I18+'Alstrom, Melanie Yolandia'!I19)>12)*1)+SUMPRODUCT((('Alstrom, Melanie Yolandia'!I20+'Alstrom, Melanie Yolandia'!I21)>12)*1)+SUMPRODUCT((('Alstrom, Melanie Yolandia'!I22+'Alstrom, Melanie Yolandia'!I23)>12)*1)+SUMPRODUCT((('Alstrom, Melanie Yolandia'!I24+'Alstrom, Melanie Yolandia'!I25)>12)*1)+SUMPRODUCT((('Alstrom, Melanie Yolandia'!I26+'Alstrom, Melanie Yolandia'!I27)>12)*1)+SUMPRODUCT((('Alstrom, Melanie Yolandia'!I30+'Alstrom, Melanie Yolandia'!I31)>12)*1)+SUMPRODUCT((('Alstrom, Melanie Yolandia'!I32+'Alstrom, Melanie Yolandia'!I33)>12)*1)+SUMPRODUCT((('Alstrom, Melanie Yolandia'!I34+'Alstrom, Melanie Yolandia'!I35)>12)*1)+SUMPRODUCT((('Alstrom, Melanie Yolandia'!I36+'Alstrom, Melanie Yolandia'!I37)>12)*1)+SUMPRODUCT((('Alstrom, Melanie Yolandia'!I38+'Alstrom, Melanie Yolandia'!I39)>12)*1)+SUMPRODUCT((('Alstrom, Melanie Yolandia'!I40+'Alstrom, Melanie Yolandia'!I41)>12)*1)+SUMPRODUCT((('Alstrom, Melanie Yolandia'!I42+'Alstrom, Melanie Yolandia'!I43)>12)*1)+SUMPRODUCT((('Alstrom, Melanie Yolandia'!I45+'Alstrom, Melanie Yolandia'!I46)>12)*1)+SUMPRODUCT((('Alstrom, Melanie Yolandia'!I47+'Alstrom, Melanie Yolandia'!I48)>12)*1) | G7: =IF(MAX(SUM('Alstrom, Melanie Yolandia'!I14:I27),SUM('Alstrom, Melanie Yolandia'!I30:I43))>60,"Yes","") | H7: =IF(OR(AND(('Alstrom, Melanie Yolandia'!I14+'Alstrom, Melanie Yolandia'!I15)>0,('Alstrom, Melanie Yolandia'!I16+'Alstrom, Melanie Yolandia'!I17)>0,('Alstrom, Melanie Yolandia'!I18+'Alstrom, Melanie Yolandia'!I19)>0,('Alstrom, Melanie Yolandia'!I20+'Alstrom, Melanie Yolandia'!I21)>0,('Alstrom, Melanie Yolandia'!I22+'Alstrom, Melanie Yolandia'!I23)>0,('Alstrom, Melanie Yolandia'!I24+'Alstrom, Melanie Yolandia'!I25)>0,('Alstrom, Melanie Yolandia'!I26+'Alstrom, Melanie Yolandia'!I27)>0),AND(('Alstrom, Melanie Yolandia'!I30+'Alstrom, Melanie Yolandia'!I31)>0,('Alstrom, Melanie Yolandia'!I32+'Alstrom, Melanie Yolandia'!I33)>0,('Alstrom, Melanie Yolandia'!I34+'Alstrom, Melanie Yolandia'!I35)>0,('Alstrom, Melanie Yolandia'!I36+'Alstrom, Melanie Yolandia'!I37)>0,('Alstrom, Melanie Yolandia'!I38+'Alstrom, Melanie Yolandia'!I39)>0,('Alstrom, Melanie Yolandia'!I40+'Alstrom, Melanie Yolandia'!I41)>0,('Alstrom, Melanie Yolandia'!I42+'Alstrom, Melanie Yolandia'!I43)>0)),"Yes","") | I7: =IF('Alstrom, Melanie Yolandia'!N49>40,"Yes","") | J7: =IF(OR(AND(SUM('Alstrom, Melanie Yolandia'!I14:I27)>0,SUM('Alstrom, Melanie Yolandia'!I14:I27)<40),AND(SUM('Alstrom, Melanie Yolandia'!I30:I43)>0,SUM('Alstrom, Melanie Yolandia'!I30:I43)<40)),"Yes","") | K7: =SUMPRODUCT(('Alstrom, Melanie Yolandia'!I14:I48>0)*('Alstrom, Melanie Yolandia'!I14:I48<8)) | L7: =IF('Alstrom, Melanie Yolandia'!Q50<5,"Yes","") | M7: =IF(AND('Alstrom, Melanie Yolandia'!I49>0,'Alstrom, Melanie Yolandia'!I49<80),"Yes","") | N7: =IF(OR(F7>0,G7="Yes",H7="Yes",I7="Yes"),"⚠️ OVERWORK",IF(OR(J7="Yes",K7>0,L7="Yes",M7="Yes"),"🔻 UNDERWORK","✓ OK"))
A8: 4 | B8: Alves, Andrew Alwyn | C8: 5490 | D8: ='Alves, Andrew Alwyn'!I49 | E8: ='Alves, Andrew Alwyn'!Q50 | F8: =SUMPRODUCT((('Alves, Andrew Alwyn'!I14+'Alves, Andrew Alwyn'!I15)>12)*1)+SUMPRODUCT((('Alves, Andrew Alwyn'!I16+'Alves, Andrew Alwyn'!I17)>12)*1)+SUMPRODUCT((('Alves, Andrew Alwyn'!I18+'Alves, Andrew Alwyn'!I19)>12)*1)+SUMPRODUCT((('Alves, Andrew Alwyn'!I20+'Alves, Andrew Alwyn'!I21)>12)*1)+SUMPRODUCT((('Alves, Andrew Alwyn'!I22+'Alves, Andrew Alwyn'!I23)>12)*1)+SUMPRODUCT((('Alves, Andrew Alwyn'!I24+'Alves, Andrew Alwyn'!I25)>12)*1)+SUMPRODUCT((('Alves, Andrew Alwyn'!I26+'Alves, Andrew Alwyn'!I27)>12)*1)+SUMPRODUCT((('Alves, Andrew Alwyn'!I30+'Alves, Andrew Alwyn'!I31)>12)*1)+SUMPRODUCT((('Alves, Andrew Alwyn'!I32+'Alves, Andrew Alwyn'!I33)>12)*1)+SUMPRODUCT((('Alves, Andrew Alwyn'!I34+'Alves, Andrew Alwyn'!I35)>12)*1)+SUMPRODUCT((('Alves, Andrew Alwyn'!I36+'Alves, Andrew Alwyn'!I37)>12)*1)+SUMPRODUCT((('Alves, Andrew Alwyn'!I38+'Alves, Andrew Alwyn'!I39)>12)*1)+SUMPRODUCT((('Alves, Andrew Alwyn'!I40+'Alves, Andrew Alwyn'!I41)>12)*1)+SUMPRODUCT((('Alves, Andrew Alwyn'!I42+'Alves, Andrew Alwyn'!I43)>12)*1)+SUMPRODUCT((('Alves, Andrew Alwyn'!I45+'Alves, Andrew Alwyn'!I46)>12)*1)+SUMPRODUCT((('Alves, Andrew Alwyn'!I47+'Alves, Andrew Alwyn'!I48)>12)*1) | G8: =IF(MAX(SUM('Alves, Andrew Alwyn'!I14:I27),SUM('Alves, Andrew Alwyn'!I30:I43))>60,"Yes","") | H8: =IF(OR(AND(('Alves, Andrew Alwyn'!I14+'Alves, Andrew Alwyn'!I15)>0,('Alves, Andrew Alwyn'!I16+'Alves, Andrew Alwyn'!I17)>0,('Alves, Andrew Alwyn'!I18+'Alves, Andrew Alwyn'!I19)>0,('Alves, Andrew Alwyn'!I20+'Alves, Andrew Alwyn'!I21)>0,('Alves, Andrew Alwyn'!I22+'Alves, Andrew Alwyn'!I23)>0,('Alves, Andrew Alwyn'!I24+'Alves, Andrew Alwyn'!I25)>0,('Alves, Andrew Alwyn'!I26+'Alves, Andrew Alwyn'!I27)>0),AND(('Alves, Andrew Alwyn'!I30+'Alves, Andrew Alwyn'!I31)>0,('Alves, Andrew Alwyn'!I32+'Alves, Andrew Alwyn'!I33)>0,('Alves, Andrew Alwyn'!I34+'Alves, Andrew Alwyn'!I35)>0,('Alves, Andrew Alwyn'!I36+'Alves, Andrew Alwyn'!I37)>0,('Alves, Andrew Alwyn'!I38+'Alves, Andrew Alwyn'!I39)>0,('Alves, Andrew Alwyn'!I40+'Alves, Andrew Alwyn'!I41)>0,('Alves, Andrew Alwyn'!I42+'Alves, Andrew Alwyn'!I43)>0)),"Yes","") | I8: =IF('Alves, Andrew Alwyn'!N49>40,"Yes","") | J8: =IF(OR(AND(SUM('Alves, Andrew Alwyn'!I14:I27)>0,SUM('Alves, Andrew Alwyn'!I14:I27)<40),AND(SUM('Alves, Andrew Alwyn'!I30:I43)>0,SUM('Alves, Andrew Alwyn'!I30:I43)<40)),"Yes","") | K8: =SUMPRODUCT(('Alves, Andrew Alwyn'!I14:I48>0)*('Alves, Andrew Alwyn'!I14:I48<8)) | L8: =IF('Alves, Andrew Alwyn'!Q50<5,"Yes","") | M8: =IF(AND('Alves, Andrew Alwyn'!I49>0,'Alves, Andrew Alwyn'!I49<80),"Yes","") | N8: =IF(OR(F8>0,G8="Yes",H8="Yes",I8="Yes"),"⚠️ OVERWORK",IF(OR(J8="Yes",K8>0,L8="Yes",M8="Yes"),"🔻 UNDERWORK","✓ OK"))
A9: 5 | B9: Auguste, Nadege | C9: 5477 | D9: ='Auguste, Nadege'!I49 | E9: ='Auguste, Nadege'!Q50 | F9: =SUMPRODUCT((('Auguste, Nadege'!I14+'Auguste, Nadege'!I15)>12)*1)+SUMPRODUCT((('Auguste, Nadege'!I16+'Auguste, Nadege'!I17)>12)*1)+SUMPRODUCT((('Auguste, Nadege'!I18+'Auguste, Nadege'!I19)>12)*1)+SUMPRODUCT((('Auguste, Nadege'!I20+'Auguste, Nadege'!I21)>12)*1)+SUMPRODUCT((('Auguste, Nadege'!I22+'Auguste, Nadege'!I23)>12)*1)+SUMPRODUCT((('Auguste, Nadege'!I24+'Auguste, Nadege'!I25)>12)*1)+SUMPRODUCT((('Auguste, Nadege'!I26+'Auguste, Nadege'!I27)>12)*1)+SUMPRODUCT((('Auguste, Nadege'!I30+'Auguste, Nadege'!I31)>12)*1)+SUMPRODUCT((('Auguste, Nadege'!I32+'Auguste, Nadege'!I33)>12)*1)+SUMPRODUCT((('Auguste, Nadege'!I34+'Auguste, Nadege'!I35)>12)*1)+SUMPRODUCT((('Auguste, Nadege'!I36+'Auguste, Nadege'!I37)>12)*1)+SUMPRODUCT((('Auguste, Nadege'!I38+'Auguste, Nadege'!I39)>12)*1)+SUMPRODUCT((('Auguste, Nadege'!I40+'Auguste, Nadege'!I41)>12)*1)+SUMPRODUCT((('Auguste, Nadege'!I42+'Auguste, Nadege'!I43)>12)*1)+SUMPRODUCT((('Auguste, Nadege'!I45+'Auguste, Nadege'!I46)>12)*1)+SUMPRODUCT((('Auguste, Nadege'!I47+'Auguste, Nadege'!I48)>12)*1) | G9: =IF(MAX(SUM('Auguste, Nadege'!I14:I27),SUM('Auguste, Nadege'!I30:I43))>60,"Yes","") | H9: =IF(OR(AND(('Auguste, Nadege'!I14+'Auguste, Nadege'!I15)>0,('Auguste, Nadege'!I16+'Auguste, Nadege'!I17)>0,('Auguste, Nadege'!I18+'Auguste, Nadege'!I19)>0,('Auguste, Nadege'!I20+'Auguste, Nadege'!I21)>0,('Auguste, Nadege'!I22+'Auguste, Nadege'!I23)>0,('Auguste, Nadege'!I24+'Auguste, Nadege'!I25)>0,('Auguste, Nadege'!I26+'Auguste, Nadege'!I27)>0),AND(('Auguste, Nadege'!I30+'Auguste, Nadege'!I31)>0,('Auguste, Nadege'!I32+'Auguste, Nadege'!I33)>0,('Auguste, Nadege'!I34+'Auguste, Nadege'!I35)>0,('Auguste, Nadege'!I36+'Auguste, Nadege'!I37)>0,('Auguste, Nadege'!I38+'Auguste, Nadege'!I39)>0,('Auguste, Nadege'!I40+'Auguste, Nadege'!I41)>0,('Auguste, Nadege'!I42+'Auguste, Nadege'!I43)>0)),"Yes","") | I9: =IF('Auguste, Nadege'!N49>40,"Yes","") | J9: =IF(OR(AND(SUM('Auguste, Nadege'!I14:I27)>0,SUM('Auguste, Nadege'!I14:I27)<40),AND(SUM('Auguste, Nadege'!I30:I43)>0,SUM('Auguste, Nadege'!I30:I43)<40)),"Yes","") | K9: =SUMPRODUCT(('Auguste, Nadege'!I14:I48>0)*('Auguste, Nadege'!I14:I48<8)) | L9: =IF('Auguste, Nadege'!Q50<5,"Yes","") | M9: =IF(AND('Auguste, Nadege'!I49>0,'Auguste, Nadege'!I49<80),"Yes","") | N9: =IF(OR(F9>0,G9="Yes",H9="Yes",I9="Yes"),"⚠️ OVERWORK",IF(OR(J9="Yes",K9>0,L9="Yes",M9="Yes"),"🔻 UNDERWORK","✓ OK"))
A10: 6 | B10: Barlow, Duanne Raule Martin | C10: 4853 | D10: ='Barlow, Duanne Raule Martin'!I49 | E10: ='Barlow, Duanne Raule Martin'!Q50 | F10: =SUMPRODUCT((('Barlow, Duanne Raule Martin'!I14+'Barlow, Duanne Raule Martin'!I15)>12)*1)+SUMPRODUCT((('Barlow, Duanne Raule Martin'!I16+'Barlow, Duanne Raule Martin'!I17)>12)*1)+SUMPRODUCT((('Barlow, Duanne Raule Martin'!I18+'Barlow, Duanne Raule Martin'!I19)>12)*1)+SUMPRODUCT((('Barlow, Duanne Raule Martin'!I20+'Barlow, Duanne Raule Martin'!I21)>12)*1)+SUMPRODUCT((('Barlow, Duanne Raule Martin'!I22+'Barlow, Duanne Raule Martin'!I23)>12)*1)+SUMPRODUCT((('Barlow, Duanne Raule Martin'!I24+'Barlow, Duanne Raule Martin'!I25)>12)*1)+SUMPRODUCT((('Barlow, Duanne Raule Martin'!I26+'Barlow, Duanne Raule Martin'!I27)>12)*1)+SUMPRODUCT((('Barlow, Duanne Raule Martin'!I30+'Barlow, Duanne Raule Martin'!I31)>12)*1)+SUMPRODUCT((('Barlow, Duanne Raule Martin'!I32+'Barlow, Duanne Raule Martin'!I33)>12)*1)+SUMPRODUCT((('Barlow, Duanne Raule Martin'!I34+'Barlow, Duanne Raule Martin'!I35)>12)*1)+SUMPRODUCT((('Barlow, Duanne Raule Martin'!I36+'Barlow, Duanne Raule Martin'!I37)>12)*1)+SUMPRODUCT((('Barlow, Duanne Raule Martin'!I38+'Barlow, Duanne Raule Martin'!I39)>12)*1)+SUMPRODUCT((('Barlow, Duanne Raule Martin'!I40+'Barlow, Duanne Raule Martin'!I41)>12)*1)+SUMPRODUCT((('Barlow, Duanne Raule Martin'!I42+'Barlow, Duanne Raule Martin'!I43)>12)*1)+SUMPRODUCT((('Barlow, Duanne Raule Martin'!I45+'Barlow, Duanne Raule Martin'!I46)>12)*1)+SUMPRODUCT((('Barlow, Duanne Raule Martin'!I47+'Barlow, Duanne Raule Martin'!I48)>12)*1) | G10: =IF(MAX(SUM('Barlow, Duanne Raule Martin'!I14:I27),SUM('Barlow, Duanne Raule Martin'!I30:I43))>60,"Yes","") | H10: =IF(OR(AND(('Barlow, Duanne Raule Martin'!I14+'Barlow, Duanne Raule Martin'!I15)>0,('Barlow, Duanne Raule Martin'!I16+'Barlow, Duanne Raule Martin'!I17)>0,('Barlow, Duanne Raule Martin'!I18+'Barlow, Duanne Raule Martin'!I19)>0,('Barlow, Duanne Raule Martin'!I20+'Barlow, Duanne Raule Martin'!I21)>0,('Barlow, Duanne Raule Martin'!I22+'Barlow, Duanne Raule Martin'!I23)>0,('Barlow, Duanne Raule Martin'!I24+'Barlow, Duanne Raule Martin'!I25)>0,('Barlow, Duanne Raule Martin'!I26+'Barlow, Duanne Raule Martin'!I27)>0),AND(('Barlow, Duanne Raule Martin'!I30+'Barlow, Duanne Raule Martin'!I31)>0,('Barlow, Duanne Raule Martin'!I32+'Barlow, Duanne Raule Martin'!I33)>0,('Barlow, Duanne Raule Martin'!I34+'Barlow, Duanne Raule Martin'!I35)>0,('Barlow, Duanne Raule Martin'!I36+'Barlow, Duanne Raule Martin'!I37)>0,('Barlow, Duanne Raule Martin'!I38+'Barlow, Duanne Raule Martin'!I39)>0,('Barlow, Duanne Raule Martin'!I40+'Barlow, Duanne Raule Martin'!I41)>0,('Barlow, Duanne Raule Martin'!I42+'Barlow, Duanne Raule Martin'!I43)>0)),"Yes","") | I10: =IF('Barlow, Duanne Raule Martin'!N49>40,"Yes","") | J10: =IF(OR(AND(SUM('Barlow, Duanne Raule Martin'!I14:I27)>0,SUM('Barlow, Duanne Raule Martin'!I14:I27)<40),AND(SUM('Barlow, Duanne Raule Martin'!I30:I43)>0,SUM('Barlow, Duanne Raule Martin'!I30:I43)<40)),"Yes","") | K10: =SUMPRODUCT(('Barlow, Duanne Raule Martin'!I14:I48>0)*('Barlow, Duanne Raule Martin'!I14:I48<8)) | L10: =IF('Barlow, Duanne Raule Martin'!Q50<5,"Yes","") | M10: =IF(AND('Barlow, Duanne Raule Martin'!I49>0,'Barlow, Duanne Raule Martin'!I49<80),"Yes","") | N10: =IF(OR(F10>0,G10="Yes",H10="Yes",I10="Yes"),"⚠️ OVERWORK",IF(OR(J10="Yes",K10>0,L10="Yes",M10="Yes"),"🔻 UNDERWORK","✓ OK"))
A11: 7 | B11: Best-Archer, Rozetta | C11: 5442 | D11: ='Best-Archer, Rozetta'!I49 | E11: ='Best-Archer, Rozetta'!Q50 | F11: =SUMPRODUCT((('Best-Archer, Rozetta'!I14+'Best-Archer, Rozetta'!I15)>12)*1)+SUMPRODUCT((('Best-Archer, Rozetta'!I16+'Best-Archer, Rozetta'!I17)>12)*1)+SUMPRODUCT((('Best-Archer, Rozetta'!I18+'Best-Archer, Rozetta'!I19)>12)*1)+SUMPRODUCT((('Best-Archer, Rozetta'!I20+'Best-Archer, Rozetta'!I21)>12)*1)+SUMPRODUCT((('Best-Archer, Rozetta'!I22+'Best-Archer, Rozetta'!I23)>12)*1)+SUMPRODUCT((('Best-Archer, Rozetta'!I24+'Best-Archer, Rozetta'!I25)>12)*1)+SUMPRODUCT((('Best-Archer, Rozetta'!I26+'Best-Archer, Rozetta'!I27)>12)*1)+SUMPRODUCT((('Best-Archer, Rozetta'!I30+'Best-Archer, Rozetta'!I31)>12)*1)+SUMPRODUCT((('Best-Archer, Rozetta'!I32+'Best-Archer, Rozetta'!I33)>12)*1)+SUMPRODUCT((('Best-Archer, Rozetta'!I34+'Best-Archer, Rozetta'!I35)>12)*1)+SUMPRODUCT((('Best-Archer, Rozetta'!I36+'Best-Archer, Rozetta'!I37)>12)*1)+SUMPRODUCT((('Best-Archer, Rozetta'!I38+'Best-Archer, Rozetta'!I39)>12)*1)+SUMPRODUCT((('Best-Archer, Rozetta'!I40+'Best-Archer, Rozetta'!I41)>12)*1)+SUMPRODUCT((('Best-Archer, Rozetta'!I42+'Best-Archer, Rozetta'!I43)>12)*1)+SUMPRODUCT((('Best-Archer, Rozetta'!I45+'Best-Archer, Rozetta'!I46)>12)*1)+SUMPRODUCT((('Best-Archer, Rozetta'!I47+'Best-Archer, Rozetta'!I48)>12)*1) | G11: =IF(MAX(SUM('Best-Archer, Rozetta'!I14:I27),SUM('Best-Archer, Rozetta'!I30:I43))>60,"Yes","") | H11: =IF(OR(AND(('Best-Archer, Rozetta'!I14+'Best-Archer, Rozetta'!I15)>0,('Best-Archer, Rozetta'!I16+'Best-Archer, Rozetta'!I17)>0,('Best-Archer, Rozetta'!I18+'Best-Archer, Rozetta'!I19)>0,('Best-Archer, Rozetta'!I20+'Best-Archer, Rozetta'!I21)>0,('Best-Archer, Rozetta'!I22+'Best-Archer, Rozetta'!I23)>0,('Best-Archer, Rozetta'!I24+'Best-Archer, Rozetta'!I25)>0,('Best-Archer, Rozetta'!I26+'Best-Archer, Rozetta'!I27)>0),AND(('Best-Archer, Rozetta'!I30+'Best-Archer, Rozetta'!I31)>0,('Best-Archer, Rozetta'!I32+'Best-Archer, Rozetta'!I33)>0,('Best-Archer, Rozetta'!I34+'Best-Archer, Rozetta'!I35)>0,('Best-Archer, Rozetta'!I36+'Best-Archer, Rozetta'!I37)>0,('Best-Archer, Rozetta'!I38+'Best-Archer, Rozetta'!I39)>0,('Best-Archer, Rozetta'!I40+'Best-Archer, Rozetta'!I41)>0,('Best-Archer, Rozetta'!I42+'Best-Archer, Rozetta'!I43)>0)),"Yes","") | I11: =IF('Best-Archer, Rozetta'!N49>40,"Yes","") | J11: =IF(OR(AND(SUM('Best-Archer, Rozetta'!I14:I27)>0,SUM('Best-Archer, Rozetta'!I14:I27)<40),AND(SUM('Best-Archer, Rozetta'!I30:I43)>0,SUM('Best-Archer, Rozetta'!I30:I43)<40)),"Yes","") | K11: =SUMPRODUCT(('Best-Archer, Rozetta'!I14:I48>0)*('Best-Archer, Rozetta'!I14:I48<8)) | L11: =IF('Best-Archer, Rozetta'!Q50<5,"Yes","") | M11: =IF(AND('Best-Archer, Rozetta'!I49>0,'Best-Archer, Rozetta'!I49<80),"Yes","") | N11: =IF(OR(F11>0,G11="Yes",H11="Yes",I11="Yes"),"⚠️ OVERWORK",IF(OR(J11="Yes",K11>0,L11="Yes",M11="Yes"),"🔻 UNDERWORK","✓ OK"))
A12: 8 | B12: Blake, Corletta A | C12: 591 | D12: ='Blake, Corletta A'!I49 | E12: ='Blake, Corletta A'!Q50 | F12: =SUMPRODUCT((('Blake, Corletta A'!I14+'Blake, Corletta A'!I15)>12)*1)+SUMPRODUCT((('Blake, Corletta A'!I16+'Blake, Corletta A'!I17)>12)*1)+SUMPRODUCT((('Blake, Corletta A'!I18+'Blake, Corletta A'!I19)>12)*1)+SUMPRODUCT((('Blake, Corletta A'!I20+'Blake, Corletta A'!I21)>12)*1)+SUMPRODUCT((('Blake, Corletta A'!I22+'Blake, Corletta A'!I23)>12)*1)+SUMPRODUCT((('Blake, Corletta A'!I24+'Blake, Corletta A'!I25)>12)*1)+SUMPRODUCT((('Blake, Corletta A'!I26+'Blake, Corletta A'!I27)>12)*1)+SUMPRODUCT((('Blake, Corletta A'!I30+'Blake, Corletta A'!I31)>12)*1)+SUMPRODUCT((('Blake, Corletta A'!I32+'Blake, Corletta A'!I33)>12)*1)+SUMPRODUCT((('Blake, Corletta A'!I34+'Blake, Corletta A'!I35)>12)*1)+SUMPRODUCT((('Blake, Corletta A'!I36+'Blake, Corletta A'!I37)>12)*1)+SUMPRODUCT((('Blake, Corletta A'!I38+'Blake, Corletta A'!I39)>12)*1)+SUMPRODUCT((('Blake, Corletta A'!I40+'Blake, Corletta A'!I41)>12)*1)+SUMPRODUCT((('Blake, Corletta A'!I42+'Blake, Corletta A'!I43)>12)*1)+SUMPRODUCT((('Blake, Corletta A'!I45+'Blake, Corletta A'!I46)>12)*1)+SUMPRODUCT((('Blake, Corletta A'!I47+'Blake, Corletta A'!I48)>12)*1) | G12: =IF(MAX(SUM('Blake, Corletta A'!I14:I27),SUM('Blake, Corletta A'!I30:I43))>60,"Yes","") | H12: =IF(OR(AND(('Blake, Corletta A'!I14+'Blake, Corletta A'!I15)>0,('Blake, Corletta A'!I16+'Blake, Corletta A'!I17)>0,('Blake, Corletta A'!I18+'Blake, Corletta A'!I19)>0,('Blake, Corletta A'!I20+'Blake, Corletta A'!I21)>0,('Blake, Corletta A'!I22+'Blake, Corletta A'!I23)>0,('Blake, Corletta A'!I24+'Blake, Corletta A'!I25)>0,('Blake, Corletta A'!I26+'Blake, Corletta A'!I27)>0),AND(('Blake, Corletta A'!I30+'Blake, Corletta A'!I31)>0,('Blake, Corletta A'!I32+'Blake, Corletta A'!I33)>0,('Blake, Corletta A'!I34+'Blake, Corletta A'!I35)>0,('Blake, Corletta A'!I36+'Blake, Corletta A'!I37)>0,('Blake, Corletta A'!I38+'Blake, Corletta A'!I39)>0,('Blake, Corletta A'!I40+'Blake, Corletta A'!I41)>0,('Blake, Corletta A'!I42+'Blake, Corletta A'!I43)>0)),"Yes","") | I12: =IF('Blake, Corletta A'!N49>40,"Yes","") | J12: =IF(OR(AND(SUM('Blake, Corletta A'!I14:I27)>0,SUM('Blake, Corletta A'!I14:I27)<40),AND(SUM('Blake, Corletta A'!I30:I43)>0,SUM('Blake, Corletta A'!I30:I43)<40)),"Yes","") | K12: =SUMPRODUCT(('Blake, Corletta A'!I14:I48>0)*('Blake, Corletta A'!I14:I48<8)) | L12: =IF('Blake, Corletta A'!Q50<5,"Yes","") | M12: =IF(AND('Blake, Corletta A'!I49>0,'Blake, Corletta A'!I49<80),"Yes","") | N12: =IF(OR(F12>0,G12="Yes",H12="Yes",I12="Yes"),"⚠️ OVERWORK",IF(OR(J12="Yes",K12>0,L12="Yes",M12="Yes"),"🔻 UNDERWORK","✓ OK"))
A13: 9 | B13: Blucher, Winston Deon | C13: 5428 | D13: ='Blucher, Winston Deon'!I49 | E13: ='Blucher, Winston Deon'!Q50 | F13: =SUMPRODUCT((('Blucher, Winston Deon'!I14+'Blucher, Winston Deon'!I15)>12)*1)+SUMPRODUCT((('Blucher, Winston Deon'!I16+'Blucher, Winston Deon'!I17)>12)*1)+SUMPRODUCT((('Blucher, Winston Deon'!I18+'Blucher, Winston Deon'!I19)>12)*1)+SUMPRODUCT((('Blucher, Winston Deon'!I20+'Blucher, Winston Deon'!I21)>12)*1)+SUMPRODUCT((('Blucher, Winston Deon'!I22+'Blucher, Winston Deon'!I23)>12)*1)+SUMPRODUCT((('Blucher, Winston Deon'!I24+'Blucher, Winston Deon'!I25)>12)*1)+SUMPRODUCT((('Blucher, Winston Deon'!I26+'Blucher, Winston Deon'!I27)>12)*1)+SUMPRODUCT((('Blucher, Winston Deon'!I30+'Blucher, Winston Deon'!I31)>12)*1)+SUMPRODUCT((('Blucher, Winston Deon'!I32+'Blucher, Winston Deon'!I33)>12)*1)+SUMPRODUCT((('Blucher, Winston Deon'!I34+'Blucher, Winston Deon'!I35)>12)*1)+SUMPRODUCT((('Blucher, Winston Deon'!I36+'Blucher, Winston Deon'!I37)>12)*1)+SUMPRODUCT((('Blucher, Winston Deon'!I38+'Blucher, Winston Deon'!I39)>12)*1)+SUMPRODUCT((('Blucher, Winston Deon'!I40+'Blucher, Winston Deon'!I41)>12)*1)+SUMPRODUCT((('Blucher, Winston Deon'!I42+'Blucher, Winston Deon'!I43)>12)*1)+SUMPRODUCT((('Blucher, Winston Deon'!I45+'Blucher, Winston Deon'!I46)>12)*1)+SUMPRODUCT((('Blucher, Winston Deon'!I47+'Blucher, Winston Deon'!I48)>12)*1) | G13: =IF(MAX(SUM('Blucher, Winston Deon'!I14:I27),SUM('Blucher, Winston Deon'!I30:I43))>60,"Yes","") | H13: =IF(OR(AND(('Blucher, Winston Deon'!I14+'Blucher, Winston Deon'!I15)>0,('Blucher, Winston Deon'!I16+'Blucher, Winston Deon'!I17)>0,('Blucher, Winston Deon'!I18+'Blucher, Winston Deon'!I19)>0,('Blucher, Winston Deon'!I20+'Blucher, Winston Deon'!I21)>0,('Blucher, Winston Deon'!I22+'Blucher, Winston Deon'!I23)>0,('Blucher, Winston Deon'!I24+'Blucher, Winston Deon'!I25)>0,('Blucher, Winston Deon'!I26+'Blucher, Winston Deon'!I27)>0),AND(('Blucher, Winston Deon'!I30+'Blucher, Winston Deon'!I31)>0,('Blucher, Winston Deon'!I32+'Blucher, Winston Deon'!I33)>0,('Blucher, Winston Deon'!I34+'Blucher, Winston Deon'!I35)>0,('Blucher, Winston Deon'!I36+'Blucher, Winston Deon'!I37)>0,('Blucher, Winston Deon'!I38+'Blucher, Winston Deon'!I39)>0,('Blucher, Winston Deon'!I40+'Blucher, Winston Deon'!I41)>0,('Blucher, Winston Deon'!I42+'Blucher, Winston Deon'!I43)>0)),"Yes","") | I13: =IF('Blucher, Winston Deon'!N49>40,"Yes","") | J13: =IF(OR(AND(SUM('Blucher, Winston Deon'!I14:I27)>0,SUM('Blucher, Winston Deon'!I14:I27)<40),AND(SUM('Blucher, Winston Deon'!I30:I43)>0,SUM('Blucher, Winston Deon'!I30:I43)<40)),"Yes","") | K13: =SUMPRODUCT(('Blucher, Winston Deon'!I14:I48>0)*('Blucher, Winston Deon'!I14:I48<8)) | L13: =IF('Blucher, Winston Deon'!Q50<5,"Yes","") | M13: =IF(AND('Blucher, Winston Deon'!I49>0,'Blucher, Winston Deon'!I49<80),"Yes","") | N13: =IF(OR(F13>0,G13="Yes",H13="Yes",I13="Yes"),"⚠️ OVERWORK",IF(OR(J13="Yes",K13>0,L13="Yes",M13="Yes"),"🔻 UNDERWORK","✓ OK"))
A14: 10 | B14: Braithwaite, Miglon Alexis | C14: 5229 | D14: ='Braithwaite, Miglon Alexis'!I49 | E14: ='Braithwaite, Miglon Alexis'!Q50 | F14: =SUMPRODUCT((('Braithwaite, Miglon Alexis'!I14+'Braithwaite, Miglon Alexis'!I15)>12)*1)+SUMPRODUCT((('Braithwaite, Miglon Alexis'!I16+'Braithwaite, Miglon Alexis'!I17)>12)*1)+SUMPRODUCT((('Braithwaite, Miglon Alexis'!I18+'Braithwaite, Miglon Alexis'!I19)>12)*1)+SUMPRODUCT((('Braithwaite, Miglon Alexis'!I20+'Braithwaite, Miglon Alexis'!I21)>12)*1)+SUMPRODUCT((('Braithwaite, Miglon Alexis'!I22+'Braithwaite, Miglon Alexis'!I23)>12)*1)+SUMPRODUCT((('Braithwaite, Miglon Alexis'!I24+'Braithwaite, Miglon Alexis'!I25)>12)*1)+SUMPRODUCT((('Braithwaite, Miglon Alexis'!I26+'Braithwaite, Miglon Alexis'!I27)>12)*1)+SUMPRODUCT((('Braithwaite, Miglon Alexis'!I30+'Braithwaite, Miglon Alexis'!I31)>12)*1)+SUMPRODUCT((('Braithwaite, Miglon Alexis'!I32+'Braithwaite, Miglon Alexis'!I33)>12)*1)+SUMPRODUCT((('Braithwaite, Miglon Alexis'!I34+'Braithwaite, Miglon Alexis'!I35)>12)*1)+SUMPRODUCT((('Braithwaite, Miglon Alexis'!I36+'Braithwaite, Miglon Alexis'!I37)>12)*1)+SUMPRODUCT((('Braithwaite, Miglon Alexis'!I38+'Braithwaite, Miglon Alexis'!I39)>12)*1)+SUMPRODUCT((('Braithwaite, Miglon Alexis'!I40+'Braithwaite, Miglon Alexis'!I41)>12)*1)+SUMPRODUCT((('Braithwaite, Miglon Alexis'!I42+'Braithwaite, Miglon Alexis'!I43)>12)*1)+SUMPRODUCT((('Braithwaite, Miglon Alexis'!I45+'Braithwaite, Miglon Alexis'!I46)>12)*1)+SUMPRODUCT((('Braithwaite, Miglon Alexis'!I47+'Braithwaite, Miglon Alexis'!I48)>12)*1) | G14: =IF(MAX(SUM('Braithwaite, Miglon Alexis'!I14:I27),SUM('Braithwaite, Miglon Alexis'!I30:I43))>60,"Yes","") | H14: =IF(OR(AND(('Braithwaite, Miglon Alexis'!I14+'Braithwaite, Miglon Alexis'!I15)>0,('Braithwaite, Miglon Alexis'!I16+'Braithwaite, Miglon Alexis'!I17)>0,('Braithwaite, Miglon Alexis'!I18+'Braithwaite, Miglon Alexis'!I19)>0,('Braithwaite, Miglon Alexis'!I20+'Braithwaite, Miglon Alexis'!I21)>0,('Braithwaite, Miglon Alexis'!I22+'Braithwaite, Miglon Alexis'!I23)>0,('Braithwaite, Miglon Alexis'!I24+'Braithwaite, Miglon Alexis'!I25)>0,('Braithwaite, Miglon Alexis'!I26+'Braithwaite, Miglon Alexis'!I27)>0),AND(('Braithwaite, Miglon Alexis'!I30+'Braithwaite, Miglon Alexis'!I31)>0,('Braithwaite, Miglon Alexis'!I32+'Braithwaite, Miglon Alexis'!I33)>0,('Braithwaite, Miglon Alexis'!I34+'Braithwaite, Miglon Alexis'!I35)>0,('Braithwaite, Miglon Alexis'!I36+'Braithwaite, Miglon Alexis'!I37)>0,('Braithwaite, Miglon Alexis'!I38+'Braithwaite, Miglon Alexis'!I39)>0,('Braithwaite, Miglon Alexis'!I40+'Braithwaite, Miglon Alexis'!I41)>0,('Braithwaite, Miglon Alexis'!I42+'Braithwaite, Miglon Alexis'!I43)>0)),"Yes","") | I14: =IF('Braithwaite, Miglon Alexis'!N49>40,"Yes","") | J14: =IF(OR(AND(SUM('Braithwaite, Miglon Alexis'!I14:I27)>0,SUM('Braithwaite, Miglon Alexis'!I14:I27)<40),AND(SUM('Braithwaite, Miglon Alexis'!I30:I43)>0,SUM('Braithwaite, Miglon Alexis'!I30:I43)<40)),"Yes","") | K14: =SUMPRODUCT(('Braithwaite, Miglon Alexis'!I14:I48>0)*('Braithwaite, Miglon Alexis'!I14:I48<8)) | L14: =IF('Braithwaite, Miglon Alexis'!Q50<5,"Yes","") | M14: =IF(AND('Braithwaite, Miglon Alexis'!I49>0,'Braithwaite, Miglon Alexis'!I49<80),"Yes","") | N14: =IF(OR(F14>0,G14="Yes",H14="Yes",I14="Yes"),"⚠️ OVERWORK",IF(OR(J14="Yes",K14>0,L14="Yes",M14="Yes"),"🔻 UNDERWORK","✓ OK"))
A15: 11 | B15: Breedy, Orin Wayne | C15: 3645 | D15: ='Breedy, Orin Wayne'!I49 | E15: ='Breedy, Orin Wayne'!Q50 | F15: =SUMPRODUCT((('Breedy, Orin Wayne'!I14+'Breedy, Orin Wayne'!I15)>12)*1)+SUMPRODUCT((('Breedy, Orin Wayne'!I16+'Breedy, Orin Wayne'!I17)>12)*1)+SUMPRODUCT((('Breedy, Orin Wayne'!I18+'Breedy, Orin Wayne'!I19)>12)*1)+SUMPRODUCT((('Breedy, Orin Wayne'!I20+'Breedy, Orin Wayne'!I21)>12)*1)+SUMPRODUCT((('Breedy, Orin Wayne'!I22+'Breedy, Orin Wayne'!I23)>12)*1)+SUMPRODUCT((('Breedy, Orin Wayne'!I24+'Breedy, Orin Wayne'!I25)>12)*1)+SUMPRODUCT((('Breedy, Orin Wayne'!I26+'Breedy, Orin Wayne'!I27)>12)*1)+SUMPRODUCT((('Breedy, Orin Wayne'!I30+'Breedy, Orin Wayne'!I31)>12)*1)+SUMPRODUCT((('Breedy, Orin Wayne'!I32+'Breedy, Orin Wayne'!I33)>12)*1)+SUMPRODUCT((('Breedy, Orin Wayne'!I34+'Breedy, Orin Wayne'!I35)>12)*1)+SUMPRODUCT((('Breedy, Orin Wayne'!I36+'Breedy, Orin Wayne'!I37)>12)*1)+SUMPRODUCT((('Breedy, Orin Wayne'!I38+'Breedy, Orin Wayne'!I39)>12)*1)+SUMPRODUCT((('Breedy, Orin Wayne'!I40+'Breedy, Orin Wayne'!I41)>12)*1)+SUMPRODUCT((('Breedy, Orin Wayne'!I42+'Breedy, Orin Wayne'!I43)>12)*1)+SUMPRODUCT((('Breedy, Orin Wayne'!I45+'Breedy, Orin Wayne'!I46)>12)*1)+SUMPRODUCT((('Breedy, Orin Wayne'!I47+'Breedy, Orin Wayne'!I48)>12)*1) | G15: =IF(MAX(SUM('Breedy, Orin Wayne'!I14:I27),SUM('Breedy, Orin Wayne'!I30:I43))>60,"Yes","") | H15: =IF(OR(AND(('Breedy, Orin Wayne'!I14+'Breedy, Orin Wayne'!I15)>0,('Breedy, Orin Wayne'!I16+'Breedy, Orin Wayne'!I17)>0,('Breedy, Orin Wayne'!I18+'Breedy, Orin Wayne'!I19)>0,('Breedy, Orin Wayne'!I20+'Breedy, Orin Wayne'!I21)>0,('Breedy, Orin Wayne'!I22+'Breedy, Orin Wayne'!I23)>0,('Breedy, Orin Wayne'!I24+'Breedy, Orin Wayne'!I25)>0,('Breedy, Orin Wayne'!I26+'Breedy, Orin Wayne'!I27)>0),AND(('Breedy, Orin Wayne'!I30+'Breedy, Orin Wayne'!I31)>0,('Breedy, Orin Wayne'!I32+'Breedy, Orin Wayne'!I33)>0,('Breedy, Orin Wayne'!I34+'Breedy, Orin Wayne'!I35)>0,('Breedy, Orin Wayne'!I36+'Breedy, Orin Wayne'!I37)>0,('Breedy, Orin Wayne'!I38+'Breedy, Orin Wayne'!I39)>0,('Breedy, Orin Wayne'!I40+'Breedy, Orin Wayne'!I41)>0,('Breedy, Orin Wayne'!I42+'Breedy, Orin Wayne'!I43)>0)),"Yes","") | I15: =IF('Breedy, Orin Wayne'!N49>40,"Yes","") | J15: =IF(OR(AND(SUM('Breedy, Orin Wayne'!I14:I27)>0,SUM('Breedy, Orin Wayne'!I14:I27)<40),AND(SUM('Breedy, Orin Wayne'!I30:I43)>0,SUM('Breedy, Orin Wayne'!I30:I43)<40)),"Yes","") | K15: =SUMPRODUCT(('Breedy, Orin Wayne'!I14:I48>0)*('Breedy, Orin Wayne'!I14:I48<8)) | L15: =IF('Breedy, Orin Wayne'!Q50<5,"Yes","") | M15: =IF(AND('Breedy, Orin Wayne'!I49>0,'Breedy, Orin Wayne'!I49<80),"Yes","") | N15: =IF(OR(F15>0,G15="Yes",H15="Yes",I15="Yes"),"⚠️ OVERWORK",IF(OR(J15="Yes",K15>0,L15="Yes",M15="Yes"),"🔻 UNDERWORK","✓ OK"))
A16: 12 | B16: Breedy, Phoolkumarie | C16: 3752 | D16: ='Breedy, Phoolkumarie'!I49 | E16: ='Breedy, Phoolkumarie'!Q50 | F16: =SUMPRODUCT((('Breedy, Phoolkumarie'!I14+'Breedy, Phoolkumarie'!I15)>12)*1)+SUMPRODUCT((('Breedy, Phoolkumarie'!I16+'Breedy, Phoolkumarie'!I17)>12)*1)+SUMPRODUCT((('Breedy, Phoolkumarie'!I18+'Breedy, Phoolkumarie'!I19)>12)*1)+SUMPRODUCT((('Breedy, Phoolkumarie'!I20+'Breedy, Phoolkumarie'!I21)>12)*1)+SUMPRODUCT((('Breedy, Phoolkumarie'!I22+'Breedy, Phoolkumarie'!I23)>12)*1)+SUMPRODUCT((('Breedy, Phoolkumarie'!I24+'Breedy, Phoolkumarie'!I25)>12)*1)+SUMPRODUCT((('Breedy, Phoolkumarie'!I26+'Breedy, Phoolkumarie'!I27)>12)*1)+SUMPRODUCT((('Breedy, Phoolkumarie'!I30+'Breedy, Phoolkumarie'!I31)>12)*1)+SUMPRODUCT((('Breedy, Phoolkumarie'!I32+'Breedy, Phoolkumarie'!I33)>12)*1)+SUMPRODUCT((('Breedy, Phoolkumarie'!I34+'Breedy, Phoolkumarie'!I35)>12)*1)+SUMPRODUCT((('Breedy, Phoolkumarie'!I36+'Breedy, Phoolkumarie'!I37)>12)*1)+SUMPRODUCT((('Breedy, Phoolkumarie'!I38+'Breedy, Phoolkumarie'!I39)>12)*1)+SUMPRODUCT((('Breedy, Phoolkumarie'!I40+'Breedy, Phoolkumarie'!I41)>12)*1)+SUMPRODUCT((('Breedy, Phoolkumarie'!I42+'Breedy, Phoolkumarie'!I43)>12)*1)+SUMPRODUCT((('Breedy, Phoolkumarie'!I45+'Breedy, Phoolkumarie'!I46)>12)*1)+SUMPRODUCT((('Breedy, Phoolkumarie'!I47+'Breedy, Phoolkumarie'!I48)>12)*1) | G16: =IF(MAX(SUM('Breedy, Phoolkumarie'!I14:I27),SUM('Breedy, Phoolkumarie'!I30:I43))>60,"Yes","") | H16: =IF(OR(AND(('Breedy, Phoolkumarie'!I14+'Breedy, Phoolkumarie'!I15)>0,('Breedy, Phoolkumarie'!I16+'Breedy, Phoolkumarie'!I17)>0,('Breedy, Phoolkumarie'!I18+'Breedy, Phoolkumarie'!I19)>0,('Breedy, Phoolkumarie'!I20+'Breedy, Phoolkumarie'!I21)>0,('Breedy, Phoolkumarie'!I22+'Breedy, Phoolkumarie'!I23)>0,('Breedy, Phoolkumarie'!I24+'Breedy, Phoolkumarie'!I25)>0,('Breedy, Phoolkumarie'!I26+'Breedy, Phoolkumarie'!I27)>0),AND(('Breedy, Phoolkumarie'!I30+'Breedy, Phoolkumarie'!I31)>0,('Breedy, Phoolkumarie'!I32+'Breedy, Phoolkumarie'!I33)>0,('Breedy, Phoolkumarie'!I34+'Breedy, Phoolkumarie'!I35)>0,('Breedy, Phoolkumarie'!I36+'Breedy, Phoolkumarie'!I37)>0,('Breedy, Phoolkumarie'!I38+'Breedy, Phoolkumarie'!I39)>0,('Breedy, Phoolkumarie'!I40+'Breedy, Phoolkumarie'!I41)>0,('Breedy, Phoolkumarie'!I42+'Breedy, Phoolkumarie'!I43)>0)),"Yes","") | I16: =IF('Breedy, Phoolkumarie'!N49>40,"Yes","") | J16: =IF(OR(AND(SUM('Breedy, Phoolkumarie'!I14:I27)>0,SUM('Breedy, Phoolkumarie'!I14:I27)<40),AND(SUM('Breedy, Phoolkumarie'!I30:I43)>0,SUM('Breedy, Phoolkumarie'!I30:I43)<40)),"Yes","") | K16: =SUMPRODUCT(('Breedy, Phoolkumarie'!I14:I48>0)*('Breedy, Phoolkumarie'!I14:I48<8)) | L16: =IF('Breedy, Phoolkumarie'!Q50<5,"Yes","") | M16: =IF(AND('Breedy, Phoolkumarie'!I49>0,'Breedy, Phoolkumarie'!I49<80),"Yes","") | N16: =IF(OR(F16>0,G16="Yes",H16="Yes",I16="Yes"),"⚠️ OVERWORK",IF(OR(J16="Yes",K16>0,L16="Yes",M16="Yes"),"🔻 UNDERWORK","✓ OK"))
A17: 13 | B17: Brewster, Hilroy | C17: 1511 | D17: ='Brewster, Hilroy'!I49 | E17: ='Brewster, Hilroy'!Q50 | F17: =SUMPRODUCT((('Brewster, Hilroy'!I14+'Brewster, Hilroy'!I15)>12)*1)+SUMPRODUCT((('Brewster, Hilroy'!I16+'Brewster, Hilroy'!I17)>12)*1)+SUMPRODUCT((('Brewster, Hilroy'!I18+'Brewster, Hilroy'!I19)>12)*1)+SUMPRODUCT((('Brewster, Hilroy'!I20+'Brewster, Hilroy'!I21)>12)*1)+SUMPRODUCT((('Brewster, Hilroy'!I22+'Brewster, Hilroy'!I23)>12)*1)+SUMPRODUCT((('Brewster, Hilroy'!I24+'Brewster, Hilroy'!I25)>12)*1)+SUMPRODUCT((('Brewster, Hilroy'!I26+'Brewster, Hilroy'!I27)>12)*1)+SUMPRODUCT((('Brewster, Hilroy'!I30+'Brewster, Hilroy'!I31)>12)*1)+SUMPRODUCT((('Brewster, Hilroy'!I32+'Brewster, Hilroy'!I33)>12)*1)+SUMPRODUCT((('Brewster, Hilroy'!I34+'Brewster, Hilroy'!I35)>12)*1)+SUMPRODUCT((('Brewster, Hilroy'!I36+'Brewster, Hilroy'!I37)>12)*1)+SUMPRODUCT((('Brewster, Hilroy'!I38+'Brewster, Hilroy'!I39)>12)*1)+SUMPRODUCT((('Brewster, Hilroy'!I40+'Brewster, Hilroy'!I41)>12)*1)+SUMPRODUCT((('Brewster, Hilroy'!I42+'Brewster, Hilroy'!I43)>12)*1)+SUMPRODUCT((('Brewster, Hilroy'!I45+'Brewster, Hilroy'!I46)>12)*1)+SUMPRODUCT((('Brewster, Hilroy'!I47+'Brewster, Hilroy'!I48)>12)*1) | G17: =IF(MAX(SUM('Brewster, Hilroy'!I14:I27),SUM('Brewster, Hilroy'!I30:I43))>60,"Yes","") | H17: =IF(OR(AND(('Brewster, Hilroy'!I14+'Brewster, Hilroy'!I15)>0,('Brewster, Hilroy'!I16+'Brewster, Hilroy'!I17)>0,('Brewster, Hilroy'!I18+'Brewster, Hilroy'!I19)>0,('Brewster, Hilroy'!I20+'Brewster, Hilroy'!I21)>0,('Brewster, Hilroy'!I22+'Brewster, Hilroy'!I23)>0,('Brewster, Hilroy'!I24+'Brewster, Hilroy'!I25)>0,('Brewster, Hilroy'!I26+'Brewster, Hilroy'!I27)>0),AND(('Brewster, Hilroy'!I30+'Brewster, Hilroy'!I31)>0,('Brewster, Hilroy'!I32+'Brewster, Hilroy'!I33)>0,('Brewster, Hilroy'!I34+'Brewster, Hilroy'!I35)>0,('Brewster, Hilroy'!I36+'Brewster, Hilroy'!I37)>0,('Brewster, Hilroy'!I38+'Brewster, Hilroy'!I39)>0,('Brewster, Hilroy'!I40+'Brewster, Hilroy'!I41)>0,('Brewster, Hilroy'!I42+'Brewster, Hilroy'!I43)>0)),"Yes","") | I17: =IF('Brewster, Hilroy'!N49>40,"Yes","") | J17: =IF(OR(AND(SUM('Brewster, Hilroy'!I14:I27)>0,SUM('Brewster, Hilroy'!I14:I27)<40),AND(SUM('Brewster, Hilroy'!I30:I43)>0,SUM('Brewster, Hilroy'!I30:I43)<40)),"Yes","") | K17: =SUMPRODUCT(('Brewster, Hilroy'!I14:I48>0)*('Brewster, Hilroy'!I14:I48<8)) | L17: =IF('Brewster, Hilroy'!Q50<5,"Yes","") | M17: =IF(AND('Brewster, Hilroy'!I49>0,'Brewster, Hilroy'!I49<80),"Yes","") | N17: =IF(OR(F17>0,G17="Yes",H17="Yes",I17="Yes"),"⚠️ OVERWORK",IF(OR(J17="Yes",K17>0,L17="Yes",M17="Yes"),"🔻 UNDERWORK","✓ OK"))
A18: 14 | B18: Browne, Marvina Feona | C18: 3909 | D18: ='Browne, Marvina Feona'!I49 | E18: ='Browne, Marvina Feona'!Q50 | F18: =SUMPRODUCT((('Browne, Marvina Feona'!I14+'Browne, Marvina Feona'!I15)>12)*1)+SUMPRODUCT((('Browne, Marvina Feona'!I16+'Browne, Marvina Feona'!I17)>12)*1)+SUMPRODUCT((('Browne, Marvina Feona'!I18+'Browne, Marvina Feona'!I19)>12)*1)+SUMPRODUCT((('Browne, Marvina Feona'!I20+'Browne, Marvina Feona'!I21)>12)*1)+SUMPRODUCT((('Browne, Marvina Feona'!I22+'Browne, Marvina Feona'!I23)>12)*1)+SUMPRODUCT((('Browne, Marvina Feona'!I24+'Browne, Marvina Feona'!I25)>12)*1)+SUMPRODUCT((('Browne, Marvina Feona'!I26+'Browne, Marvina Feona'!I27)>12)*1)+SUMPRODUCT((('Browne, Marvina Feona'!I30+'Browne, Marvina Feona'!I31)>12)*1)+SUMPRODUCT((('Browne, Marvina Feona'!I32+'Browne, Marvina Feona'!I33)>12)*1)+SUMPRODUCT((('Browne, Marvina Feona'!I34+'Browne, Marvina Feona'!I35)>12)*1)+SUMPRODUCT((('Browne, Marvina Feona'!I36+'Browne, Marvina Feona'!I37)>12)*1)+SUMPRODUCT((('Browne, Marvina Feona'!I38+'Browne, Marvina Feona'!I39)>12)*1)+SUMPRODUCT((('Browne, Marvina Feona'!I40+'Browne, Marvina Feona'!I41)>12)*1)+SUMPRODUCT((('Browne, Marvina Feona'!I42+'Browne, Marvina Feona'!I43)>12)*1)+SUMPRODUCT((('Browne, Marvina Feona'!I45+'Browne, Marvina Feona'!I46)>12)*1)+SUMPRODUCT((('Browne, Marvina Feona'!I47+'Browne, Marvina Feona'!I48)>12)*1) | G18: =IF(MAX(SUM('Browne, Marvina Feona'!I14:I27),SUM('Browne, Marvina Feona'!I30:I43))>60,"Yes","") | H18: =IF(OR(AND(('Browne, Marvina Feona'!I14+'Browne, Marvina Feona'!I15)>0,('Browne, Marvina Feona'!I16+'Browne, Marvina Feona'!I17)>0,('Browne, Marvina Feona'!I18+'Browne, Marvina Feona'!I19)>0,('Browne, Marvina Feona'!I20+'Browne, Marvina Feona'!I21)>0,('Browne, Marvina Feona'!I22+'Browne, Marvina Feona'!I23)>0,('Browne, Marvina Feona'!I24+'Browne, Marvina Feona'!I25)>0,('Browne, Marvina Feona'!I26+'Browne, Marvina Feona'!I27)>0),AND(('Browne, Marvina Feona'!I30+'Browne, Marvina Feona'!I31)>0,('Browne, Marvina Feona'!I32+'Browne, Marvina Feona'!I33)>0,('Browne, Marvina Feona'!I34+'Browne, Marvina Feona'!I35)>0,('Browne, Marvina Feona'!I36+'Browne, Marvina Feona'!I37)>0,('Browne, Marvina Feona'!I38+'Browne, Marvina Feona'!I39)>0,('Browne, Marvina Feona'!I40+'Browne, Marvina Feona'!I41)>0,('Browne, Marvina Feona'!I42+'Browne, Marvina Feona'!I43)>0)),"Yes","") | I18: =IF('Browne, Marvina Feona'!N49>40,"Yes","") | J18: =IF(OR(AND(SUM('Browne, Marvina Feona'!I14:I27)>0,SUM('Browne, Marvina Feona'!I14:I27)<40),AND(SUM('Browne, Marvina Feona'!I30:I43)>0,SUM('Browne, Marvina Feona'!I30:I43)<40)),"Yes","") | K18: =SUMPRODUCT(('Browne, Marvina Feona'!I14:I48>0)*('Browne, Marvina Feona'!I14:I48<8)) | L18: =IF('Browne, Marvina Feona'!Q50<5,"Yes","") | M18: =IF(AND('Browne, Marvina Feona'!I49>0,'Browne, Marvina Feona'!I49<80),"Yes","") | N18: =IF(OR(F18>0,G18="Yes",H18="Yes",I18="Yes"),"⚠️ OVERWORK",IF(OR(J18="Yes",K18>0,L18="Yes",M18="Yes"),"🔻 UNDERWORK","✓ OK"))
A19: 15 | B19: Bullen, Herman Fitzgerald | C19: 4131 | D19: ='Bullen, Herman Fitzgerald'!I49 | E19: ='Bullen, Herman Fitzgerald'!Q50 | F19: =SUMPRODUCT((('Bullen, Herman Fitzgerald'!I14+'Bullen, Herman Fitzgerald'!I15)>12)*1)+SUMPRODUCT((('Bullen, Herman Fitzgerald'!I16+'Bullen, Herman Fitzgerald'!I17)>12)*1)+SUMPRODUCT((('Bullen, Herman Fitzgerald'!I18+'Bullen, Herman Fitzgerald'!I19)>12)*1)+SUMPRODUCT((('Bullen, Herman Fitzgerald'!I20+'Bullen, Herman Fitzgerald'!I21)>12)*1)+SUMPRODUCT((('Bullen, Herman Fitzgerald'!I22+'Bullen, Herman Fitzgerald'!I23)>12)*1)+SUMPRODUCT((('Bullen, Herman Fitzgerald'!I24+'Bullen, Herman Fitzgerald'!I25)>12)*1)+SUMPRODUCT((('Bullen, Herman Fitzgerald'!I26+'Bullen, Herman Fitzgerald'!I27)>12)*1)+SUMPRODUCT((('Bullen, Herman Fitzgerald'!I30+'Bullen, Herman Fitzgerald'!I31)>12)*1)+SUMPRODUCT((('Bullen, Herman Fitzgerald'!I32+'Bullen, Herman Fitzgerald'!I33)>12)*1)+SUMPRODUCT((('Bullen, Herman Fitzgerald'!I34+'Bullen, Herman Fitzgerald'!I35)>12)*1)+SUMPRODUCT((('Bullen, Herman Fitzgerald'!I36+'Bullen, Herman Fitzgerald'!I37)>12)*1)+SUMPRODUCT((('Bullen, Herman Fitzgerald'!I38+'Bullen, Herman Fitzgerald'!I39)>12)*1)+SUMPRODUCT((('Bullen, Herman Fitzgerald'!I40+'Bullen, Herman Fitzgerald'!I41)>12)*1)+SUMPRODUCT((('Bullen, Herman Fitzgerald'!I42+'Bullen, Herman Fitzgerald'!I43)>12)*1)+SUMPRODUCT((('Bullen, Herman Fitzgerald'!I45+'Bullen, Herman Fitzgerald'!I46)>12)*1)+SUMPRODUCT((('Bullen, Herman Fitzgerald'!I47+'Bullen, Herman Fitzgerald'!I48)>12)*1) | G19: =IF(MAX(SUM('Bullen, Herman Fitzgerald'!I14:I27),SUM('Bullen, Herman Fitzgerald'!I30:I43))>60,"Yes","") | H19: =IF(OR(AND(('Bullen, Herman Fitzgerald'!I14+'Bullen, Herman Fitzgerald'!I15)>0,('Bullen, Herman Fitzgerald'!I16+'Bullen, Herman Fitzgerald'!I17)>0,('Bullen, Herman Fitzgerald'!I18+'Bullen, Herman Fitzgerald'!I19)>0,('Bullen, Herman Fitzgerald'!I20+'Bullen, Herman Fitzgerald'!I21)>0,('Bullen, Herman Fitzgerald'!I22+'Bullen, Herman Fitzgerald'!I23)>0,('Bullen, Herman Fitzgerald'!I24+'Bullen, Herman Fitzgerald'!I25)>0,('Bullen, Herman Fitzgerald'!I26+'Bullen, Herman Fitzgerald'!I27)>0),AND(('Bullen, Herman Fitzgerald'!I30+'Bullen, Herman Fitzgerald'!I31)>0,('Bullen, Herman Fitzgerald'!I32+'Bullen, Herman Fitzgerald'!I33)>0,('Bullen, Herman Fitzgerald'!I34+'Bullen, Herman Fitzgerald'!I35)>0,('Bullen, Herman Fitzgerald'!I36+'Bullen, Herman Fitzgerald'!I37)>0,('Bullen, Herman Fitzgerald'!I38+'Bullen, Herman Fitzgerald'!I39)>0,('Bullen, Herman Fitzgerald'!I40+'Bullen, Herman Fitzgerald'!I41)>0,('Bullen, Herman Fitzgerald'!I42+'Bullen, Herman Fitzgerald'!I43)>0)),"Yes","") | I19: =IF('Bullen, Herman Fitzgerald'!N49>40,"Yes","") | J19: =IF(OR(AND(SUM('Bullen, Herman Fitzgerald'!I14:I27)>0,SUM('Bullen, Herman Fitzgerald'!I14:I27)<40),AND(SUM('Bullen, Herman Fitzgerald'!I30:I43)>0,SUM('Bullen, Herman Fitzgerald'!I30:I43)<40)),"Yes","") | K19: =SUMPRODUCT(('Bullen, Herman Fitzgerald'!I14:I48>0)*('Bullen, Herman Fitzgerald'!I14:I48<8)) | L19: =IF('Bullen, Herman Fitzgerald'!Q50<5,"Yes","") | M19: =IF(AND('Bullen, Herman Fitzgerald'!I49>0,'Bullen, Herman Fitzgerald'!I49<80),"Yes","") | N19: =IF(OR(F19>0,G19="Yes",H19="Yes",I19="Yes"),"⚠️ OVERWORK",IF(OR(J19="Yes",K19>0,L19="Yes",M19="Yes"),"🔻 UNDERWORK","✓ OK"))
A20: 16 | B20: Bumbury, Joan | C20: 3348 | D20: ='Bumbury, Joan'!I49 | E20: ='Bumbury, Joan'!Q50 | F20: =SUMPRODUCT((('Bumbury, Joan'!I14+'Bumbury, Joan'!I15)>12)*1)+SUMPRODUCT((('Bumbury, Joan'!I16+'Bumbury, Joan'!I17)>12)*1)+SUMPRODUCT((('Bumbury, Joan'!I18+'Bumbury, Joan'!I19)>12)*1)+SUMPRODUCT((('Bumbury, Joan'!I20+'Bumbury, Joan'!I21)>12)*1)+SUMPRODUCT((('Bumbury, Joan'!I22+'Bumbury, Joan'!I23)>12)*1)+SUMPRODUCT((('Bumbury, Joan'!I24+'Bumbury, Joan'!I25)>12)*1)+SUMPRODUCT((('Bumbury, Joan'!I26+'Bumbury, Joan'!I27)>12)*1)+SUMPRODUCT((('Bumbury, Joan'!I30+'Bumbury, Joan'!I31)>12)*1)+SUMPRODUCT((('Bumbury, Joan'!I32+'Bumbury, Joan'!I33)>12)*1)+SUMPRODUCT((('Bumbury, Joan'!I34+'Bumbury, Joan'!I35)>12)*1)+SUMPRODUCT((('Bumbury, Joan'!I36+'Bumbury, Joan'!I37)>12)*1)+SUMPRODUCT((('Bumbury, Joan'!I38+'Bumbury, Joan'!I39)>12)*1)+SUMPRODUCT((('Bumbury, Joan'!I40+'Bumbury, Joan'!I41)>12)*1)+SUMPRODUCT((('Bumbury, Joan'!I42+'Bumbury, Joan'!I43)>12)*1)+SUMPRODUCT((('Bumbury, Joan'!I45+'Bumbury, Joan'!I46)>12)*1)+SUMPRODUCT((('Bumbury, Joan'!I47+'Bumbury, Joan'!I48)>12)*1) | G20: =IF(MAX(SUM('Bumbury, Joan'!I14:I27),SUM('Bumbury, Joan'!I30:I43))>60,"Yes","") | H20: =IF(OR(AND(('Bumbury, Joan'!I14+'Bumbury, Joan'!I15)>0,('Bumbury, Joan'!I16+'Bumbury, Joan'!I17)>0,('Bumbury, Joan'!I18+'Bumbury, Joan'!I19)>0,('Bumbury, Joan'!I20+'Bumbury, Joan'!I21)>0,('Bumbury, Joan'!I22+'Bumbury, Joan'!I23)>0,('Bumbury, Joan'!I24+'Bumbury, Joan'!I25)>0,('Bumbury, Joan'!I26+'Bumbury, Joan'!I27)>0),AND(('Bumbury, Joan'!I30+'Bumbury, Joan'!I31)>0,('Bumbury, Joan'!I32+'Bumbury, Joan'!I33)>0,('Bumbury, Joan'!I34+'Bumbury, Joan'!I35)>0,('Bumbury, Joan'!I36+'Bumbury, Joan'!I37)>0,('Bumbury, Joan'!I38+'Bumbury, Joan'!I39)>0,('Bumbury, Joan'!I40+'Bumbury, Joan'!I41)>0,('Bumbury, Joan'!I42+'Bumbury, Joan'!I43)>0)),"Yes","") | I20: =IF('Bumbury, Joan'!N49>40,"Yes","") | J20: =IF(OR(AND(SUM('Bumbury, Joan'!I14:I27)>0,SUM('Bumbury, Joan'!I14:I27)<40),AND(SUM('Bumbury, Joan'!I30:I43)>0,SUM('Bumbury, Joan'!I30:I43)<40)),"Yes","") | K20: =SUMPRODUCT(('Bumbury, Joan'!I14:I48>0)*('Bumbury, Joan'!I14:I48<8)) | L20: =IF('Bumbury, Joan'!Q50<5,"Yes","") | M20: =IF(AND('Bumbury, Joan'!I49>0,'Bumbury, Joan'!I49<80),"Yes","") | N20: =IF(OR(F20>0,G20="Yes",H20="Yes",I20="Yes"),"⚠️ OVERWORK",IF(OR(J20="Yes",K20>0,L20="Yes",M20="Yes"),"🔻 UNDERWORK","✓ OK"))
A21: 17 | B21: Chester, Violet | C21: 4175 | D21: ='Chester, Violet'!I49 | E21: ='Chester, Violet'!Q50 | F21: =SUMPRODUCT((('Chester, Violet'!I14+'Chester, Violet'!I15)>12)*1)+SUMPRODUCT((('Chester, Violet'!I16+'Chester, Violet'!I17)>12)*1)+SUMPRODUCT((('Chester, Violet'!I18+'Chester, Violet'!I19)>12)*1)+SUMPRODUCT((('Chester, Violet'!I20+'Chester, Violet'!I21)>12)*1)+SUMPRODUCT((('Chester, Violet'!I22+'Chester, Violet'!I23)>12)*1)+SUMPRODUCT((('Chester, Violet'!I24+'Chester, Violet'!I25)>12)*1)+SUMPRODUCT((('Chester, Violet'!I26+'Chester, Violet'!I27)>12)*1)+SUMPRODUCT((('Chester, Violet'!I30+'Chester, Violet'!I31)>12)*1)+SUMPRODUCT((('Chester, Violet'!I32+'Chester, Violet'!I33)>12)*1)+SUMPRODUCT((('Chester, Violet'!I34+'Chester, Violet'!I35)>12)*1)+SUMPRODUCT((('Chester, Violet'!I36+'Chester, Violet'!I37)>12)*1)+SUMPRODUCT((('Chester, Violet'!I38+'Chester, Violet'!I39)>12)*1)+SUMPRODUCT((('Chester, Violet'!I40+'Chester, Violet'!I41)>12)*1)+SUMPRODUCT((('Chester, Violet'!I42+'Chester, Violet'!I43)>12)*1)+SUMPRODUCT((('Chester, Violet'!I45+'Chester, Violet'!I46)>12)*1)+SUMPRODUCT((('Chester, Violet'!I47+'Chester, Violet'!I48)>12)*1) | G21: =IF(MAX(SUM('Chester, Violet'!I14:I27),SUM('Chester, Violet'!I30:I43))>60,"Yes","") | H21: =IF(OR(AND(('Chester, Violet'!I14+'Chester, Violet'!I15)>0,('Chester, Violet'!I16+'Chester, Violet'!I17)>0,('Chester, Violet'!I18+'Chester, Violet'!I19)>0,('Chester, Violet'!I20+'Chester, Violet'!I21)>0,('Chester, Violet'!I22+'Chester, Violet'!I23)>0,('Chester, Violet'!I24+'Chester, Violet'!I25)>0,('Chester, Violet'!I26+'Chester, Violet'!I27)>0),AND(('Chester, Violet'!I30+'Chester, Violet'!I31)>0,('Chester, Violet'!I32+'Chester, Violet'!I33)>0,('Chester, Violet'!I34+'Chester, Violet'!I35)>0,('Chester, Violet'!I36+'Chester, Violet'!I37)>0,('Chester, Violet'!I38+'Chester, Violet'!I39)>0,('Chester, Violet'!I40+'Chester, Violet'!I41)>0,('Chester, Violet'!I42+'Chester, Violet'!I43)>0)),"Yes","") | I21: =IF('Chester, Violet'!N49>40,"Yes","") | J21: =IF(OR(AND(SUM('Chester, Violet'!I14:I27)>0,SUM('Chester, Violet'!I14:I27)<40),AND(SUM('Chester, Violet'!I30:I43)>0,SUM('Chester, Violet'!I30:I43)<40)),"Yes","") | K21: =SUMPRODUCT(('Chester, Violet'!I14:I48>0)*('Chester, Violet'!I14:I48<8)) | L21: =IF('Chester, Violet'!Q50<5,"Yes","") | M21: =IF(AND('Chester, Violet'!I49>0,'Chester, Violet'!I49<80),"Yes","") | N21: =IF(OR(F21>0,G21="Yes",H21="Yes",I21="Yes"),"⚠️ OVERWORK",IF(OR(J21="Yes",K21>0,L21="Yes",M21="Yes"),"🔻 UNDERWORK","✓ OK"))
A22: 18 | B22: Clarke, Penopolly | C22: 2380 | D22: ='Clarke, Penopolly'!I49 | E22: ='Clarke, Penopolly'!Q50 | F22: =SUMPRODUCT((('Clarke, Penopolly'!I14+'Clarke, Penopolly'!I15)>12)*1)+SUMPRODUCT((('Clarke, Penopolly'!I16+'Clarke, Penopolly'!I17)>12)*1)+SUMPRODUCT((('Clarke, Penopolly'!I18+'Clarke, Penopolly'!I19)>12)*1)+SUMPRODUCT((('Clarke, Penopolly'!I20+'Clarke, Penopolly'!I21)>12)*1)+SUMPRODUCT((('Clarke, Penopolly'!I22+'Clarke, Penopolly'!I23)>12)*1)+SUMPRODUCT((('Clarke, Penopolly'!I24+'Clarke, Penopolly'!I25)>12)*1)+SUMPRODUCT((('Clarke, Penopolly'!I26+'Clarke, Penopolly'!I27)>12)*1)+SUMPRODUCT((('Clarke, Penopolly'!I30+'Clarke, Penopolly'!I31)>12)*1)+SUMPRODUCT((('Clarke, Penopolly'!I32+'Clarke, Penopolly'!I33)>12)*1)+SUMPRODUCT((('Clarke, Penopolly'!I34+'Clarke, Penopolly'!I35)>12)*1)+SUMPRODUCT((('Clarke, Penopolly'!I36+'Clarke, Penopolly'!I37)>12)*1)+SUMPRODUCT((('Clarke, Penopolly'!I38+'Clarke, Penopolly'!I39)>12)*1)+SUMPRODUCT((('Clarke, Penopolly'!I40+'Clarke, Penopolly'!I41)>12)*1)+SUMPRODUCT((('Clarke, Penopolly'!I42+'Clarke, Penopolly'!I43)>12)*1)+SUMPRODUCT((('Clarke, Penopolly'!I45+'Clarke, Penopolly'!I46)>12)*1)+SUMPRODUCT((('Clarke, Penopolly'!I47+'Clarke, Penopolly'!I48)>12)*1) | G22: =IF(MAX(SUM('Clarke, Penopolly'!I14:I27),SUM('Clarke, Penopolly'!I30:I43))>60,"Yes","") | H22: =IF(OR(AND(('Clarke, Penopolly'!I14+'Clarke, Penopolly'!I15)>0,('Clarke, Penopolly'!I16+'Clarke, Penopolly'!I17)>0,('Clarke, Penopolly'!I18+'Clarke, Penopolly'!I19)>0,('Clarke, Penopolly'!I20+'Clarke, Penopolly'!I21)>0,('Clarke, Penopolly'!I22+'Clarke, Penopolly'!I23)>0,('Clarke, Penopolly'!I24+'Clarke, Penopolly'!I25)>0,('Clarke, Penopolly'!I26+'Clarke, Penopolly'!I27)>0),AND(('Clarke, Penopolly'!I30+'Clarke, Penopolly'!I31)>0,('Clarke, Penopolly'!I32+'Clarke, Penopolly'!I33)>0,('Clarke, Penopolly'!I34+'Clarke, Penopolly'!I35)>0,('Clarke, Penopolly'!I36+'Clarke, Penopolly'!I37)>0,('Clarke, Penopolly'!I38+'Clarke, Penopolly'!I39)>0,('Clarke, Penopolly'!I40+'Clarke, Penopolly'!I41)>0,('Clarke, Penopolly'!I42+'Clarke, Penopolly'!I43)>0)),"Yes","") | I22: =IF('Clarke, Penopolly'!N49>40,"Yes","") | J22: =IF(OR(AND(SUM('Clarke, Penopolly'!I14:I27)>0,SUM('Clarke, Penopolly'!I14:I27)<40),AND(SUM('Clarke, Penopolly'!I30:I43)>0,SUM('Clarke, Penopolly'!I30:I43)<40)),"Yes","") | K22: =SUMPRODUCT(('Clarke, Penopolly'!I14:I48>0)*('Clarke, Penopolly'!I14:I48<8)) | L22: =IF('Clarke, Penopolly'!Q50<5,"Yes","") | M22: =IF(AND('Clarke, Penopolly'!I49>0,'Clarke, Penopolly'!I49<80),"Yes","") | N22: =IF(OR(F22>0,G22="Yes",H22="Yes",I22="Yes"),"⚠️ OVERWORK",IF(OR(J22="Yes",K22>0,L22="Yes",M22="Yes"),"🔻 UNDERWORK","✓ OK"))
A23: 19 | B23: Clarke, Richard | C23: 3399 | D23: ='Clarke, Richard'!I49 | E23: ='Clarke, Richard'!Q50 | F23: =SUMPRODUCT((('Clarke, Richard'!I14+'Clarke, Richard'!I15)>12)*1)+SUMPRODUCT((('Clarke, Richard'!I16+'Clarke, Richard'!I17)>12)*1)+SUMPRODUCT((('Clarke, Richard'!I18+'Clarke, Richard'!I19)>12)*1)+SUMPRODUCT((('Clarke, Richard'!I20+'Clarke, Richard'!I21)>12)*1)+SUMPRODUCT((('Clarke, Richard'!I22+'Clarke, Richard'!I23)>12)*1)+SUMPRODUCT((('Clarke, Richard'!I24+'Clarke, Richard'!I25)>12)*1)+SUMPRODUCT((('Clarke, Richard'!I26+'Clarke, Richard'!I27)>12)*1)+SUMPRODUCT((('Clarke, Richard'!I30+'Clarke, Richard'!I31)>12)*1)+SUMPRODUCT((('Clarke, Richard'!I32+'Clarke, Richard'!I33)>12)*1)+SUMPRODUCT((('Clarke, Richard'!I34+'Clarke, Richard'!I35)>12)*1)+SUMPRODUCT((('Clarke, Richard'!I36+'Clarke, Richard'!I37)>12)*1)+SUMPRODUCT((('Clarke, Richard'!I38+'Clarke, Richard'!I39)>12)*1)+SUMPRODUCT((('Clarke, Richard'!I40+'Clarke, Richard'!I41)>12)*1)+SUMPRODUCT((('Clarke, Richard'!I42+'Clarke, Richard'!I43)>12)*1)+SUMPRODUCT((('Clarke, Richard'!I45+'Clarke, Richard'!I46)>12)*1)+SUMPRODUCT((('Clarke, Richard'!I47+'Clarke, Richard'!I48)>12)*1) | G23: =IF(MAX(SUM('Clarke, Richard'!I14:I27),SUM('Clarke, Richard'!I30:I43))>60,"Yes","") | H23: =IF(OR(AND(('Clarke, Richard'!I14+'Clarke, Richard'!I15)>0,('Clarke, Richard'!I16+'Clarke, Richard'!I17)>0,('Clarke, Richard'!I18+'Clarke, Richard'!I19)>0,('Clarke, Richard'!I20+'Clarke, Richard'!I21)>0,('Clarke, Richard'!I22+'Clarke, Richard'!I23)>0,('Clarke, Richard'!I24+'Clarke, Richard'!I25)>0,('Clarke, Richard'!I26+'Clarke, Richard'!I27)>0),AND(('Clarke, Richard'!I30+'Clarke, Richard'!I31)>0,('Clarke, Richard'!I32+'Clarke, Richard'!I33)>0,('Clarke, Richard'!I34+'Clarke, Richard'!I35)>0,('Clarke, Richard'!I36+'Clarke, Richard'!I37)>0,('Clarke, Richard'!I38+'Clarke, Richard'!I39)>0,('Clarke, Richard'!I40+'Clarke, Richard'!I41)>0,('Clarke, Richard'!I42+'Clarke, Richard'!I43)>0)),"Yes","") | I23: =IF('Clarke, Richard'!N49>40,"Yes","") | J23: =IF(OR(AND(SUM('Clarke, Richard'!I14:I27)>0,SUM('Clarke, Richard'!I14:I27)<40),AND(SUM('Clarke, Richard'!I30:I43)>0,SUM('Clarke, Richard'!I30:I43)<40)),"Yes","") | K23: =SUMPRODUCT(('Clarke, Richard'!I14:I48>0)*('Clarke, Richard'!I14:I48<8)) | L23: =IF('Clarke, Richard'!Q50<5,"Yes","") | M23: =IF(AND('Clarke, Richard'!I49>0,'Clarke, Richard'!I49<80),"Yes","") | N23: =IF(OR(F23>0,G23="Yes",H23="Yes",I23="Yes"),"⚠️ OVERWORK",IF(OR(J23="Yes",K23>0,L23="Yes",M23="Yes"),"🔻 UNDERWORK","✓ OK"))
A24: 20 | B24: Cockfield, Nichola Roxann | C24: 4250 | D24: ='Cockfield, Nichola Roxann'!I49 | E24: ='Cockfield, Nichola Roxann'!Q50 | F24: =SUMPRODUCT((('Cockfield, Nichola Roxann'!I14+'Cockfield, Nichola Roxann'!I15)>12)*1)+SUMPRODUCT((('Cockfield, Nichola Roxann'!I16+'Cockfield, Nichola Roxann'!I17)>12)*1)+SUMPRODUCT((('Cockfield, Nichola Roxann'!I18+'Cockfield, Nichola Roxann'!I19)>12)*1)+SUMPRODUCT((('Cockfield, Nichola Roxann'!I20+'Cockfield, Nichola Roxann'!I21)>12)*1)+SUMPRODUCT((('Cockfield, Nichola Roxann'!I22+'Cockfield, Nichola Roxann'!I23)>12)*1)+SUMPRODUCT((('Cockfield, Nichola Roxann'!I24+'Cockfield, Nichola Roxann'!I25)>12)*1)+SUMPRODUCT((('Cockfield, Nichola Roxann'!I26+'Cockfield, Nichola Roxann'!I27)>12)*1)+SUMPRODUCT((('Cockfield, Nichola Roxann'!I30+'Cockfield, Nichola Roxann'!I31)>12)*1)+SUMPRODUCT((('Cockfield, Nichola Roxann'!I32+'Cockfield, Nichola Roxann'!I33)>12)*1)+SUMPRODUCT((('Cockfield, Nichola Roxann'!I34+'Cockfield, Nichola Roxann'!I35)>12)*1)+SUMPRODUCT((('Cockfield, Nichola Roxann'!I36+'Cockfield, Nichola Roxann'!I37)>12)*1)+SUMPRODUCT((('Cockfield, Nichola Roxann'!I38+'Cockfield, Nichola Roxann'!I39)>12)*1)+SUMPRODUCT((('Cockfield, Nichola Roxann'!I40+'Cockfield, Nichola Roxann'!I41)>12)*1)+SUMPRODUCT((('Cockfield, Nichola Roxann'!I42+'Cockfield, Nichola Roxann'!I43)>12)*1)+SUMPRODUCT((('Cockfield, Nichola Roxann'!I45+'Cockfield, Nichola Roxann'!I46)>12)*1)+SUMPRODUCT((('Cockfield, Nichola Roxann'!I47+'Cockfield, Nichola Roxann'!I48)>12)*1) | G24: =IF(MAX(SUM('Cockfield, Nichola Roxann'!I14:I27),SUM('Cockfield, Nichola Roxann'!I30:I43))>60,"Yes","") | H24: =IF(OR(AND(('Cockfield, Nichola Roxann'!I14+'Cockfield, Nichola Roxann'!I15)>0,('Cockfield, Nichola Roxann'!I16+'Cockfield, Nichola Roxann'!I17)>0,('Cockfield, Nichola Roxann'!I18+'Cockfield, Nichola Roxann'!I19)>0,('Cockfield, Nichola Roxann'!I20+'Cockfield, Nichola Roxann'!I21)>0,('Cockfield, Nichola Roxann'!I22+'Cockfield, Nichola Roxann'!I23)>0,('Cockfield, Nichola Roxann'!I24+'Cockfield, Nichola Roxann'!I25)>0,('Cockfield, Nichola Roxann'!I26+'Cockfield, Nichola Roxann'!I27)>0),AND(('Cockfield, Nichola Roxann'!I30+'Cockfield, Nichola Roxann'!I31)>0,('Cockfield, Nichola Roxann'!I32+'Cockfield, Nichola Roxann'!I33)>0,('Cockfield, Nichola Roxann'!I34+'Cockfield, Nichola Roxann'!I35)>0,('Cockfield, Nichola Roxann'!I36+'Cockfield, Nichola Roxann'!I37)>0,('Cockfield, Nichola Roxann'!I38+'Cockfield, Nichola Roxann'!I39)>0,('Cockfield, Nichola Roxann'!I40+'Cockfield, Nichola Roxann'!I41)>0,('Cockfield, Nichola Roxann'!I42+'Cockfield, Nichola Roxann'!I43)>0)),"Yes","") | I24: =IF('Cockfield, Nichola Roxann'!N49>40,"Yes","") | J24: =IF(OR(AND(SUM('Cockfield, Nichola Roxann'!I14:I27)>0,SUM('Cockfield, Nichola Roxann'!I14:I27)<40),AND(SUM('Cockfield, Nichola Roxann'!I30:I43)>0,SUM('Cockfield, Nichola Roxann'!I30:I43)<40)),"Yes","") | K24: =SUMPRODUCT(('Cockfield, Nichola Roxann'!I14:I48>0)*('Cockfield, Nichola Roxann'!I14:I48<8)) | L24: =IF('Cockfield, Nichola Roxann'!Q50<5,"Yes","") | M24: =IF(AND('Cockfield, Nichola Roxann'!I49>0,'Cockfield, Nichola Roxann'!I49<80),"Yes","") | N24: =IF(OR(F24>0,G24="Yes",H24="Yes",I24="Yes"),"⚠️ OVERWORK",IF(OR(J24="Yes",K24>0,L24="Yes",M24="Yes"),"🔻 UNDERWORK","✓ OK"))
A25: 21 | B25: Cort, Neville Orvil | C25: 3773 | D25: ='Cort, Neville Orvil'!I49 | E25: ='Cort, Neville Orvil'!Q50 | F25: =SUMPRODUCT((('Cort, Neville Orvil'!I14+'Cort, Neville Orvil'!I15)>12)*1)+SUMPRODUCT((('Cort, Neville Orvil'!I16+'Cort, Neville Orvil'!I17)>12)*1)+SUMPRODUCT((('Cort, Neville Orvil'!I18+'Cort, Neville Orvil'!I19)>12)*1)+SUMPRODUCT((('Cort, Neville Orvil'!I20+'Cort, Neville Orvil'!I21)>12)*1)+SUMPRODUCT((('Cort, Neville Orvil'!I22+'Cort, Neville Orvil'!I23)>12)*1)+SUMPRODUCT((('Cort, Neville Orvil'!I24+'Cort, Neville Orvil'!I25)>12)*1)+SUMPRODUCT((('Cort, Neville Orvil'!I26+'Cort, Neville Orvil'!I27)>12)*1)+SUMPRODUCT((('Cort, Neville Orvil'!I30+'Cort, Neville Orvil'!I31)>12)*1)+SUMPRODUCT((('Cort, Neville Orvil'!I32+'Cort, Neville Orvil'!I33)>12)*1)+SUMPRODUCT((('Cort, Neville Orvil'!I34+'Cort, Neville Orvil'!I35)>12)*1)+SUMPRODUCT((('Cort, Neville Orvil'!I36+'Cort, Neville Orvil'!I37)>12)*1)+SUMPRODUCT((('Cort, Neville Orvil'!I38+'Cort, Neville Orvil'!I39)>12)*1)+SUMPRODUCT((('Cort, Neville Orvil'!I40+'Cort, Neville Orvil'!I41)>12)*1)+SUMPRODUCT((('Cort, Neville Orvil'!I42+'Cort, Neville Orvil'!I43)>12)*1)+SUMPRODUCT((('Cort, Neville Orvil'!I45+'Cort, Neville Orvil'!I46)>12)*1)+SUMPRODUCT((('Cort, Neville Orvil'!I47+'Cort, Neville Orvil'!I48)>12)*1) | G25: =IF(MAX(SUM('Cort, Neville Orvil'!I14:I27),SUM('Cort, Neville Orvil'!I30:I43))>60,"Yes","") | H25: =IF(OR(AND(('Cort, Neville Orvil'!I14+'Cort, Neville Orvil'!I15)>0,('Cort, Neville Orvil'!I16+'Cort, Neville Orvil'!I17)>0,('Cort, Neville Orvil'!I18+'Cort, Neville Orvil'!I19)>0,('Cort, Neville Orvil'!I20+'Cort, Neville Orvil'!I21)>0,('Cort, Neville Orvil'!I22+'Cort, Neville Orvil'!I23)>0,('Cort, Neville Orvil'!I24+'Cort, Neville Orvil'!I25)>0,('Cort, Neville Orvil'!I26+'Cort, Neville Orvil'!I27)>0),AND(('Cort, Neville Orvil'!I30+'Cort, Neville Orvil'!I31)>0,('Cort, Neville Orvil'!I32+'Cort, Neville Orvil'!I33)>0,('Cort, Neville Orvil'!I34+'Cort, Neville Orvil'!I35)>0,('Cort, Neville Orvil'!I36+'Cort, Neville Orvil'!I37)>0,('Cort, Neville Orvil'!I38+'Cort, Neville Orvil'!I39)>0,('Cort, Neville Orvil'!I40+'Cort, Neville Orvil'!I41)>0,('Cort, Neville Orvil'!I42+'Cort, Neville Orvil'!I43)>0)),"Yes","") | I25: =IF('Cort, Neville Orvil'!N49>40,"Yes","") | J25: =IF(OR(AND(SUM('Cort, Neville Orvil'!I14:I27)>0,SUM('Cort, Neville Orvil'!I14:I27)<40),AND(SUM('Cort, Neville Orvil'!I30:I43)>0,SUM('Cort, Neville Orvil'!I30:I43)<40)),"Yes","") | K25: =SUMPRODUCT(('Cort, Neville Orvil'!I14:I48>0)*('Cort, Neville Orvil'!I14:I48<8)) | L25: =IF('Cort, Neville Orvil'!Q50<5,"Yes","") | M25: =IF(AND('Cort, Neville Orvil'!I49>0,'Cort, Neville Orvil'!I49<80),"Yes","") | N25: =IF(OR(F25>0,G25="Yes",H25="Yes",I25="Yes"),"⚠️ OVERWORK",IF(OR(J25="Yes",K25>0,L25="Yes",M25="Yes"),"🔻 UNDERWORK","✓ OK"))
A26: 22 | B26: Crandon, Andrea Lorette | C26: 1973 | D26: ='Crandon, Andrea Lorette'!I49 | E26: ='Crandon, Andrea Lorette'!Q50 | F26: =SUMPRODUCT((('Crandon, Andrea Lorette'!I14+'Crandon, Andrea Lorette'!I15)>12)*1)+SUMPRODUCT((('Crandon, Andrea Lorette'!I16+'Crandon, Andrea Lorette'!I17)>12)*1)+SUMPRODUCT((('Crandon, Andrea Lorette'!I18+'Crandon, Andrea Lorette'!I19)>12)*1)+SUMPRODUCT((('Crandon, Andrea Lorette'!I20+'Crandon, Andrea Lorette'!I21)>12)*1)+SUMPRODUCT((('Crandon, Andrea Lorette'!I22+'Crandon, Andrea Lorette'!I23)>12)*1)+SUMPRODUCT((('Crandon, Andrea Lorette'!I24+'Crandon, Andrea Lorette'!I25)>12)*1)+SUMPRODUCT((('Crandon, Andrea Lorette'!I26+'Crandon, Andrea Lorette'!I27)>12)*1)+SUMPRODUCT((('Crandon, Andrea Lorette'!I30+'Crandon, Andrea Lorette'!I31)>12)*1)+SUMPRODUCT((('Crandon, Andrea Lorette'!I32+'Crandon, Andrea Lorette'!I33)>12)*1)+SUMPRODUCT((('Crandon, Andrea Lorette'!I34+'Crandon, Andrea Lorette'!I35)>12)*1)+SUMPRODUCT((('Crandon, Andrea Lorette'!I36+'Crandon, Andrea Lorette'!I37)>12)*1)+SUMPRODUCT((('Crandon, Andrea Lorette'!I38+'Crandon, Andrea Lorette'!I39)>12)*1)+SUMPRODUCT((('Crandon, Andrea Lorette'!I40+'Crandon, Andrea Lorette'!I41)>12)*1)+SUMPRODUCT((('Crandon, Andrea Lorette'!I42+'Crandon, Andrea Lorette'!I43)>12)*1)+SUMPRODUCT((('Crandon, Andrea Lorette'!I45+'Crandon, Andrea Lorette'!I46)>12)*1)+SUMPRODUCT((('Crandon, Andrea Lorette'!I47+'Crandon, Andrea Lorette'!I48)>12)*1) | G26: =IF(MAX(SUM('Crandon, Andrea Lorette'!I14:I27),SUM('Crandon, Andrea Lorette'!I30:I43))>60,"Yes","") | H26: =IF(OR(AND(('Crandon, Andrea Lorette'!I14+'Crandon, Andrea Lorette'!I15)>0,('Crandon, Andrea Lorette'!I16+'Crandon, Andrea Lorette'!I17)>0,('Crandon, Andrea Lorette'!I18+'Crandon, Andrea Lorette'!I19)>0,('Crandon, Andrea Lorette'!I20+'Crandon, Andrea Lorette'!I21)>0,('Crandon, Andrea Lorette'!I22+'Crandon, Andrea Lorette'!I23)>0,('Crandon, Andrea Lorette'!I24+'Crandon, Andrea Lorette'!I25)>0,('Crandon, Andrea Lorette'!I26+'Crandon, Andrea Lorette'!I27)>0),AND(('Crandon, Andrea Lorette'!I30+'Crandon, Andrea Lorette'!I31)>0,('Crandon, Andrea Lorette'!I32+'Crandon, Andrea Lorette'!I33)>0,('Crandon, Andrea Lorette'!I34+'Crandon, Andrea Lorette'!I35)>0,('Crandon, Andrea Lorette'!I36+'Crandon, Andrea Lorette'!I37)>0,('Crandon, Andrea Lorette'!I38+'Crandon, Andrea Lorette'!I39)>0,('Crandon, Andrea Lorette'!I40+'Crandon, Andrea Lorette'!I41)>0,('Crandon, Andrea Lorette'!I42+'Crandon, Andrea Lorette'!I43)>0)),"Yes","") | I26: =IF('Crandon, Andrea Lorette'!N49>40,"Yes","") | J26: =IF(OR(AND(SUM('Crandon, Andrea Lorette'!I14:I27)>0,SUM('Crandon, Andrea Lorette'!I14:I27)<40),AND(SUM('Crandon, Andrea Lorette'!I30:I43)>0,SUM('Crandon, Andrea Lorette'!I30:I43)<40)),"Yes","") | K26: =SUMPRODUCT(('Crandon, Andrea Lorette'!I14:I48>0)*('Crandon, Andrea Lorette'!I14:I48<8)) | L26: =IF('Crandon, Andrea Lorette'!Q50<5,"Yes","") | M26: =IF(AND('Crandon, Andrea Lorette'!I49>0,'Crandon, Andrea Lorette'!I49<80),"Yes","") | N26: =IF(OR(F26>0,G26="Yes",H26="Yes",I26="Yes"),"⚠️ OVERWORK",IF(OR(J26="Yes",K26>0,L26="Yes",M26="Yes"),"🔻 UNDERWORK","✓ OK"))
A27: 23 | B27: De Santos, Sandra | C27: 1641 | D27: ='De Santos, Sandra'!I49 | E27: ='De Santos, Sandra'!Q50 | F27: =SUMPRODUCT((('De Santos, Sandra'!I14+'De Santos, Sandra'!I15)>12)*1)+SUMPRODUCT((('De Santos, Sandra'!I16+'De Santos, Sandra'!I17)>12)*1)+SUMPRODUCT((('De Santos, Sandra'!I18+'De Santos, Sandra'!I19)>12)*1)+SUMPRODUCT((('De Santos, Sandra'!I20+'De Santos, Sandra'!I21)>12)*1)+SUMPRODUCT((('De Santos, Sandra'!I22+'De Santos, Sandra'!I23)>12)*1)+SUMPRODUCT((('De Santos, Sandra'!I24+'De Santos, Sandra'!I25)>12)*1)+SUMPRODUCT((('De Santos, Sandra'!I26+'De Santos, Sandra'!I27)>12)*1)+SUMPRODUCT((('De Santos, Sandra'!I30+'De Santos, Sandra'!I31)>12)*1)+SUMPRODUCT((('De Santos, Sandra'!I32+'De Santos, Sandra'!I33)>12)*1)+SUMPRODUCT((('De Santos, Sandra'!I34+'De Santos, Sandra'!I35)>12)*1)+SUMPRODUCT((('De Santos, Sandra'!I36+'De Santos, Sandra'!I37)>12)*1)+SUMPRODUCT((('De Santos, Sandra'!I38+'De Santos, Sandra'!I39)>12)*1)+SUMPRODUCT((('De Santos, Sandra'!I40+'De Santos, Sandra'!I41)>12)*1)+SUMPRODUCT((('De Santos, Sandra'!I42+'De Santos, Sandra'!I43)>12)*1)+SUMPRODUCT((('De Santos, Sandra'!I45+'De Santos, Sandra'!I46)>12)*1)+SUMPRODUCT((('De Santos, Sandra'!I47+'De Santos, Sandra'!I48)>12)*1) | G27: =IF(MAX(SUM('De Santos, Sandra'!I14:I27),SUM('De Santos, Sandra'!I30:I43))>60,"Yes","") | H27: =IF(OR(AND(('De Santos, Sandra'!I14+'De Santos, Sandra'!I15)>0,('De Santos, Sandra'!I16+'De Santos, Sandra'!I17)>0,('De Santos, Sandra'!I18+'De Santos, Sandra'!I19)>0,('De Santos, Sandra'!I20+'De Santos, Sandra'!I21)>0,('De Santos, Sandra'!I22+'De Santos, Sandra'!I23)>0,('De Santos, Sandra'!I24+'De Santos, Sandra'!I25)>0,('De Santos, Sandra'!I26+'De Santos, Sandra'!I27)>0),AND(('De Santos, Sandra'!I30+'De Santos, Sandra'!I31)>0,('De Santos, Sandra'!I32+'De Santos, Sandra'!I33)>0,('De Santos, Sandra'!I34+'De Santos, Sandra'!I35)>0,('De Santos, Sandra'!I36+'De Santos, Sandra'!I37)>0,('De Santos, Sandra'!I38+'De Santos, Sandra'!I39)>0,('De Santos, Sandra'!I40+'De Santos, Sandra'!I41)>0,('De Santos, Sandra'!I42+'De Santos, Sandra'!I43)>0)),"Yes","") | I27: =IF('De Santos, Sandra'!N49>40,"Yes","") | J27: =IF(OR(AND(SUM('De Santos, Sandra'!I14:I27)>0,SUM('De Santos, Sandra'!I14:I27)<40),AND(SUM('De Santos, Sandra'!I30:I43)>0,SUM('De Santos, Sandra'!I30:I43)<40)),"Yes","") | K27: =SUMPRODUCT(('De Santos, Sandra'!I14:I48>0)*('De Santos, Sandra'!I14:I48<8)) | L27: =IF('De Santos, Sandra'!Q50<5,"Yes","") | M27: =IF(AND('De Santos, Sandra'!I49>0,'De Santos, Sandra'!I49<80),"Yes","") | N27: =IF(OR(F27>0,G27="Yes",H27="Yes",I27="Yes"),"⚠️ OVERWORK",IF(OR(J27="Yes",K27>0,L27="Yes",M27="Yes"),"🔻 UNDERWORK","✓ OK"))
A28: 24 | B28: December, Prince Ryan | C28: 1059 | D28: ='December, Prince Ryan'!I49 | E28: ='December, Prince Ryan'!Q50 | F28: =SUMPRODUCT((('December, Prince Ryan'!I14+'December, Prince Ryan'!I15)>12)*1)+SUMPRODUCT((('December, Prince Ryan'!I16+'December, Prince Ryan'!I17)>12)*1)+SUMPRODUCT((('December, Prince Ryan'!I18+'December, Prince Ryan'!I19)>12)*1)+SUMPRODUCT((('December, Prince Ryan'!I20+'December, Prince Ryan'!I21)>12)*1)+SUMPRODUCT((('December, Prince Ryan'!I22+'December, Prince Ryan'!I23)>12)*1)+SUMPRODUCT((('December, Prince Ryan'!I24+'December, Prince Ryan'!I25)>12)*1)+SUMPRODUCT((('December, Prince Ryan'!I26+'December, Prince Ryan'!I27)>12)*1)+SUMPRODUCT((('December, Prince Ryan'!I30+'December, Prince Ryan'!I31)>12)*1)+SUMPRODUCT((('December, Prince Ryan'!I32+'December, Prince Ryan'!I33)>12)*1)+SUMPRODUCT((('December, Prince Ryan'!I34+'December, Prince Ryan'!I35)>12)*1)+SUMPRODUCT((('December, Prince Ryan'!I36+'December, Prince Ryan'!I37)>12)*1)+SUMPRODUCT((('December, Prince Ryan'!I38+'December, Prince Ryan'!I39)>12)*1)+SUMPRODUCT((('December, Prince Ryan'!I40+'December, Prince Ryan'!I41)>12)*1)+SUMPRODUCT((('December, Prince Ryan'!I42+'December, Prince Ryan'!I43)>12)*1)+SUMPRODUCT((('December, Prince Ryan'!I45+'December, Prince Ryan'!I46)>12)*1)+SUMPRODUCT((('December, Prince Ryan'!I47+'December, Prince Ryan'!I48)>12)*1) | G28: =IF(MAX(SUM('December, Prince Ryan'!I14:I27),SUM('December, Prince Ryan'!I30:I43))>60,"Yes","") | H28: =IF(OR(AND(('December, Prince Ryan'!I14+'December, Prince Ryan'!I15)>0,('December, Prince Ryan'!I16+'December, Prince Ryan'!I17)>0,('December, Prince Ryan'!I18+'December, Prince Ryan'!I19)>0,('December, Prince Ryan'!I20+'December, Prince Ryan'!I21)>0,('December, Prince Ryan'!I22+'December, Prince Ryan'!I23)>0,('December, Prince Ryan'!I24+'December, Prince Ryan'!I25)>0,('December, Prince Ryan'!I26+'December, Prince Ryan'!I27)>0),AND(('December, Prince Ryan'!I30+'December, Prince Ryan'!I31)>0,('December, Prince Ryan'!I32+'December, Prince Ryan'!I33)>0,('December, Prince Ryan'!I34+'December, Prince Ryan'!I35)>0,('December, Prince Ryan'!I36+'December, Prince Ryan'!I37)>0,('December, Prince Ryan'!I38+'December, Prince Ryan'!I39)>0,('December, Prince Ryan'!I40+'December, Prince Ryan'!I41)>0,('December, Prince Ryan'!I42+'December, Prince Ryan'!I43)>0)),"Yes","") | I28: =IF('December, Prince Ryan'!N49>40,"Yes","") | J28: =IF(OR(AND(SUM('December, Prince Ryan'!I14:I27)>0,SUM('December, Prince Ryan'!I14:I27)<40),AND(SUM('December, Prince Ryan'!I30:I43)>0,SUM('December, Prince Ryan'!I30:I43)<40)),"Yes","") | K28: =SUMPRODUCT(('December, Prince Ryan'!I14:I48>0)*('December, Prince Ryan'!I14:I48<8)) | L28: =IF('December, Prince Ryan'!Q50<5,"Yes","") | M28: =IF(AND('December, Prince Ryan'!I49>0,'December, Prince Ryan'!I49<80),"Yes","") | N28: =IF(OR(F28>0,G28="Yes",H28="Yes",I28="Yes"),"⚠️ OVERWORK",IF(OR(J28="Yes",K28>0,L28="Yes",M28="Yes"),"🔻 UNDERWORK","✓ OK"))
A29: 25 | B29: December, Roxanne | C29: 594 | D29: ='December, Roxanne'!I49 | E29: ='December, Roxanne'!Q50 | F29: =SUMPRODUCT((('December, Roxanne'!I14+'December, Roxanne'!I15)>12)*1)+SUMPRODUCT((('December, Roxanne'!I16+'December, Roxanne'!I17)>12)*1)+SUMPRODUCT((('December, Roxanne'!I18+'December, Roxanne'!I19)>12)*1)+SUMPRODUCT((('December, Roxanne'!I20+'December, Roxanne'!I21)>12)*1)+SUMPRODUCT((('December, Roxanne'!I22+'December, Roxanne'!I23)>12)*1)+SUMPRODUCT((('December, Roxanne'!I24+'December, Roxanne'!I25)>12)*1)+SUMPRODUCT((('December, Roxanne'!I26+'December, Roxanne'!I27)>12)*1)+SUMPRODUCT((('December, Roxanne'!I30+'December, Roxanne'!I31)>12)*1)+SUMPRODUCT((('December, Roxanne'!I32+'December, Roxanne'!I33)>12)*1)+SUMPRODUCT((('December, Roxanne'!I34+'December, Roxanne'!I35)>12)*1)+SUMPRODUCT((('December, Roxanne'!I36+'December, Roxanne'!I37)>12)*1)+SUMPRODUCT((('December, Roxanne'!I38+'December, Roxanne'!I39)>12)*1)+SUMPRODUCT((('December, Roxanne'!I40+'December, Roxanne'!I41)>12)*1)+SUMPRODUCT((('December, Roxanne'!I42+'December, Roxanne'!I43)>12)*1)+SUMPRODUCT((('December, Roxanne'!I45+'December, Roxanne'!I46)>12)*1)+SUMPRODUCT((('December, Roxanne'!I47+'December, Roxanne'!I48)>12)*1) | G29: =IF(MAX(SUM('December, Roxanne'!I14:I27),SUM('December, Roxanne'!I30:I43))>60,"Yes","") | H29: =IF(OR(AND(('December, Roxanne'!I14+'December, Roxanne'!I15)>0,('December, Roxanne'!I16+'December, Roxanne'!I17)>0,('December, Roxanne'!I18+'December, Roxanne'!I19)>0,('December, Roxanne'!I20+'December, Roxanne'!I21)>0,('December, Roxanne'!I22+'December, Roxanne'!I23)>0,('December, Roxanne'!I24+'December, Roxanne'!I25)>0,('December, Roxanne'!I26+'December, Roxanne'!I27)>0),AND(('December, Roxanne'!I30+'December, Roxanne'!I31)>0,('December, Roxanne'!I32+'December, Roxanne'!I33)>0,('December, Roxanne'!I34+'December, Roxanne'!I35)>0,('December, Roxanne'!I36+'December, Roxanne'!I37)>0,('December, Roxanne'!I38+'December, Roxanne'!I39)>0,('December, Roxanne'!I40+'December, Roxanne'!I41)>0,('December, Roxanne'!I42+'December, Roxanne'!I43)>0)),"Yes","") | I29: =IF('December, Roxanne'!N49>40,"Yes","") | J29: =IF(OR(AND(SUM('December, Roxanne'!I14:I27)>0,SUM('December, Roxanne'!I14:I27)<40),AND(SUM('December, Roxanne'!I30:I43)>0,SUM('December, Roxanne'!I30:I43)<40)),"Yes","") | K29: =SUMPRODUCT(('December, Roxanne'!I14:I48>0)*('December, Roxanne'!I14:I48<8)) | L29: =IF('December, Roxanne'!Q50<5,"Yes","") | M29: =IF(AND('December, Roxanne'!I49>0,'December, Roxanne'!I49<80),"Yes","") | N29: =IF(OR(F29>0,G29="Yes",H29="Yes",I29="Yes"),"⚠️ OVERWORK",IF(OR(J29="Yes",K29>0,L29="Yes",M29="Yes"),"🔻 UNDERWORK","✓ OK"))
A30: 26 | B30: Douglas, Nicola Onica | C30: 5462 | D30: ='Douglas, Nicola Onica'!I49 | E30: ='Douglas, Nicola Onica'!Q50 | F30: =SUMPRODUCT((('Douglas, Nicola Onica'!I14+'Douglas, Nicola Onica'!I15)>12)*1)+SUMPRODUCT((('Douglas, Nicola Onica'!I16+'Douglas, Nicola Onica'!I17)>12)*1)+SUMPRODUCT((('Douglas, Nicola Onica'!I18+'Douglas, Nicola Onica'!I19)>12)*1)+SUMPRODUCT((('Douglas, Nicola Onica'!I20+'Douglas, Nicola Onica'!I21)>12)*1)+SUMPRODUCT((('Douglas, Nicola Onica'!I22+'Douglas, Nicola Onica'!I23)>12)*1)+SUMPRODUCT((('Douglas, Nicola Onica'!I24+'Douglas, Nicola Onica'!I25)>12)*1)+SUMPRODUCT((('Douglas, Nicola Onica'!I26+'Douglas, Nicola Onica'!I27)>12)*1)+SUMPRODUCT((('Douglas, Nicola Onica'!I30+'Douglas, Nicola Onica'!I31)>12)*1)+SUMPRODUCT((('Douglas, Nicola Onica'!I32+'Douglas, Nicola Onica'!I33)>12)*1)+SUMPRODUCT((('Douglas, Nicola Onica'!I34+'Douglas, Nicola Onica'!I35)>12)*1)+SUMPRODUCT((('Douglas, Nicola Onica'!I36+'Douglas, Nicola Onica'!I37)>12)*1)+SUMPRODUCT((('Douglas, Nicola Onica'!I38+'Douglas, Nicola Onica'!I39)>12)*1)+SUMPRODUCT((('Douglas, Nicola Onica'!I40+'Douglas, Nicola Onica'!I41)>12)*1)+SUMPRODUCT((('Douglas, Nicola Onica'!I42+'Douglas, Nicola Onica'!I43)>12)*1)+SUMPRODUCT((('Douglas, Nicola Onica'!I45+'Douglas, Nicola Onica'!I46)>12)*1)+SUMPRODUCT((('Douglas, Nicola Onica'!I47+'Douglas, Nicola Onica'!I48)>12)*1) | G30: =IF(MAX(SUM('Douglas, Nicola Onica'!I14:I27),SUM('Douglas, Nicola Onica'!I30:I43))>60,"Yes","") | H30: =IF(OR(AND(('Douglas, Nicola Onica'!I14+'Douglas, Nicola Onica'!I15)>0,('Douglas, Nicola Onica'!I16+'Douglas, Nicola Onica'!I17)>0,('Douglas, Nicola Onica'!I18+'Douglas, Nicola Onica'!I19)>0,('Douglas, Nicola Onica'!I20+'Douglas, Nicola Onica'!I21)>0,('Douglas, Nicola Onica'!I22+'Douglas, Nicola Onica'!I23)>0,('Douglas, Nicola Onica'!I24+'Douglas, Nicola Onica'!I25)>0,('Douglas, Nicola Onica'!I26+'Douglas, Nicola Onica'!I27)>0),AND(('Douglas, Nicola Onica'!I30+'Douglas, Nicola Onica'!I31)>0,('Douglas, Nicola Onica'!I32+'Douglas, Nicola Onica'!I33)>0,('Douglas, Nicola Onica'!I34+'Douglas, Nicola Onica'!I35)>0,('Douglas, Nicola Onica'!I36+'Douglas, Nicola Onica'!I37)>0,('Douglas, Nicola Onica'!I38+'Douglas, Nicola Onica'!I39)>0,('Douglas, Nicola Onica'!I40+'Douglas, Nicola Onica'!I41)>0,('Douglas, Nicola Onica'!I42+'Douglas, Nicola Onica'!I43)>0)),"Yes","") | I30: =IF('Douglas, Nicola Onica'!N49>40,"Yes","") | J30: =IF(OR(AND(SUM('Douglas, Nicola Onica'!I14:I27)>0,SUM('Douglas, Nicola Onica'!I14:I27)<40),AND(SUM('Douglas, Nicola Onica'!I30:I43)>0,SUM('Douglas, Nicola Onica'!I30:I43)<40)),"Yes","") | K30: =SUMPRODUCT(('Douglas, Nicola Onica'!I14:I48>0)*('Douglas, Nicola Onica'!I14:I48<8)) | L30: =IF('Douglas, Nicola Onica'!Q50<5,"Yes","") | M30: =IF(AND('Douglas, Nicola Onica'!I49>0,'Douglas, Nicola Onica'!I49<80),"Yes","") | N30: =IF(OR(F30>0,G30="Yes",H30="Yes",I30="Yes"),"⚠️ OVERWORK",IF(OR(J30="Yes",K30>0,L30="Yes",M30="Yes"),"🔻 UNDERWORK","✓ OK"))
A31: 27 | B31: Dyer, Roxanne | C31: 3750 | D31: ='Dyer, Roxanne'!I49 | E31: ='Dyer, Roxanne'!Q50 | F31: =SUMPRODUCT((('Dyer, Roxanne'!I14+'Dyer, Roxanne'!I15)>12)*1)+SUMPRODUCT((('Dyer, Roxanne'!I16+'Dyer, Roxanne'!I17)>12)*1)+SUMPRODUCT((('Dyer, Roxanne'!I18+'Dyer, Roxanne'!I19)>12)*1)+SUMPRODUCT((('Dyer, Roxanne'!I20+'Dyer, Roxanne'!I21)>12)*1)+SUMPRODUCT((('Dyer, Roxanne'!I22+'Dyer, Roxanne'!I23)>12)*1)+SUMPRODUCT((('Dyer, Roxanne'!I24+'Dyer, Roxanne'!I25)>12)*1)+SUMPRODUCT((('Dyer, Roxanne'!I26+'Dyer, Roxanne'!I27)>12)*1)+SUMPRODUCT((('Dyer, Roxanne'!I30+'Dyer, Roxanne'!I31)>12)*1)+SUMPRODUCT((('Dyer, Roxanne'!I32+'Dyer, Roxanne'!I33)>12)*1)+SUMPRODUCT((('Dyer, Roxanne'!I34+'Dyer, Roxanne'!I35)>12)*1)+SUMPRODUCT((('Dyer, Roxanne'!I36+'Dyer, Roxanne'!I37)>12)*1)+SUMPRODUCT((('Dyer, Roxanne'!I38+'Dyer, Roxanne'!I39)>12)*1)+SUMPRODUCT((('Dyer, Roxanne'!I40+'Dyer, Roxanne'!I41)>12)*1)+SUMPRODUCT((('Dyer, Roxanne'!I42+'Dyer, Roxanne'!I43)>12)*1)+SUMPRODUCT((('Dyer, Roxanne'!I45+'Dyer, Roxanne'!I46)>12)*1)+SUMPRODUCT((('Dyer, Roxanne'!I47+'Dyer, Roxanne'!I48)>12)*1) | G31: =IF(MAX(SUM('Dyer, Roxanne'!I14:I27),SUM('Dyer, Roxanne'!I30:I43))>60,"Yes","") | H31: =IF(OR(AND(('Dyer, Roxanne'!I14+'Dyer, Roxanne'!I15)>0,('Dyer, Roxanne'!I16+'Dyer, Roxanne'!I17)>0,('Dyer, Roxanne'!I18+'Dyer, Roxanne'!I19)>0,('Dyer, Roxanne'!I20+'Dyer, Roxanne'!I21)>0,('Dyer, Roxanne'!I22+'Dyer, Roxanne'!I23)>0,('Dyer, Roxanne'!I24+'Dyer, Roxanne'!I25)>0,('Dyer, Roxanne'!I26+'Dyer, Roxanne'!I27)>0),AND(('Dyer, Roxanne'!I30+'Dyer, Roxanne'!I31)>0,('Dyer, Roxanne'!I32+'Dyer, Roxanne'!I33)>0,('Dyer, Roxanne'!I34+'Dyer, Roxanne'!I35)>0,('Dyer, Roxanne'!I36+'Dyer, Roxanne'!I37)>0,('Dyer, Roxanne'!I38+'Dyer, Roxanne'!I39)>0,('Dyer, Roxanne'!I40+'Dyer, Roxanne'!I41)>0,('Dyer, Roxanne'!I42+'Dyer, Roxanne'!I43)>0)),"Yes","") | I31: =IF('Dyer, Roxanne'!N49>40,"Yes","") | J31: =IF(OR(AND(SUM('Dyer, Roxanne'!I14:I27)>0,SUM('Dyer, Roxanne'!I14:I27)<40),AND(SUM('Dyer, Roxanne'!I30:I43)>0,SUM('Dyer, Roxanne'!I30:I43)<40)),"Yes","") | K31: =SUMPRODUCT(('Dyer, Roxanne'!I14:I48>0)*('Dyer, Roxanne'!I14:I48<8)) | L31: =IF('Dyer, Roxanne'!Q50<5,"Yes","") | M31: =IF(AND('Dyer, Roxanne'!I49>0,'Dyer, Roxanne'!I49<80),"Yes","") | N31: =IF(OR(F31>0,G31="Yes",H31="Yes",I31="Yes"),"⚠️ OVERWORK",IF(OR(J31="Yes",K31>0,L31="Yes",M31="Yes"),"🔻 UNDERWORK","✓ OK"))
A32: 28 | B32: Edwards, Shakwana | C32: 1826 | D32: ='Edwards, Shakwana'!I49 | E32: ='Edwards, Shakwana'!Q50 | F32: =SUMPRODUCT((('Edwards, Shakwana'!I14+'Edwards, Shakwana'!I15)>12)*1)+SUMPRODUCT((('Edwards, Shakwana'!I16+'Edwards, Shakwana'!I17)>12)*1)+SUMPRODUCT((('Edwards, Shakwana'!I18+'Edwards, Shakwana'!I19)>12)*1)+SUMPRODUCT((('Edwards, Shakwana'!I20+'Edwards, Shakwana'!I21)>12)*1)+SUMPRODUCT((('Edwards, Shakwana'!I22+'Edwards, Shakwana'!I23)>12)*1)+SUMPRODUCT((('Edwards, Shakwana'!I24+'Edwards, Shakwana'!I25)>12)*1)+SUMPRODUCT((('Edwards, Shakwana'!I26+'Edwards, Shakwana'!I27)>12)*1)+SUMPRODUCT((('Edwards, Shakwana'!I30+'Edwards, Shakwana'!I31)>12)*1)+SUMPRODUCT((('Edwards, Shakwana'!I32+'Edwards, Shakwana'!I33)>12)*1)+SUMPRODUCT((('Edwards, Shakwana'!I34+'Edwards, Shakwana'!I35)>12)*1)+SUMPRODUCT((('Edwards, Shakwana'!I36+'Edwards, Shakwana'!I37)>12)*1)+SUMPRODUCT((('Edwards, Shakwana'!I38+'Edwards, Shakwana'!I39)>12)*1)+SUMPRODUCT((('Edwards, Shakwana'!I40+'Edwards, Shakwana'!I41)>12)*1)+SUMPRODUCT((('Edwards, Shakwana'!I42+'Edwards, Shakwana'!I43)>12)*1)+SUMPRODUCT((('Edwards, Shakwana'!I45+'Edwards, Shakwana'!I46)>12)*1)+SUMPRODUCT((('Edwards, Shakwana'!I47+'Edwards, Shakwana'!I48)>12)*1) | G32: =IF(MAX(SUM('Edwards, Shakwana'!I14:I27),SUM('Edwards, Shakwana'!I30:I43))>60,"Yes","") | H32: =IF(OR(AND(('Edwards, Shakwana'!I14+'Edwards, Shakwana'!I15)>0,('Edwards, Shakwana'!I16+'Edwards, Shakwana'!I17)>0,('Edwards, Shakwana'!I18+'Edwards, Shakwana'!I19)>0,('Edwards, Shakwana'!I20+'Edwards, Shakwana'!I21)>0,('Edwards, Shakwana'!I22+'Edwards, Shakwana'!I23)>0,('Edwards, Shakwana'!I24+'Edwards, Shakwana'!I25)>0,('Edwards, Shakwana'!I26+'Edwards, Shakwana'!I27)>0),AND(('Edwards, Shakwana'!I30+'Edwards, Shakwana'!I31)>0,('Edwards, Shakwana'!I32+'Edwards, Shakwana'!I33)>0,('Edwards, Shakwana'!I34+'Edwards, Shakwana'!I35)>0,('Edwards, Shakwana'!I36+'Edwards, Shakwana'!I37)>0,('Edwards, Shakwana'!I38+'Edwards, Shakwana'!I39)>0,('Edwards, Shakwana'!I40+'Edwards, Shakwana'!I41)>0,('Edwards, Shakwana'!I42+'Edwards, Shakwana'!I43)>0)),"Yes","") | I32: =IF('Edwards, Shakwana'!N49>40,"Yes","") | J32: =IF(OR(AND(SUM('Edwards, Shakwana'!I14:I27)>0,SUM('Edwards, Shakwana'!I14:I27)<40),AND(SUM('Edwards, Shakwana'!I30:I43)>0,SUM('Edwards, Shakwana'!I30:I43)<40)),"Yes","") | K32: =SUMPRODUCT(('Edwards, Shakwana'!I14:I48>0)*('Edwards, Shakwana'!I14:I48<8)) | L32: =IF('Edwards, Shakwana'!Q50<5,"Yes","") | M32: =IF(AND('Edwards, Shakwana'!I49>0,'Edwards, Shakwana'!I49<80),"Yes","") | N32: =IF(OR(F32>0,G32="Yes",H32="Yes",I32="Yes"),"⚠️ OVERWORK",IF(OR(J32="Yes",K32>0,L32="Yes",M32="Yes"),"🔻 UNDERWORK","✓ OK"))
A33: 29 | B33: Ferguson, Aubrey Everstein | C33: 73 | D33: ='Ferguson, Aubrey Everstein'!I49 | E33: ='Ferguson, Aubrey Everstein'!Q50 | F33: =SUMPRODUCT((('Ferguson, Aubrey Everstein'!I14+'Ferguson, Aubrey Everstein'!I15)>12)*1)+SUMPRODUCT((('Ferguson, Aubrey Everstein'!I16+'Ferguson, Aubrey Everstein'!I17)>12)*1)+SUMPRODUCT((('Ferguson, Aubrey Everstein'!I18+'Ferguson, Aubrey Everstein'!I19)>12)*1)+SUMPRODUCT((('Ferguson, Aubrey Everstein'!I20+'Ferguson, Aubrey Everstein'!I21)>12)*1)+SUMPRODUCT((('Ferguson, Aubrey Everstein'!I22+'Ferguson, Aubrey Everstein'!I23)>12)*1)+SUMPRODUCT((('Ferguson, Aubrey Everstein'!I24+'Ferguson, Aubrey Everstein'!I25)>12)*1)+SUMPRODUCT((('Ferguson, Aubrey Everstein'!I26+'Ferguson, Aubrey Everstein'!I27)>12)*1)+SUMPRODUCT((('Ferguson, Aubrey Everstein'!I30+'Ferguson, Aubrey Everstein'!I31)>12)*1)+SUMPRODUCT((('Ferguson, Aubrey Everstein'!I32+'Ferguson, Aubrey Everstein'!I33)>12)*1)+SUMPRODUCT((('Ferguson, Aubrey Everstein'!I34+'Ferguson, Aubrey Everstein'!I35)>12)*1)+SUMPRODUCT((('Ferguson, Aubrey Everstein'!I36+'Ferguson, Aubrey Everstein'!I37)>12)*1)+SUMPRODUCT((('Ferguson, Aubrey Everstein'!I38+'Ferguson, Aubrey Everstein'!I39)>12)*1)+SUMPRODUCT((('Ferguson, Aubrey Everstein'!I40+'Ferguson, Aubrey Everstein'!I41)>12)*1)+SUMPRODUCT((('Ferguson, Aubrey Everstein'!I42+'Ferguson, Aubrey Everstein'!I43)>12)*1)+SUMPRODUCT((('Ferguson, Aubrey Everstein'!I45+'Ferguson, Aubrey Everstein'!I46)>12)*1)+SUMPRODUCT((('Ferguson, Aubrey Everstein'!I47+'Ferguson, Aubrey Everstein'!I48)>12)*1) | G33: =IF(MAX(SUM('Ferguson, Aubrey Everstein'!I14:I27),SUM('Ferguson, Aubrey Everstein'!I30:I43))>60,"Yes","") | H33: =IF(OR(AND(('Ferguson, Aubrey Everstein'!I14+'Ferguson, Aubrey Everstein'!I15)>0,('Ferguson, Aubrey Everstein'!I16+'Ferguson, Aubrey Everstein'!I17)>0,('Ferguson, Aubrey Everstein'!I18+'Ferguson, Aubrey Everstein'!I19)>0,('Ferguson, Aubrey Everstein'!I20+'Ferguson, Aubrey Everstein'!I21)>0,('Ferguson, Aubrey Everstein'!I22+'Ferguson, Aubrey Everstein'!I23)>0,('Ferguson, Aubrey Everstein'!I24+'Ferguson, Aubrey Everstein'!I25)>0,('Ferguson, Aubrey Everstein'!I26+'Ferguson, Aubrey Everstein'!I27)>0),AND(('Ferguson, Aubrey Everstein'!I30+'Ferguson, Aubrey Everstein'!I31)>0,('Ferguson, Aubrey Everstein'!I32+'Ferguson, Aubrey Everstein'!I33)>0,('Ferguson, Aubrey Everstein'!I34+'Ferguson, Aubrey Everstein'!I35)>0,('Ferguson, Aubrey Everstein'!I36+'Ferguson, Aubrey Everstein'!I37)>0,('Ferguson, Aubrey Everstein'!I38+'Ferguson, Aubrey Everstein'!I39)>0,('Ferguson, Aubrey Everstein'!I40+'Ferguson, Aubrey Everstein'!I41)>0,('Ferguson, Aubrey Everstein'!I42+'Ferguson, Aubrey Everstein'!I43)>0)),"Yes","") | I33: =IF('Ferguson, Aubrey Everstein'!N49>40,"Yes","") | J33: =IF(OR(AND(SUM('Ferguson, Aubrey Everstein'!I14:I27)>0,SUM('Ferguson, Aubrey Everstein'!I14:I27)<40),AND(SUM('Ferguson, Aubrey Everstein'!I30:I43)>0,SUM('Ferguson, Aubrey Everstein'!I30:I43)<40)),"Yes","") | K33: =SUMPRODUCT(('Ferguson, Aubrey Everstein'!I14:I48>0)*('Ferguson, Aubrey Everstein'!I14:I48<8)) | L33: =IF('Ferguson, Aubrey Everstein'!Q50<5,"Yes","") | M33: =IF(AND('Ferguson, Aubrey Everstein'!I49>0,'Ferguson, Aubrey Everstein'!I49<80),"Yes","") | N33: =IF(OR(F33>0,G33="Yes",H33="Yes",I33="Yes"),"⚠️ OVERWORK",IF(OR(J33="Yes",K33>0,L33="Yes",M33="Yes"),"🔻 UNDERWORK","✓ OK"))
A34: 30 | B34: Gay, Fredline | C34: 5210 | D34: ='Gay, Fredline'!I49 | E34: ='Gay, Fredline'!Q50 | F34: =SUMPRODUCT((('Gay, Fredline'!I14+'Gay, Fredline'!I15)>12)*1)+SUMPRODUCT((('Gay, Fredline'!I16+'Gay, Fredline'!I17)>12)*1)+SUMPRODUCT((('Gay, Fredline'!I18+'Gay, Fredline'!I19)>12)*1)+SUMPRODUCT((('Gay, Fredline'!I20+'Gay, Fredline'!I21)>12)*1)+SUMPRODUCT((('Gay, Fredline'!I22+'Gay, Fredline'!I23)>12)*1)+SUMPRODUCT((('Gay, Fredline'!I24+'Gay, Fredline'!I25)>12)*1)+SUMPRODUCT((('Gay, Fredline'!I26+'Gay, Fredline'!I27)>12)*1)+SUMPRODUCT((('Gay, Fredline'!I30+'Gay, Fredline'!I31)>12)*1)+SUMPRODUCT((('Gay, Fredline'!I32+'Gay, Fredline'!I33)>12)*1)+SUMPRODUCT((('Gay, Fredline'!I34+'Gay, Fredline'!I35)>12)*1)+SUMPRODUCT((('Gay, Fredline'!I36+'Gay, Fredline'!I37)>12)*1)+SUMPRODUCT((('Gay, Fredline'!I38+'Gay, Fredline'!I39)>12)*1)+SUMPRODUCT((('Gay, Fredline'!I40+'Gay, Fredline'!I41)>12)*1)+SUMPRODUCT((('Gay, Fredline'!I42+'Gay, Fredline'!I43)>12)*1)+SUMPRODUCT((('Gay, Fredline'!I45+'Gay, Fredline'!I46)>12)*1)+SUMPRODUCT((('Gay, Fredline'!I47+'Gay, Fredline'!I48)>12)*1) | G34: =IF(MAX(SUM('Gay, Fredline'!I14:I27),SUM('Gay, Fredline'!I30:I43))>60,"Yes","") | H34: =IF(OR(AND(('Gay, Fredline'!I14+'Gay, Fredline'!I15)>0,('Gay, Fredline'!I16+'Gay, Fredline'!I17)>0,('Gay, Fredline'!I18+'Gay, Fredline'!I19)>0,('Gay, Fredline'!I20+'Gay, Fredline'!I21)>0,('Gay, Fredline'!I22+'Gay, Fredline'!I23)>0,('Gay, Fredline'!I24+'Gay, Fredline'!I25)>0,('Gay, Fredline'!I26+'Gay, Fredline'!I27)>0),AND(('Gay, Fredline'!I30+'Gay, Fredline'!I31)>0,('Gay, Fredline'!I32+'Gay, Fredline'!I33)>0,('Gay, Fredline'!I34+'Gay, Fredline'!I35)>0,('Gay, Fredline'!I36+'Gay, Fredline'!I37)>0,('Gay, Fredline'!I38+'Gay, Fredline'!I39)>0,('Gay, Fredline'!I40+'Gay, Fredline'!I41)>0,('Gay, Fredline'!I42+'Gay, Fredline'!I43)>0)),"Yes","") | I34: =IF('Gay, Fredline'!N49>40,"Yes","") | J34: =IF(OR(AND(SUM('Gay, Fredline'!I14:I27)>0,SUM('Gay, Fredline'!I14:I27)<40),AND(SUM('Gay, Fredline'!I30:I43)>0,SUM('Gay, Fredline'!I30:I43)<40)),"Yes","") | K34: =SUMPRODUCT(('Gay, Fredline'!I14:I48>0)*('Gay, Fredline'!I14:I48<8)) | L34: =IF('Gay, Fredline'!Q50<5,"Yes","") | M34: =IF(AND('Gay, Fredline'!I49>0,'Gay, Fredline'!I49<80),"Yes","") | N34: =IF(OR(F34>0,G34="Yes",H34="Yes",I34="Yes"),"⚠️ OVERWORK",IF(OR(J34="Yes",K34>0,L34="Yes",M34="Yes"),"🔻 UNDERWORK","✓ OK"))
A35: 31 | B35: George, Alana Elizabeth | C35: 5223 | D35: ='George, Alana Elizabeth'!I49 | E35: ='George, Alana Elizabeth'!Q50 | F35: =SUMPRODUCT((('George, Alana Elizabeth'!I14+'George, Alana Elizabeth'!I15)>12)*1)+SUMPRODUCT((('George, Alana Elizabeth'!I16+'George, Alana Elizabeth'!I17)>12)*1)+SUMPRODUCT((('George, Alana Elizabeth'!I18+'George, Alana Elizabeth'!I19)>12)*1)+SUMPRODUCT((('George, Alana Elizabeth'!I20+'George, Alana Elizabeth'!I21)>12)*1)+SUMPRODUCT((('George, Alana Elizabeth'!I22+'George, Alana Elizabeth'!I23)>12)*1)+SUMPRODUCT((('George, Alana Elizabeth'!I24+'George, Alana Elizabeth'!I25)>12)*1)+SUMPRODUCT((('George, Alana Elizabeth'!I26+'George, Alana Elizabeth'!I27)>12)*1)+SUMPRODUCT((('George, Alana Elizabeth'!I30+'George, Alana Elizabeth'!I31)>12)*1)+SUMPRODUCT((('George, Alana Elizabeth'!I32+'George, Alana Elizabeth'!I33)>12)*1)+SUMPRODUCT((('George, Alana Elizabeth'!I34+'George, Alana Elizabeth'!I35)>12)*1)+SUMPRODUCT((('George, Alana Elizabeth'!I36+'George, Alana Elizabeth'!I37)>12)*1)+SUMPRODUCT((('George, Alana Elizabeth'!I38+'George, Alana Elizabeth'!I39)>12)*1)+SUMPRODUCT((('George, Alana Elizabeth'!I40+'George, Alana Elizabeth'!I41)>12)*1)+SUMPRODUCT((('George, Alana Elizabeth'!I42+'George, Alana Elizabeth'!I43)>12)*1)+SUMPRODUCT((('George, Alana Elizabeth'!I45+'George, Alana Elizabeth'!I46)>12)*1)+SUMPRODUCT((('George, Alana Elizabeth'!I47+'George, Alana Elizabeth'!I48)>12)*1) | G35: =IF(MAX(SUM('George, Alana Elizabeth'!I14:I27),SUM('George, Alana Elizabeth'!I30:I43))>60,"Yes","") | H35: =IF(OR(AND(('George, Alana Elizabeth'!I14+'George, Alana Elizabeth'!I15)>0,('George, Alana Elizabeth'!I16+'George, Alana Elizabeth'!I17)>0,('George, Alana Elizabeth'!I18+'George, Alana Elizabeth'!I19)>0,('George, Alana Elizabeth'!I20+'George, Alana Elizabeth'!I21)>0,('George, Alana Elizabeth'!I22+'George, Alana Elizabeth'!I23)>0,('George, Alana Elizabeth'!I24+'George, Alana Elizabeth'!I25)>0,('George, Alana Elizabeth'!I26+'George, Alana Elizabeth'!I27)>0),AND(('George, Alana Elizabeth'!I30+'George, Alana Elizabeth'!I31)>0,('George, Alana Elizabeth'!I32+'George, Alana Elizabeth'!I33)>0,('George, Alana Elizabeth'!I34+'George, Alana Elizabeth'!I35)>0,('George, Alana Elizabeth'!I36+'George, Alana Elizabeth'!I37)>0,('George, Alana Elizabeth'!I38+'George, Alana Elizabeth'!I39)>0,('George, Alana Elizabeth'!I40+'George, Alana Elizabeth'!I41)>0,('George, Alana Elizabeth'!I42+'George, Alana Elizabeth'!I43)>0)),"Yes","") | I35: =IF('George, Alana Elizabeth'!N49>40,"Yes","") | J35: =IF(OR(AND(SUM('George, Alana Elizabeth'!I14:I27)>0,SUM('George, Alana Elizabeth'!I14:I27)<40),AND(SUM('George, Alana Elizabeth'!I30:I43)>0,SUM('George, Alana Elizabeth'!I30:I43)<40)),"Yes","") | K35: =SUMPRODUCT(('George, Alana Elizabeth'!I14:I48>0)*('George, Alana Elizabeth'!I14:I48<8)) | L35: =IF('George, Alana Elizabeth'!Q50<5,"Yes","") | M35: =IF(AND('George, Alana Elizabeth'!I49>0,'George, Alana Elizabeth'!I49<80),"Yes","") | N35: =IF(OR(F35>0,G35="Yes",H35="Yes",I35="Yes"),"⚠️ OVERWORK",IF(OR(J35="Yes",K35>0,L35="Yes",M35="Yes"),"🔻 UNDERWORK","✓ OK"))
A36: 32 | B36: Glenn, Tonette Tessa | C36: 5527 | D36: ='Glenn, Tonette Tessa'!I49 | E36: ='Glenn, Tonette Tessa'!Q50 | F36: =SUMPRODUCT((('Glenn, Tonette Tessa'!I14+'Glenn, Tonette Tessa'!I15)>12)*1)+SUMPRODUCT((('Glenn, Tonette Tessa'!I16+'Glenn, Tonette Tessa'!I17)>12)*1)+SUMPRODUCT((('Glenn, Tonette Tessa'!I18+'Glenn, Tonette Tessa'!I19)>12)*1)+SUMPRODUCT((('Glenn, Tonette Tessa'!I20+'Glenn, Tonette Tessa'!I21)>12)*1)+SUMPRODUCT((('Glenn, Tonette Tessa'!I22+'Glenn, Tonette Tessa'!I23)>12)*1)+SUMPRODUCT((('Glenn, Tonette Tessa'!I24+'Glenn, Tonette Tessa'!I25)>12)*1)+SUMPRODUCT((('Glenn, Tonette Tessa'!I26+'Glenn, Tonette Tessa'!I27)>12)*1)+SUMPRODUCT((('Glenn, Tonette Tessa'!I30+'Glenn, Tonette Tessa'!I31)>12)*1)+SUMPRODUCT((('Glenn, Tonette Tessa'!I32+'Glenn, Tonette Tessa'!I33)>12)*1)+SUMPRODUCT((('Glenn, Tonette Tessa'!I34+'Glenn, Tonette Tessa'!I35)>12)*1)+SUMPRODUCT((('Glenn, Tonette Tessa'!I36+'Glenn, Tonette Tessa'!I37)>12)*1)+SUMPRODUCT((('Glenn, Tonette Tessa'!I38+'Glenn, Tonette Tessa'!I39)>12)*1)+SUMPRODUCT((('Glenn, Tonette Tessa'!I40+'Glenn, Tonette Tessa'!I41)>12)*1)+SUMPRODUCT((('Glenn, Tonette Tessa'!I42+'Glenn, Tonette Tessa'!I43)>12)*1)+SUMPRODUCT((('Glenn, Tonette Tessa'!I45+'Glenn, Tonette Tessa'!I46)>12)*1)+SUMPRODUCT((('Glenn, Tonette Tessa'!I47+'Glenn, Tonette Tessa'!I48)>12)*1) | G36: =IF(MAX(SUM('Glenn, Tonette Tessa'!I14:I27),SUM('Glenn, Tonette Tessa'!I30:I43))>60,"Yes","") | H36: =IF(OR(AND(('Glenn, Tonette Tessa'!I14+'Glenn, Tonette Tessa'!I15)>0,('Glenn, Tonette Tessa'!I16+'Glenn, Tonette Tessa'!I17)>0,('Glenn, Tonette Tessa'!I18+'Glenn, Tonette Tessa'!I19)>0,('Glenn, Tonette Tessa'!I20+'Glenn, Tonette Tessa'!I21)>0,('Glenn, Tonette Tessa'!I22+'Glenn, Tonette Tessa'!I23)>0,('Glenn, Tonette Tessa'!I24+'Glenn, Tonette Tessa'!I25)>0,('Glenn, Tonette Tessa'!I26+'Glenn, Tonette Tessa'!I27)>0),AND(('Glenn, Tonette Tessa'!I30+'Glenn, Tonette Tessa'!I31)>0,('Glenn, Tonette Tessa'!I32+'Glenn, Tonette Tessa'!I33)>0,('Glenn, Tonette Tessa'!I34+'Glenn, Tonette Tessa'!I35)>0,('Glenn, Tonette Tessa'!I36+'Glenn, Tonette Tessa'!I37)>0,('Glenn, Tonette Tessa'!I38+'Glenn, Tonette Tessa'!I39)>0,('Glenn, Tonette Tessa'!I40+'Glenn, Tonette Tessa'!I41)>0,('Glenn, Tonette Tessa'!I42+'Glenn, Tonette Tessa'!I43)>0)),"Yes","") | I36: =IF('Glenn, Tonette Tessa'!N49>40,"Yes","") | J36: =IF(OR(AND(SUM('Glenn, Tonette Tessa'!I14:I27)>0,SUM('Glenn, Tonette Tessa'!I14:I27)<40),AND(SUM('Glenn, Tonette Tessa'!I30:I43)>0,SUM('Glenn, Tonette Tessa'!I30:I43)<40)),"Yes","") | K36: =SUMPRODUCT(('Glenn, Tonette Tessa'!I14:I48>0)*('Glenn, Tonette Tessa'!I14:I48<8)) | L36: =IF('Glenn, Tonette Tessa'!Q50<5,"Yes","") | M36: =IF(AND('Glenn, Tonette Tessa'!I49>0,'Glenn, Tonette Tessa'!I49<80),"Yes","") | N36: =IF(OR(F36>0,G36="Yes",H36="Yes",I36="Yes"),"⚠️ OVERWORK",IF(OR(J36="Yes",K36>0,L36="Yes",M36="Yes"),"🔻 UNDERWORK","✓ OK"))
A37: 33 | B37: Gordon, Kim Natasha | C37: 4176 | D37: ='Gordon, Kim Natasha'!I49 | E37: ='Gordon, Kim Natasha'!Q50 | F37: =SUMPRODUCT((('Gordon, Kim Natasha'!I14+'Gordon, Kim Natasha'!I15)>12)*1)+SUMPRODUCT((('Gordon, Kim Natasha'!I16+'Gordon, Kim Natasha'!I17)>12)*1)+SUMPRODUCT((('Gordon, Kim Natasha'!I18+'Gordon, Kim Natasha'!I19)>12)*1)+SUMPRODUCT((('Gordon, Kim Natasha'!I20+'Gordon, Kim Natasha'!I21)>12)*1)+SUMPRODUCT((('Gordon, Kim Natasha'!I22+'Gordon, Kim Natasha'!I23)>12)*1)+SUMPRODUCT((('Gordon, Kim Natasha'!I24+'Gordon, Kim Natasha'!I25)>12)*1)+SUMPRODUCT((('Gordon, Kim Natasha'!I26+'Gordon, Kim Natasha'!I27)>12)*1)+SUMPRODUCT((('Gordon, Kim Natasha'!I30+'Gordon, Kim Natasha'!I31)>12)*1)+SUMPRODUCT((('Gordon, Kim Natasha'!I32+'Gordon, Kim Natasha'!I33)>12)*1)+SUMPRODUCT((('Gordon, Kim Natasha'!I34+'Gordon, Kim Natasha'!I35)>12)*1)+SUMPRODUCT((('Gordon, Kim Natasha'!I36+'Gordon, Kim Natasha'!I37)>12)*1)+SUMPRODUCT((('Gordon, Kim Natasha'!I38+'Gordon, Kim Natasha'!I39)>12)*1)+SUMPRODUCT((('Gordon, Kim Natasha'!I40+'Gordon, Kim Natasha'!I41)>12)*1)+SUMPRODUCT((('Gordon, Kim Natasha'!I42+'Gordon, Kim Natasha'!I43)>12)*1)+SUMPRODUCT((('Gordon, Kim Natasha'!I45+'Gordon, Kim Natasha'!I46)>12)*1)+SUMPRODUCT((('Gordon, Kim Natasha'!I47+'Gordon, Kim Natasha'!I48)>12)*1) | G37: =IF(MAX(SUM('Gordon, Kim Natasha'!I14:I27),SUM('Gordon, Kim Natasha'!I30:I43))>60,"Yes","") | H37: =IF(OR(AND(('Gordon, Kim Natasha'!I14+'Gordon, Kim Natasha'!I15)>0,('Gordon, Kim Natasha'!I16+'Gordon, Kim Natasha'!I17)>0,('Gordon, Kim Natasha'!I18+'Gordon, Kim Natasha'!I19)>0,('Gordon, Kim Natasha'!I20+'Gordon, Kim Natasha'!I21)>0,('Gordon, Kim Natasha'!I22+'Gordon, Kim Natasha'!I23)>0,('Gordon, Kim Natasha'!I24+'Gordon, Kim Natasha'!I25)>0,('Gordon, Kim Natasha'!I26+'Gordon, Kim Natasha'!I27)>0),AND(('Gordon, Kim Natasha'!I30+'Gordon, Kim Natasha'!I31)>0,('Gordon, Kim Natasha'!I32+'Gordon, Kim Natasha'!I33)>0,('Gordon, Kim Natasha'!I34+'Gordon, Kim Natasha'!I35)>0,('Gordon, Kim Natasha'!I36+'Gordon, Kim Natasha'!I37)>0,('Gordon, Kim Natasha'!I38+'Gordon, Kim Natasha'!I39)>0,('Gordon, Kim Natasha'!I40+'Gordon, Kim Natasha'!I41)>0,('Gordon, Kim Natasha'!I42+'Gordon, Kim Natasha'!I43)>0)),"Yes","") | I37: =IF('Gordon, Kim Natasha'!N49>40,"Yes","") | J37: =IF(OR(AND(SUM('Gordon, Kim Natasha'!I14:I27)>0,SUM('Gordon, Kim Natasha'!I14:I27)<40),AND(SUM('Gordon, Kim Natasha'!I30:I43)>0,SUM('Gordon, Kim Natasha'!I30:I43)<40)),"Yes","") | K37: =SUMPRODUCT(('Gordon, Kim Natasha'!I14:I48>0)*('Gordon, Kim Natasha'!I14:I48<8)) | L37: =IF('Gordon, Kim Natasha'!Q50<5,"Yes","") | M37: =IF(AND('Gordon, Kim Natasha'!I49>0,'Gordon, Kim Natasha'!I49<80),"Yes","") | N37: =IF(OR(F37>0,G37="Yes",H37="Yes",I37="Yes"),"⚠️ OVERWORK",IF(OR(J37="Yes",K37>0,L37="Yes",M37="Yes"),"🔻 UNDERWORK","✓ OK"))
A38: 34 | B38: Gordon, Mijah Ulanna | C38: 5524 | D38: ='Gordon, Mijah Ulanna'!I49 | E38: ='Gordon, Mijah Ulanna'!Q50 | F38: =SUMPRODUCT((('Gordon, Mijah Ulanna'!I14+'Gordon, Mijah Ulanna'!I15)>12)*1)+SUMPRODUCT((('Gordon, Mijah Ulanna'!I16+'Gordon, Mijah Ulanna'!I17)>12)*1)+SUMPRODUCT((('Gordon, Mijah Ulanna'!I18+'Gordon, Mijah Ulanna'!I19)>12)*1)+SUMPRODUCT((('Gordon, Mijah Ulanna'!I20+'Gordon, Mijah Ulanna'!I21)>12)*1)+SUMPRODUCT((('Gordon, Mijah Ulanna'!I22+'Gordon, Mijah Ulanna'!I23)>12)*1)+SUMPRODUCT((('Gordon, Mijah Ulanna'!I24+'Gordon, Mijah Ulanna'!I25)>12)*1)+SUMPRODUCT((('Gordon, Mijah Ulanna'!I26+'Gordon, Mijah Ulanna'!I27)>12)*1)+SUMPRODUCT((('Gordon, Mijah Ulanna'!I30+'Gordon, Mijah Ulanna'!I31)>12)*1)+SUMPRODUCT((('Gordon, Mijah Ulanna'!I32+'Gordon, Mijah Ulanna'!I33)>12)*1)+SUMPRODUCT((('Gordon, Mijah Ulanna'!I34+'Gordon, Mijah Ulanna'!I35)>12)*1)+SUMPRODUCT((('Gordon, Mijah Ulanna'!I36+'Gordon, Mijah Ulanna'!I37)>12)*1)+SUMPRODUCT((('Gordon, Mijah Ulanna'!I38+'Gordon, Mijah Ulanna'!I39)>12)*1)+SUMPRODUCT((('Gordon, Mijah Ulanna'!I40+'Gordon, Mijah Ulanna'!I41)>12)*1)+SUMPRODUCT((('Gordon, Mijah Ulanna'!I42+'Gordon, Mijah Ulanna'!I43)>12)*1)+SUMPRODUCT((('Gordon, Mijah Ulanna'!I45+'Gordon, Mijah Ulanna'!I46)>12)*1)+SUMPRODUCT((('Gordon, Mijah Ulanna'!I47+'Gordon, Mijah Ulanna'!I48)>12)*1) | G38: =IF(MAX(SUM('Gordon, Mijah Ulanna'!I14:I27),SUM('Gordon, Mijah Ulanna'!I30:I43))>60,"Yes","") | H38: =IF(OR(AND(('Gordon, Mijah Ulanna'!I14+'Gordon, Mijah Ulanna'!I15)>0,('Gordon, Mijah Ulanna'!I16+'Gordon, Mijah Ulanna'!I17)>0,('Gordon, Mijah Ulanna'!I18+'Gordon, Mijah Ulanna'!I19)>0,('Gordon, Mijah Ulanna'!I20+'Gordon, Mijah Ulanna'!I21)>0,('Gordon, Mijah Ulanna'!I22+'Gordon, Mijah Ulanna'!I23)>0,('Gordon, Mijah Ulanna'!I24+'Gordon, Mijah Ulanna'!I25)>0,('Gordon, Mijah Ulanna'!I26+'Gordon, Mijah Ulanna'!I27)>0),AND(('Gordon, Mijah Ulanna'!I30+'Gordon, Mijah Ulanna'!I31)>0,('Gordon, Mijah Ulanna'!I32+'Gordon, Mijah Ulanna'!I33)>0,('Gordon, Mijah Ulanna'!I34+'Gordon, Mijah Ulanna'!I35)>0,('Gordon, Mijah Ulanna'!I36+'Gordon, Mijah Ulanna'!I37)>0,('Gordon, Mijah Ulanna'!I38+'Gordon, Mijah Ulanna'!I39)>0,('Gordon, Mijah Ulanna'!I40+'Gordon, Mijah Ulanna'!I41)>0,('Gordon, Mijah Ulanna'!I42+'Gordon, Mijah Ulanna'!I43)>0)),"Yes","") | I38: =IF('Gordon, Mijah Ulanna'!N49>40,"Yes","") | J38: =IF(OR(AND(SUM('Gordon, Mijah Ulanna'!I14:I27)>0,SUM('Gordon, Mijah Ulanna'!I14:I27)<40),AND(SUM('Gordon, Mijah Ulanna'!I30:I43)>0,SUM('Gordon, Mijah Ulanna'!I30:I43)<40)),"Yes","") | K38: =SUMPRODUCT(('Gordon, Mijah Ulanna'!I14:I48>0)*('Gordon, Mijah Ulanna'!I14:I48<8)) | L38: =IF('Gordon, Mijah Ulanna'!Q50<5,"Yes","") | M38: =IF(AND('Gordon, Mijah Ulanna'!I49>0,'Gordon, Mijah Ulanna'!I49<80),"Yes","") | N38: =IF(OR(F38>0,G38="Yes",H38="Yes",I38="Yes"),"⚠️ OVERWORK",IF(OR(J38="Yes",K38>0,L38="Yes",M38="Yes"),"🔻 UNDERWORK","✓ OK"))
A39: 35 | B39: Greaves, George Anthony | C39: 5517 | D39: ='Greaves, George Anthony'!I49 | E39: ='Greaves, George Anthony'!Q50 | F39: =SUMPRODUCT((('Greaves, George Anthony'!I14+'Greaves, George Anthony'!I15)>12)*1)+SUMPRODUCT((('Greaves, George Anthony'!I16+'Greaves, George Anthony'!I17)>12)*1)+SUMPRODUCT((('Greaves, George Anthony'!I18+'Greaves, George Anthony'!I19)>12)*1)+SUMPRODUCT((('Greaves, George Anthony'!I20+'Greaves, George Anthony'!I21)>12)*1)+SUMPRODUCT((('Greaves, George Anthony'!I22+'Greaves, George Anthony'!I23)>12)*1)+SUMPRODUCT((('Greaves, George Anthony'!I24+'Greaves, George Anthony'!I25)>12)*1)+SUMPRODUCT((('Greaves, George Anthony'!I26+'Greaves, George Anthony'!I27)>12)*1)+SUMPRODUCT((('Greaves, George Anthony'!I30+'Greaves, George Anthony'!I31)>12)*1)+SUMPRODUCT((('Greaves, George Anthony'!I32+'Greaves, George Anthony'!I33)>12)*1)+SUMPRODUCT((('Greaves, George Anthony'!I34+'Greaves, George Anthony'!I35)>12)*1)+SUMPRODUCT((('Greaves, George Anthony'!I36+'Greaves, George Anthony'!I37)>12)*1)+SUMPRODUCT((('Greaves, George Anthony'!I38+'Greaves, George Anthony'!I39)>12)*1)+SUMPRODUCT((('Greaves, George Anthony'!I40+'Greaves, George Anthony'!I41)>12)*1)+SUMPRODUCT((('Greaves, George Anthony'!I42+'Greaves, George Anthony'!I43)>12)*1)+SUMPRODUCT((('Greaves, George Anthony'!I45+'Greaves, George Anthony'!I46)>12)*1)+SUMPRODUCT((('Greaves, George Anthony'!I47+'Greaves, George Anthony'!I48)>12)*1) | G39: =IF(MAX(SUM('Greaves, George Anthony'!I14:I27),SUM('Greaves, George Anthony'!I30:I43))>60,"Yes","") | H39: =IF(OR(AND(('Greaves, George Anthony'!I14+'Greaves, George Anthony'!I15)>0,('Greaves, George Anthony'!I16+'Greaves, George Anthony'!I17)>0,('Greaves, George Anthony'!I18+'Greaves, George Anthony'!I19)>0,('Greaves, George Anthony'!I20+'Greaves, George Anthony'!I21)>0,('Greaves, George Anthony'!I22+'Greaves, George Anthony'!I23)>0,('Greaves, George Anthony'!I24+'Greaves, George Anthony'!I25)>0,('Greaves, George Anthony'!I26+'Greaves, George Anthony'!I27)>0),AND(('Greaves, George Anthony'!I30+'Greaves, George Anthony'!I31)>0,('Greaves, George Anthony'!I32+'Greaves, George Anthony'!I33)>0,('Greaves, George Anthony'!I34+'Greaves, George Anthony'!I35)>0,('Greaves, George Anthony'!I36+'Greaves, George Anthony'!I37)>0,('Greaves, George Anthony'!I38+'Greaves, George Anthony'!I39)>0,('Greaves, George Anthony'!I40+'Greaves, George Anthony'!I41)>0,('Greaves, George Anthony'!I42+'Greaves, George Anthony'!I43)>0)),"Yes","") | I39: =IF('Greaves, George Anthony'!N49>40,"Yes","") | J39: =IF(OR(AND(SUM('Greaves, George Anthony'!I14:I27)>0,SUM('Greaves, George Anthony'!I14:I27)<40),AND(SUM('Greaves, George Anthony'!I30:I43)>0,SUM('Greaves, George Anthony'!I30:I43)<40)),"Yes","") | K39: =SUMPRODUCT(('Greaves, George Anthony'!I14:I48>0)*('Greaves, George Anthony'!I14:I48<8)) | L39: =IF('Greaves, George Anthony'!Q50<5,"Yes","") | M39: =IF(AND('Greaves, George Anthony'!I49>0,'Greaves, George Anthony'!I49<80),"Yes","") | N39: =IF(OR(F39>0,G39="Yes",H39="Yes",I39="Yes"),"⚠️ OVERWORK",IF(OR(J39="Yes",K39>0,L39="Yes",M39="Yes"),"🔻 UNDERWORK","✓ OK"))
A40: 36 | B40: Griffith, Richard Darc | C40: 4703 | D40: ='Griffith, Richard Darc'!I49 | E40: ='Griffith, Richard Darc'!Q50 | F40: =SUMPRODUCT((('Griffith, Richard Darc'!I14+'Griffith, Richard Darc'!I15)>12)*1)+SUMPRODUCT((('Griffith, Richard Darc'!I16+'Griffith, Richard Darc'!I17)>12)*1)+SUMPRODUCT((('Griffith, Richard Darc'!I18+'Griffith, Richard Darc'!I19)>12)*1)+SUMPRODUCT((('Griffith, Richard Darc'!I20+'Griffith, Richard Darc'!I21)>12)*1)+SUMPRODUCT((('Griffith, Richard Darc'!I22+'Griffith, Richard Darc'!I23)>12)*1)+SUMPRODUCT((('Griffith, Richard Darc'!I24+'Griffith, Richard Darc'!I25)>12)*1)+SUMPRODUCT((('Griffith, Richard Darc'!I26+'Griffith, Richard Darc'!I27)>12)*1)+SUMPRODUCT((('Griffith, Richard Darc'!I30+'Griffith, Richard Darc'!I31)>12)*1)+SUMPRODUCT((('Griffith, Richard Darc'!I32+'Griffith, Richard Darc'!I33)>12)*1)+SUMPRODUCT((('Griffith, Richard Darc'!I34+'Griffith, Richard Darc'!I35)>12)*1)+SUMPRODUCT((('Griffith, Richard Darc'!I36+'Griffith, Richard Darc'!I37)>12)*1)+SUMPRODUCT((('Griffith, Richard Darc'!I38+'Griffith, Richard Darc'!I39)>12)*1)+SUMPRODUCT((('Griffith, Richard Darc'!I40+'Griffith, Richard Darc'!I41)>12)*1)+SUMPRODUCT((('Griffith, Richard Darc'!I42+'Griffith, Richard Darc'!I43)>12)*1)+SUMPRODUCT((('Griffith, Richard Darc'!I45+'Griffith, Richard Darc'!I46)>12)*1)+SUMPRODUCT((('Griffith, Richard Darc'!I47+'Griffith, Richard Darc'!I48)>12)*1) | G40: =IF(MAX(SUM('Griffith, Richard Darc'!I14:I27),SUM('Griffith, Richard Darc'!I30:I43))>60,"Yes","") | H40: =IF(OR(AND(('Griffith, Richard Darc'!I14+'Griffith, Richard Darc'!I15)>0,('Griffith, Richard Darc'!I16+'Griffith, Richard Darc'!I17)>0,('Griffith, Richard Darc'!I18+'Griffith, Richard Darc'!I19)>0,('Griffith, Richard Darc'!I20+'Griffith, Richard Darc'!I21)>0,('Griffith, Richard Darc'!I22+'Griffith, Richard Darc'!I23)>0,('Griffith, Richard Darc'!I24+'Griffith, Richard Darc'!I25)>0,('Griffith, Richard Darc'!I26+'Griffith, Richard Darc'!I27)>0),AND(('Griffith, Richard Darc'!I30+'Griffith, Richard Darc'!I31)>0,('Griffith, Richard Darc'!I32+'Griffith, Richard Darc'!I33)>0,('Griffith, Richard Darc'!I34+'Griffith, Richard Darc'!I35)>0,('Griffith, Richard Darc'!I36+'Griffith, Richard Darc'!I37)>0,('Griffith, Richard Darc'!I38+'Griffith, Richard Darc'!I39)>0,('Griffith, Richard Darc'!I40+'Griffith, Richard Darc'!I41)>0,('Griffith, Richard Darc'!I42+'Griffith, Richard Darc'!I43)>0)),"Yes","") | I40: =IF('Griffith, Richard Darc'!N49>40,"Yes","") | J40: =IF(OR(AND(SUM('Griffith, Richard Darc'!I14:I27)>0,SUM('Griffith, Richard Darc'!I14:I27)<40),AND(SUM('Griffith, Richard Darc'!I30:I43)>0,SUM('Griffith, Richard Darc'!I30:I43)<40)),"Yes","") | K40: =SUMPRODUCT(('Griffith, Richard Darc'!I14:I48>0)*('Griffith, Richard Darc'!I14:I48<8)) | L40: =IF('Griffith, Richard Darc'!Q50<5,"Yes","") | M40: =IF(AND('Griffith, Richard Darc'!I49>0,'Griffith, Richard Darc'!I49<80),"Yes","") | N40: =IF(OR(F40>0,G40="Yes",H40="Yes",I40="Yes"),"⚠️ OVERWORK",IF(OR(J40="Yes",K40>0,L40="Yes",M40="Yes"),"🔻 UNDERWORK","✓ OK"))
A41: 37 | B41: Guillaume, Ruschama | C41: 5482 | D41: ='Guillaume, Ruschama'!I49 | E41: ='Guillaume, Ruschama'!Q50 | F41: =SUMPRODUCT((('Guillaume, Ruschama'!I14+'Guillaume, Ruschama'!I15)>12)*1)+SUMPRODUCT((('Guillaume, Ruschama'!I16+'Guillaume, Ruschama'!I17)>12)*1)+SUMPRODUCT((('Guillaume, Ruschama'!I18+'Guillaume, Ruschama'!I19)>12)*1)+SUMPRODUCT((('Guillaume, Ruschama'!I20+'Guillaume, Ruschama'!I21)>12)*1)+SUMPRODUCT((('Guillaume, Ruschama'!I22+'Guillaume, Ruschama'!I23)>12)*1)+SUMPRODUCT((('Guillaume, Ruschama'!I24+'Guillaume, Ruschama'!I25)>12)*1)+SUMPRODUCT((('Guillaume, Ruschama'!I26+'Guillaume, Ruschama'!I27)>12)*1)+SUMPRODUCT((('Guillaume, Ruschama'!I30+'Guillaume, Ruschama'!I31)>12)*1)+SUMPRODUCT((('Guillaume, Ruschama'!I32+'Guillaume, Ruschama'!I33)>12)*1)+SUMPRODUCT((('Guillaume, Ruschama'!I34+'Guillaume, Ruschama'!I35)>12)*1)+SUMPRODUCT((('Guillaume, Ruschama'!I36+'Guillaume, Ruschama'!I37)>12)*1)+SUMPRODUCT((('Guillaume, Ruschama'!I38+'Guillaume, Ruschama'!I39)>12)*1)+SUMPRODUCT((('Guillaume, Ruschama'!I40+'Guillaume, Ruschama'!I41)>12)*1)+SUMPRODUCT((('Guillaume, Ruschama'!I42+'Guillaume, Ruschama'!I43)>12)*1)+SUMPRODUCT((('Guillaume, Ruschama'!I45+'Guillaume, Ruschama'!I46)>12)*1)+SUMPRODUCT((('Guillaume, Ruschama'!I47+'Guillaume, Ruschama'!I48)>12)*1) | G41: =IF(MAX(SUM('Guillaume, Ruschama'!I14:I27),SUM('Guillaume, Ruschama'!I30:I43))>60,"Yes","") | H41: =IF(OR(AND(('Guillaume, Ruschama'!I14+'Guillaume, Ruschama'!I15)>0,('Guillaume, Ruschama'!I16+'Guillaume, Ruschama'!I17)>0,('Guillaume, Ruschama'!I18+'Guillaume, Ruschama'!I19)>0,('Guillaume, Ruschama'!I20+'Guillaume, Ruschama'!I21)>0,('Guillaume, Ruschama'!I22+'Guillaume, Ruschama'!I23)>0,('Guillaume, Ruschama'!I24+'Guillaume, Ruschama'!I25)>0,('Guillaume, Ruschama'!I26+'Guillaume, Ruschama'!I27)>0),AND(('Guillaume, Ruschama'!I30+'Guillaume, Ruschama'!I31)>0,('Guillaume, Ruschama'!I32+'Guillaume, Ruschama'!I33)>0,('Guillaume, Ruschama'!I34+'Guillaume, Ruschama'!I35)>0,('Guillaume, Ruschama'!I36+'Guillaume, Ruschama'!I37)>0,('Guillaume, Ruschama'!I38+'Guillaume, Ruschama'!I39)>0,('Guillaume, Ruschama'!I40+'Guillaume, Ruschama'!I41)>0,('Guillaume, Ruschama'!I42+'Guillaume, Ruschama'!I43)>0)),"Yes","") | I41: =IF('Guillaume, Ruschama'!N49>40,"Yes","") | J41: =IF(OR(AND(SUM('Guillaume, Ruschama'!I14:I27)>0,SUM('Guillaume, Ruschama'!I14:I27)<40),AND(SUM('Guillaume, Ruschama'!I30:I43)>0,SUM('Guillaume, Ruschama'!I30:I43)<40)),"Yes","") | K41: =SUMPRODUCT(('Guillaume, Ruschama'!I14:I48>0)*('Guillaume, Ruschama'!I14:I48<8)) | L41: =IF('Guillaume, Ruschama'!Q50<5,"Yes","") | M41: =IF(AND('Guillaume, Ruschama'!I49>0,'Guillaume, Ruschama'!I49<80),"Yes","") | N41: =IF(OR(F41>0,G41="Yes",H41="Yes",I41="Yes"),"⚠️ OVERWORK",IF(OR(J41="Yes",K41>0,L41="Yes",M41="Yes"),"🔻 UNDERWORK","✓ OK"))
A42: 38 | B42: Halley, Sherian Patricia | C42: 5396 | D42: ='Halley, Sherian Patricia'!I49 | E42: ='Halley, Sherian Patricia'!Q50 | F42: =SUMPRODUCT((('Halley, Sherian Patricia'!I14+'Halley, Sherian Patricia'!I15)>12)*1)+SUMPRODUCT((('Halley, Sherian Patricia'!I16+'Halley, Sherian Patricia'!I17)>12)*1)+SUMPRODUCT((('Halley, Sherian Patricia'!I18+'Halley, Sherian Patricia'!I19)>12)*1)+SUMPRODUCT((('Halley, Sherian Patricia'!I20+'Halley, Sherian Patricia'!I21)>12)*1)+SUMPRODUCT((('Halley, Sherian Patricia'!I22+'Halley, Sherian Patricia'!I23)>12)*1)+SUMPRODUCT((('Halley, Sherian Patricia'!I24+'Halley, Sherian Patricia'!I25)>12)*1)+SUMPRODUCT((('Halley, Sherian Patricia'!I26+'Halley, Sherian Patricia'!I27)>12)*1)+SUMPRODUCT((('Halley, Sherian Patricia'!I30+'Halley, Sherian Patricia'!I31)>12)*1)+SUMPRODUCT((('Halley, Sherian Patricia'!I32+'Halley, Sherian Patricia'!I33)>12)*1)+SUMPRODUCT((('Halley, Sherian Patricia'!I34+'Halley, Sherian Patricia'!I35)>12)*1)+SUMPRODUCT((('Halley, Sherian Patricia'!I36+'Halley, Sherian Patricia'!I37)>12)*1)+SUMPRODUCT((('Halley, Sherian Patricia'!I38+'Halley, Sherian Patricia'!I39)>12)*1)+SUMPRODUCT((('Halley, Sherian Patricia'!I40+'Halley, Sherian Patricia'!I41)>12)*1)+SUMPRODUCT((('Halley, Sherian Patricia'!I42+'Halley, Sherian Patricia'!I43)>12)*1)+SUMPRODUCT((('Halley, Sherian Patricia'!I45+'Halley, Sherian Patricia'!I46)>12)*1)+SUMPRODUCT((('Halley, Sherian Patricia'!I47+'Halley, Sherian Patricia'!I48)>12)*1) | G42: =IF(MAX(SUM('Halley, Sherian Patricia'!I14:I27),SUM('Halley, Sherian Patricia'!I30:I43))>60,"Yes","") | H42: =IF(OR(AND(('Halley, Sherian Patricia'!I14+'Halley, Sherian Patricia'!I15)>0,('Halley, Sherian Patricia'!I16+'Halley, Sherian Patricia'!I17)>0,('Halley, Sherian Patricia'!I18+'Halley, Sherian Patricia'!I19)>0,('Halley, Sherian Patricia'!I20+'Halley, Sherian Patricia'!I21)>0,('Halley, Sherian Patricia'!I22+'Halley, Sherian Patricia'!I23)>0,('Halley, Sherian Patricia'!I24+'Halley, Sherian Patricia'!I25)>0,('Halley, Sherian Patricia'!I26+'Halley, Sherian Patricia'!I27)>0),AND(('Halley, Sherian Patricia'!I30+'Halley, Sherian Patricia'!I31)>0,('Halley, Sherian Patricia'!I32+'Halley, Sherian Patricia'!I33)>0,('Halley, Sherian Patricia'!I34+'Halley, Sherian Patricia'!I35)>0,('Halley, Sherian Patricia'!I36+'Halley, Sherian Patricia'!I37)>0,('Halley, Sherian Patricia'!I38+'Halley, Sherian Patricia'!I39)>0,('Halley, Sherian Patricia'!I40+'Halley, Sherian Patricia'!I41)>0,('Halley, Sherian Patricia'!I42+'Halley, Sherian Patricia'!I43)>0)),"Yes","") | I42: =IF('Halley, Sherian Patricia'!N49>40,"Yes","") | J42: =IF(OR(AND(SUM('Halley, Sherian Patricia'!I14:I27)>0,SUM('Halley, Sherian Patricia'!I14:I27)<40),AND(SUM('Halley, Sherian Patricia'!I30:I43)>0,SUM('Halley, Sherian Patricia'!I30:I43)<40)),"Yes","") | K42: =SUMPRODUCT(('Halley, Sherian Patricia'!I14:I48>0)*('Halley, Sherian Patricia'!I14:I48<8)) | L42: =IF('Halley, Sherian Patricia'!Q50<5,"Yes","") | M42: =IF(AND('Halley, Sherian Patricia'!I49>0,'Halley, Sherian Patricia'!I49<80),"Yes","") | N42: =IF(OR(F42>0,G42="Yes",H42="Yes",I42="Yes"),"⚠️ OVERWORK",IF(OR(J42="Yes",K42>0,L42="Yes",M42="Yes"),"🔻 UNDERWORK","✓ OK"))
A43: 39 | B43: Haynes, Beryl | C43: 2687 | D43: ='Haynes, Beryl'!I49 | E43: ='Haynes, Beryl'!Q50 | F43: =SUMPRODUCT((('Haynes, Beryl'!I14+'Haynes, Beryl'!I15)>12)*1)+SUMPRODUCT((('Haynes, Beryl'!I16+'Haynes, Beryl'!I17)>12)*1)+SUMPRODUCT((('Haynes, Beryl'!I18+'Haynes, Beryl'!I19)>12)*1)+SUMPRODUCT((('Haynes, Beryl'!I20+'Haynes, Beryl'!I21)>12)*1)+SUMPRODUCT((('Haynes, Beryl'!I22+'Haynes, Beryl'!I23)>12)*1)+SUMPRODUCT((('Haynes, Beryl'!I24+'Haynes, Beryl'!I25)>12)*1)+SUMPRODUCT((('Haynes, Beryl'!I26+'Haynes, Beryl'!I27)>12)*1)+SUMPRODUCT((('Haynes, Beryl'!I30+'Haynes, Beryl'!I31)>12)*1)+SUMPRODUCT((('Haynes, Beryl'!I32+'Haynes, Beryl'!I33)>12)*1)+SUMPRODUCT((('Haynes, Beryl'!I34+'Haynes, Beryl'!I35)>12)*1)+SUMPRODUCT((('Haynes, Beryl'!I36+'Haynes, Beryl'!I37)>12)*1)+SUMPRODUCT((('Haynes, Beryl'!I38+'Haynes, Beryl'!I39)>12)*1)+SUMPRODUCT((('Haynes, Beryl'!I40+'Haynes, Beryl'!I41)>12)*1)+SUMPRODUCT((('Haynes, Beryl'!I42+'Haynes, Beryl'!I43)>12)*1)+SUMPRODUCT((('Haynes, Beryl'!I45+'Haynes, Beryl'!I46)>12)*1)+SUMPRODUCT((('Haynes, Beryl'!I47+'Haynes, Beryl'!I48)>12)*1) | G43: =IF(MAX(SUM('Haynes, Beryl'!I14:I27),SUM('Haynes, Beryl'!I30:I43))>60,"Yes","") | H43: =IF(OR(AND(('Haynes, Beryl'!I14+'Haynes, Beryl'!I15)>0,('Haynes, Beryl'!I16+'Haynes, Beryl'!I17)>0,('Haynes, Beryl'!I18+'Haynes, Beryl'!I19)>0,('Haynes, Beryl'!I20+'Haynes, Beryl'!I21)>0,('Haynes, Beryl'!I22+'Haynes, Beryl'!I23)>0,('Haynes, Beryl'!I24+'Haynes, Beryl'!I25)>0,('Haynes, Beryl'!I26+'Haynes, Beryl'!I27)>0),AND(('Haynes, Beryl'!I30+'Haynes, Beryl'!I31)>0,('Haynes, Beryl'!I32+'Haynes, Beryl'!I33)>0,('Haynes, Beryl'!I34+'Haynes, Beryl'!I35)>0,('Haynes, Beryl'!I36+'Haynes, Beryl'!I37)>0,('Haynes, Beryl'!I38+'Haynes, Beryl'!I39)>0,('Haynes, Beryl'!I40+'Haynes, Beryl'!I41)>0,('Haynes, Beryl'!I42+'Haynes, Beryl'!I43)>0)),"Yes","") | I43: =IF('Haynes, Beryl'!N49>40,"Yes","") | J43: =IF(OR(AND(SUM('Haynes, Beryl'!I14:I27)>0,SUM('Haynes, Beryl'!I14:I27)<40),AND(SUM('Haynes, Beryl'!I30:I43)>0,SUM('Haynes, Beryl'!I30:I43)<40)),"Yes","") | K43: =SUMPRODUCT(('Haynes, Beryl'!I14:I48>0)*('Haynes, Beryl'!I14:I48<8)) | L43: =IF('Haynes, Beryl'!Q50<5,"Yes","") | M43: =IF(AND('Haynes, Beryl'!I49>0,'Haynes, Beryl'!I49<80),"Yes","") | N43: =IF(OR(F43>0,G43="Yes",H43="Yes",I43="Yes"),"⚠️ OVERWORK",IF(OR(J43="Yes",K43>0,L43="Yes",M43="Yes"),"🔻 UNDERWORK","✓ OK"))
A44: 40 | B44: Haynes, Suzette | C44: 1791 | D44: ='Haynes, Suzette'!I49 | E44: ='Haynes, Suzette'!Q50 | F44: =SUMPRODUCT((('Haynes, Suzette'!I14+'Haynes, Suzette'!I15)>12)*1)+SUMPRODUCT((('Haynes, Suzette'!I16+'Haynes, Suzette'!I17)>12)*1)+SUMPRODUCT((('Haynes, Suzette'!I18+'Haynes, Suzette'!I19)>12)*1)+SUMPRODUCT((('Haynes, Suzette'!I20+'Haynes, Suzette'!I21)>12)*1)+SUMPRODUCT((('Haynes, Suzette'!I22+'Haynes, Suzette'!I23)>12)*1)+SUMPRODUCT((('Haynes, Suzette'!I24+'Haynes, Suzette'!I25)>12)*1)+SUMPRODUCT((('Haynes, Suzette'!I26+'Haynes, Suzette'!I27)>12)*1)+SUMPRODUCT((('Haynes, Suzette'!I30+'Haynes, Suzette'!I31)>12)*1)+SUMPRODUCT((('Haynes, Suzette'!I32+'Haynes, Suzette'!I33)>12)*1)+SUMPRODUCT((('Haynes, Suzette'!I34+'Haynes, Suzette'!I35)>12)*1)+SUMPRODUCT((('Haynes, Suzette'!I36+'Haynes, Suzette'!I37)>12)*1)+SUMPRODUCT((('Haynes, Suzette'!I38+'Haynes, Suzette'!I39)>12)*1)+SUMPRODUCT((('Haynes, Suzette'!I40+'Haynes, Suzette'!I41)>12)*1)+SUMPRODUCT((('Haynes, Suzette'!I42+'Haynes, Suzette'!I43)>12)*1)+SUMPRODUCT((('Haynes, Suzette'!I45+'Haynes, Suzette'!I46)>12)*1)+SUMPRODUCT((('Haynes, Suzette'!I47+'Haynes, Suzette'!I48)>12)*1) | G44: =IF(MAX(SUM('Haynes, Suzette'!I14:I27),SUM('Haynes, Suzette'!I30:I43))>60,"Yes","") | H44: =IF(OR(AND(('Haynes, Suzette'!I14+'Haynes, Suzette'!I15)>0,('Haynes, Suzette'!I16+'Haynes, Suzette'!I17)>0,('Haynes, Suzette'!I18+'Haynes, Suzette'!I19)>0,('Haynes, Suzette'!I20+'Haynes, Suzette'!I21)>0,('Haynes, Suzette'!I22+'Haynes, Suzette'!I23)>0,('Haynes, Suzette'!I24+'Haynes, Suzette'!I25)>0,('Haynes, Suzette'!I26+'Haynes, Suzette'!I27)>0),AND(('Haynes, Suzette'!I30+'Haynes, Suzette'!I31)>0,('Haynes, Suzette'!I32+'Haynes, Suzette'!I33)>0,('Haynes, Suzette'!I34+'Haynes, Suzette'!I35)>0,('Haynes, Suzette'!I36+'Haynes, Suzette'!I37)>0,('Haynes, Suzette'!I38+'Haynes, Suzette'!I39)>0,('Haynes, Suzette'!I40+'Haynes, Suzette'!I41)>0,('Haynes, Suzette'!I42+'Haynes, Suzette'!I43)>0)),"Yes","") | I44: =IF('Haynes, Suzette'!N49>40,"Yes","") | J44: =IF(OR(AND(SUM('Haynes, Suzette'!I14:I27)>0,SUM('Haynes, Suzette'!I14:I27)<40),AND(SUM('Haynes, Suzette'!I30:I43)>0,SUM('Haynes, Suzette'!I30:I43)<40)),"Yes","") | K44: =SUMPRODUCT(('Haynes, Suzette'!I14:I48>0)*('Haynes, Suzette'!I14:I48<8)) | L44: =IF('Haynes, Suzette'!Q50<5,"Yes","") | M44: =IF(AND('Haynes, Suzette'!I49>0,'Haynes, Suzette'!I49<80),"Yes","") | N44: =IF(OR(F44>0,G44="Yes",H44="Yes",I44="Yes"),"⚠️ OVERWORK",IF(OR(J44="Yes",K44>0,L44="Yes",M44="Yes"),"🔻 UNDERWORK","✓ OK"))
A45: 41 | B45: Henry, Sonia | C45: 5488 | D45: ='Henry, Sonia'!I49 | E45: ='Henry, Sonia'!Q50 | F45: =SUMPRODUCT((('Henry, Sonia'!I14+'Henry, Sonia'!I15)>12)*1)+SUMPRODUCT((('Henry, Sonia'!I16+'Henry, Sonia'!I17)>12)*1)+SUMPRODUCT((('Henry, Sonia'!I18+'Henry, Sonia'!I19)>12)*1)+SUMPRODUCT((('Henry, Sonia'!I20+'Henry, Sonia'!I21)>12)*1)+SUMPRODUCT((('Henry, Sonia'!I22+'Henry, Sonia'!I23)>12)*1)+SUMPRODUCT((('Henry, Sonia'!I24+'Henry, Sonia'!I25)>12)*1)+SUMPRODUCT((('Henry, Sonia'!I26+'Henry, Sonia'!I27)>12)*1)+SUMPRODUCT((('Henry, Sonia'!I30+'Henry, Sonia'!I31)>12)*1)+SUMPRODUCT((('Henry, Sonia'!I32+'Henry, Sonia'!I33)>12)*1)+SUMPRODUCT((('Henry, Sonia'!I34+'Henry, Sonia'!I35)>12)*1)+SUMPRODUCT((('Henry, Sonia'!I36+'Henry, Sonia'!I37)>12)*1)+SUMPRODUCT((('Henry, Sonia'!I38+'Henry, Sonia'!I39)>12)*1)+SUMPRODUCT((('Henry, Sonia'!I40+'Henry, Sonia'!I41)>12)*1)+SUMPRODUCT((('Henry, Sonia'!I42+'Henry, Sonia'!I43)>12)*1)+SUMPRODUCT((('Henry, Sonia'!I45+'Henry, Sonia'!I46)>12)*1)+SUMPRODUCT((('Henry, Sonia'!I47+'Henry, Sonia'!I48)>12)*1) | G45: =IF(MAX(SUM('Henry, Sonia'!I14:I27),SUM('Henry, Sonia'!I30:I43))>60,"Yes","") | H45: =IF(OR(AND(('Henry, Sonia'!I14+'Henry, Sonia'!I15)>0,('Henry, Sonia'!I16+'Henry, Sonia'!I17)>0,('Henry, Sonia'!I18+'Henry, Sonia'!I19)>0,('Henry, Sonia'!I20+'Henry, Sonia'!I21)>0,('Henry, Sonia'!I22+'Henry, Sonia'!I23)>0,('Henry, Sonia'!I24+'Henry, Sonia'!I25)>0,('Henry, Sonia'!I26+'Henry, Sonia'!I27)>0),AND(('Henry, Sonia'!I30+'Henry, Sonia'!I31)>0,('Henry, Sonia'!I32+'Henry, Sonia'!I33)>0,('Henry, Sonia'!I34+'Henry, Sonia'!I35)>0,('Henry, Sonia'!I36+'Henry, Sonia'!I37)>0,('Henry, Sonia'!I38+'Henry, Sonia'!I39)>0,('Henry, Sonia'!I40+'Henry, Sonia'!I41)>0,('Henry, Sonia'!I42+'Henry, Sonia'!I43)>0)),"Yes","") | I45: =IF('Henry, Sonia'!N49>40,"Yes","") | J45: =IF(OR(AND(SUM('Henry, Sonia'!I14:I27)>0,SUM('Henry, Sonia'!I14:I27)<40),AND(SUM('Henry, Sonia'!I30:I43)>0,SUM('Henry, Sonia'!I30:I43)<40)),"Yes","") | K45: =SUMPRODUCT(('Henry, Sonia'!I14:I48>0)*('Henry, Sonia'!I14:I48<8)) | L45: =IF('Henry, Sonia'!Q50<5,"Yes","") | M45: =IF(AND('Henry, Sonia'!I49>0,'Henry, Sonia'!I49<80),"Yes","") | N45: =IF(OR(F45>0,G45="Yes",H45="Yes",I45="Yes"),"⚠️ OVERWORK",IF(OR(J45="Yes",K45>0,L45="Yes",M45="Yes"),"🔻 UNDERWORK","✓ OK"))
A46: 42 | B46: Hinds, Cassie Candacie | C46: 5531 | D46: ='Hinds, Cassie Candacie'!I49 | E46: ='Hinds, Cassie Candacie'!Q50 | F46: =SUMPRODUCT((('Hinds, Cassie Candacie'!I14+'Hinds, Cassie Candacie'!I15)>12)*1)+SUMPRODUCT((('Hinds, Cassie Candacie'!I16+'Hinds, Cassie Candacie'!I17)>12)*1)+SUMPRODUCT((('Hinds, Cassie Candacie'!I18+'Hinds, Cassie Candacie'!I19)>12)*1)+SUMPRODUCT((('Hinds, Cassie Candacie'!I20+'Hinds, Cassie Candacie'!I21)>12)*1)+SUMPRODUCT((('Hinds, Cassie Candacie'!I22+'Hinds, Cassie Candacie'!I23)>12)*1)+SUMPRODUCT((('Hinds, Cassie Candacie'!I24+'Hinds, Cassie Candacie'!I25)>12)*1)+SUMPRODUCT((('Hinds, Cassie Candacie'!I26+'Hinds, Cassie Candacie'!I27)>12)*1)+SUMPRODUCT((('Hinds, Cassie Candacie'!I30+'Hinds, Cassie Candacie'!I31)>12)*1)+SUMPRODUCT((('Hinds, Cassie Candacie'!I32+'Hinds, Cassie Candacie'!I33)>12)*1)+SUMPRODUCT((('Hinds, Cassie Candacie'!I34+'Hinds, Cassie Candacie'!I35)>12)*1)+SUMPRODUCT((('Hinds, Cassie Candacie'!I36+'Hinds, Cassie Candacie'!I37)>12)*1)+SUMPRODUCT((('Hinds, Cassie Candacie'!I38+'Hinds, Cassie Candacie'!I39)>12)*1)+SUMPRODUCT((('Hinds, Cassie Candacie'!I40+'Hinds, Cassie Candacie'!I41)>12)*1)+SUMPRODUCT((('Hinds, Cassie Candacie'!I42+'Hinds, Cassie Candacie'!I43)>12)*1)+SUMPRODUCT((('Hinds, Cassie Candacie'!I45+'Hinds, Cassie Candacie'!I46)>12)*1)+SUMPRODUCT((('Hinds, Cassie Candacie'!I47+'Hinds, Cassie Candacie'!I48)>12)*1) | G46: =IF(MAX(SUM('Hinds, Cassie Candacie'!I14:I27),SUM('Hinds, Cassie Candacie'!I30:I43))>60,"Yes","") | H46: =IF(OR(AND(('Hinds, Cassie Candacie'!I14+'Hinds, Cassie Candacie'!I15)>0,('Hinds, Cassie Candacie'!I16+'Hinds, Cassie Candacie'!I17)>0,('Hinds, Cassie Candacie'!I18+'Hinds, Cassie Candacie'!I19)>0,('Hinds, Cassie Candacie'!I20+'Hinds, Cassie Candacie'!I21)>0,('Hinds, Cassie Candacie'!I22+'Hinds, Cassie Candacie'!I23)>0,('Hinds, Cassie Candacie'!I24+'Hinds, Cassie Candacie'!I25)>0,('Hinds, Cassie Candacie'!I26+'Hinds, Cassie Candacie'!I27)>0),AND(('Hinds, Cassie Candacie'!I30+'Hinds, Cassie Candacie'!I31)>0,('Hinds, Cassie Candacie'!I32+'Hinds, Cassie Candacie'!I33)>0,('Hinds, Cassie Candacie'!I34+'Hinds, Cassie Candacie'!I35)>0,('Hinds, Cassie Candacie'!I36+'Hinds, Cassie Candacie'!I37)>0,('Hinds, Cassie Candacie'!I38+'Hinds, Cassie Candacie'!I39)>0,('Hinds, Cassie Candacie'!I40+'Hinds, Cassie Candacie'!I41)>0,('Hinds, Cassie Candacie'!I42+'Hinds, Cassie Candacie'!I43)>0)),"Yes","") | I46: =IF('Hinds, Cassie Candacie'!N49>40,"Yes","") | J46: =IF(OR(AND(SUM('Hinds, Cassie Candacie'!I14:I27)>0,SUM('Hinds, Cassie Candacie'!I14:I27)<40),AND(SUM('Hinds, Cassie Candacie'!I30:I43)>0,SUM('Hinds, Cassie Candacie'!I30:I43)<40)),"Yes","") | K46: =SUMPRODUCT(('Hinds, Cassie Candacie'!I14:I48>0)*('Hinds, Cassie Candacie'!I14:I48<8)) | L46: =IF('Hinds, Cassie Candacie'!Q50<5,"Yes","") | M46: =IF(AND('Hinds, Cassie Candacie'!I49>0,'Hinds, Cassie Candacie'!I49<80),"Yes","") | N46: =IF(OR(F46>0,G46="Yes",H46="Yes",I46="Yes"),"⚠️ OVERWORK",IF(OR(J46="Yes",K46>0,L46="Yes",M46="Yes"),"🔻 UNDERWORK","✓ OK"))
A47: 43 | B47: Holder, Tomeka | C47: 4887 | D47: ='Holder, Tomeka'!I49 | E47: ='Holder, Tomeka'!Q50 | F47: =SUMPRODUCT((('Holder, Tomeka'!I14+'Holder, Tomeka'!I15)>12)*1)+SUMPRODUCT((('Holder, Tomeka'!I16+'Holder, Tomeka'!I17)>12)*1)+SUMPRODUCT((('Holder, Tomeka'!I18+'Holder, Tomeka'!I19)>12)*1)+SUMPRODUCT((('Holder, Tomeka'!I20+'Holder, Tomeka'!I21)>12)*1)+SUMPRODUCT((('Holder, Tomeka'!I22+'Holder, Tomeka'!I23)>12)*1)+SUMPRODUCT((('Holder, Tomeka'!I24+'Holder, Tomeka'!I25)>12)*1)+SUMPRODUCT((('Holder, Tomeka'!I26+'Holder, Tomeka'!I27)>12)*1)+SUMPRODUCT((('Holder, Tomeka'!I30+'Holder, Tomeka'!I31)>12)*1)+SUMPRODUCT((('Holder, Tomeka'!I32+'Holder, Tomeka'!I33)>12)*1)+SUMPRODUCT((('Holder, Tomeka'!I34+'Holder, Tomeka'!I35)>12)*1)+SUMPRODUCT((('Holder, Tomeka'!I36+'Holder, Tomeka'!I37)>12)*1)+SUMPRODUCT((('Holder, Tomeka'!I38+'Holder, Tomeka'!I39)>12)*1)+SUMPRODUCT((('Holder, Tomeka'!I40+'Holder, Tomeka'!I41)>12)*1)+SUMPRODUCT((('Holder, Tomeka'!I42+'Holder, Tomeka'!I43)>12)*1)+SUMPRODUCT((('Holder, Tomeka'!I45+'Holder, Tomeka'!I46)>12)*1)+SUMPRODUCT((('Holder, Tomeka'!I47+'Holder, Tomeka'!I48)>12)*1) | G47: =IF(MAX(SUM('Holder, Tomeka'!I14:I27),SUM('Holder, Tomeka'!I30:I43))>60,"Yes","") | H47: =IF(OR(AND(('Holder, Tomeka'!I14+'Holder, Tomeka'!I15)>0,('Holder, Tomeka'!I16+'Holder, Tomeka'!I17)>0,('Holder, Tomeka'!I18+'Holder, Tomeka'!I19)>0,('Holder, Tomeka'!I20+'Holder, Tomeka'!I21)>0,('Holder, Tomeka'!I22+'Holder, Tomeka'!I23)>0,('Holder, Tomeka'!I24+'Holder, Tomeka'!I25)>0,('Holder, Tomeka'!I26+'Holder, Tomeka'!I27)>0),AND(('Holder, Tomeka'!I30+'Holder, Tomeka'!I31)>0,('Holder, Tomeka'!I32+'Holder, Tomeka'!I33)>0,('Holder, Tomeka'!I34+'Holder, Tomeka'!I35)>0,('Holder, Tomeka'!I36+'Holder, Tomeka'!I37)>0,('Holder, Tomeka'!I38+'Holder, Tomeka'!I39)>0,('Holder, Tomeka'!I40+'Holder, Tomeka'!I41)>0,('Holder, Tomeka'!I42+'Holder, Tomeka'!I43)>0)),"Yes","") | I47: =IF('Holder, Tomeka'!N49>40,"Yes","") | J47: =IF(OR(AND(SUM('Holder, Tomeka'!I14:I27)>0,SUM('Holder, Tomeka'!I14:I27)<40),AND(SUM('Holder, Tomeka'!I30:I43)>0,SUM('Holder, Tomeka'!I30:I43)<40)),"Yes","") | K47: =SUMPRODUCT(('Holder, Tomeka'!I14:I48>0)*('Holder, Tomeka'!I14:I48<8)) | L47: =IF('Holder, Tomeka'!Q50<5,"Yes","") | M47: =IF(AND('Holder, Tomeka'!I49>0,'Holder, Tomeka'!I49<80),"Yes","") | N47: =IF(OR(F47>0,G47="Yes",H47="Yes",I47="Yes"),"⚠️ OVERWORK",IF(OR(J47="Yes",K47>0,L47="Yes",M47="Yes"),"🔻 UNDERWORK","✓ OK"))
A48: 44 | B48: Howell, Allison | C48: 3184 | D48: ='Howell, Allison'!I49 | E48: ='Howell, Allison'!Q50 | F48: =SUMPRODUCT((('Howell, Allison'!I14+'Howell, Allison'!I15)>12)*1)+SUMPRODUCT((('Howell, Allison'!I16+'Howell, Allison'!I17)>12)*1)+SUMPRODUCT((('Howell, Allison'!I18+'Howell, Allison'!I19)>12)*1)+SUMPRODUCT((('Howell, Allison'!I20+'Howell, Allison'!I21)>12)*1)+SUMPRODUCT((('Howell, Allison'!I22+'Howell, Allison'!I23)>12)*1)+SUMPRODUCT((('Howell, Allison'!I24+'Howell, Allison'!I25)>12)*1)+SUMPRODUCT((('Howell, Allison'!I26+'Howell, Allison'!I27)>12)*1)+SUMPRODUCT((('Howell, Allison'!I30+'Howell, Allison'!I31)>12)*1)+SUMPRODUCT((('Howell, Allison'!I32+'Howell, Allison'!I33)>12)*1)+SUMPRODUCT((('Howell, Allison'!I34+'Howell, Allison'!I35)>12)*1)+SUMPRODUCT((('Howell, Allison'!I36+'Howell, Allison'!I37)>12)*1)+SUMPRODUCT((('Howell, Allison'!I38+'Howell, Allison'!I39)>12)*1)+SUMPRODUCT((('Howell, Allison'!I40+'Howell, Allison'!I41)>12)*1)+SUMPRODUCT((('Howell, Allison'!I42+'Howell, Allison'!I43)>12)*1)+SUMPRODUCT((('Howell, Allison'!I45+'Howell, Allison'!I46)>12)*1)+SUMPRODUCT((('Howell, Allison'!I47+'Howell, Allison'!I48)>12)*1) | G48: =IF(MAX(SUM('Howell, Allison'!I14:I27),SUM('Howell, Allison'!I30:I43))>60,"Yes","") | H48: =IF(OR(AND(('Howell, Allison'!I14+'Howell, Allison'!I15)>0,('Howell, Allison'!I16+'Howell, Allison'!I17)>0,('Howell, Allison'!I18+'Howell, Allison'!I19)>0,('Howell, Allison'!I20+'Howell, Allison'!I21)>0,('Howell, Allison'!I22+'Howell, Allison'!I23)>0,('Howell, Allison'!I24+'Howell, Allison'!I25)>0,('Howell, Allison'!I26+'Howell, Allison'!I27)>0),AND(('Howell, Allison'!I30+'Howell, Allison'!I31)>0,('Howell, Allison'!I32+'Howell, Allison'!I33)>0,('Howell, Allison'!I34+'Howell, Allison'!I35)>0,('Howell, Allison'!I36+'Howell, Allison'!I37)>0,('Howell, Allison'!I38+'Howell, Allison'!I39)>0,('Howell, Allison'!I40+'Howell, Allison'!I41)>0,('Howell, Allison'!I42+'Howell, Allison'!I43)>0)),"Yes","") | I48: =IF('Howell, Allison'!N49>40,"Yes","") | J48: =IF(OR(AND(SUM('Howell, Allison'!I14:I27)>0,SUM('Howell, Allison'!I14:I27)<40),AND(SUM('Howell, Allison'!I30:I43)>0,SUM('Howell, Allison'!I30:I43)<40)),"Yes","") | K48: =SUMPRODUCT(('Howell, Allison'!I14:I48>0)*('Howell, Allison'!I14:I48<8)) | L48: =IF('Howell, Allison'!Q50<5,"Yes","") | M48: =IF(AND('Howell, Allison'!I49>0,'Howell, Allison'!I49<80),"Yes","") | N48: =IF(OR(F48>0,G48="Yes",H48="Yes",I48="Yes"),"⚠️ OVERWORK",IF(OR(J48="Yes",K48>0,L48="Yes",M48="Yes"),"🔻 UNDERWORK","✓ OK"))
A49: 45 | B49: Hudson, Paulette Veronica | C49: 2134 | D49: ='Hudson, Paulette Veronica'!I49 | E49: ='Hudson, Paulette Veronica'!Q50 | F49: =SUMPRODUCT((('Hudson, Paulette Veronica'!I14+'Hudson, Paulette Veronica'!I15)>12)*1)+SUMPRODUCT((('Hudson, Paulette Veronica'!I16+'Hudson, Paulette Veronica'!I17)>12)*1)+SUMPRODUCT((('Hudson, Paulette Veronica'!I18+'Hudson, Paulette Veronica'!I19)>12)*1)+SUMPRODUCT((('Hudson, Paulette Veronica'!I20+'Hudson, Paulette Veronica'!I21)>12)*1)+SUMPRODUCT((('Hudson, Paulette Veronica'!I22+'Hudson, Paulette Veronica'!I23)>12)*1)+SUMPRODUCT((('Hudson, Paulette Veronica'!I24+'Hudson, Paulette Veronica'!I25)>12)*1)+SUMPRODUCT((('Hudson, Paulette Veronica'!I26+'Hudson, Paulette Veronica'!I27)>12)*1)+SUMPRODUCT((('Hudson, Paulette Veronica'!I30+'Hudson, Paulette Veronica'!I31)>12)*1)+SUMPRODUCT((('Hudson, Paulette Veronica'!I32+'Hudson, Paulette Veronica'!I33)>12)*1)+SUMPRODUCT((('Hudson, Paulette Veronica'!I34+'Hudson, Paulette Veronica'!I35)>12)*1)+SUMPRODUCT((('Hudson, Paulette Veronica'!I36+'Hudson, Paulette Veronica'!I37)>12)*1)+SUMPRODUCT((('Hudson, Paulette Veronica'!I38+'Hudson, Paulette Veronica'!I39)>12)*1)+SUMPRODUCT((('Hudson, Paulette Veronica'!I40+'Hudson, Paulette Veronica'!I41)>12)*1)+SUMPRODUCT((('Hudson, Paulette Veronica'!I42+'Hudson, Paulette Veronica'!I43)>12)*1)+SUMPRODUCT((('Hudson, Paulette Veronica'!I45+'Hudson, Paulette Veronica'!I46)>12)*1)+SUMPRODUCT((('Hudson, Paulette Veronica'!I47+'Hudson, Paulette Veronica'!I48)>12)*1) | G49: =IF(MAX(SUM('Hudson, Paulette Veronica'!I14:I27),SUM('Hudson, Paulette Veronica'!I30:I43))>60,"Yes","") | H49: =IF(OR(AND(('Hudson, Paulette Veronica'!I14+'Hudson, Paulette Veronica'!I15)>0,('Hudson, Paulette Veronica'!I16+'Hudson, Paulette Veronica'!I17)>0,('Hudson, Paulette Veronica'!I18+'Hudson, Paulette Veronica'!I19)>0,('Hudson, Paulette Veronica'!I20+'Hudson, Paulette Veronica'!I21)>0,('Hudson, Paulette Veronica'!I22+'Hudson, Paulette Veronica'!I23)>0,('Hudson, Paulette Veronica'!I24+'Hudson, Paulette Veronica'!I25)>0,('Hudson, Paulette Veronica'!I26+'Hudson, Paulette Veronica'!I27)>0),AND(('Hudson, Paulette Veronica'!I30+'Hudson, Paulette Veronica'!I31)>0,('Hudson, Paulette Veronica'!I32+'Hudson, Paulette Veronica'!I33)>0,('Hudson, Paulette Veronica'!I34+'Hudson, Paulette Veronica'!I35)>0,('Hudson, Paulette Veronica'!I36+'Hudson, Paulette Veronica'!I37)>0,('Hudson, Paulette Veronica'!I38+'Hudson, Paulette Veronica'!I39)>0,('Hudson, Paulette Veronica'!I40+'Hudson, Paulette Veronica'!I41)>0,('Hudson, Paulette Veronica'!I42+'Hudson, Paulette Veronica'!I43)>0)),"Yes","") | I49: =IF('Hudson, Paulette Veronica'!N49>40,"Yes","") | J49: =IF(OR(AND(SUM('Hudson, Paulette Veronica'!I14:I27)>0,SUM('Hudson, Paulette Veronica'!I14:I27)<40),AND(SUM('Hudson, Paulette Veronica'!I30:I43)>0,SUM('Hudson, Paulette Veronica'!I30:I43)<40)),"Yes","") | K49: =SUMPRODUCT(('Hudson, Paulette Veronica'!I14:I48>0)*('Hudson, Paulette Veronica'!I14:I48<8)) | L49: =IF('Hudson, Paulette Veronica'!Q50<5,"Yes","") | M49: =IF(AND('Hudson, Paulette Veronica'!I49>0,'Hudson, Paulette Veronica'!I49<80),"Yes","") | N49: =IF(OR(F49>0,G49="Yes",H49="Yes",I49="Yes"),"⚠️ OVERWORK",IF(OR(J49="Yes",K49>0,L49="Yes",M49="Yes"),"🔻 UNDERWORK","✓ OK"))
A50: 46 | B50: Jacques, Valy-Ana | C50: 5522 | D50: ='Jacques, Valy-Ana'!I49 | E50: ='Jacques, Valy-Ana'!Q50 | F50: =SUMPRODUCT((('Jacques, Valy-Ana'!I14+'Jacques, Valy-Ana'!I15)>12)*1)+SUMPRODUCT((('Jacques, Valy-Ana'!I16+'Jacques, Valy-Ana'!I17)>12)*1)+SUMPRODUCT((('Jacques, Valy-Ana'!I18+'Jacques, Valy-Ana'!I19)>12)*1)+SUMPRODUCT((('Jacques, Valy-Ana'!I20+'Jacques, Valy-Ana'!I21)>12)*1)+SUMPRODUCT((('Jacques, Valy-Ana'!I22+'Jacques, Valy-Ana'!I23)>12)*1)+SUMPRODUCT((('Jacques, Valy-Ana'!I24+'Jacques, Valy-Ana'!I25)>12)*1)+SUMPRODUCT((('Jacques, Valy-Ana'!I26+'Jacques, Valy-Ana'!I27)>12)*1)+SUMPRODUCT((('Jacques, Valy-Ana'!I30+'Jacques, Valy-Ana'!I31)>12)*1)+SUMPRODUCT((('Jacques, Valy-Ana'!I32+'Jacques, Valy-Ana'!I33)>12)*1)+SUMPRODUCT((('Jacques, Valy-Ana'!I34+'Jacques, Valy-Ana'!I35)>12)*1)+SUMPRODUCT((('Jacques, Valy-Ana'!I36+'Jacques, Valy-Ana'!I37)>12)*1)+SUMPRODUCT((('Jacques, Valy-Ana'!I38+'Jacques, Valy-Ana'!I39)>12)*1)+SUMPRODUCT((('Jacques, Valy-Ana'!I40+'Jacques, Valy-Ana'!I41)>12)*1)+SUMPRODUCT((('Jacques, Valy-Ana'!I42+'Jacques, Valy-Ana'!I43)>12)*1)+SUMPRODUCT((('Jacques, Valy-Ana'!I45+'Jacques, Valy-Ana'!I46)>12)*1)+SUMPRODUCT((('Jacques, Valy-Ana'!I47+'Jacques, Valy-Ana'!I48)>12)*1) | G50: =IF(MAX(SUM('Jacques, Valy-Ana'!I14:I27),SUM('Jacques, Valy-Ana'!I30:I43))>60,"Yes","") | H50: =IF(OR(AND(('Jacques, Valy-Ana'!I14+'Jacques, Valy-Ana'!I15)>0,('Jacques, Valy-Ana'!I16+'Jacques, Valy-Ana'!I17)>0,('Jacques, Valy-Ana'!I18+'Jacques, Valy-Ana'!I19)>0,('Jacques, Valy-Ana'!I20+'Jacques, Valy-Ana'!I21)>0,('Jacques, Valy-Ana'!I22+'Jacques, Valy-Ana'!I23)>0,('Jacques, Valy-Ana'!I24+'Jacques, Valy-Ana'!I25)>0,('Jacques, Valy-Ana'!I26+'Jacques, Valy-Ana'!I27)>0),AND(('Jacques, Valy-Ana'!I30+'Jacques, Valy-Ana'!I31)>0,('Jacques, Valy-Ana'!I32+'Jacques, Valy-Ana'!I33)>0,('Jacques, Valy-Ana'!I34+'Jacques, Valy-Ana'!I35)>0,('Jacques, Valy-Ana'!I36+'Jacques, Valy-Ana'!I37)>0,('Jacques, Valy-Ana'!I38+'Jacques, Valy-Ana'!I39)>0,('Jacques, Valy-Ana'!I40+'Jacques, Valy-Ana'!I41)>0,('Jacques, Valy-Ana'!I42+'Jacques, Valy-Ana'!I43)>0)),"Yes","") | I50: =IF('Jacques, Valy-Ana'!N49>40,"Yes","") | J50: =IF(OR(AND(SUM('Jacques, Valy-Ana'!I14:I27)>0,SUM('Jacques, Valy-Ana'!I14:I27)<40),AND(SUM('Jacques, Valy-Ana'!I30:I43)>0,SUM('Jacques, Valy-Ana'!I30:I43)<40)),"Yes","") | K50: =SUMPRODUCT(('Jacques, Valy-Ana'!I14:I48>0)*('Jacques, Valy-Ana'!I14:I48<8)) | L50: =IF('Jacques, Valy-Ana'!Q50<5,"Yes","") | M50: =IF(AND('Jacques, Valy-Ana'!I49>0,'Jacques, Valy-Ana'!I49<80),"Yes","") | N50: =IF(OR(F50>0,G50="Yes",H50="Yes",I50="Yes"),"⚠️ OVERWORK",IF(OR(J50="Yes",K50>0,L50="Yes",M50="Yes"),"🔻 UNDERWORK","✓ OK"))
A51: 47 | B51: James, Grace | C51: 5511 | D51: ='James, Grace'!I49 | E51: ='James, Grace'!Q50 | F51: =SUMPRODUCT((('James, Grace'!I14+'James, Grace'!I15)>12)*1)+SUMPRODUCT((('James, Grace'!I16+'James, Grace'!I17)>12)*1)+SUMPRODUCT((('James, Grace'!I18+'James, Grace'!I19)>12)*1)+SUMPRODUCT((('James, Grace'!I20+'James, Grace'!I21)>12)*1)+SUMPRODUCT((('James, Grace'!I22+'James, Grace'!I23)>12)*1)+SUMPRODUCT((('James, Grace'!I24+'James, Grace'!I25)>12)*1)+SUMPRODUCT((('James, Grace'!I26+'James, Grace'!I27)>12)*1)+SUMPRODUCT((('James, Grace'!I30+'James, Grace'!I31)>12)*1)+SUMPRODUCT((('James, Grace'!I32+'James, Grace'!I33)>12)*1)+SUMPRODUCT((('James, Grace'!I34+'James, Grace'!I35)>12)*1)+SUMPRODUCT((('James, Grace'!I36+'James, Grace'!I37)>12)*1)+SUMPRODUCT((('James, Grace'!I38+'James, Grace'!I39)>12)*1)+SUMPRODUCT((('James, Grace'!I40+'James, Grace'!I41)>12)*1)+SUMPRODUCT((('James, Grace'!I42+'James, Grace'!I43)>12)*1)+SUMPRODUCT((('James, Grace'!I45+'James, Grace'!I46)>12)*1)+SUMPRODUCT((('James, Grace'!I47+'James, Grace'!I48)>12)*1) | G51: =IF(MAX(SUM('James, Grace'!I14:I27),SUM('James, Grace'!I30:I43))>60,"Yes","") | H51: =IF(OR(AND(('James, Grace'!I14+'James, Grace'!I15)>0,('James, Grace'!I16+'James, Grace'!I17)>0,('James, Grace'!I18+'James, Grace'!I19)>0,('James, Grace'!I20+'James, Grace'!I21)>0,('James, Grace'!I22+'James, Grace'!I23)>0,('James, Grace'!I24+'James, Grace'!I25)>0,('James, Grace'!I26+'James, Grace'!I27)>0),AND(('James, Grace'!I30+'James, Grace'!I31)>0,('James, Grace'!I32+'James, Grace'!I33)>0,('James, Grace'!I34+'James, Grace'!I35)>0,('James, Grace'!I36+'James, Grace'!I37)>0,('James, Grace'!I38+'James, Grace'!I39)>0,('James, Grace'!I40+'James, Grace'!I41)>0,('James, Grace'!I42+'James, Grace'!I43)>0)),"Yes","") | I51: =IF('James, Grace'!N49>40,"Yes","") | J51: =IF(OR(AND(SUM('James, Grace'!I14:I27)>0,SUM('James, Grace'!I14:I27)<40),AND(SUM('James, Grace'!I30:I43)>0,SUM('James, Grace'!I30:I43)<40)),"Yes","") | K51: =SUMPRODUCT(('James, Grace'!I14:I48>0)*('James, Grace'!I14:I48<8)) | L51: =IF('James, Grace'!Q50<5,"Yes","") | M51: =IF(AND('James, Grace'!I49>0,'James, Grace'!I49<80),"Yes","") | N51: =IF(OR(F51>0,G51="Yes",H51="Yes",I51="Yes"),"⚠️ OVERWORK",IF(OR(J51="Yes",K51>0,L51="Yes",M51="Yes"),"🔻 UNDERWORK","✓ OK"))
A52: 48 | B52: Jean-Charles-Bellefleur, Ellianna | C52: 5480 | D52: ='Jean-Charles-Bellefleur, Ellian'!I49 | E52: ='Jean-Charles-Bellefleur, Ellian'!Q50 | F52: =SUMPRODUCT((('Jean-Charles-Bellefleur, Ellian'!I14+'Jean-Charles-Bellefleur, Ellian'!I15)>12)*1)+SUMPRODUCT((('Jean-Charles-Bellefleur, Ellian'!I16+'Jean-Charles-Bellefleur, Ellian'!I17)>12)*1)+SUMPRODUCT((('Jean-Charles-Bellefleur, Ellian'!I18+'Jean-Charles-Bellefleur, Ellian'!I19)>12)*1)+SUMPRODUCT((('Jean-Charles-Bellefleur, Ellian'!I20+'Jean-Charles-Bellefleur, Ellian'!I21)>12)*1)+SUMPRODUCT((('Jean-Charles-Bellefleur, Ellian'!I22+'Jean-Charles-Bellefleur, Ellian'!I23)>12)*1)+SUMPRODUCT((('Jean-Charles-Bellefleur, Ellian'!I24+'Jean-Charles-Bellefleur, Ellian'!I25)>12)*1)+SUMPRODUCT((('Jean-Charles-Bellefleur, Ellian'!I26+'Jean-Charles-Bellefleur, Ellian'!I27)>12)*1)+SUMPRODUCT((('Jean-Charles-Bellefleur, Ellian'!I30+'Jean-Charles-Bellefleur, Ellian'!I31)>12)*1)+SUMPRODUCT((('Jean-Charles-Bellefleur, Ellian'!I32+'Jean-Charles-Bellefleur, Ellian'!I33)>12)*1)+SUMPRODUCT((('Jean-Charles-Bellefleur, Ellian'!I34+'Jean-Charles-Bellefleur, Ellian'!I35)>12)*1)+SUMPRODUCT((('Jean-Charles-Bellefleur, Ellian'!I36+'Jean-Charles-Bellefleur, Ellian'!I37)>12)*1)+SUMPRODUCT((('Jean-Charles-Bellefleur, Ellian'!I38+'Jean-Charles-Bellefleur, Ellian'!I39)>12)*1)+SUMPRODUCT((('Jean-Charles-Bellefleur, Ellian'!I40+'Jean-Charles-Bellefleur, Ellian'!I41)>12)*1)+SUMPRODUCT((('Jean-Charles-Bellefleur, Ellian'!I42+'Jean-Charles-Bellefleur, Ellian'!I43)>12)*1)+SUMPRODUCT((('Jean-Charles-Bellefleur, Ellian'!I45+'Jean-Charles-Bellefleur, Ellian'!I46)>12)*1)+SUMPRODUCT((('Jean-Charles-Bellefleur, Ellian'!I47+'Jean-Charles-Bellefleur, Ellian'!I48)>12)*1) | G52: =IF(MAX(SUM('Jean-Charles-Bellefleur, Ellian'!I14:I27),SUM('Jean-Charles-Bellefleur, Ellian'!I30:I43))>60,"Yes","") | H52: =IF(OR(AND(('Jean-Charles-Bellefleur, Ellian'!I14+'Jean-Charles-Bellefleur, Ellian'!I15)>0,('Jean-Charles-Bellefleur, Ellian'!I16+'Jean-Charles-Bellefleur, Ellian'!I17)>0,('Jean-Charles-Bellefleur, Ellian'!I18+'Jean-Charles-Bellefleur, Ellian'!I19)>0,('Jean-Charles-Bellefleur, Ellian'!I20+'Jean-Charles-Bellefleur, Ellian'!I21)>0,('Jean-Charles-Bellefleur, Ellian'!I22+'Jean-Charles-Bellefleur, Ellian'!I23)>0,('Jean-Charles-Bellefleur, Ellian'!I24+'Jean-Charles-Bellefleur, Ellian'!I25)>0,('Jean-Charles-Bellefleur, Ellian'!I26+'Jean-Charles-Bellefleur, Ellian'!I27)>0),AND(('Jean-Charles-Bellefleur, Ellian'!I30+'Jean-Charles-Bellefleur, Ellian'!I31)>0,('Jean-Charles-Bellefleur, Ellian'!I32+'Jean-Charles-Bellefleur, Ellian'!I33)>0,('Jean-Charles-Bellefleur, Ellian'!I34+'Jean-Charles-Bellefleur, Ellian'!I35)>0,('Jean-Charles-Bellefleur, Ellian'!I36+'Jean-Charles-Bellefleur, Ellian'!I37)>0,('Jean-Charles-Bellefleur, Ellian'!I38+'Jean-Charles-Bellefleur, Ellian'!I39)>0,('Jean-Charles-Bellefleur, Ellian'!I40+'Jean-Charles-Bellefleur, Ellian'!I41)>0,('Jean-Charles-Bellefleur, Ellian'!I42+'Jean-Charles-Bellefleur, Ellian'!I43)>0)),"Yes","") | I52: =IF('Jean-Charles-Bellefleur, Ellian'!N49>40,"Yes","") | J52: =IF(OR(AND(SUM('Jean-Charles-Bellefleur, Ellian'!I14:I27)>0,SUM('Jean-Charles-Bellefleur, Ellian'!I14:I27)<40),AND(SUM('Jean-Charles-Bellefleur, Ellian'!I30:I43)>0,SUM('Jean-Charles-Bellefleur, Ellian'!I30:I43)<40)),"Yes","") | K52: =SUMPRODUCT(('Jean-Charles-Bellefleur, Ellian'!I14:I48>0)*('Jean-Charles-Bellefleur, Ellian'!I14:I48<8)) | L52: =IF('Jean-Charles-Bellefleur, Ellian'!Q50<5,"Yes","") | M52: =IF(AND('Jean-Charles-Bellefleur, Ellian'!I49>0,'Jean-Charles-Bellefleur, Ellian'!I49<80),"Yes","") | N52: =IF(OR(F52>0,G52="Yes",H52="Yes",I52="Yes"),"⚠️ OVERWORK",IF(OR(J52="Yes",K52>0,L52="Yes",M52="Yes"),"🔻 UNDERWORK","✓ OK"))
A53: 49 | B53: Jerrick, Jacqueline | C53: 3499 | D53: ='Jerrick, Jacqueline'!I49 | E53: ='Jerrick, Jacqueline'!Q50 | F53: =SUMPRODUCT((('Jerrick, Jacqueline'!I14+'Jerrick, Jacqueline'!I15)>12)*1)+SUMPRODUCT((('Jerrick, Jacqueline'!I16+'Jerrick, Jacqueline'!I17)>12)*1)+SUMPRODUCT((('Jerrick, Jacqueline'!I18+'Jerrick, Jacqueline'!I19)>12)*1)+SUMPRODUCT((('Jerrick, Jacqueline'!I20+'Jerrick, Jacqueline'!I21)>12)*1)+SUMPRODUCT((('Jerrick, Jacqueline'!I22+'Jerrick, Jacqueline'!I23)>12)*1)+SUMPRODUCT((('Jerrick, Jacqueline'!I24+'Jerrick, Jacqueline'!I25)>12)*1)+SUMPRODUCT((('Jerrick, Jacqueline'!I26+'Jerrick, Jacqueline'!I27)>12)*1)+SUMPRODUCT((('Jerrick, Jacqueline'!I30+'Jerrick, Jacqueline'!I31)>12)*1)+SUMPRODUCT((('Jerrick, Jacqueline'!I32+'Jerrick, Jacqueline'!I33)>12)*1)+SUMPRODUCT((('Jerrick, Jacqueline'!I34+'Jerrick, Jacqueline'!I35)>12)*1)+SUMPRODUCT((('Jerrick, Jacqueline'!I36+'Jerrick, Jacqueline'!I37)>12)*1)+SUMPRODUCT((('Jerrick, Jacqueline'!I38+'Jerrick, Jacqueline'!I39)>12)*1)+SUMPRODUCT((('Jerrick, Jacqueline'!I40+'Jerrick, Jacqueline'!I41)>12)*1)+SUMPRODUCT((('Jerrick, Jacqueline'!I42+'Jerrick, Jacqueline'!I43)>12)*1)+SUMPRODUCT((('Jerrick, Jacqueline'!I45+'Jerrick, Jacqueline'!I46)>12)*1)+SUMPRODUCT((('Jerrick, Jacqueline'!I47+'Jerrick, Jacqueline'!I48)>12)*1) | G53: =IF(MAX(SUM('Jerrick, Jacqueline'!I14:I27),SUM('Jerrick, Jacqueline'!I30:I43))>60,"Yes","") | H53: =IF(OR(AND(('Jerrick, Jacqueline'!I14+'Jerrick, Jacqueline'!I15)>0,('Jerrick, Jacqueline'!I16+'Jerrick, Jacqueline'!I17)>0,('Jerrick, Jacqueline'!I18+'Jerrick, Jacqueline'!I19)>0,('Jerrick, Jacqueline'!I20+'Jerrick, Jacqueline'!I21)>0,('Jerrick, Jacqueline'!I22+'Jerrick, Jacqueline'!I23)>0,('Jerrick, Jacqueline'!I24+'Jerrick, Jacqueline'!I25)>0,('Jerrick, Jacqueline'!I26+'Jerrick, Jacqueline'!I27)>0),AND(('Jerrick, Jacqueline'!I30+'Jerrick, Jacqueline'!I31)>0,('Jerrick, Jacqueline'!I32+'Jerrick, Jacqueline'!I33)>0,('Jerrick, Jacqueline'!I34+'Jerrick, Jacqueline'!I35)>0,('Jerrick, Jacqueline'!I36+'Jerrick, Jacqueline'!I37)>0,('Jerrick, Jacqueline'!I38+'Jerrick, Jacqueline'!I39)>0,('Jerrick, Jacqueline'!I40+'Jerrick, Jacqueline'!I41)>0,('Jerrick, Jacqueline'!I42+'Jerrick, Jacqueline'!I43)>0)),"Yes","") | I53: =IF('Jerrick, Jacqueline'!N49>40,"Yes","") | J53: =IF(OR(AND(SUM('Jerrick, Jacqueline'!I14:I27)>0,SUM('Jerrick, Jacqueline'!I14:I27)<40),AND(SUM('Jerrick, Jacqueline'!I30:I43)>0,SUM('Jerrick, Jacqueline'!I30:I43)<40)),"Yes","") | K53: =SUMPRODUCT(('Jerrick, Jacqueline'!I14:I48>0)*('Jerrick, Jacqueline'!I14:I48<8)) | L53: =IF('Jerrick, Jacqueline'!Q50<5,"Yes","") | M53: =IF(AND('Jerrick, Jacqueline'!I49>0,'Jerrick, Jacqueline'!I49<80),"Yes","") | N53: =IF(OR(F53>0,G53="Yes",H53="Yes",I53="Yes"),"⚠️ OVERWORK",IF(OR(J53="Yes",K53>0,L53="Yes",M53="Yes"),"🔻 UNDERWORK","✓ OK"))
A54: 50 | B54: Jn Charles, Vital | C54: 5479 | D54: ='Jn Charles, Vital'!I49 | E54: ='Jn Charles, Vital'!Q50 | F54: =SUMPRODUCT((('Jn Charles, Vital'!I14+'Jn Charles, Vital'!I15)>12)*1)+SUMPRODUCT((('Jn Charles, Vital'!I16+'Jn Charles, Vital'!I17)>12)*1)+SUMPRODUCT((('Jn Charles, Vital'!I18+'Jn Charles, Vital'!I19)>12)*1)+SUMPRODUCT((('Jn Charles, Vital'!I20+'Jn Charles, Vital'!I21)>12)*1)+SUMPRODUCT((('Jn Charles, Vital'!I22+'Jn Charles, Vital'!I23)>12)*1)+SUMPRODUCT((('Jn Charles, Vital'!I24+'Jn Charles, Vital'!I25)>12)*1)+SUMPRODUCT((('Jn Charles, Vital'!I26+'Jn Charles, Vital'!I27)>12)*1)+SUMPRODUCT((('Jn Charles, Vital'!I30+'Jn Charles, Vital'!I31)>12)*1)+SUMPRODUCT((('Jn Charles, Vital'!I32+'Jn Charles, Vital'!I33)>12)*1)+SUMPRODUCT((('Jn Charles, Vital'!I34+'Jn Charles, Vital'!I35)>12)*1)+SUMPRODUCT((('Jn Charles, Vital'!I36+'Jn Charles, Vital'!I37)>12)*1)+SUMPRODUCT((('Jn Charles, Vital'!I38+'Jn Charles, Vital'!I39)>12)*1)+SUMPRODUCT((('Jn Charles, Vital'!I40+'Jn Charles, Vital'!I41)>12)*1)+SUMPRODUCT((('Jn Charles, Vital'!I42+'Jn Charles, Vital'!I43)>12)*1)+SUMPRODUCT((('Jn Charles, Vital'!I45+'Jn Charles, Vital'!I46)>12)*1)+SUMPRODUCT((('Jn Charles, Vital'!I47+'Jn Charles, Vital'!I48)>12)*1) | G54: =IF(MAX(SUM('Jn Charles, Vital'!I14:I27),SUM('Jn Charles, Vital'!I30:I43))>60,"Yes","") | H54: =IF(OR(AND(('Jn Charles, Vital'!I14+'Jn Charles, Vital'!I15)>0,('Jn Charles, Vital'!I16+'Jn Charles, Vital'!I17)>0,('Jn Charles, Vital'!I18+'Jn Charles, Vital'!I19)>0,('Jn Charles, Vital'!I20+'Jn Charles, Vital'!I21)>0,('Jn Charles, Vital'!I22+'Jn Charles, Vital'!I23)>0,('Jn Charles, Vital'!I24+'Jn Charles, Vital'!I25)>0,('Jn Charles, Vital'!I26+'Jn Charles, Vital'!I27)>0),AND(('Jn Charles, Vital'!I30+'Jn Charles, Vital'!I31)>0,('Jn Charles, Vital'!I32+'Jn Charles, Vital'!I33)>0,('Jn Charles, Vital'!I34+'Jn Charles, Vital'!I35)>0,('Jn Charles, Vital'!I36+'Jn Charles, Vital'!I37)>0,('Jn Charles, Vital'!I38+'Jn Charles, Vital'!I39)>0,('Jn Charles, Vital'!I40+'Jn Charles, Vital'!I41)>0,('Jn Charles, Vital'!I42+'Jn Charles, Vital'!I43)>0)),"Yes","") | I54: =IF('Jn Charles, Vital'!N49>40,"Yes","") | J54: =IF(OR(AND(SUM('Jn Charles, Vital'!I14:I27)>0,SUM('Jn Charles, Vital'!I14:I27)<40),AND(SUM('Jn Charles, Vital'!I30:I43)>0,SUM('Jn Charles, Vital'!I30:I43)<40)),"Yes","") | K54: =SUMPRODUCT(('Jn Charles, Vital'!I14:I48>0)*('Jn Charles, Vital'!I14:I48<8)) | L54: =IF('Jn Charles, Vital'!Q50<5,"Yes","") | M54: =IF(AND('Jn Charles, Vital'!I49>0,'Jn Charles, Vital'!I49<80),"Yes","") | N54: =IF(OR(F54>0,G54="Yes",H54="Yes",I54="Yes"),"⚠️ OVERWORK",IF(OR(J54="Yes",K54>0,L54="Yes",M54="Yes"),"🔻 UNDERWORK","✓ OK"))
A55: 51 | B55: Joe, Dawn Annitha | C55: 0970 | D55: ='Joe, Dawn Annitha'!I49 | E55: ='Joe, Dawn Annitha'!Q50 | F55: =SUMPRODUCT((('Joe, Dawn Annitha'!I14+'Joe, Dawn Annitha'!I15)>12)*1)+SUMPRODUCT((('Joe, Dawn Annitha'!I16+'Joe, Dawn Annitha'!I17)>12)*1)+SUMPRODUCT((('Joe, Dawn Annitha'!I18+'Joe, Dawn Annitha'!I19)>12)*1)+SUMPRODUCT((('Joe, Dawn Annitha'!I20+'Joe, Dawn Annitha'!I21)>12)*1)+SUMPRODUCT((('Joe, Dawn Annitha'!I22+'Joe, Dawn Annitha'!I23)>12)*1)+SUMPRODUCT((('Joe, Dawn Annitha'!I24+'Joe, Dawn Annitha'!I25)>12)*1)+SUMPRODUCT((('Joe, Dawn Annitha'!I26+'Joe, Dawn Annitha'!I27)>12)*1)+SUMPRODUCT((('Joe, Dawn Annitha'!I30+'Joe, Dawn Annitha'!I31)>12)*1)+SUMPRODUCT((('Joe, Dawn Annitha'!I32+'Joe, Dawn Annitha'!I33)>12)*1)+SUMPRODUCT((('Joe, Dawn Annitha'!I34+'Joe, Dawn Annitha'!I35)>12)*1)+SUMPRODUCT((('Joe, Dawn Annitha'!I36+'Joe, Dawn Annitha'!I37)>12)*1)+SUMPRODUCT((('Joe, Dawn Annitha'!I38+'Joe, Dawn Annitha'!I39)>12)*1)+SUMPRODUCT((('Joe, Dawn Annitha'!I40+'Joe, Dawn Annitha'!I41)>12)*1)+SUMPRODUCT((('Joe, Dawn Annitha'!I42+'Joe, Dawn Annitha'!I43)>12)*1)+SUMPRODUCT((('Joe, Dawn Annitha'!I45+'Joe, Dawn Annitha'!I46)>12)*1)+SUMPRODUCT((('Joe, Dawn Annitha'!I47+'Joe, Dawn Annitha'!I48)>12)*1) | G55: =IF(MAX(SUM('Joe, Dawn Annitha'!I14:I27),SUM('Joe, Dawn Annitha'!I30:I43))>60,"Yes","") | H55: =IF(OR(AND(('Joe, Dawn Annitha'!I14+'Joe, Dawn Annitha'!I15)>0,('Joe, Dawn Annitha'!I16+'Joe, Dawn Annitha'!I17)>0,('Joe, Dawn Annitha'!I18+'Joe, Dawn Annitha'!I19)>0,('Joe, Dawn Annitha'!I20+'Joe, Dawn Annitha'!I21)>0,('Joe, Dawn Annitha'!I22+'Joe, Dawn Annitha'!I23)>0,('Joe, Dawn Annitha'!I24+'Joe, Dawn Annitha'!I25)>0,('Joe, Dawn Annitha'!I26+'Joe, Dawn Annitha'!I27)>0),AND(('Joe, Dawn Annitha'!I30+'Joe, Dawn Annitha'!I31)>0,('Joe, Dawn Annitha'!I32+'Joe, Dawn Annitha'!I33)>0,('Joe, Dawn Annitha'!I34+'Joe, Dawn Annitha'!I35)>0,('Joe, Dawn Annitha'!I36+'Joe, Dawn Annitha'!I37)>0,('Joe, Dawn Annitha'!I38+'Joe, Dawn Annitha'!I39)>0,('Joe, Dawn Annitha'!I40+'Joe, Dawn Annitha'!I41)>0,('Joe, Dawn Annitha'!I42+'Joe, Dawn Annitha'!I43)>0)),"Yes","") | I55: =IF('Joe, Dawn Annitha'!N49>40,"Yes","") | J55: =IF(OR(AND(SUM('Joe, Dawn Annitha'!I14:I27)>0,SUM('Joe, Dawn Annitha'!I14:I27)<40),AND(SUM('Joe, Dawn Annitha'!I30:I43)>0,SUM('Joe, Dawn Annitha'!I30:I43)<40)),"Yes","") | K55: =SUMPRODUCT(('Joe, Dawn Annitha'!I14:I48>0)*('Joe, Dawn Annitha'!I14:I48<8)) | L55: =IF('Joe, Dawn Annitha'!Q50<5,"Yes","") | M55: =IF(AND('Joe, Dawn Annitha'!I49>0,'Joe, Dawn Annitha'!I49<80),"Yes","") | N55: =IF(OR(F55>0,G55="Yes",H55="Yes",I55="Yes"),"⚠️ OVERWORK",IF(OR(J55="Yes",K55>0,L55="Yes",M55="Yes"),"🔻 UNDERWORK","✓ OK"))
A56: 52 | B56: Joe, Yvette Pamela | C56: 4581 | D56: ='Joe, Yvette Pamela'!I49 | E56: ='Joe, Yvette Pamela'!Q50 | F56: =SUMPRODUCT((('Joe, Yvette Pamela'!I14+'Joe, Yvette Pamela'!I15)>12)*1)+SUMPRODUCT((('Joe, Yvette Pamela'!I16+'Joe, Yvette Pamela'!I17)>12)*1)+SUMPRODUCT((('Joe, Yvette Pamela'!I18+'Joe, Yvette Pamela'!I19)>12)*1)+SUMPRODUCT((('Joe, Yvette Pamela'!I20+'Joe, Yvette Pamela'!I21)>12)*1)+SUMPRODUCT((('Joe, Yvette Pamela'!I22+'Joe, Yvette Pamela'!I23)>12)*1)+SUMPRODUCT((('Joe, Yvette Pamela'!I24+'Joe, Yvette Pamela'!I25)>12)*1)+SUMPRODUCT((('Joe, Yvette Pamela'!I26+'Joe, Yvette Pamela'!I27)>12)*1)+SUMPRODUCT((('Joe, Yvette Pamela'!I30+'Joe, Yvette Pamela'!I31)>12)*1)+SUMPRODUCT((('Joe, Yvette Pamela'!I32+'Joe, Yvette Pamela'!I33)>12)*1)+SUMPRODUCT((('Joe, Yvette Pamela'!I34+'Joe, Yvette Pamela'!I35)>12)*1)+SUMPRODUCT((('Joe, Yvette Pamela'!I36+'Joe, Yvette Pamela'!I37)>12)*1)+SUMPRODUCT((('Joe, Yvette Pamela'!I38+'Joe, Yvette Pamela'!I39)>12)*1)+SUMPRODUCT((('Joe, Yvette Pamela'!I40+'Joe, Yvette Pamela'!I41)>12)*1)+SUMPRODUCT((('Joe, Yvette Pamela'!I42+'Joe, Yvette Pamela'!I43)>12)*1)+SUMPRODUCT((('Joe, Yvette Pamela'!I45+'Joe, Yvette Pamela'!I46)>12)*1)+SUMPRODUCT((('Joe, Yvette Pamela'!I47+'Joe, Yvette Pamela'!I48)>12)*1) | G56: =IF(MAX(SUM('Joe, Yvette Pamela'!I14:I27),SUM('Joe, Yvette Pamela'!I30:I43))>60,"Yes","") | H56: =IF(OR(AND(('Joe, Yvette Pamela'!I14+'Joe, Yvette Pamela'!I15)>0,('Joe, Yvette Pamela'!I16+'Joe, Yvette Pamela'!I17)>0,('Joe, Yvette Pamela'!I18+'Joe, Yvette Pamela'!I19)>0,('Joe, Yvette Pamela'!I20+'Joe, Yvette Pamela'!I21)>0,('Joe, Yvette Pamela'!I22+'Joe, Yvette Pamela'!I23)>0,('Joe, Yvette Pamela'!I24+'Joe, Yvette Pamela'!I25)>0,('Joe, Yvette Pamela'!I26+'Joe, Yvette Pamela'!I27)>0),AND(('Joe, Yvette Pamela'!I30+'Joe, Yvette Pamela'!I31)>0,('Joe, Yvette Pamela'!I32+'Joe, Yvette Pamela'!I33)>0,('Joe, Yvette Pamela'!I34+'Joe, Yvette Pamela'!I35)>0,('Joe, Yvette Pamela'!I36+'Joe, Yvette Pamela'!I37)>0,('Joe, Yvette Pamela'!I38+'Joe, Yvette Pamela'!I39)>0,('Joe, Yvette Pamela'!I40+'Joe, Yvette Pamela'!I41)>0,('Joe, Yvette Pamela'!I42+'Joe, Yvette Pamela'!I43)>0)),"Yes","") | I56: =IF('Joe, Yvette Pamela'!N49>40,"Yes","") | J56: =IF(OR(AND(SUM('Joe, Yvette Pamela'!I14:I27)>0,SUM('Joe, Yvette Pamela'!I14:I27)<40),AND(SUM('Joe, Yvette Pamela'!I30:I43)>0,SUM('Joe, Yvette Pamela'!I30:I43)<40)),"Yes","") | K56: =SUMPRODUCT(('Joe, Yvette Pamela'!I14:I48>0)*('Joe, Yvette Pamela'!I14:I48<8)) | L56: =IF('Joe, Yvette Pamela'!Q50<5,"Yes","") | M56: =IF(AND('Joe, Yvette Pamela'!I49>0,'Joe, Yvette Pamela'!I49<80),"Yes","") | N56: =IF(OR(F56>0,G56="Yes",H56="Yes",I56="Yes"),"⚠️ OVERWORK",IF(OR(J56="Yes",K56>0,L56="Yes",M56="Yes"),"🔻 UNDERWORK","✓ OK"))
A57: 53 | B57: Johnson, Carl Anthony | C57: 4127 | D57: ='Johnson, Carl Anthony'!I49 | E57: ='Johnson, Carl Anthony'!Q50 | F57: =SUMPRODUCT((('Johnson, Carl Anthony'!I14+'Johnson, Carl Anthony'!I15)>12)*1)+SUMPRODUCT((('Johnson, Carl Anthony'!I16+'Johnson, Carl Anthony'!I17)>12)*1)+SUMPRODUCT((('Johnson, Carl Anthony'!I18+'Johnson, Carl Anthony'!I19)>12)*1)+SUMPRODUCT((('Johnson, Carl Anthony'!I20+'Johnson, Carl Anthony'!I21)>12)*1)+SUMPRODUCT((('Johnson, Carl Anthony'!I22+'Johnson, Carl Anthony'!I23)>12)*1)+SUMPRODUCT((('Johnson, Carl Anthony'!I24+'Johnson, Carl Anthony'!I25)>12)*1)+SUMPRODUCT((('Johnson, Carl Anthony'!I26+'Johnson, Carl Anthony'!I27)>12)*1)+SUMPRODUCT((('Johnson, Carl Anthony'!I30+'Johnson, Carl Anthony'!I31)>12)*1)+SUMPRODUCT((('Johnson, Carl Anthony'!I32+'Johnson, Carl Anthony'!I33)>12)*1)+SUMPRODUCT((('Johnson, Carl Anthony'!I34+'Johnson, Carl Anthony'!I35)>12)*1)+SUMPRODUCT((('Johnson, Carl Anthony'!I36+'Johnson, Carl Anthony'!I37)>12)*1)+SUMPRODUCT((('Johnson, Carl Anthony'!I38+'Johnson, Carl Anthony'!I39)>12)*1)+SUMPRODUCT((('Johnson, Carl Anthony'!I40+'Johnson, Carl Anthony'!I41)>12)*1)+SUMPRODUCT((('Johnson, Carl Anthony'!I42+'Johnson, Carl Anthony'!I43)>12)*1)+SUMPRODUCT((('Johnson, Carl Anthony'!I45+'Johnson, Carl Anthony'!I46)>12)*1)+SUMPRODUCT((('Johnson, Carl Anthony'!I47+'Johnson, Carl Anthony'!I48)>12)*1) | G57: =IF(MAX(SUM('Johnson, Carl Anthony'!I14:I27),SUM('Johnson, Carl Anthony'!I30:I43))>60,"Yes","") | H57: =IF(OR(AND(('Johnson, Carl Anthony'!I14+'Johnson, Carl Anthony'!I15)>0,('Johnson, Carl Anthony'!I16+'Johnson, Carl Anthony'!I17)>0,('Johnson, Carl Anthony'!I18+'Johnson, Carl Anthony'!I19)>0,('Johnson, Carl Anthony'!I20+'Johnson, Carl Anthony'!I21)>0,('Johnson, Carl Anthony'!I22+'Johnson, Carl Anthony'!I23)>0,('Johnson, Carl Anthony'!I24+'Johnson, Carl Anthony'!I25)>0,('Johnson, Carl Anthony'!I26+'Johnson, Carl Anthony'!I27)>0),AND(('Johnson, Carl Anthony'!I30+'Johnson, Carl Anthony'!I31)>0,('Johnson, Carl Anthony'!I32+'Johnson, Carl Anthony'!I33)>0,('Johnson, Carl Anthony'!I34+'Johnson, Carl Anthony'!I35)>0,('Johnson, Carl Anthony'!I36+'Johnson, Carl Anthony'!I37)>0,('Johnson, Carl Anthony'!I38+'Johnson, Carl Anthony'!I39)>0,('Johnson, Carl Anthony'!I40+'Johnson, Carl Anthony'!I41)>0,('Johnson, Carl Anthony'!I42+'Johnson, Carl Anthony'!I43)>0)),"Yes","") | I57: =IF('Johnson, Carl Anthony'!N49>40,"Yes","") | J57: =IF(OR(AND(SUM('Johnson, Carl Anthony'!I14:I27)>0,SUM('Johnson, Carl Anthony'!I14:I27)<40),AND(SUM('Johnson, Carl Anthony'!I30:I43)>0,SUM('Johnson, Carl Anthony'!I30:I43)<40)),"Yes","") | K57: =SUMPRODUCT(('Johnson, Carl Anthony'!I14:I48>0)*('Johnson, Carl Anthony'!I14:I48<8)) | L57: =IF('Johnson, Carl Anthony'!Q50<5,"Yes","") | M57: =IF(AND('Johnson, Carl Anthony'!I49>0,'Johnson, Carl Anthony'!I49<80),"Yes","") | N57: =IF(OR(F57>0,G57="Yes",H57="Yes",I57="Yes"),"⚠️ OVERWORK",IF(OR(J57="Yes",K57>0,L57="Yes",M57="Yes"),"🔻 UNDERWORK","✓ OK"))
A58: 54 | B58: Johnson, Samanta Natasha | C58: 4381 | D58: ='Johnson, Samanta Natasha'!I49 | E58: ='Johnson, Samanta Natasha'!Q50 | F58: =SUMPRODUCT((('Johnson, Samanta Natasha'!I14+'Johnson, Samanta Natasha'!I15)>12)*1)+SUMPRODUCT((('Johnson, Samanta Natasha'!I16+'Johnson, Samanta Natasha'!I17)>12)*1)+SUMPRODUCT((('Johnson, Samanta Natasha'!I18+'Johnson, Samanta Natasha'!I19)>12)*1)+SUMPRODUCT((('Johnson, Samanta Natasha'!I20+'Johnson, Samanta Natasha'!I21)>12)*1)+SUMPRODUCT((('Johnson, Samanta Natasha'!I22+'Johnson, Samanta Natasha'!I23)>12)*1)+SUMPRODUCT((('Johnson, Samanta Natasha'!I24+'Johnson, Samanta Natasha'!I25)>12)*1)+SUMPRODUCT((('Johnson, Samanta Natasha'!I26+'Johnson, Samanta Natasha'!I27)>12)*1)+SUMPRODUCT((('Johnson, Samanta Natasha'!I30+'Johnson, Samanta Natasha'!I31)>12)*1)+SUMPRODUCT((('Johnson, Samanta Natasha'!I32+'Johnson, Samanta Natasha'!I33)>12)*1)+SUMPRODUCT((('Johnson, Samanta Natasha'!I34+'Johnson, Samanta Natasha'!I35)>12)*1)+SUMPRODUCT((('Johnson, Samanta Natasha'!I36+'Johnson, Samanta Natasha'!I37)>12)*1)+SUMPRODUCT((('Johnson, Samanta Natasha'!I38+'Johnson, Samanta Natasha'!I39)>12)*1)+SUMPRODUCT((('Johnson, Samanta Natasha'!I40+'Johnson, Samanta Natasha'!I41)>12)*1)+SUMPRODUCT((('Johnson, Samanta Natasha'!I42+'Johnson, Samanta Natasha'!I43)>12)*1)+SUMPRODUCT((('Johnson, Samanta Natasha'!I45+'Johnson, Samanta Natasha'!I46)>12)*1)+SUMPRODUCT((('Johnson, Samanta Natasha'!I47+'Johnson, Samanta Natasha'!I48)>12)*1) | G58: =IF(MAX(SUM('Johnson, Samanta Natasha'!I14:I27),SUM('Johnson, Samanta Natasha'!I30:I43))>60,"Yes","") | H58: =IF(OR(AND(('Johnson, Samanta Natasha'!I14+'Johnson, Samanta Natasha'!I15)>0,('Johnson, Samanta Natasha'!I16+'Johnson, Samanta Natasha'!I17)>0,('Johnson, Samanta Natasha'!I18+'Johnson, Samanta Natasha'!I19)>0,('Johnson, Samanta Natasha'!I20+'Johnson, Samanta Natasha'!I21)>0,('Johnson, Samanta Natasha'!I22+'Johnson, Samanta Natasha'!I23)>0,('Johnson, Samanta Natasha'!I24+'Johnson, Samanta Natasha'!I25)>0,('Johnson, Samanta Natasha'!I26+'Johnson, Samanta Natasha'!I27)>0),AND(('Johnson, Samanta Natasha'!I30+'Johnson, Samanta Natasha'!I31)>0,('Johnson, Samanta Natasha'!I32+'Johnson, Samanta Natasha'!I33)>0,('Johnson, Samanta Natasha'!I34+'Johnson, Samanta Natasha'!I35)>0,('Johnson, Samanta Natasha'!I36+'Johnson, Samanta Natasha'!I37)>0,('Johnson, Samanta Natasha'!I38+'Johnson, Samanta Natasha'!I39)>0,('Johnson, Samanta Natasha'!I40+'Johnson, Samanta Natasha'!I41)>0,('Johnson, Samanta Natasha'!I42+'Johnson, Samanta Natasha'!I43)>0)),"Yes","") | I58: =IF('Johnson, Samanta Natasha'!N49>40,"Yes","") | J58: =IF(OR(AND(SUM('Johnson, Samanta Natasha'!I14:I27)>0,SUM('Johnson, Samanta Natasha'!I14:I27)<40),AND(SUM('Johnson, Samanta Natasha'!I30:I43)>0,SUM('Johnson, Samanta Natasha'!I30:I43)<40)),"Yes","") | K58: =SUMPRODUCT(('Johnson, Samanta Natasha'!I14:I48>0)*('Johnson, Samanta Natasha'!I14:I48<8)) | L58: =IF('Johnson, Samanta Natasha'!Q50<5,"Yes","") | M58: =IF(AND('Johnson, Samanta Natasha'!I49>0,'Johnson, Samanta Natasha'!I49<80),"Yes","") | N58: =IF(OR(F58>0,G58="Yes",H58="Yes",I58="Yes"),"⚠️ OVERWORK",IF(OR(J58="Yes",K58>0,L58="Yes",M58="Yes"),"🔻 UNDERWORK","✓ OK"))
A59: 55 | B59: Joseph, Arlene | C59: 3573 | D59: ='Joseph, Arlene'!I49 | E59: ='Joseph, Arlene'!Q50 | F59: =SUMPRODUCT((('Joseph, Arlene'!I14+'Joseph, Arlene'!I15)>12)*1)+SUMPRODUCT((('Joseph, Arlene'!I16+'Joseph, Arlene'!I17)>12)*1)+SUMPRODUCT((('Joseph, Arlene'!I18+'Joseph, Arlene'!I19)>12)*1)+SUMPRODUCT((('Joseph, Arlene'!I20+'Joseph, Arlene'!I21)>12)*1)+SUMPRODUCT((('Joseph, Arlene'!I22+'Joseph, Arlene'!I23)>12)*1)+SUMPRODUCT((('Joseph, Arlene'!I24+'Joseph, Arlene'!I25)>12)*1)+SUMPRODUCT((('Joseph, Arlene'!I26+'Joseph, Arlene'!I27)>12)*1)+SUMPRODUCT((('Joseph, Arlene'!I30+'Joseph, Arlene'!I31)>12)*1)+SUMPRODUCT((('Joseph, Arlene'!I32+'Joseph, Arlene'!I33)>12)*1)+SUMPRODUCT((('Joseph, Arlene'!I34+'Joseph, Arlene'!I35)>12)*1)+SUMPRODUCT((('Joseph, Arlene'!I36+'Joseph, Arlene'!I37)>12)*1)+SUMPRODUCT((('Joseph, Arlene'!I38+'Joseph, Arlene'!I39)>12)*1)+SUMPRODUCT((('Joseph, Arlene'!I40+'Joseph, Arlene'!I41)>12)*1)+SUMPRODUCT((('Joseph, Arlene'!I42+'Joseph, Arlene'!I43)>12)*1)+SUMPRODUCT((('Joseph, Arlene'!I45+'Joseph, Arlene'!I46)>12)*1)+SUMPRODUCT((('Joseph, Arlene'!I47+'Joseph, Arlene'!I48)>12)*1) | G59: =IF(MAX(SUM('Joseph, Arlene'!I14:I27),SUM('Joseph, Arlene'!I30:I43))>60,"Yes","") | H59: =IF(OR(AND(('Joseph, Arlene'!I14+'Joseph, Arlene'!I15)>0,('Joseph, Arlene'!I16+'Joseph, Arlene'!I17)>0,('Joseph, Arlene'!I18+'Joseph, Arlene'!I19)>0,('Joseph, Arlene'!I20+'Joseph, Arlene'!I21)>0,('Joseph, Arlene'!I22+'Joseph, Arlene'!I23)>0,('Joseph, Arlene'!I24+'Joseph, Arlene'!I25)>0,('Joseph, Arlene'!I26+'Joseph, Arlene'!I27)>0),AND(('Joseph, Arlene'!I30+'Joseph, Arlene'!I31)>0,('Joseph, Arlene'!I32+'Joseph, Arlene'!I33)>0,('Joseph, Arlene'!I34+'Joseph, Arlene'!I35)>0,('Joseph, Arlene'!I36+'Joseph, Arlene'!I37)>0,('Joseph, Arlene'!I38+'Joseph, Arlene'!I39)>0,('Joseph, Arlene'!I40+'Joseph, Arlene'!I41)>0,('Joseph, Arlene'!I42+'Joseph, Arlene'!I43)>0)),"Yes","") | I59: =IF('Joseph, Arlene'!N49>40,"Yes","") | J59: =IF(OR(AND(SUM('Joseph, Arlene'!I14:I27)>0,SUM('Joseph, Arlene'!I14:I27)<40),AND(SUM('Joseph, Arlene'!I30:I43)>0,SUM('Joseph, Arlene'!I30:I43)<40)),"Yes","") | K59: =SUMPRODUCT(('Joseph, Arlene'!I14:I48>0)*('Joseph, Arlene'!I14:I48<8)) | L59: =IF('Joseph, Arlene'!Q50<5,"Yes","") | M59: =IF(AND('Joseph, Arlene'!I49>0,'Joseph, Arlene'!I49<80),"Yes","") | N59: =IF(OR(F59>0,G59="Yes",H59="Yes",I59="Yes"),"⚠️ OVERWORK",IF(OR(J59="Yes",K59>0,L59="Yes",M59="Yes"),"🔻 UNDERWORK","✓ OK"))
A60: 56 | B60: Joseph, Ivan King | C60: 5460 | D60: ='Joseph, Ivan King'!I49 | E60: ='Joseph, Ivan King'!Q50 | F60: =SUMPRODUCT((('Joseph, Ivan King'!I14+'Joseph, Ivan King'!I15)>12)*1)+SUMPRODUCT((('Joseph, Ivan King'!I16+'Joseph, Ivan King'!I17)>12)*1)+SUMPRODUCT((('Joseph, Ivan King'!I18+'Joseph, Ivan King'!I19)>12)*1)+SUMPRODUCT((('Joseph, Ivan King'!I20+'Joseph, Ivan King'!I21)>12)*1)+SUMPRODUCT((('Joseph, Ivan King'!I22+'Joseph, Ivan King'!I23)>12)*1)+SUMPRODUCT((('Joseph, Ivan King'!I24+'Joseph, Ivan King'!I25)>12)*1)+SUMPRODUCT((('Joseph, Ivan King'!I26+'Joseph, Ivan King'!I27)>12)*1)+SUMPRODUCT((('Joseph, Ivan King'!I30+'Joseph, Ivan King'!I31)>12)*1)+SUMPRODUCT((('Joseph, Ivan King'!I32+'Joseph, Ivan King'!I33)>12)*1)+SUMPRODUCT((('Joseph, Ivan King'!I34+'Joseph, Ivan King'!I35)>12)*1)+SUMPRODUCT((('Joseph, Ivan King'!I36+'Joseph, Ivan King'!I37)>12)*1)+SUMPRODUCT((('Joseph, Ivan King'!I38+'Joseph, Ivan King'!I39)>12)*1)+SUMPRODUCT((('Joseph, Ivan King'!I40+'Joseph, Ivan King'!I41)>12)*1)+SUMPRODUCT((('Joseph, Ivan King'!I42+'Joseph, Ivan King'!I43)>12)*1)+SUMPRODUCT((('Joseph, Ivan King'!I45+'Joseph, Ivan King'!I46)>12)*1)+SUMPRODUCT((('Joseph, Ivan King'!I47+'Joseph, Ivan King'!I48)>12)*1) | G60: =IF(MAX(SUM('Joseph, Ivan King'!I14:I27),SUM('Joseph, Ivan King'!I30:I43))>60,"Yes","") | H60: =IF(OR(AND(('Joseph, Ivan King'!I14+'Joseph, Ivan King'!I15)>0,('Joseph, Ivan King'!I16+'Joseph, Ivan King'!I17)>0,('Joseph, Ivan King'!I18+'Joseph, Ivan King'!I19)>0,('Joseph, Ivan King'!I20+'Joseph, Ivan King'!I21)>0,('Joseph, Ivan King'!I22+'Joseph, Ivan King'!I23)>0,('Joseph, Ivan King'!I24+'Joseph, Ivan King'!I25)>0,('Joseph, Ivan King'!I26+'Joseph, Ivan King'!I27)>0),AND(('Joseph, Ivan King'!I30+'Joseph, Ivan King'!I31)>0,('Joseph, Ivan King'!I32+'Joseph, Ivan King'!I33)>0,('Joseph, Ivan King'!I34+'Joseph, Ivan King'!I35)>0,('Joseph, Ivan King'!I36+'Joseph, Ivan King'!I37)>0,('Joseph, Ivan King'!I38+'Joseph, Ivan King'!I39)>0,('Joseph, Ivan King'!I40+'Joseph, Ivan King'!I41)>0,('Joseph, Ivan King'!I42+'Joseph, Ivan King'!I43)>0)),"Yes","") | I60: =IF('Joseph, Ivan King'!N49>40,"Yes","") | J60: =IF(OR(AND(SUM('Joseph, Ivan King'!I14:I27)>0,SUM('Joseph, Ivan King'!I14:I27)<40),AND(SUM('Joseph, Ivan King'!I30:I43)>0,SUM('Joseph, Ivan King'!I30:I43)<40)),"Yes","") | K60: =SUMPRODUCT(('Joseph, Ivan King'!I14:I48>0)*('Joseph, Ivan King'!I14:I48<8)) | L60: =IF('Joseph, Ivan King'!Q50<5,"Yes","") | M60: =IF(AND('Joseph, Ivan King'!I49>0,'Joseph, Ivan King'!I49<80),"Yes","") | N60: =IF(OR(F60>0,G60="Yes",H60="Yes",I60="Yes"),"⚠️ OVERWORK",IF(OR(J60="Yes",K60>0,L60="Yes",M60="Yes"),"🔻 UNDERWORK","✓ OK"))
A61: 57 | B61: Julian, Maurice Mark | C61: 1044 | D61: ='Julian, Maurice Mark'!I49 | E61: ='Julian, Maurice Mark'!Q50 | F61: =SUMPRODUCT((('Julian, Maurice Mark'!I14+'Julian, Maurice Mark'!I15)>12)*1)+SUMPRODUCT((('Julian, Maurice Mark'!I16+'Julian, Maurice Mark'!I17)>12)*1)+SUMPRODUCT((('Julian, Maurice Mark'!I18+'Julian, Maurice Mark'!I19)>12)*1)+SUMPRODUCT((('Julian, Maurice Mark'!I20+'Julian, Maurice Mark'!I21)>12)*1)+SUMPRODUCT((('Julian, Maurice Mark'!I22+'Julian, Maurice Mark'!I23)>12)*1)+SUMPRODUCT((('Julian, Maurice Mark'!I24+'Julian, Maurice Mark'!I25)>12)*1)+SUMPRODUCT((('Julian, Maurice Mark'!I26+'Julian, Maurice Mark'!I27)>12)*1)+SUMPRODUCT((('Julian, Maurice Mark'!I30+'Julian, Maurice Mark'!I31)>12)*1)+SUMPRODUCT((('Julian, Maurice Mark'!I32+'Julian, Maurice Mark'!I33)>12)*1)+SUMPRODUCT((('Julian, Maurice Mark'!I34+'Julian, Maurice Mark'!I35)>12)*1)+SUMPRODUCT((('Julian, Maurice Mark'!I36+'Julian, Maurice Mark'!I37)>12)*1)+SUMPRODUCT((('Julian, Maurice Mark'!I38+'Julian, Maurice Mark'!I39)>12)*1)+SUMPRODUCT((('Julian, Maurice Mark'!I40+'Julian, Maurice Mark'!I41)>12)*1)+SUMPRODUCT((('Julian, Maurice Mark'!I42+'Julian, Maurice Mark'!I43)>12)*1)+SUMPRODUCT((('Julian, Maurice Mark'!I45+'Julian, Maurice Mark'!I46)>12)*1)+SUMPRODUCT((('Julian, Maurice Mark'!I47+'Julian, Maurice Mark'!I48)>12)*1) | G61: =IF(MAX(SUM('Julian, Maurice Mark'!I14:I27),SUM('Julian, Maurice Mark'!I30:I43))>60,"Yes","") | H61: =IF(OR(AND(('Julian, Maurice Mark'!I14+'Julian, Maurice Mark'!I15)>0,('Julian, Maurice Mark'!I16+'Julian, Maurice Mark'!I17)>0,('Julian, Maurice Mark'!I18+'Julian, Maurice Mark'!I19)>0,('Julian, Maurice Mark'!I20+'Julian, Maurice Mark'!I21)>0,('Julian, Maurice Mark'!I22+'Julian, Maurice Mark'!I23)>0,('Julian, Maurice Mark'!I24+'Julian, Maurice Mark'!I25)>0,('Julian, Maurice Mark'!I26+'Julian, Maurice Mark'!I27)>0),AND(('Julian, Maurice Mark'!I30+'Julian, Maurice Mark'!I31)>0,('Julian, Maurice Mark'!I32+'Julian, Maurice Mark'!I33)>0,('Julian, Maurice Mark'!I34+'Julian, Maurice Mark'!I35)>0,('Julian, Maurice Mark'!I36+'Julian, Maurice Mark'!I37)>0,('Julian, Maurice Mark'!I38+'Julian, Maurice Mark'!I39)>0,('Julian, Maurice Mark'!I40+'Julian, Maurice Mark'!I41)>0,('Julian, Maurice Mark'!I42+'Julian, Maurice Mark'!I43)>0)),"Yes","") | I61: =IF('Julian, Maurice Mark'!N49>40,"Yes","") | J61: =IF(OR(AND(SUM('Julian, Maurice Mark'!I14:I27)>0,SUM('Julian, Maurice Mark'!I14:I27)<40),AND(SUM('Julian, Maurice Mark'!I30:I43)>0,SUM('Julian, Maurice Mark'!I30:I43)<40)),"Yes","") | K61: =SUMPRODUCT(('Julian, Maurice Mark'!I14:I48>0)*('Julian, Maurice Mark'!I14:I48<8)) | L61: =IF('Julian, Maurice Mark'!Q50<5,"Yes","") | M61: =IF(AND('Julian, Maurice Mark'!I49>0,'Julian, Maurice Mark'!I49<80),"Yes","") | N61: =IF(OR(F61>0,G61="Yes",H61="Yes",I61="Yes"),"⚠️ OVERWORK",IF(OR(J61="Yes",K61>0,L61="Yes",M61="Yes"),"🔻 UNDERWORK","✓ OK"))
A62: 58 | B62: Jupiter, Moira Natalie | C62: 4410 | D62: ='Jupiter, Moira Natalie'!I49 | E62: ='Jupiter, Moira Natalie'!Q50 | F62: =SUMPRODUCT((('Jupiter, Moira Natalie'!I14+'Jupiter, Moira Natalie'!I15)>12)*1)+SUMPRODUCT((('Jupiter, Moira Natalie'!I16+'Jupiter, Moira Natalie'!I17)>12)*1)+SUMPRODUCT((('Jupiter, Moira Natalie'!I18+'Jupiter, Moira Natalie'!I19)>12)*1)+SUMPRODUCT((('Jupiter, Moira Natalie'!I20+'Jupiter, Moira Natalie'!I21)>12)*1)+SUMPRODUCT((('Jupiter, Moira Natalie'!I22+'Jupiter, Moira Natalie'!I23)>12)*1)+SUMPRODUCT((('Jupiter, Moira Natalie'!I24+'Jupiter, Moira Natalie'!I25)>12)*1)+SUMPRODUCT((('Jupiter, Moira Natalie'!I26+'Jupiter, Moira Natalie'!I27)>12)*1)+SUMPRODUCT((('Jupiter, Moira Natalie'!I30+'Jupiter, Moira Natalie'!I31)>12)*1)+SUMPRODUCT((('Jupiter, Moira Natalie'!I32+'Jupiter, Moira Natalie'!I33)>12)*1)+SUMPRODUCT((('Jupiter, Moira Natalie'!I34+'Jupiter, Moira Natalie'!I35)>12)*1)+SUMPRODUCT((('Jupiter, Moira Natalie'!I36+'Jupiter, Moira Natalie'!I37)>12)*1)+SUMPRODUCT((('Jupiter, Moira Natalie'!I38+'Jupiter, Moira Natalie'!I39)>12)*1)+SUMPRODUCT((('Jupiter, Moira Natalie'!I40+'Jupiter, Moira Natalie'!I41)>12)*1)+SUMPRODUCT((('Jupiter, Moira Natalie'!I42+'Jupiter, Moira Natalie'!I43)>12)*1)+SUMPRODUCT((('Jupiter, Moira Natalie'!I45+'Jupiter, Moira Natalie'!I46)>12)*1)+SUMPRODUCT((('Jupiter, Moira Natalie'!I47+'Jupiter, Moira Natalie'!I48)>12)*1) | G62: =IF(MAX(SUM('Jupiter, Moira Natalie'!I14:I27),SUM('Jupiter, Moira Natalie'!I30:I43))>60,"Yes","") | H62: =IF(OR(AND(('Jupiter, Moira Natalie'!I14+'Jupiter, Moira Natalie'!I15)>0,('Jupiter, Moira Natalie'!I16+'Jupiter, Moira Natalie'!I17)>0,('Jupiter, Moira Natalie'!I18+'Jupiter, Moira Natalie'!I19)>0,('Jupiter, Moira Natalie'!I20+'Jupiter, Moira Natalie'!I21)>0,('Jupiter, Moira Natalie'!I22+'Jupiter, Moira Natalie'!I23)>0,('Jupiter, Moira Natalie'!I24+'Jupiter, Moira Natalie'!I25)>0,('Jupiter, Moira Natalie'!I26+'Jupiter, Moira Natalie'!I27)>0),AND(('Jupiter, Moira Natalie'!I30+'Jupiter, Moira Natalie'!I31)>0,('Jupiter, Moira Natalie'!I32+'Jupiter, Moira Natalie'!I33)>0,('Jupiter, Moira Natalie'!I34+'Jupiter, Moira Natalie'!I35)>0,('Jupiter, Moira Natalie'!I36+'Jupiter, Moira Natalie'!I37)>0,('Jupiter, Moira Natalie'!I38+'Jupiter, Moira Natalie'!I39)>0,('Jupiter, Moira Natalie'!I40+'Jupiter, Moira Natalie'!I41)>0,('Jupiter, Moira Natalie'!I42+'Jupiter, Moira Natalie'!I43)>0)),"Yes","") | I62: =IF('Jupiter, Moira Natalie'!N49>40,"Yes","") | J62: =IF(OR(AND(SUM('Jupiter, Moira Natalie'!I14:I27)>0,SUM('Jupiter, Moira Natalie'!I14:I27)<40),AND(SUM('Jupiter, Moira Natalie'!I30:I43)>0,SUM('Jupiter, Moira Natalie'!I30:I43)<40)),"Yes","") | K62: =SUMPRODUCT(('Jupiter, Moira Natalie'!I14:I48>0)*('Jupiter, Moira Natalie'!I14:I48<8)) | L62: =IF('Jupiter, Moira Natalie'!Q50<5,"Yes","") | M62: =IF(AND('Jupiter, Moira Natalie'!I49>0,'Jupiter, Moira Natalie'!I49<80),"Yes","") | N62: =IF(OR(F62>0,G62="Yes",H62="Yes",I62="Yes"),"⚠️ OVERWORK",IF(OR(J62="Yes",K62>0,L62="Yes",M62="Yes"),"🔻 UNDERWORK","✓ OK"))
A63: 59 | B63: Kanhai, Grace | C63: 2657 | D63: ='Kanhai, Grace'!I49 | E63: ='Kanhai, Grace'!Q50 | F63: =SUMPRODUCT((('Kanhai, Grace'!I14+'Kanhai, Grace'!I15)>12)*1)+SUMPRODUCT((('Kanhai, Grace'!I16+'Kanhai, Grace'!I17)>12)*1)+SUMPRODUCT((('Kanhai, Grace'!I18+'Kanhai, Grace'!I19)>12)*1)+SUMPRODUCT((('Kanhai, Grace'!I20+'Kanhai, Grace'!I21)>12)*1)+SUMPRODUCT((('Kanhai, Grace'!I22+'Kanhai, Grace'!I23)>12)*1)+SUMPRODUCT((('Kanhai, Grace'!I24+'Kanhai, Grace'!I25)>12)*1)+SUMPRODUCT((('Kanhai, Grace'!I26+'Kanhai, Grace'!I27)>12)*1)+SUMPRODUCT((('Kanhai, Grace'!I30+'Kanhai, Grace'!I31)>12)*1)+SUMPRODUCT((('Kanhai, Grace'!I32+'Kanhai, Grace'!I33)>12)*1)+SUMPRODUCT((('Kanhai, Grace'!I34+'Kanhai, Grace'!I35)>12)*1)+SUMPRODUCT((('Kanhai, Grace'!I36+'Kanhai, Grace'!I37)>12)*1)+SUMPRODUCT((('Kanhai, Grace'!I38+'Kanhai, Grace'!I39)>12)*1)+SUMPRODUCT((('Kanhai, Grace'!I40+'Kanhai, Grace'!I41)>12)*1)+SUMPRODUCT((('Kanhai, Grace'!I42+'Kanhai, Grace'!I43)>12)*1)+SUMPRODUCT((('Kanhai, Grace'!I45+'Kanhai, Grace'!I46)>12)*1)+SUMPRODUCT((('Kanhai, Grace'!I47+'Kanhai, Grace'!I48)>12)*1) | G63: =IF(MAX(SUM('Kanhai, Grace'!I14:I27),SUM('Kanhai, Grace'!I30:I43))>60,"Yes","") | H63: =IF(OR(AND(('Kanhai, Grace'!I14+'Kanhai, Grace'!I15)>0,('Kanhai, Grace'!I16+'Kanhai, Grace'!I17)>0,('Kanhai, Grace'!I18+'Kanhai, Grace'!I19)>0,('Kanhai, Grace'!I20+'Kanhai, Grace'!I21)>0,('Kanhai, Grace'!I22+'Kanhai, Grace'!I23)>0,('Kanhai, Grace'!I24+'Kanhai, Grace'!I25)>0,('Kanhai, Grace'!I26+'Kanhai, Grace'!I27)>0),AND(('Kanhai, Grace'!I30+'Kanhai, Grace'!I31)>0,('Kanhai, Grace'!I32+'Kanhai, Grace'!I33)>0,('Kanhai, Grace'!I34+'Kanhai, Grace'!I35)>0,('Kanhai, Grace'!I36+'Kanhai, Grace'!I37)>0,('Kanhai, Grace'!I38+'Kanhai, Grace'!I39)>0,('Kanhai, Grace'!I40+'Kanhai, Grace'!I41)>0,('Kanhai, Grace'!I42+'Kanhai, Grace'!I43)>0)),"Yes","") | I63: =IF('Kanhai, Grace'!N49>40,"Yes","") | J63: =IF(OR(AND(SUM('Kanhai, Grace'!I14:I27)>0,SUM('Kanhai, Grace'!I14:I27)<40),AND(SUM('Kanhai, Grace'!I30:I43)>0,SUM('Kanhai, Grace'!I30:I43)<40)),"Yes","") | K63: =SUMPRODUCT(('Kanhai, Grace'!I14:I48>0)*('Kanhai, Grace'!I14:I48<8)) | L63: =IF('Kanhai, Grace'!Q50<5,"Yes","") | M63: =IF(AND('Kanhai, Grace'!I49>0,'Kanhai, Grace'!I49<80),"Yes","") | N63: =IF(OR(F63>0,G63="Yes",H63="Yes",I63="Yes"),"⚠️ OVERWORK",IF(OR(J63="Yes",K63>0,L63="Yes",M63="Yes"),"🔻 UNDERWORK","✓ OK"))
A64: 60 | B64: Leow, Donovan Antonio | C64: 5333 | D64: ='Leow, Donovan Antonio'!I49 | E64: ='Leow, Donovan Antonio'!Q50 | F64: =SUMPRODUCT((('Leow, Donovan Antonio'!I14+'Leow, Donovan Antonio'!I15)>12)*1)+SUMPRODUCT((('Leow, Donovan Antonio'!I16+'Leow, Donovan Antonio'!I17)>12)*1)+SUMPRODUCT((('Leow, Donovan Antonio'!I18+'Leow, Donovan Antonio'!I19)>12)*1)+SUMPRODUCT((('Leow, Donovan Antonio'!I20+'Leow, Donovan Antonio'!I21)>12)*1)+SUMPRODUCT((('Leow, Donovan Antonio'!I22+'Leow, Donovan Antonio'!I23)>12)*1)+SUMPRODUCT((('Leow, Donovan Antonio'!I24+'Leow, Donovan Antonio'!I25)>12)*1)+SUMPRODUCT((('Leow, Donovan Antonio'!I26+'Leow, Donovan Antonio'!I27)>12)*1)+SUMPRODUCT((('Leow, Donovan Antonio'!I30+'Leow, Donovan Antonio'!I31)>12)*1)+SUMPRODUCT((('Leow, Donovan Antonio'!I32+'Leow, Donovan Antonio'!I33)>12)*1)+SUMPRODUCT((('Leow, Donovan Antonio'!I34+'Leow, Donovan Antonio'!I35)>12)*1)+SUMPRODUCT((('Leow, Donovan Antonio'!I36+'Leow, Donovan Antonio'!I37)>12)*1)+SUMPRODUCT((('Leow, Donovan Antonio'!I38+'Leow, Donovan Antonio'!I39)>12)*1)+SUMPRODUCT((('Leow, Donovan Antonio'!I40+'Leow, Donovan Antonio'!I41)>12)*1)+SUMPRODUCT((('Leow, Donovan Antonio'!I42+'Leow, Donovan Antonio'!I43)>12)*1)+SUMPRODUCT((('Leow, Donovan Antonio'!I45+'Leow, Donovan Antonio'!I46)>12)*1)+SUMPRODUCT((('Leow, Donovan Antonio'!I47+'Leow, Donovan Antonio'!I48)>12)*1) | G64: =IF(MAX(SUM('Leow, Donovan Antonio'!I14:I27),SUM('Leow, Donovan Antonio'!I30:I43))>60,"Yes","") | H64: =IF(OR(AND(('Leow, Donovan Antonio'!I14+'Leow, Donovan Antonio'!I15)>0,('Leow, Donovan Antonio'!I16+'Leow, Donovan Antonio'!I17)>0,('Leow, Donovan Antonio'!I18+'Leow, Donovan Antonio'!I19)>0,('Leow, Donovan Antonio'!I20+'Leow, Donovan Antonio'!I21)>0,('Leow, Donovan Antonio'!I22+'Leow, Donovan Antonio'!I23)>0,('Leow, Donovan Antonio'!I24+'Leow, Donovan Antonio'!I25)>0,('Leow, Donovan Antonio'!I26+'Leow, Donovan Antonio'!I27)>0),AND(('Leow, Donovan Antonio'!I30+'Leow, Donovan Antonio'!I31)>0,('Leow, Donovan Antonio'!I32+'Leow, Donovan Antonio'!I33)>0,('Leow, Donovan Antonio'!I34+'Leow, Donovan Antonio'!I35)>0,('Leow, Donovan Antonio'!I36+'Leow, Donovan Antonio'!I37)>0,('Leow, Donovan Antonio'!I38+'Leow, Donovan Antonio'!I39)>0,('Leow, Donovan Antonio'!I40+'Leow, Donovan Antonio'!I41)>0,('Leow, Donovan Antonio'!I42+'Leow, Donovan Antonio'!I43)>0)),"Yes","") | I64: =IF('Leow, Donovan Antonio'!N49>40,"Yes","") | J64: =IF(OR(AND(SUM('Leow, Donovan Antonio'!I14:I27)>0,SUM('Leow, Donovan Antonio'!I14:I27)<40),AND(SUM('Leow, Donovan Antonio'!I30:I43)>0,SUM('Leow, Donovan Antonio'!I30:I43)<40)),"Yes","") | K64: =SUMPRODUCT(('Leow, Donovan Antonio'!I14:I48>0)*('Leow, Donovan Antonio'!I14:I48<8)) | L64: =IF('Leow, Donovan Antonio'!Q50<5,"Yes","") | M64: =IF(AND('Leow, Donovan Antonio'!I49>0,'Leow, Donovan Antonio'!I49<80),"Yes","") | N64: =IF(OR(F64>0,G64="Yes",H64="Yes",I64="Yes"),"⚠️ OVERWORK",IF(OR(J64="Yes",K64>0,L64="Yes",M64="Yes"),"🔻 UNDERWORK","✓ OK"))
A65: 61 | B65: Lesperance, Lorance | C65: 5483 | D65: ='Lesperance, Lorance'!I49 | E65: ='Lesperance, Lorance'!Q50 | F65: =SUMPRODUCT((('Lesperance, Lorance'!I14+'Lesperance, Lorance'!I15)>12)*1)+SUMPRODUCT((('Lesperance, Lorance'!I16+'Lesperance, Lorance'!I17)>12)*1)+SUMPRODUCT((('Lesperance, Lorance'!I18+'Lesperance, Lorance'!I19)>12)*1)+SUMPRODUCT((('Lesperance, Lorance'!I20+'Lesperance, Lorance'!I21)>12)*1)+SUMPRODUCT((('Lesperance, Lorance'!I22+'Lesperance, Lorance'!I23)>12)*1)+SUMPRODUCT((('Lesperance, Lorance'!I24+'Lesperance, Lorance'!I25)>12)*1)+SUMPRODUCT((('Lesperance, Lorance'!I26+'Lesperance, Lorance'!I27)>12)*1)+SUMPRODUCT((('Lesperance, Lorance'!I30+'Lesperance, Lorance'!I31)>12)*1)+SUMPRODUCT((('Lesperance, Lorance'!I32+'Lesperance, Lorance'!I33)>12)*1)+SUMPRODUCT((('Lesperance, Lorance'!I34+'Lesperance, Lorance'!I35)>12)*1)+SUMPRODUCT((('Lesperance, Lorance'!I36+'Lesperance, Lorance'!I37)>12)*1)+SUMPRODUCT((('Lesperance, Lorance'!I38+'Lesperance, Lorance'!I39)>12)*1)+SUMPRODUCT((('Lesperance, Lorance'!I40+'Lesperance, Lorance'!I41)>12)*1)+SUMPRODUCT((('Lesperance, Lorance'!I42+'Lesperance, Lorance'!I43)>12)*1)+SUMPRODUCT((('Lesperance, Lorance'!I45+'Lesperance, Lorance'!I46)>12)*1)+SUMPRODUCT((('Lesperance, Lorance'!I47+'Lesperance, Lorance'!I48)>12)*1) | G65: =IF(MAX(SUM('Lesperance, Lorance'!I14:I27),SUM('Lesperance, Lorance'!I30:I43))>60,"Yes","") | H65: =IF(OR(AND(('Lesperance, Lorance'!I14+'Lesperance, Lorance'!I15)>0,('Lesperance, Lorance'!I16+'Lesperance, Lorance'!I17)>0,('Lesperance, Lorance'!I18+'Lesperance, Lorance'!I19)>0,('Lesperance, Lorance'!I20+'Lesperance, Lorance'!I21)>0,('Lesperance, Lorance'!I22+'Lesperance, Lorance'!I23)>0,('Lesperance, Lorance'!I24+'Lesperance, Lorance'!I25)>0,('Lesperance, Lorance'!I26+'Lesperance, Lorance'!I27)>0),AND(('Lesperance, Lorance'!I30+'Lesperance, Lorance'!I31)>0,('Lesperance, Lorance'!I32+'Lesperance, Lorance'!I33)>0,('Lesperance, Lorance'!I34+'Lesperance, Lorance'!I35)>0,('Lesperance, Lorance'!I36+'Lesperance, Lorance'!I37)>0,('Lesperance, Lorance'!I38+'Lesperance, Lorance'!I39)>0,('Lesperance, Lorance'!I40+'Lesperance, Lorance'!I41)>0,('Lesperance, Lorance'!I42+'Lesperance, Lorance'!I43)>0)),"Yes","") | I65: =IF('Lesperance, Lorance'!N49>40,"Yes","") | J65: =IF(OR(AND(SUM('Lesperance, Lorance'!I14:I27)>0,SUM('Lesperance, Lorance'!I14:I27)<40),AND(SUM('Lesperance, Lorance'!I30:I43)>0,SUM('Lesperance, Lorance'!I30:I43)<40)),"Yes","") | K65: =SUMPRODUCT(('Lesperance, Lorance'!I14:I48>0)*('Lesperance, Lorance'!I14:I48<8)) | L65: =IF('Lesperance, Lorance'!Q50<5,"Yes","") | M65: =IF(AND('Lesperance, Lorance'!I49>0,'Lesperance, Lorance'!I49<80),"Yes","") | N65: =IF(OR(F65>0,G65="Yes",H65="Yes",I65="Yes"),"⚠️ OVERWORK",IF(OR(J65="Yes",K65>0,L65="Yes",M65="Yes"),"🔻 UNDERWORK","✓ OK"))
A66: 62 | B66: London, Desiree | C66: 3416 | D66: ='London, Desiree'!I49 | E66: ='London, Desiree'!Q50 | F66: =SUMPRODUCT((('London, Desiree'!I14+'London, Desiree'!I15)>12)*1)+SUMPRODUCT((('London, Desiree'!I16+'London, Desiree'!I17)>12)*1)+SUMPRODUCT((('London, Desiree'!I18+'London, Desiree'!I19)>12)*1)+SUMPRODUCT((('London, Desiree'!I20+'London, Desiree'!I21)>12)*1)+SUMPRODUCT((('London, Desiree'!I22+'London, Desiree'!I23)>12)*1)+SUMPRODUCT((('London, Desiree'!I24+'London, Desiree'!I25)>12)*1)+SUMPRODUCT((('London, Desiree'!I26+'London, Desiree'!I27)>12)*1)+SUMPRODUCT((('London, Desiree'!I30+'London, Desiree'!I31)>12)*1)+SUMPRODUCT((('London, Desiree'!I32+'London, Desiree'!I33)>12)*1)+SUMPRODUCT((('London, Desiree'!I34+'London, Desiree'!I35)>12)*1)+SUMPRODUCT((('London, Desiree'!I36+'London, Desiree'!I37)>12)*1)+SUMPRODUCT((('London, Desiree'!I38+'London, Desiree'!I39)>12)*1)+SUMPRODUCT((('London, Desiree'!I40+'London, Desiree'!I41)>12)*1)+SUMPRODUCT((('London, Desiree'!I42+'London, Desiree'!I43)>12)*1)+SUMPRODUCT((('London, Desiree'!I45+'London, Desiree'!I46)>12)*1)+SUMPRODUCT((('London, Desiree'!I47+'London, Desiree'!I48)>12)*1) | G66: =IF(MAX(SUM('London, Desiree'!I14:I27),SUM('London, Desiree'!I30:I43))>60,"Yes","") | H66: =IF(OR(AND(('London, Desiree'!I14+'London, Desiree'!I15)>0,('London, Desiree'!I16+'London, Desiree'!I17)>0,('London, Desiree'!I18+'London, Desiree'!I19)>0,('London, Desiree'!I20+'London, Desiree'!I21)>0,('London, Desiree'!I22+'London, Desiree'!I23)>0,('London, Desiree'!I24+'London, Desiree'!I25)>0,('London, Desiree'!I26+'London, Desiree'!I27)>0),AND(('London, Desiree'!I30+'London, Desiree'!I31)>0,('London, Desiree'!I32+'London, Desiree'!I33)>0,('London, Desiree'!I34+'London, Desiree'!I35)>0,('London, Desiree'!I36+'London, Desiree'!I37)>0,('London, Desiree'!I38+'London, Desiree'!I39)>0,('London, Desiree'!I40+'London, Desiree'!I41)>0,('London, Desiree'!I42+'London, Desiree'!I43)>0)),"Yes","") | I66: =IF('London, Desiree'!N49>40,"Yes","") | J66: =IF(OR(AND(SUM('London, Desiree'!I14:I27)>0,SUM('London, Desiree'!I14:I27)<40),AND(SUM('London, Desiree'!I30:I43)>0,SUM('London, Desiree'!I30:I43)<40)),"Yes","") | K66: =SUMPRODUCT(('London, Desiree'!I14:I48>0)*('London, Desiree'!I14:I48<8)) | L66: =IF('London, Desiree'!Q50<5,"Yes","") | M66: =IF(AND('London, Desiree'!I49>0,'London, Desiree'!I49<80),"Yes","") | N66: =IF(OR(F66>0,G66="Yes",H66="Yes",I66="Yes"),"⚠️ OVERWORK",IF(OR(J66="Yes",K66>0,L66="Yes",M66="Yes"),"🔻 UNDERWORK","✓ OK"))
A67: 63 | B67: Lucas, Akida Maurissa | C67: 5530 | D67: ='Lucas, Akida Maurissa'!I49 | E67: ='Lucas, Akida Maurissa'!Q50 | F67: =SUMPRODUCT((('Lucas, Akida Maurissa'!I14+'Lucas, Akida Maurissa'!I15)>12)*1)+SUMPRODUCT((('Lucas, Akida Maurissa'!I16+'Lucas, Akida Maurissa'!I17)>12)*1)+SUMPRODUCT((('Lucas, Akida Maurissa'!I18+'Lucas, Akida Maurissa'!I19)>12)*1)+SUMPRODUCT((('Lucas, Akida Maurissa'!I20+'Lucas, Akida Maurissa'!I21)>12)*1)+SUMPRODUCT((('Lucas, Akida Maurissa'!I22+'Lucas, Akida Maurissa'!I23)>12)*1)+SUMPRODUCT((('Lucas, Akida Maurissa'!I24+'Lucas, Akida Maurissa'!I25)>12)*1)+SUMPRODUCT((('Lucas, Akida Maurissa'!I26+'Lucas, Akida Maurissa'!I27)>12)*1)+SUMPRODUCT((('Lucas, Akida Maurissa'!I30+'Lucas, Akida Maurissa'!I31)>12)*1)+SUMPRODUCT((('Lucas, Akida Maurissa'!I32+'Lucas, Akida Maurissa'!I33)>12)*1)+SUMPRODUCT((('Lucas, Akida Maurissa'!I34+'Lucas, Akida Maurissa'!I35)>12)*1)+SUMPRODUCT((('Lucas, Akida Maurissa'!I36+'Lucas, Akida Maurissa'!I37)>12)*1)+SUMPRODUCT((('Lucas, Akida Maurissa'!I38+'Lucas, Akida Maurissa'!I39)>12)*1)+SUMPRODUCT((('Lucas, Akida Maurissa'!I40+'Lucas, Akida Maurissa'!I41)>12)*1)+SUMPRODUCT((('Lucas, Akida Maurissa'!I42+'Lucas, Akida Maurissa'!I43)>12)*1)+SUMPRODUCT((('Lucas, Akida Maurissa'!I45+'Lucas, Akida Maurissa'!I46)>12)*1)+SUMPRODUCT((('Lucas, Akida Maurissa'!I47+'Lucas, Akida Maurissa'!I48)>12)*1) | G67: =IF(MAX(SUM('Lucas, Akida Maurissa'!I14:I27),SUM('Lucas, Akida Maurissa'!I30:I43))>60,"Yes","") | H67: =IF(OR(AND(('Lucas, Akida Maurissa'!I14+'Lucas, Akida Maurissa'!I15)>0,('Lucas, Akida Maurissa'!I16+'Lucas, Akida Maurissa'!I17)>0,('Lucas, Akida Maurissa'!I18+'Lucas, Akida Maurissa'!I19)>0,('Lucas, Akida Maurissa'!I20+'Lucas, Akida Maurissa'!I21)>0,('Lucas, Akida Maurissa'!I22+'Lucas, Akida Maurissa'!I23)>0,('Lucas, Akida Maurissa'!I24+'Lucas, Akida Maurissa'!I25)>0,('Lucas, Akida Maurissa'!I26+'Lucas, Akida Maurissa'!I27)>0),AND(('Lucas, Akida Maurissa'!I30+'Lucas, Akida Maurissa'!I31)>0,('Lucas, Akida Maurissa'!I32+'Lucas, Akida Maurissa'!I33)>0,('Lucas, Akida Maurissa'!I34+'Lucas, Akida Maurissa'!I35)>0,('Lucas, Akida Maurissa'!I36+'Lucas, Akida Maurissa'!I37)>0,('Lucas, Akida Maurissa'!I38+'Lucas, Akida Maurissa'!I39)>0,('Lucas, Akida Maurissa'!I40+'Lucas, Akida Maurissa'!I41)>0,('Lucas, Akida Maurissa'!I42+'Lucas, Akida Maurissa'!I43)>0)),"Yes","") | I67: =IF('Lucas, Akida Maurissa'!N49>40,"Yes","") | J67: =IF(OR(AND(SUM('Lucas, Akida Maurissa'!I14:I27)>0,SUM('Lucas, Akida Maurissa'!I14:I27)<40),AND(SUM('Lucas, Akida Maurissa'!I30:I43)>0,SUM('Lucas, Akida Maurissa'!I30:I43)<40)),"Yes","") | K67: =SUMPRODUCT(('Lucas, Akida Maurissa'!I14:I48>0)*('Lucas, Akida Maurissa'!I14:I48<8)) | L67: =IF('Lucas, Akida Maurissa'!Q50<5,"Yes","") | M67: =IF(AND('Lucas, Akida Maurissa'!I49>0,'Lucas, Akida Maurissa'!I49<80),"Yes","") | N67: =IF(OR(F67>0,G67="Yes",H67="Yes",I67="Yes"),"⚠️ OVERWORK",IF(OR(J67="Yes",K67>0,L67="Yes",M67="Yes"),"🔻 UNDERWORK","✓ OK"))
A68: 64 | B68: Lyken, Janessa Nodata | C68: 1094 | D68: ='Lyken, Janessa Nodata'!I49 | E68: ='Lyken, Janessa Nodata'!Q50 | F68: =SUMPRODUCT((('Lyken, Janessa Nodata'!I14+'Lyken, Janessa Nodata'!I15)>12)*1)+SUMPRODUCT((('Lyken, Janessa Nodata'!I16+'Lyken, Janessa Nodata'!I17)>12)*1)+SUMPRODUCT((('Lyken, Janessa Nodata'!I18+'Lyken, Janessa Nodata'!I19)>12)*1)+SUMPRODUCT((('Lyken, Janessa Nodata'!I20+'Lyken, Janessa Nodata'!I21)>12)*1)+SUMPRODUCT((('Lyken, Janessa Nodata'!I22+'Lyken, Janessa Nodata'!I23)>12)*1)+SUMPRODUCT((('Lyken, Janessa Nodata'!I24+'Lyken, Janessa Nodata'!I25)>12)*1)+SUMPRODUCT((('Lyken, Janessa Nodata'!I26+'Lyken, Janessa Nodata'!I27)>12)*1)+SUMPRODUCT((('Lyken, Janessa Nodata'!I30+'Lyken, Janessa Nodata'!I31)>12)*1)+SUMPRODUCT((('Lyken, Janessa Nodata'!I32+'Lyken, Janessa Nodata'!I33)>12)*1)+SUMPRODUCT((('Lyken, Janessa Nodata'!I34+'Lyken, Janessa Nodata'!I35)>12)*1)+SUMPRODUCT((('Lyken, Janessa Nodata'!I36+'Lyken, Janessa Nodata'!I37)>12)*1)+SUMPRODUCT((('Lyken, Janessa Nodata'!I38+'Lyken, Janessa Nodata'!I39)>12)*1)+SUMPRODUCT((('Lyken, Janessa Nodata'!I40+'Lyken, Janessa Nodata'!I41)>12)*1)+SUMPRODUCT((('Lyken, Janessa Nodata'!I42+'Lyken, Janessa Nodata'!I43)>12)*1)+SUMPRODUCT((('Lyken, Janessa Nodata'!I45+'Lyken, Janessa Nodata'!I46)>12)*1)+SUMPRODUCT((('Lyken, Janessa Nodata'!I47+'Lyken, Janessa Nodata'!I48)>12)*1) | G68: =IF(MAX(SUM('Lyken, Janessa Nodata'!I14:I27),SUM('Lyken, Janessa Nodata'!I30:I43))>60,"Yes","") | H68: =IF(OR(AND(('Lyken, Janessa Nodata'!I14+'Lyken, Janessa Nodata'!I15)>0,('Lyken, Janessa Nodata'!I16+'Lyken, Janessa Nodata'!I17)>0,('Lyken, Janessa Nodata'!I18+'Lyken, Janessa Nodata'!I19)>0,('Lyken, Janessa Nodata'!I20+'Lyken, Janessa Nodata'!I21)>0,('Lyken, Janessa Nodata'!I22+'Lyken, Janessa Nodata'!I23)>0,('Lyken, Janessa Nodata'!I24+'Lyken, Janessa Nodata'!I25)>0,('Lyken, Janessa Nodata'!I26+'Lyken, Janessa Nodata'!I27)>0),AND(('Lyken, Janessa Nodata'!I30+'Lyken, Janessa Nodata'!I31)>0,('Lyken, Janessa Nodata'!I32+'Lyken, Janessa Nodata'!I33)>0,('Lyken, Janessa Nodata'!I34+'Lyken, Janessa Nodata'!I35)>0,('Lyken, Janessa Nodata'!I36+'Lyken, Janessa Nodata'!I37)>0,('Lyken, Janessa Nodata'!I38+'Lyken, Janessa Nodata'!I39)>0,('Lyken, Janessa Nodata'!I40+'Lyken, Janessa Nodata'!I41)>0,('Lyken, Janessa Nodata'!I42+'Lyken, Janessa Nodata'!I43)>0)),"Yes","") | I68: =IF('Lyken, Janessa Nodata'!N49>40,"Yes","") | J68: =IF(OR(AND(SUM('Lyken, Janessa Nodata'!I14:I27)>0,SUM('Lyken, Janessa Nodata'!I14:I27)<40),AND(SUM('Lyken, Janessa Nodata'!I30:I43)>0,SUM('Lyken, Janessa Nodata'!I30:I43)<40)),"Yes","") | K68: =SUMPRODUCT(('Lyken, Janessa Nodata'!I14:I48>0)*('Lyken, Janessa Nodata'!I14:I48<8)) | L68: =IF('Lyken, Janessa Nodata'!Q50<5,"Yes","") | M68: =IF(AND('Lyken, Janessa Nodata'!I49>0,'Lyken, Janessa Nodata'!I49<80),"Yes","") | N68: =IF(OR(F68>0,G68="Yes",H68="Yes",I68="Yes"),"⚠️ OVERWORK",IF(OR(J68="Yes",K68>0,L68="Yes",M68="Yes"),"🔻 UNDERWORK","✓ OK"))
A69: 65 | B69: Mc Almont, Philip Edward | C69: 2254 | D69: ='Mc Almont, Philip Edward'!I49 | E69: ='Mc Almont, Philip Edward'!Q50 | F69: =SUMPRODUCT((('Mc Almont, Philip Edward'!I14+'Mc Almont, Philip Edward'!I15)>12)*1)+SUMPRODUCT((('Mc Almont, Philip Edward'!I16+'Mc Almont, Philip Edward'!I17)>12)*1)+SUMPRODUCT((('Mc Almont, Philip Edward'!I18+'Mc Almont, Philip Edward'!I19)>12)*1)+SUMPRODUCT((('Mc Almont, Philip Edward'!I20+'Mc Almont, Philip Edward'!I21)>12)*1)+SUMPRODUCT((('Mc Almont, Philip Edward'!I22+'Mc Almont, Philip Edward'!I23)>12)*1)+SUMPRODUCT((('Mc Almont, Philip Edward'!I24+'Mc Almont, Philip Edward'!I25)>12)*1)+SUMPRODUCT((('Mc Almont, Philip Edward'!I26+'Mc Almont, Philip Edward'!I27)>12)*1)+SUMPRODUCT((('Mc Almont, Philip Edward'!I30+'Mc Almont, Philip Edward'!I31)>12)*1)+SUMPRODUCT((('Mc Almont, Philip Edward'!I32+'Mc Almont, Philip Edward'!I33)>12)*1)+SUMPRODUCT((('Mc Almont, Philip Edward'!I34+'Mc Almont, Philip Edward'!I35)>12)*1)+SUMPRODUCT((('Mc Almont, Philip Edward'!I36+'Mc Almont, Philip Edward'!I37)>12)*1)+SUMPRODUCT((('Mc Almont, Philip Edward'!I38+'Mc Almont, Philip Edward'!I39)>12)*1)+SUMPRODUCT((('Mc Almont, Philip Edward'!I40+'Mc Almont, Philip Edward'!I41)>12)*1)+SUMPRODUCT((('Mc Almont, Philip Edward'!I42+'Mc Almont, Philip Edward'!I43)>12)*1)+SUMPRODUCT((('Mc Almont, Philip Edward'!I45+'Mc Almont, Philip Edward'!I46)>12)*1)+SUMPRODUCT((('Mc Almont, Philip Edward'!I47+'Mc Almont, Philip Edward'!I48)>12)*1) | G69: =IF(MAX(SUM('Mc Almont, Philip Edward'!I14:I27),SUM('Mc Almont, Philip Edward'!I30:I43))>60,"Yes","") | H69: =IF(OR(AND(('Mc Almont, Philip Edward'!I14+'Mc Almont, Philip Edward'!I15)>0,('Mc Almont, Philip Edward'!I16+'Mc Almont, Philip Edward'!I17)>0,('Mc Almont, Philip Edward'!I18+'Mc Almont, Philip Edward'!I19)>0,('Mc Almont, Philip Edward'!I20+'Mc Almont, Philip Edward'!I21)>0,('Mc Almont, Philip Edward'!I22+'Mc Almont, Philip Edward'!I23)>0,('Mc Almont, Philip Edward'!I24+'Mc Almont, Philip Edward'!I25)>0,('Mc Almont, Philip Edward'!I26+'Mc Almont, Philip Edward'!I27)>0),AND(('Mc Almont, Philip Edward'!I30+'Mc Almont, Philip Edward'!I31)>0,('Mc Almont, Philip Edward'!I32+'Mc Almont, Philip Edward'!I33)>0,('Mc Almont, Philip Edward'!I34+'Mc Almont, Philip Edward'!I35)>0,('Mc Almont, Philip Edward'!I36+'Mc Almont, Philip Edward'!I37)>0,('Mc Almont, Philip Edward'!I38+'Mc Almont, Philip Edward'!I39)>0,('Mc Almont, Philip Edward'!I40+'Mc Almont, Philip Edward'!I41)>0,('Mc Almont, Philip Edward'!I42+'Mc Almont, Philip Edward'!I43)>0)),"Yes","") | I69: =IF('Mc Almont, Philip Edward'!N49>40,"Yes","") | J69: =IF(OR(AND(SUM('Mc Almont, Philip Edward'!I14:I27)>0,SUM('Mc Almont, Philip Edward'!I14:I27)<40),AND(SUM('Mc Almont, Philip Edward'!I30:I43)>0,SUM('Mc Almont, Philip Edward'!I30:I43)<40)),"Yes","") | K69: =SUMPRODUCT(('Mc Almont, Philip Edward'!I14:I48>0)*('Mc Almont, Philip Edward'!I14:I48<8)) | L69: =IF('Mc Almont, Philip Edward'!Q50<5,"Yes","") | M69: =IF(AND('Mc Almont, Philip Edward'!I49>0,'Mc Almont, Philip Edward'!I49<80),"Yes","") | N69: =IF(OR(F69>0,G69="Yes",H69="Yes",I69="Yes"),"⚠️ OVERWORK",IF(OR(J69="Yes",K69>0,L69="Yes",M69="Yes"),"🔻 UNDERWORK","✓ OK"))
A70: 66 | B70: Mc Caddy, Shundell | C70: 1392 | D70: ='Mc Caddy, Shundell'!I49 | E70: ='Mc Caddy, Shundell'!Q50 | F70: =SUMPRODUCT((('Mc Caddy, Shundell'!I14+'Mc Caddy, Shundell'!I15)>12)*1)+SUMPRODUCT((('Mc Caddy, Shundell'!I16+'Mc Caddy, Shundell'!I17)>12)*1)+SUMPRODUCT((('Mc Caddy, Shundell'!I18+'Mc Caddy, Shundell'!I19)>12)*1)+SUMPRODUCT((('Mc Caddy, Shundell'!I20+'Mc Caddy, Shundell'!I21)>12)*1)+SUMPRODUCT((('Mc Caddy, Shundell'!I22+'Mc Caddy, Shundell'!I23)>12)*1)+SUMPRODUCT((('Mc Caddy, Shundell'!I24+'Mc Caddy, Shundell'!I25)>12)*1)+SUMPRODUCT((('Mc Caddy, Shundell'!I26+'Mc Caddy, Shundell'!I27)>12)*1)+SUMPRODUCT((('Mc Caddy, Shundell'!I30+'Mc Caddy, Shundell'!I31)>12)*1)+SUMPRODUCT((('Mc Caddy, Shundell'!I32+'Mc Caddy, Shundell'!I33)>12)*1)+SUMPRODUCT((('Mc Caddy, Shundell'!I34+'Mc Caddy, Shundell'!I35)>12)*1)+SUMPRODUCT((('Mc Caddy, Shundell'!I36+'Mc Caddy, Shundell'!I37)>12)*1)+SUMPRODUCT((('Mc Caddy, Shundell'!I38+'Mc Caddy, Shundell'!I39)>12)*1)+SUMPRODUCT((('Mc Caddy, Shundell'!I40+'Mc Caddy, Shundell'!I41)>12)*1)+SUMPRODUCT((('Mc Caddy, Shundell'!I42+'Mc Caddy, Shundell'!I43)>12)*1)+SUMPRODUCT((('Mc Caddy, Shundell'!I45+'Mc Caddy, Shundell'!I46)>12)*1)+SUMPRODUCT((('Mc Caddy, Shundell'!I47+'Mc Caddy, Shundell'!I48)>12)*1) | G70: =IF(MAX(SUM('Mc Caddy, Shundell'!I14:I27),SUM('Mc Caddy, Shundell'!I30:I43))>60,"Yes","") | H70: =IF(OR(AND(('Mc Caddy, Shundell'!I14+'Mc Caddy, Shundell'!I15)>0,('Mc Caddy, Shundell'!I16+'Mc Caddy, Shundell'!I17)>0,('Mc Caddy, Shundell'!I18+'Mc Caddy, Shundell'!I19)>0,('Mc Caddy, Shundell'!I20+'Mc Caddy, Shundell'!I21)>0,('Mc Caddy, Shundell'!I22+'Mc Caddy, Shundell'!I23)>0,('Mc Caddy, Shundell'!I24+'Mc Caddy, Shundell'!I25)>0,('Mc Caddy, Shundell'!I26+'Mc Caddy, Shundell'!I27)>0),AND(('Mc Caddy, Shundell'!I30+'Mc Caddy, Shundell'!I31)>0,('Mc Caddy, Shundell'!I32+'Mc Caddy, Shundell'!I33)>0,('Mc Caddy, Shundell'!I34+'Mc Caddy, Shundell'!I35)>0,('Mc Caddy, Shundell'!I36+'Mc Caddy, Shundell'!I37)>0,('Mc Caddy, Shundell'!I38+'Mc Caddy, Shundell'!I39)>0,('Mc Caddy, Shundell'!I40+'Mc Caddy, Shundell'!I41)>0,('Mc Caddy, Shundell'!I42+'Mc Caddy, Shundell'!I43)>0)),"Yes","") | I70: =IF('Mc Caddy, Shundell'!N49>40,"Yes","") | J70: =IF(OR(AND(SUM('Mc Caddy, Shundell'!I14:I27)>0,SUM('Mc Caddy, Shundell'!I14:I27)<40),AND(SUM('Mc Caddy, Shundell'!I30:I43)>0,SUM('Mc Caddy, Shundell'!I30:I43)<40)),"Yes","") | K70: =SUMPRODUCT(('Mc Caddy, Shundell'!I14:I48>0)*('Mc Caddy, Shundell'!I14:I48<8)) | L70: =IF('Mc Caddy, Shundell'!Q50<5,"Yes","") | M70: =IF(AND('Mc Caddy, Shundell'!I49>0,'Mc Caddy, Shundell'!I49<80),"Yes","") | N70: =IF(OR(F70>0,G70="Yes",H70="Yes",I70="Yes"),"⚠️ OVERWORK",IF(OR(J70="Yes",K70>0,L70="Yes",M70="Yes"),"🔻 UNDERWORK","✓ OK"))
A71: 67 | B71: Mc Calmont, Karen Marcelle | C71: 1966 | D71: ='Mc Calmont, Karen Marcelle'!I49 | E71: ='Mc Calmont, Karen Marcelle'!Q50 | F71: =SUMPRODUCT((('Mc Calmont, Karen Marcelle'!I14+'Mc Calmont, Karen Marcelle'!I15)>12)*1)+SUMPRODUCT((('Mc Calmont, Karen Marcelle'!I16+'Mc Calmont, Karen Marcelle'!I17)>12)*1)+SUMPRODUCT((('Mc Calmont, Karen Marcelle'!I18+'Mc Calmont, Karen Marcelle'!I19)>12)*1)+SUMPRODUCT((('Mc Calmont, Karen Marcelle'!I20+'Mc Calmont, Karen Marcelle'!I21)>12)*1)+SUMPRODUCT((('Mc Calmont, Karen Marcelle'!I22+'Mc Calmont, Karen Marcelle'!I23)>12)*1)+SUMPRODUCT((('Mc Calmont, Karen Marcelle'!I24+'Mc Calmont, Karen Marcelle'!I25)>12)*1)+SUMPRODUCT((('Mc Calmont, Karen Marcelle'!I26+'Mc Calmont, Karen Marcelle'!I27)>12)*1)+SUMPRODUCT((('Mc Calmont, Karen Marcelle'!I30+'Mc Calmont, Karen Marcelle'!I31)>12)*1)+SUMPRODUCT((('Mc Calmont, Karen Marcelle'!I32+'Mc Calmont, Karen Marcelle'!I33)>12)*1)+SUMPRODUCT((('Mc Calmont, Karen Marcelle'!I34+'Mc Calmont, Karen Marcelle'!I35)>12)*1)+SUMPRODUCT((('Mc Calmont, Karen Marcelle'!I36+'Mc Calmont, Karen Marcelle'!I37)>12)*1)+SUMPRODUCT((('Mc Calmont, Karen Marcelle'!I38+'Mc Calmont, Karen Marcelle'!I39)>12)*1)+SUMPRODUCT((('Mc Calmont, Karen Marcelle'!I40+'Mc Calmont, Karen Marcelle'!I41)>12)*1)+SUMPRODUCT((('Mc Calmont, Karen Marcelle'!I42+'Mc Calmont, Karen Marcelle'!I43)>12)*1)+SUMPRODUCT((('Mc Calmont, Karen Marcelle'!I45+'Mc Calmont, Karen Marcelle'!I46)>12)*1)+SUMPRODUCT((('Mc Calmont, Karen Marcelle'!I47+'Mc Calmont, Karen Marcelle'!I48)>12)*1) | G71: =IF(MAX(SUM('Mc Calmont, Karen Marcelle'!I14:I27),SUM('Mc Calmont, Karen Marcelle'!I30:I43))>60,"Yes","") | H71: =IF(OR(AND(('Mc Calmont, Karen Marcelle'!I14+'Mc Calmont, Karen Marcelle'!I15)>0,('Mc Calmont, Karen Marcelle'!I16+'Mc Calmont, Karen Marcelle'!I17)>0,('Mc Calmont, Karen Marcelle'!I18+'Mc Calmont, Karen Marcelle'!I19)>0,('Mc Calmont, Karen Marcelle'!I20+'Mc Calmont, Karen Marcelle'!I21)>0,('Mc Calmont, Karen Marcelle'!I22+'Mc Calmont, Karen Marcelle'!I23)>0,('Mc Calmont, Karen Marcelle'!I24+'Mc Calmont, Karen Marcelle'!I25)>0,('Mc Calmont, Karen Marcelle'!I26+'Mc Calmont, Karen Marcelle'!I27)>0),AND(('Mc Calmont, Karen Marcelle'!I30+'Mc Calmont, Karen Marcelle'!I31)>0,('Mc Calmont, Karen Marcelle'!I32+'Mc Calmont, Karen Marcelle'!I33)>0,('Mc Calmont, Karen Marcelle'!I34+'Mc Calmont, Karen Marcelle'!I35)>0,('Mc Calmont, Karen Marcelle'!I36+'Mc Calmont, Karen Marcelle'!I37)>0,('Mc Calmont, Karen Marcelle'!I38+'Mc Calmont, Karen Marcelle'!I39)>0,('Mc Calmont, Karen Marcelle'!I40+'Mc Calmont, Karen Marcelle'!I41)>0,('Mc Calmont, Karen Marcelle'!I42+'Mc Calmont, Karen Marcelle'!I43)>0)),"Yes","") | I71: =IF('Mc Calmont, Karen Marcelle'!N49>40,"Yes","") | J71: =IF(OR(AND(SUM('Mc Calmont, Karen Marcelle'!I14:I27)>0,SUM('Mc Calmont, Karen Marcelle'!I14:I27)<40),AND(SUM('Mc Calmont, Karen Marcelle'!I30:I43)>0,SUM('Mc Calmont, Karen Marcelle'!I30:I43)<40)),"Yes","") | K71: =SUMPRODUCT(('Mc Calmont, Karen Marcelle'!I14:I48>0)*('Mc Calmont, Karen Marcelle'!I14:I48<8)) | L71: =IF('Mc Calmont, Karen Marcelle'!Q50<5,"Yes","") | M71: =IF(AND('Mc Calmont, Karen Marcelle'!I49>0,'Mc Calmont, Karen Marcelle'!I49<80),"Yes","") | N71: =IF(OR(F71>0,G71="Yes",H71="Yes",I71="Yes"),"⚠️ OVERWORK",IF(OR(J71="Yes",K71>0,L71="Yes",M71="Yes"),"🔻 UNDERWORK","✓ OK"))
A72: 68 | B72: Mc Lean, Ibeno | C72: 3415 | D72: ='Mc Lean, Ibeno'!I49 | E72: ='Mc Lean, Ibeno'!Q50 | F72: =SUMPRODUCT((('Mc Lean, Ibeno'!I14+'Mc Lean, Ibeno'!I15)>12)*1)+SUMPRODUCT((('Mc Lean, Ibeno'!I16+'Mc Lean, Ibeno'!I17)>12)*1)+SUMPRODUCT((('Mc Lean, Ibeno'!I18+'Mc Lean, Ibeno'!I19)>12)*1)+SUMPRODUCT((('Mc Lean, Ibeno'!I20+'Mc Lean, Ibeno'!I21)>12)*1)+SUMPRODUCT((('Mc Lean, Ibeno'!I22+'Mc Lean, Ibeno'!I23)>12)*1)+SUMPRODUCT((('Mc Lean, Ibeno'!I24+'Mc Lean, Ibeno'!I25)>12)*1)+SUMPRODUCT((('Mc Lean, Ibeno'!I26+'Mc Lean, Ibeno'!I27)>12)*1)+SUMPRODUCT((('Mc Lean, Ibeno'!I30+'Mc Lean, Ibeno'!I31)>12)*1)+SUMPRODUCT((('Mc Lean, Ibeno'!I32+'Mc Lean, Ibeno'!I33)>12)*1)+SUMPRODUCT((('Mc Lean, Ibeno'!I34+'Mc Lean, Ibeno'!I35)>12)*1)+SUMPRODUCT((('Mc Lean, Ibeno'!I36+'Mc Lean, Ibeno'!I37)>12)*1)+SUMPRODUCT((('Mc Lean, Ibeno'!I38+'Mc Lean, Ibeno'!I39)>12)*1)+SUMPRODUCT((('Mc Lean, Ibeno'!I40+'Mc Lean, Ibeno'!I41)>12)*1)+SUMPRODUCT((('Mc Lean, Ibeno'!I42+'Mc Lean, Ibeno'!I43)>12)*1)+SUMPRODUCT((('Mc Lean, Ibeno'!I45+'Mc Lean, Ibeno'!I46)>12)*1)+SUMPRODUCT((('Mc Lean, Ibeno'!I47+'Mc Lean, Ibeno'!I48)>12)*1) | G72: =IF(MAX(SUM('Mc Lean, Ibeno'!I14:I27),SUM('Mc Lean, Ibeno'!I30:I43))>60,"Yes","") | H72: =IF(OR(AND(('Mc Lean, Ibeno'!I14+'Mc Lean, Ibeno'!I15)>0,('Mc Lean, Ibeno'!I16+'Mc Lean, Ibeno'!I17)>0,('Mc Lean, Ibeno'!I18+'Mc Lean, Ibeno'!I19)>0,('Mc Lean, Ibeno'!I20+'Mc Lean, Ibeno'!I21)>0,('Mc Lean, Ibeno'!I22+'Mc Lean, Ibeno'!I23)>0,('Mc Lean, Ibeno'!I24+'Mc Lean, Ibeno'!I25)>0,('Mc Lean, Ibeno'!I26+'Mc Lean, Ibeno'!I27)>0),AND(('Mc Lean, Ibeno'!I30+'Mc Lean, Ibeno'!I31)>0,('Mc Lean, Ibeno'!I32+'Mc Lean, Ibeno'!I33)>0,('Mc Lean, Ibeno'!I34+'Mc Lean, Ibeno'!I35)>0,('Mc Lean, Ibeno'!I36+'Mc Lean, Ibeno'!I37)>0,('Mc Lean, Ibeno'!I38+'Mc Lean, Ibeno'!I39)>0,('Mc Lean, Ibeno'!I40+'Mc Lean, Ibeno'!I41)>0,('Mc Lean, Ibeno'!I42+'Mc Lean, Ibeno'!I43)>0)),"Yes","") | I72: =IF('Mc Lean, Ibeno'!N49>40,"Yes","") | J72: =IF(OR(AND(SUM('Mc Lean, Ibeno'!I14:I27)>0,SUM('Mc Lean, Ibeno'!I14:I27)<40),AND(SUM('Mc Lean, Ibeno'!I30:I43)>0,SUM('Mc Lean, Ibeno'!I30:I43)<40)),"Yes","") | K72: =SUMPRODUCT(('Mc Lean, Ibeno'!I14:I48>0)*('Mc Lean, Ibeno'!I14:I48<8)) | L72: =IF('Mc Lean, Ibeno'!Q50<5,"Yes","") | M72: =IF(AND('Mc Lean, Ibeno'!I49>0,'Mc Lean, Ibeno'!I49<80),"Yes","") | N72: =IF(OR(F72>0,G72="Yes",H72="Yes",I72="Yes"),"⚠️ OVERWORK",IF(OR(J72="Yes",K72>0,L72="Yes",M72="Yes"),"🔻 UNDERWORK","✓ OK"))
A73: 69 | B73: Moore, Ferdinand Oliver | C73: 4094 | D73: ='Moore, Ferdinand Oliver'!I49 | E73: ='Moore, Ferdinand Oliver'!Q50 | F73: =SUMPRODUCT((('Moore, Ferdinand Oliver'!I14+'Moore, Ferdinand Oliver'!I15)>12)*1)+SUMPRODUCT((('Moore, Ferdinand Oliver'!I16+'Moore, Ferdinand Oliver'!I17)>12)*1)+SUMPRODUCT((('Moore, Ferdinand Oliver'!I18+'Moore, Ferdinand Oliver'!I19)>12)*1)+SUMPRODUCT((('Moore, Ferdinand Oliver'!I20+'Moore, Ferdinand Oliver'!I21)>12)*1)+SUMPRODUCT((('Moore, Ferdinand Oliver'!I22+'Moore, Ferdinand Oliver'!I23)>12)*1)+SUMPRODUCT((('Moore, Ferdinand Oliver'!I24+'Moore, Ferdinand Oliver'!I25)>12)*1)+SUMPRODUCT((('Moore, Ferdinand Oliver'!I26+'Moore, Ferdinand Oliver'!I27)>12)*1)+SUMPRODUCT((('Moore, Ferdinand Oliver'!I30+'Moore, Ferdinand Oliver'!I31)>12)*1)+SUMPRODUCT((('Moore, Ferdinand Oliver'!I32+'Moore, Ferdinand Oliver'!I33)>12)*1)+SUMPRODUCT((('Moore, Ferdinand Oliver'!I34+'Moore, Ferdinand Oliver'!I35)>12)*1)+SUMPRODUCT((('Moore, Ferdinand Oliver'!I36+'Moore, Ferdinand Oliver'!I37)>12)*1)+SUMPRODUCT((('Moore, Ferdinand Oliver'!I38+'Moore, Ferdinand Oliver'!I39)>12)*1)+SUMPRODUCT((('Moore, Ferdinand Oliver'!I40+'Moore, Ferdinand Oliver'!I41)>12)*1)+SUMPRODUCT((('Moore, Ferdinand Oliver'!I42+'Moore, Ferdinand Oliver'!I43)>12)*1)+SUMPRODUCT((('Moore, Ferdinand Oliver'!I45+'Moore, Ferdinand Oliver'!I46)>12)*1)+SUMPRODUCT((('Moore, Ferdinand Oliver'!I47+'Moore, Ferdinand Oliver'!I48)>12)*1) | G73: =IF(MAX(SUM('Moore, Ferdinand Oliver'!I14:I27),SUM('Moore, Ferdinand Oliver'!I30:I43))>60,"Yes","") | H73: =IF(OR(AND(('Moore, Ferdinand Oliver'!I14+'Moore, Ferdinand Oliver'!I15)>0,('Moore, Ferdinand Oliver'!I16+'Moore, Ferdinand Oliver'!I17)>0,('Moore, Ferdinand Oliver'!I18+'Moore, Ferdinand Oliver'!I19)>0,('Moore, Ferdinand Oliver'!I20+'Moore, Ferdinand Oliver'!I21)>0,('Moore, Ferdinand Oliver'!I22+'Moore, Ferdinand Oliver'!I23)>0,('Moore, Ferdinand Oliver'!I24+'Moore, Ferdinand Oliver'!I25)>0,('Moore, Ferdinand Oliver'!I26+'Moore, Ferdinand Oliver'!I27)>0),AND(('Moore, Ferdinand Oliver'!I30+'Moore, Ferdinand Oliver'!I31)>0,('Moore, Ferdinand Oliver'!I32+'Moore, Ferdinand Oliver'!I33)>0,('Moore, Ferdinand Oliver'!I34+'Moore, Ferdinand Oliver'!I35)>0,('Moore, Ferdinand Oliver'!I36+'Moore, Ferdinand Oliver'!I37)>0,('Moore, Ferdinand Oliver'!I38+'Moore, Ferdinand Oliver'!I39)>0,('Moore, Ferdinand Oliver'!I40+'Moore, Ferdinand Oliver'!I41)>0,('Moore, Ferdinand Oliver'!I42+'Moore, Ferdinand Oliver'!I43)>0)),"Yes","") | I73: =IF('Moore, Ferdinand Oliver'!N49>40,"Yes","") | J73: =IF(OR(AND(SUM('Moore, Ferdinand Oliver'!I14:I27)>0,SUM('Moore, Ferdinand Oliver'!I14:I27)<40),AND(SUM('Moore, Ferdinand Oliver'!I30:I43)>0,SUM('Moore, Ferdinand Oliver'!I30:I43)<40)),"Yes","") | K73: =SUMPRODUCT(('Moore, Ferdinand Oliver'!I14:I48>0)*('Moore, Ferdinand Oliver'!I14:I48<8)) | L73: =IF('Moore, Ferdinand Oliver'!Q50<5,"Yes","") | M73: =IF(AND('Moore, Ferdinand Oliver'!I49>0,'Moore, Ferdinand Oliver'!I49<80),"Yes","") | N73: =IF(OR(F73>0,G73="Yes",H73="Yes",I73="Yes"),"⚠️ OVERWORK",IF(OR(J73="Yes",K73>0,L73="Yes",M73="Yes"),"🔻 UNDERWORK","✓ OK"))
A74: 70 | B74: Moore, Kaye Elizabeth | C74: 5068 | D74: ='Moore, Kaye Elizabeth'!I49 | E74: ='Moore, Kaye Elizabeth'!Q50 | F74: =SUMPRODUCT((('Moore, Kaye Elizabeth'!I14+'Moore, Kaye Elizabeth'!I15)>12)*1)+SUMPRODUCT((('Moore, Kaye Elizabeth'!I16+'Moore, Kaye Elizabeth'!I17)>12)*1)+SUMPRODUCT((('Moore, Kaye Elizabeth'!I18+'Moore, Kaye Elizabeth'!I19)>12)*1)+SUMPRODUCT((('Moore, Kaye Elizabeth'!I20+'Moore, Kaye Elizabeth'!I21)>12)*1)+SUMPRODUCT((('Moore, Kaye Elizabeth'!I22+'Moore, Kaye Elizabeth'!I23)>12)*1)+SUMPRODUCT((('Moore, Kaye Elizabeth'!I24+'Moore, Kaye Elizabeth'!I25)>12)*1)+SUMPRODUCT((('Moore, Kaye Elizabeth'!I26+'Moore, Kaye Elizabeth'!I27)>12)*1)+SUMPRODUCT((('Moore, Kaye Elizabeth'!I30+'Moore, Kaye Elizabeth'!I31)>12)*1)+SUMPRODUCT((('Moore, Kaye Elizabeth'!I32+'Moore, Kaye Elizabeth'!I33)>12)*1)+SUMPRODUCT((('Moore, Kaye Elizabeth'!I34+'Moore, Kaye Elizabeth'!I35)>12)*1)+SUMPRODUCT((('Moore, Kaye Elizabeth'!I36+'Moore, Kaye Elizabeth'!I37)>12)*1)+SUMPRODUCT((('Moore, Kaye Elizabeth'!I38+'Moore, Kaye Elizabeth'!I39)>12)*1)+SUMPRODUCT((('Moore, Kaye Elizabeth'!I40+'Moore, Kaye Elizabeth'!I41)>12)*1)+SUMPRODUCT((('Moore, Kaye Elizabeth'!I42+'Moore, Kaye Elizabeth'!I43)>12)*1)+SUMPRODUCT((('Moore, Kaye Elizabeth'!I45+'Moore, Kaye Elizabeth'!I46)>12)*1)+SUMPRODUCT((('Moore, Kaye Elizabeth'!I47+'Moore, Kaye Elizabeth'!I48)>12)*1) | G74: =IF(MAX(SUM('Moore, Kaye Elizabeth'!I14:I27),SUM('Moore, Kaye Elizabeth'!I30:I43))>60,"Yes","") | H74: =IF(OR(AND(('Moore, Kaye Elizabeth'!I14+'Moore, Kaye Elizabeth'!I15)>0,('Moore, Kaye Elizabeth'!I16+'Moore, Kaye Elizabeth'!I17)>0,('Moore, Kaye Elizabeth'!I18+'Moore, Kaye Elizabeth'!I19)>0,('Moore, Kaye Elizabeth'!I20+'Moore, Kaye Elizabeth'!I21)>0,('Moore, Kaye Elizabeth'!I22+'Moore, Kaye Elizabeth'!I23)>0,('Moore, Kaye Elizabeth'!I24+'Moore, Kaye Elizabeth'!I25)>0,('Moore, Kaye Elizabeth'!I26+'Moore, Kaye Elizabeth'!I27)>0),AND(('Moore, Kaye Elizabeth'!I30+'Moore, Kaye Elizabeth'!I31)>0,('Moore, Kaye Elizabeth'!I32+'Moore, Kaye Elizabeth'!I33)>0,('Moore, Kaye Elizabeth'!I34+'Moore, Kaye Elizabeth'!I35)>0,('Moore, Kaye Elizabeth'!I36+'Moore, Kaye Elizabeth'!I37)>0,('Moore, Kaye Elizabeth'!I38+'Moore, Kaye Elizabeth'!I39)>0,('Moore, Kaye Elizabeth'!I40+'Moore, Kaye Elizabeth'!I41)>0,('Moore, Kaye Elizabeth'!I42+'Moore, Kaye Elizabeth'!I43)>0)),"Yes","") | I74: =IF('Moore, Kaye Elizabeth'!N49>40,"Yes","") | J74: =IF(OR(AND(SUM('Moore, Kaye Elizabeth'!I14:I27)>0,SUM('Moore, Kaye Elizabeth'!I14:I27)<40),AND(SUM('Moore, Kaye Elizabeth'!I30:I43)>0,SUM('Moore, Kaye Elizabeth'!I30:I43)<40)),"Yes","") | K74: =SUMPRODUCT(('Moore, Kaye Elizabeth'!I14:I48>0)*('Moore, Kaye Elizabeth'!I14:I48<8)) | L74: =IF('Moore, Kaye Elizabeth'!Q50<5,"Yes","") | M74: =IF(AND('Moore, Kaye Elizabeth'!I49>0,'Moore, Kaye Elizabeth'!I49<80),"Yes","") | N74: =IF(OR(F74>0,G74="Yes",H74="Yes",I74="Yes"),"⚠️ OVERWORK",IF(OR(J74="Yes",K74>0,L74="Yes",M74="Yes"),"🔻 UNDERWORK","✓ OK"))
